Workbook
Name ColumnTitle1: #REF!
Name ColumnTitleRegion1..B11.1: #REF!
Name Company_Name: #REF!
Name Profit_table: #REF!
Name RowTitleRegion1..D5: #REF!

Sheet Insutrcution for whole process
A1: check box | B1: Instruction for whole process
A2: FALSE | B2: 0. save as a new file
A3: FALSE | B3: 1. check detail for strata rep contacts, update if necessary
A4: FALSE | B4: 2. check detail for strata roll contacts, update if neccssary
A5: FALSE | B5: 3. update Amanda Energy bills using python code | C5: get invoice pdf from amanda energy | D5: get_Amanda_inovice.py | E5: output.csv
A6: FALSE | B6: 4. update auto meter reading (SwitchDin) | C6: download data from billing dashboard | D6: process_meter_data.py | E6: formatted data
A7: FALSE | B7: 5. update manual meter reading | C7: request manual meter reading ahead of time | D7: January 1st | E7: April 1st | F7: July 1st | G7: October 1st
A8: FALSE | B8: 6. check Tariff Rates, update if necessary
A9: FALSE | B9: 7. update master billing sheet to current billing cycle: | C9: cluster name and billing month
A10: FALSE | B10: 8. check supply table as follow, remove supply charge as request.
A11: FALSE | B11: 9. run VB code
A12: FALSE | B12: 10. Hide sensitve info sheet
B14: Instruction for VB code:
A15: FALSE | B15: 1. open tab 'Developer'
A16: FALSE | B16: 2. choose 'Visual Basic'
A17: FALSE | B17: 3. add module
A18: FALSE | B18: 4. copy and paste VB code | F18: Sub GenerateDynamicLotSheets() Dim wsTemplate As Worksheet Dim newSheet As Worksheet Dim strataRoll As Worksheet Dim clusterValue As String Dim maxLotNo As Long Dim rng As Range Dim cell As Range Dim i As Long ' Define the template sheet and reference sheet Set wsTemplate = ThisWorkbook.Sheets("Lot 1") Set strataRoll = ThisWorkbook.Sheets("Strata Roll") ' Get the Cluster value from D7 of the template sheet clusterValue = wsTemplate.Range("E7").Value ' Initialize the maximum Lot No maxLotNo = 0 ' Search "Strata Roll" for the maximum Lot No matching the Cluster value With strataRoll Set rng = .Range("A2", .Cells(.Rows.Count, "A").End(xlUp)) ' Assume data starts from A2 For Each cell In rng ' Check if the corresponding row's Cluster matches the target Cluster If .Cells(cell.Row, "B").Value = clusterValue Then ' Ensure the cell value in column A is numeric before comparing If IsNumeric(cell.Value) Then ' Compare the numeric Lot No directly If CLng(cell.Value) > maxLotNo Then maxLotNo = CLng(cell.Value) End If End If End If Next cell End With ' Check if any Lot No was found for the given Cluster If maxLotNo = 0 Then MsgBox "No Lot No found for Cluster value " & clusterValue & "!", vbExclamation Exit Sub End If ' Generate worksheets for Lot 2 to maxLotNo For i = 2 To maxLotNo ' Copy the template sheet wsTemplate.Copy After:=ThisWorkbook.Sheets(ThisWorkbook.Sheets.Count) Set newSheet = ThisWorkbook.Sheets(ThisWorkbook.Sheets.Count) ' Rename the new sheet newSheet.Name = "Lot " & i ' Update the Lot No in the new sheet (e.g., D8 cell) newSheet.Range("E8").Value = i Next i MsgBox "Successfully created Lot 2 to Lot " & maxLotNo & " worksheets!", vbInformation End Sub
A19: FALSE | B19: 5. run
A20: FALSE | B20: 6. remove VB code
B22: Invoicing table
B23: Cluster | C23: Account setup fee | D23: Q1 | E23: Q2 | F23: Q3 | G23: Q4 | H23: Jan-Feb | I23: Mar | J23: Redundant Invoices | K23: Contract Update
B24: 1A | C24: 1018 | D24: self- issued | E24: self- issued | F24: self- issued | G24: 1077 | H24: 1091 | J24: 1039 for Q1-Q3 | K24: Signed
B25: 1B | C25: 1019 | D25: self- issued | E25: self- issued | F25: self- issued | G25: 1069 | H25: 1092 | J25: 1043 for Q1-Q3 | K25: Weekend | M25: paid
B26: 1C | C26: 1020 | D26: 1044 | E26: 1044 | F26: 1044 | G26: 1070 | H26: 1093 | K26: Signed | M26: not paid
B27: 2A | C27: 1021 | D27: self- issued | E27: self- issued | F27: self- issued | G27: 1071 | J27: 1045 for Q2-Q3 | K27: Holiday | M27: Credit Note allocated
B28: 2B | C28: 1022 | D28: self- issued | E28: 1046 | F28: 1046 | G28: 1082 | H28: 1094 | K28: Weekend | M28: self- issued
B29: 3A | C29: 1023 | D29: self- issued | E29: 1047 | F29: 1047 | G29: 1081 | K29: Weekend
B30: 3B | C30: 1024 | D30: self- issued | E30: 1083 | F30: 1083 | G30: 1083 | H30: 1095 | J30: 1048 for Q2-Q3 | K30: FIFO working
B32: Supply charge table
B33: Cluster | C33: Amanda energy supply charge | D33: SwitchDin | E33: ChargeFox | F33: EV charger cost of electricy @P2P rate | G33: P2P trade rate for lots with export | H33: P2P rate for lots with no export | I33: Agreement and action items | J33: BESS status | K33: billing cycle | L33: P2P borrow/lend
B34: 1A | C34: Included | D34: Not included | E34: Not included | F34: Included | G34: 0.22$/kwh | H34: 0.36$/kwh | I34: July 1st 2025 | J34: ON | K34: quarterly | L34: 2
B35: 1B | C35: Included | D35: Not included Till May 2025 | E35: Not included | F35: Included | G35: 0.22$/kwh | H35: 0.22$/kwh | I35: July 1st 2025 | J35: ON | K35: quarterly | L35: 2
B36: 1C | C36: Included | D36: Included | E36: Included | F36: Included | G36: 0.22$/kwh | H36: 0.22$/kwh | J36: ON | K36: quarterly | L36: 2
B37: 2A | C37: Included | D37: Not included | E37: Not included | G37: 0.22$/kwh | H37: 0.22$/kwh | I37: July 1st 2025 | J37: ON | K37: quarterly | L37: 2
B38: 2B | C38: Included | D38: Included | E38: Not included | G38: 0.22$/kwh | H38: 0.22$/kwh | I38: July 1st 2025 | J38: ON | K38: quarterly | L38: 2
B39: 3A | C39: Not included | D39: Not included | E39: Not included | G39: 0.22$/kwh | H39: 0.22$/kwh | I39: July 1st 2025 | J39: ON | K39: quarterly | L39: 0
B40: 3B | C40: Not included | D40: Not included | E40: Not included | G40: 0.22$/kwh | H40: 0.22$/kwh | I40: July 1st 2025 | J40: ON | K40: quarterly | L40: 0
B41: FALSE | C41: FALSE | D41: FALSE | E41: FALSE | F41: FALSE | G41: FALSE | H41: FALSE | I41: FALSE | J41: FALSE | K41: FALSE | L41: FALSE

Sheet strata rep contacts
A1: Cluster | B1: Strata company name | C1: ABN | D1: Parcel Address | E1: Energy Representative | F1: Energy Representative email | G1: Strata Council Chair | H1: Strata Council Email | I1: Energy supply charge incl in strata fees | J1: Cluster battery | K1: Invividual lot battery | L1: number of lots | M1: Account Name | N1: BSB | O1: Account #
A2: 1A | B2: The Owners of Cluster 1A Witchcliffe Ecovillage Survey Strata 77784 | C2: ABN: 29 857 461 927 | D2: Lot 10, 10347 Bussell Hwy Witchcliffe WA | E2: Peter Froehlich (lot 13) | F2: froehlich.fp@gmail.com | G2: to be confirmed by strata | H2: wevcluster1a@gmail.com | J2: ✓ | M2: Owners Cluster 1A | N2: 633-000 | O2: 209 071 927
B3: 24 Lots | E3: Lindy Dunlop | F3: lindyjdunlop@hotmail.com | L3: 24
A4: 1B | B4: The Owners of Cluster 1B Witchcliffe Ecovillage Survey Strata 77785 | C4: ABN: 31 962 028 201 | D4: Lot 17, 10347 Bussell Hwy Witchcliffe WA | E4: Paul Wilkinson (lot 12) | F4: mail2paul07@gmail.com | G4: to be confirmed by strata | H4: wevcluster1b@gmail.com | J4: ✓ | M4: 1B Admin Fund | N4: 633000 | O4: 208 200 014
B5: 21 Lots | L5: 21
A6: 1C | B6: The Owners of Cluster 1C Witchcliffe Ecovillage Survey Strata 77786 | C6: ABN: 80 608 251 481 | D6: Lot 11, 10347 Bussell Hwy Witchcliffe WA | E6: Laurence Hansen (Lot 19) | F6: logs1@iinet.net.au | G6: to be confirmed by strata | H6: wevcluster1c@gmail.com | J6: ✓ | M6: WEV Cluster 1C Strata Account | N6: 633 000 | O6: 216 423 913
B7: 19 Lots | L7: 19
A9: 2A | B9: The Owners of Cluster 2A Witchcliffe Ecovillage Survey Strata 77787 | C9: ABN: 38 248 842 277 | D9: Lot 7 10347 Bussell Hwy Witchcliffe WA | E9: Bouwe Hamersma (Lot 5) | F9: bouwe.hamersma@gmail.com | G9: to be confirmed by strata | H9: wevcluster2a@gmail.com | J9: ✓ | M9: 2A ADMIN FUND | N9: 306-188 | O9: 352588
B10: 23 Lots | L10: 23
A11: 2B | B11: The Owners of Cluster 2B Witchcliffe Ecovillage Survey Strata 77788 | C11: ABN: 64 989 501 940 | D11: Lot 8, 10347 Bussell Hwy Witchcliffe WA | E11: Alison Askew (Lot 10) | F11: alisonaskew123@gmail.com | G11: to be confirmed by strata | H11: wevcluster2b@gmail.com | J11: ✓ | M11: The Owners of Cluster 2B Witchcliffe | N11: 633000 | O11: 209 181 437
B12: 22 Lots | L12: 22
A14: 3A | B14: The Owners of Cluster 3A Witchcliffe Ecovillage Survey Strata 77790 | C14: ABN: 22315195710 | D14: 2 Karrack Crescent, Witchcliffe WA | E14: Elaine Clocherty (Lot 15) | F14: elaineclocherty@gmail.com | G14: to be confirmed by strata | H14: wevcluster3a@gmail.com | I14: ✓ | J14: ✓ | M14: WEV Cluster 3A Strata | N14: 633 000 | O14: 223 075 870
B15: 27 Lots | L15: 27
A16: 3B | B16: The Owners of Cluster 3B Witchcliffe Ecovillage Survey Strata 77791 | C16: ABN: 11801467982 | D16: 3 Karrack Crescent, Witchcliffe WA | E16: Jason McHattan (Lot13) | F16: jasonmchattan@gmail.com | G16: to be confirmed by strata | H16: wevcluster3b@gmail.com | I16: ✓ | J16: ✓ | M16: 3B Admin Fund | N16: 306-412 | O16: 0020794
B17: 19 Lots | E17: Tim Thomson (Lot 8) | F17: timjcthomson@gmail.com | L17: 19
B18: The Owners of Cluster 3C Witchcliffe Ecovillage Survey Strata 83347 | C18: ABN: 86675221914 | D18: Lot 18 Karrack Crescent Witchcliffe WA | E18: ?? | G18: to be confirmed by strata | H18: wevcluster3c@gmail.com | I18: ✓ | K18: ✓
B19: 15 Short Stay | L19: 15
B21: The Owners of Cluster 4A Witchcliffe Ecovillage Survey Strata 85752 | C21: ABN: 33 677 155 303 | D21: 22 Gnuraren Grove, Witchcliffe WA | E21: ?? | G21: Caroline Bannister (Lot18) | H21: wevcluster4a@gmail.com | I21: ✓ | K21: ✓
B22: 26 lots | L22: 26
B23: The Owners of Cluster 4B Witchcliffe Ecovillage Survey Strata 85753 | C23: ABN: 24 266 141 390 | D23: 23 Mulal Avenue, Witchcliffe WA | E23: Manuel Mall (Lot 3) | F23: carolinandmanuel@gmail.com | G23: Jenny Challen (Lot 9) | H23: wevcluster4b@gmail.com | I23: ✓ | K23: ✓
B24: 20 lots | E24: Jenny Challen (Lot 9) | F24: jenny@challen.com.au | L24: 20

Sheet strata roll
A1: Lot | B1: cluster | C1: Meter# | D1: Block Type | E1: Owner | F1: Street Address | G1: Suburb | H1: State | I1: Post Code | J1: Unit Entitlement | K1: UE % over Cluster | L1: Calculated Battery Allocation (kWh) | M1: Inverter Model | N1: Applied Battery Allocation (kWh) | O1: Export Capacity (kW) | P1: Energy Meter Installed | Q1: PV Installed | R1: Functional Droplet | S1: Stage of Dev. | T1: Phone 1 | U1: Phone 2 | V1: Email | W1: Meter Number | X1: Occupant 1 Start Date | Y1: Occupant 1 End date | Z1: Inverter start date
A2: 1 | B2: 1A | D2: Cottage | E2: Mead Family trust | F2: 1 Yornitj Grove | G2: Witchcliffe | H2: WA | I2: 6286 | J2: 36 | K2: 0.036 | L2: 8.352 | N2: 0 | P2: Y | Q2: N | R2: N | S2: UC | T2: 0 | U2: 0.72 | V2: 0457 578 078 | W2: 0476919881 | X2: nicholasjamesmead@gmail.co | Z2: 45292 | AA2: Current
A3: 2 | B3: 1A | D3: Cottage | E3: Margareta Roeck | F3: 3 Yornitj Grove | G3: Witchcliffe | H3: WA | I3: 6286 | J3: 36 | K3: 0.036 | L3: 8.352 | N3: 0 | P3: Y | Q3: N | R3: N | S3: UC | T3: 0 | U3: 0.72 | V3: 0416732634 | X3: maroeck@gmail.com | Z3: 45292 | AA3: Current
A4: 3 | B4: 1A | C4: 50002872 | D4: Cottage | E4: Battigielli | F4: 5 Yornitj Grove | G4: Witchcliffe | H4: WA | I4: 6286 | J4: 37 | K4: 0.037 | L4: 8.584 | N4: 0 | P4: Y | Q4: N | R4: N | S4: O | T4: 0 | U4: 0.72 | V4: 0424154036 | X4: emailalexhughes@gmail.com | Z4: 45292 | AA4: Current
A5: 4 | B5: 1A | C5: 50002869 | D5: Cottage | E5: Paul Jurjevich & Trish Rushton | F5: 7 Yornitj Grove | G5: Witchcliffe | H5: WA | I5: 6286 | J5: 38 | K5: 0.038 | L5: 8.816 | M5: Symo 5.0 | N5: 8.816 | O5: 6.64 | P5: Y | Q5: Y | R5: Y | S5: O | T5: 4.7808 | U5: 0.72 | V5: 0412261482 | W5: 0403732723 | X5: mulloway9@icloud.com | Z5: 45292 | AA5: Current
A6: 5 | B6: 1A | C6: 50002879 | D6: Cottage | E6: Dwyer | F6: 9 Yornitj Grove | G6: Witchcliffe | H6: WA | I6: 6286 | J6: 39 | K6: 0.039 | L6: 9.048 | M6: Symo 5.0 | N6: 9.048 | O6: 6.4 | P6: Y | Q6: Y | R6: Y | S6: O | T6: 4.608 | U6: 0.72 | V6: 0408744572 | W6: 0437286462 | X6: mammoth@iinet.net.au | Z6: 45292 | AA6: Current
A7: 6 | B7: 1A | C7: 50002865 | D7: Cottage | E7: Gillespie | F7: 11 Yornitj Grove | G7: Witchcliffe | H7: WA | I7: 6286 | J7: 39 | K7: 0.039 | L7: 9.048 | M7: Symo 8.2 | N7: 9.048 | O7: 10.88 | P7: Y | Q7: Y | R7: Y | S7: O | T7: 7.8336 | U7: 0.72 | V7: 0417950370 | W7: 0429196637 | X7: barbaragillespie@iinet.net.au | Z7: 45292 | AA7: Current
A8: 7 | B8: 1A | D8: Cottage | E8: Rio & Alix Healey-­‐Diaz | F8: 13 Yornitj Grove | G8: Witchcliffe | H8: WA | I8: 6286 | J8: 37 | K8: 0.037 | L8: 8.584 | N8: 0 | P8: Y | Q8: N | R8: N | S8: O | T8: 0 | U8: 0.72 | V8: 0425890670 | X8: alixward@gmail.com | Z8: 45292 | AA8: Current
A9: 8 | B9: 1A | C9: 50002846 | D9: Cottage | E9: Marcus Browne & Sook-­‐JaRebecchi | F9: 15 Yornitj Grove | G9: Witchcliffe | H9: WA | I9: 6286 | J9: 36 | K9: 0.036 | L9: 8.352 | M9: Symo 5.0 | N9: 8.352 | O9: 6.6 | P9: Y | Q9: Y | R9: Y | S9: O | T9: 4.752 | U9: 0.72 | V9: 0433290368 | W9: 0448279836 | X9: marcus@mishack.com.au | Z9: 45292 | AA9: Current
A10: 9 | B10: 1A | D10: Cottage | E10: Jasmine Heah | F10: 17 Yornitj Grove | G10: Witchcliffe | H10: WA | I10: 6286 | J10: 36 | K10: 0.036 | L10: 8.352 | N10: 0 | P10: Y | Q10: N | R10: N | S10: O | T10: 0 | U10: 0.72 | V10: 0408323274 | X10: jasmine_heah@hotmail.com | Z10: 45292 | AA10: Current
A11: 10 | B11: 1A | D11: Family | E11: Pernille Stent | F11: 51 Mardo Drive | G11: Witchcliffe | H11: WA | I11: 6286 | J11: 53 | K11: 0.053 | L11: 12.296 | M11: Symo 5.0 | N11: 12.296 | O11: 6.4 | P11: Y | Q11: Y | R11: Y | S11: O | T11: 4.608 | U11: 0.72 | V11: 0410416005 | X11: pernille@designbutton.net.au | Z11: 45292 | AA11: Current
A12: 11 | B12: 1A | C12: 50002848 | D12: Family | E12: Levi Holden | F12: 49 Mardo Drive | G12: Witchcliffe | H12: WA | I12: 6286 | J12: 52 | K12: 0.052 | L12: 12.064 | M12: Symo 5.0 | N12: 12.064 | O12: 6.4 | P12: Y | Q12: Y | R12: Y | S12: O | T12: 4.608 | U12: 0.72 | V12: 0427444150 | X12: levi.holden@optusnet.com.au | Z12: 45292 | AA12: Current
A13: 12 | B13: 1A | D13: Family | E13: Matt & Kate Shaw | F13: 47 Mardo Drive | G13: Witchcliffe | H13: WA | I13: 6286 | J13: 52 | K13: 0.052 | L13: 12.064 | N13: 0 | P13: Y | Q13: N | R13: N | S13: UC | T13: 0 | U13: 0.72 | V13: 0428088590 | W13: 0431001084 | X13: shaw76@hotmail.co.uk | Z13: 45292 | AA13: Current
A14: 13 | B14: 1A | C14: 50002739 | D14: Family | E14: Peter Froehlich & Lydia Walzel | F14: 45 Mardo Drive | G14: Witchcliffe | H14: WA | I14: 6286 | J14: 52 | K14: 0.052 | L14: 12.064 | M14: Symo 10.0 | N14: 12.064 | O14: 12.8 | P14: Y | Q14: Y | R14: Y | S14: O | T14: 9.216 | U14: 0.72 | V14: 0418946078 | W14: 0419928925 | X14: froehlich.fp@gmail.com | Z14: 45292 | AA14: Current
A15: 14 | B15: 1A | D15: Family | E15: Priscila Goncalves | F15: 43 Mardo Drive | G15: Witchcliffe | H15: WA | I15: 6286 | J15: 52 | K15: 0.052 | L15: 12.064 | M15: Symo 10.0 | N15: 12.064 | O15: 13.2 | P15: Y | Q15: Y | R15: N | S15: UC | T15: 9.504 | U15: 0.72 | V15: 0475716267 | W15: 0475716400 | X15: diego.barneche@ymail.com | Z15: 45292 | AA15: Current
A16: 15 | B16: 1A | D16: Family | E16: Jeﬀ & Jo Thierfelder | F16: 41 Mardo Drive | G16: Witchcliffe | H16: WA | I16: 6286 | J16: 53 | K16: 0.053 | L16: 12.296 | N16: 0 | P16: Y | Q16: N | R16: N | S16: UC | T16: 0 | U16: 0.72 | V16: 0409770316 | W16: 0421589548 | X16: jeﬀ.thierfelder@iinet.net.au | Z16: 45292 | AA16: Current
A17: 16 | B17: 1A | C17: 50002855 | D17: Family | E17: Libby Davy | F17: 3 Mannitj Place | G17: Witchcliffe | H17: WA | I17: 6286 | J17: 55 | K17: 0.055 | L17: 12.76 | M17: Symo 5.0 | N17: 12.76 | O17: 6.6 | P17: Y | Q17: Y | R17: Y | S17: O | T17: 4.752 | U17: 0.72 | V17: 0413993452 | X17: libby@humanbells.com | Z17: 45292 | AA17: Current
A18: 17 | B18: 1A | C18: 50002877 | D18: Family | E18: Henry & Jo Weldon | F18: 5 Mannitj Place | G18: Witchcliffe | H18: WA | I18: 6286 | J18: 55 | K18: 0.055 | L18: 12.76 | M18: Symo 8.2 | N18: 12.76 | O18: 10.9 | P18: Y | Q18: Y | R18: Y | S18: O | T18: 7.848 | U18: 0.72 | V18: 0407076552 | W18: 0407388196 | X18: henryweldon90@gmail.com | Z18: 45292 | AA18: Current
A19: 18 | B19: 1A | D19: Family | E19: Liz Kirk | F19: 7 Mannitj Place | G19: Witchcliffe | H19: WA | I19: 6286 | J19: 55 | K19: 0.055 | L19: 12.76 | N19: 0 | Q19: N | R19: N | S19: V | T19: 0 | U19: 0.72 | V19: 0408751379 | X19: lizk@beyondergo.com.au | Z19: 45292 | AA19: Current
A20: 19 | B20: 1A | C20: 50002864 | D20: Family | E20: Lindy Dunlop | F20: 9 Mannitj Place | G20: Witchcliffe | H20: WA | I20: 6286 | J20: 55 | K20: 0.055 | L20: 12.76 | M20: Symo 10.0 | N20: 12.76 | O20: 12.8 | P20: Y | Q20: Y | R20: Y | S20: O | T20: 9.216 | U20: 0.72 | V20: 0493385725 | X20: lindyjdunlop@hotmail.com | Z20: 45292 | AA20: Current
A21: 20 | B21: 1A | C21: 50002710 | D21: Groupie | E21: Elke Light | F21: 30 Kulbardi Way | G21: Witchcliffe | H21: WA | I21: 6286 | J21: 26 | K21: 0.026 | L21: 6.032 | M21: Symo 5.0 | N21: 6.032 | O21: 6.4 | P21: Y | Q21: Y | R21: Y | S21: O | T21: 4.608 | U21: 0.72 | V21: 0439968661 | X21: lightelke@gmail.com | Z21: 45292 | AA21: Current
A22: 21 | B22: 1A | C22: 50002719 | D22: Groupie | E22: Deborah Woodman | F22: 28 Kulbardi Way | G22: Witchcliffe | H22: WA | I22: 6286 | J22: 26 | K22: 0.026 | L22: 6.032 | M22: Symo 5.0 | N22: 6.032 | O22: 6.4 | P22: Y | Q22: Y | R22: Y | S22: O | T22: 4.608 | U22: 0.72 | V22: 0456121155 | X22: woodmandj55@gmail.com | Z22: 45292 | AA22: Current
A23: 22 | B23: 1A | C23: 50002876 | D23: Groupie | E23: Carrie & Warrick Goldsmith | F23: 26 Kulbardi Way | G23: Witchcliffe | H23: WA | I23: 6286 | J23: 26 | K23: 0.026 | L23: 6.032 | M23: Symo 5.0 | N23: 6.032 | O23: 6.4 | P23: Y | Q23: Y | R23: Y | S23: O | T23: 4.608 | U23: 0.72 | V23: 0499270453 | W23: 0447110831 | X23: carrieandwarrick@gmail.com | Z23: 45292 | AA23: Current
A24: 23 | B24: 1A | C24: 50002860 | D24: Groupie | E24: Clyde Huxtable | F24: 24 Kulbardi Way | G24: Witchcliffe | H24: WA | I24: 6286 | J24: 26 | K24: 0.026 | L24: 6.032 | M24: Symo 5.0 | N24: 6.032 | O24: 6.4 | P24: Y | Q24: Y | R24: Y | S24: O | T24: 4.608 | U24: 0.72 | V24: 0406351722 | X24: hotfire1948@hotmail.com | Z24: 45292 | AA24: Current
A25: 24 | B25: 1A | D25: Groupie | E25: Helen Rose | F25: 22 Kulbardi Way | G25: Witchcliffe | H25: WA | I25: 6286 | J25: 28 | K25: 0.028 | L25: 6.496 | N25: 0 | P25: Y | Q25: N | R25: N | S25: UC | T25: 0 | U25: 0.72 | V25: 0437445630 | X25: rosebunch5@gmail.com | Z25: 45292 | AA25: Current
A26: BESS | B26: 1A | C26: 40002686 | E26: BESS Powerpack 232kWh | J26: 1000 | K26: 1 | N26: 0 | T26: 0 | U26: 0.72
A27: EV | B27: 1A | C27: 40002693 | D27: N/A | E27: EV Charger | G27: Witchcliffe | H27: WA | I27: 6286 | K27: 0 | L27: 0 | N27: 0 | P27: Y | Q27: N | R27: Y | T27: 0 | U27: 0.72
A28: CS | B28: 1A | D28: N/A | E28: Common Services MSB | G28: Witchcliffe | H28: WA | I28: 6286 | K28: 0 | L28: 0 | N28: 0 | P28: Y | Q28: N | R28: Y | T28: 0 | U28: 0.72
A29: DB1 | B29: 1A | K29: 0 | N29: 0 | T29: 0
A30: DB2 | B30: 1A | K30: 0 | N30: 0 | T30: 0
A31: 1 | B31: 1B | C31: 50003409 | D31: Cottage | E31: Susan Gibson | F31: 78 Kulbardi Way | G31: Witchcliffe | H31: WA | I31: 6286 | J31: 42 | K31: =Table_Household_Alloc[[#This Row],[Unit Entitlement]]/1000 -> 0.042 | L31: =(J31/1000)*232 -> 9.744 | M31: Symo 5.0 | N31: =IF(Table_Household_Alloc[[#This Row],[PV Installed]]="Y",1,0)*Table_Household_Alloc[[#This Row],[Calculated Battery Allocation (kWh)]] -> 9.744 | O31: 5 | P31: Y | Q31: Y | R31: Y | S31: O
A32: 2 | B32: 1B | C32: 50003436 | D32: Cottage | E32: Karen Majer & Boyd Wykes | F32: 76 Kulbardi Way | G32: Witchcliffe | H32: WA | I32: 6286 | J32: 43 | K32: =Table_Household_Alloc[[#This Row],[Unit Entitlement]]/1000 -> 0.043 | L32: =(J32/1000)*232 -> 9.976 | M32: Symo 8.2 | N32: =IF(Table_Household_Alloc[[#This Row],[PV Installed]]="Y",1,0)*Table_Household_Alloc[[#This Row],[Calculated Battery Allocation (kWh)]] -> 9.976 | O32: 8.2 | P32: Y | Q32: Y | R32: Y | S32: O
A33: 3 | B33: 1B | C33: 50004064 | D33: Cottage | E33: Susan Hardy | F33: 74 Kulbardi Way | G33: Witchcliffe | H33: WA | I33: 6286 | J33: 43 | K33: =Table_Household_Alloc[[#This Row],[Unit Entitlement]]/1000 -> 0.043 | L33: =(J33/1000)*232 -> 9.976 | M33: Symo 5.0 | N33: =IF(Table_Household_Alloc[[#This Row],[PV Installed]]="Y",1,0)*Table_Household_Alloc[[#This Row],[Calculated Battery Allocation (kWh)]] -> 9.976 | O33: 5 | P33: Y | Q33: Y | R33: Y | S33: O
A34: 4 | B34: 1B | C34: 50003414 | D34: Cottage | E34: Jennie McCormack | F34: 72 Kulbardi Way | G34: Witchcliffe | H34: WA | I34: 6286 | J34: 45 | K34: =Table_Household_Alloc[[#This Row],[Unit Entitlement]]/1000 -> 0.045 | L34: =(J34/1000)*232 -> 10.44 | M34: Symo 5.0 | N34: =IF(Table_Household_Alloc[[#This Row],[PV Installed]]="Y",1,0)*Table_Household_Alloc[[#This Row],[Calculated Battery Allocation (kWh)]] -> 10.44 | O34: 5 | P34: Y | Q34: Y | R34: Y | S34: O
A35: 5 | B35: 1B | C35: 50003389 | D35: Cottage | E35: Michael & Britta Sorensen | F35: 70 Kulbardi Way | G35: Witchcliffe | H35: WA | I35: 6286 | J35: 46 | K35: =Table_Household_Alloc[[#This Row],[Unit Entitlement]]/1000 -> 0.046 | L35: =(J35/1000)*232 -> 10.672 | M35: Symo 8.2 | N35: =IF(Table_Household_Alloc[[#This Row],[PV Installed]]="Y",1,0)*Table_Household_Alloc[[#This Row],[Calculated Battery Allocation (kWh)]] -> 10.672 | O35: 8.2 | P35: Y | Q35: Y | R35: Y | S35: O
A36: 6 | B36: 1B | C36: 50002969 | D36: Cottage | E36: Toni Aslett | F36: 68 Kulbardi Way | G36: Witchcliffe | H36: WA | I36: 6286 | J36: 50 | K36: =Table_Household_Alloc[[#This Row],[Unit Entitlement]]/1000 -> 0.05 | L36: =(J36/1000)*232 -> 11.6 | M36: Symo 8.2 | N36: =IF(Table_Household_Alloc[[#This Row],[PV Installed]]="Y",1,0)*Table_Household_Alloc[[#This Row],[Calculated Battery Allocation (kWh)]] -> 11.6 | O36: 8.2 | P36: Y | Q36: Y | R36: Y | S36: O
A37: 7 | B37: 1B | C37: 50002951 | D37: Cottage | E37: Bridget Bolitho | F37: 66 Kulbardi Way | G37: Witchcliffe | H37: WA | I37: 6286 | J37: 52 | K37: =Table_Household_Alloc[[#This Row],[Unit Entitlement]]/1000 -> 0.052 | L37: =(J37/1000)*232 -> 12.064 | M37: Symo 5.0 | N37: =IF(Table_Household_Alloc[[#This Row],[PV Installed]]="Y",1,0)*Table_Household_Alloc[[#This Row],[Calculated Battery Allocation (kWh)]] -> 12.064 | O37: 5 | P37: Y | Q37: Y | R37: Y | S37: O
A38: 8 | B38: 1B | C38: 50002959 | D38: Family | E38: Shereen & Hamish Jolly | F38: 64 Kulbardi Way | G38: Witchcliffe | H38: WA | I38: 6286 | J38: 69 | K38: =Table_Household_Alloc[[#This Row],[Unit Entitlement]]/1000 -> 0.069 | L38: =(J38/1000)*232 -> 16.008 | M38: Symo 6.0 | N38: =IF(Table_Household_Alloc[[#This Row],[PV Installed]]="Y",1,0)*Table_Household_Alloc[[#This Row],[Calculated Battery Allocation (kWh)]] -> 16.008 | O38: 6 | P38: Y | Q38: Y | R38: Y | S38: O
A39: 9 | B39: 1B | D39: Family | E39: Phillip Crockford & Wendy Davis | F39: 62 Kulbardi Way | G39: Witchcliffe | H39: WA | I39: 6286 | J39: 55 | K39: =Table_Household_Alloc[[#This Row],[Unit Entitlement]]/1000 -> 0.055 | L39: =(J39/1000)*232 -> 12.76 | M39: Symo 10.0 | N39: =IF(Table_Household_Alloc[[#This Row],[PV Installed]]="Y",1,0)*Table_Household_Alloc[[#This Row],[Calculated Battery Allocation (kWh)]] -> 0 | P39: N | Q39: N | R39: N | S39: V
A40: 10 | B40: 1B | C40: 50003420 | D40: Family | E40: Stefan & Jennifer Widmer | F40: 60 Kulbardi Way | G40: Witchcliffe | H40: WA | I40: 6286 | J40: 57 | K40: =Table_Household_Alloc[[#This Row],[Unit Entitlement]]/1000 -> 0.057 | L40: =(J40/1000)*232 -> 13.224 | M40: Symo 5.0 | N40: =IF(Table_Household_Alloc[[#This Row],[PV Installed]]="Y",1,0)*Table_Household_Alloc[[#This Row],[Calculated Battery Allocation (kWh)]] -> 13.224 | O40: 5 | P40: Y | Q40: Y | R40: Y | S40: O
A41: 11 | B41: 1B | C41: 50003410 | D41: Family | E41: Hannah & Peter Flack | F41: 58 Kulbardi Way | G41: Witchcliffe | H41: WA | I41: 6286 | J41: 59 | K41: =Table_Household_Alloc[[#This Row],[Unit Entitlement]]/1000 -> 0.059 | L41: =(J41/1000)*232 -> 13.688 | M41: Symo 6.0 | N41: =IF(Table_Household_Alloc[[#This Row],[PV Installed]]="Y",1,0)*Table_Household_Alloc[[#This Row],[Calculated Battery Allocation (kWh)]] -> 13.688 | O41: 6 | P41: Y | Q41: Y | R41: Y | S41: O
A42: 12 | B42: 1B | C42: 50003418 | D42: Family | E42: Paul & Nicole Wilkinson | F42: 56 Kulbardi Way | G42: Witchcliffe | H42: WA | I42: 6286 | J42: 60 | K42: =Table_Household_Alloc[[#This Row],[Unit Entitlement]]/1000 -> 0.06 | L42: =(J42/1000)*232 -> 13.92 | M42: Symo 10.0 | N42: =IF(Table_Household_Alloc[[#This Row],[PV Installed]]="Y",1,0)*Table_Household_Alloc[[#This Row],[Calculated Battery Allocation (kWh)]] -> 13.92 | O42: 10 | P42: Y | Q42: Y | R42: Y | S42: O
A43: 13 | B43: 1B | C43: 50002859 | D43: Family | E43: Stephen & Dicy Hall | F43: 54 Kulbardi Way | G43: Witchcliffe | H43: WA | I43: 6286 | J43: 60 | K43: =Table_Household_Alloc[[#This Row],[Unit Entitlement]]/1000 -> 0.06 | L43: =(J43/1000)*232 -> 13.92 | M43: Symo 10.0 | N43: =IF(Table_Household_Alloc[[#This Row],[PV Installed]]="Y",1,0)*Table_Household_Alloc[[#This Row],[Calculated Battery Allocation (kWh)]] -> 13.92 | O43: 10 | P43: Y | Q43: Y | R43: Y | S43: O
A44: 14 | B44: 1B | C44: 50003396 | D44: Family | E44: Craig & Julie Headford | F44: 52 Kulbardi Way | G44: Witchcliffe | H44: WA | I44: 6286 | J44: 63 | K44: =Table_Household_Alloc[[#This Row],[Unit Entitlement]]/1000 -> 0.063 | L44: =(J44/1000)*232 -> 14.616 | M44: Symo 10.0 | N44: =IF(Table_Household_Alloc[[#This Row],[PV Installed]]="Y",1,0)*Table_Household_Alloc[[#This Row],[Calculated Battery Allocation (kWh)]] -> 14.616 | O44: 10 | P44: Y | Q44: Y | R44: Y | S44: O
A45: 15 | B45: 1B | C45: 50003401 | D45: Groupie | E45: Jema McCabe | F45: 18 Yornitj Grove | G45: Witchcliffe | H45: WA | I45: 6286 | J45: 27 | K45: =Table_Household_Alloc[[#This Row],[Unit Entitlement]]/1000 -> 0.027 | L45: =(J45/1000)*232 -> 6.264 | M45: Symo 5.0 | N45: =IF(Table_Household_Alloc[[#This Row],[PV Installed]]="Y",1,0)*Table_Household_Alloc[[#This Row],[Calculated Battery Allocation (kWh)]] -> 6.264 | O45: 5 | P45: Y | Q45: Y | R45: N | S45: O
A46: 16 | B46: 1B | C46: 50003430 | D46: Groupie | E46: Colin & Filomena Dear | F46: 20 Yornitj Grove | G46: Witchcliffe | H46: WA | I46: 6286 | J46: 27 | K46: =Table_Household_Alloc[[#This Row],[Unit Entitlement]]/1000 -> 0.027 | L46: =(J46/1000)*232 -> 6.264 | M46: Symo 5.0 | N46: =IF(Table_Household_Alloc[[#This Row],[PV Installed]]="Y",1,0)*Table_Household_Alloc[[#This Row],[Calculated Battery Allocation (kWh)]] -> 6.264 | O46: 5 | P46: Y | Q46: Y | R46: Y | S46: O
A47: 17 | B47: 1B | C47: 50003415 | D47: Groupie | E47: Candice & Bryn Papalia | F47: 22 Yornitj Grove | G47: Witchcliffe | H47: WA | I47: 6286 | J47: 27 | K47: =Table_Household_Alloc[[#This Row],[Unit Entitlement]]/1000 -> 0.027 | L47: =(J47/1000)*232 -> 6.264 | M47: Symo 5.0 | N47: =IF(Table_Household_Alloc[[#This Row],[PV Installed]]="Y",1,0)*Table_Household_Alloc[[#This Row],[Calculated Battery Allocation (kWh)]] -> 6.264 | O47: 5 | P47: Y | Q47: Y | R47: N | S47: O
A48: 18 | B48: 1B | D48: Groupie | E48: Chloe Dignam | F48: 24 Yornitj Grove | G48: Witchcliffe | H48: WA | I48: 6286 | J48: 27 | K48: =Table_Household_Alloc[[#This Row],[Unit Entitlement]]/1000 -> 0.027 | L48: =(J48/1000)*232 -> 6.264 | M48: Symo 5.0 | N48: =IF(Table_Household_Alloc[[#This Row],[PV Installed]]="Y",1,0)*Table_Household_Alloc[[#This Row],[Calculated Battery Allocation (kWh)]] -> 0 | P48: Y | Q48: N | R48: N | S48: UC
A49: 19 | B49: 1B | C49: 50003432 | D49: Groupie | E49: Alex Jolly | F49: 26 Yornitj Grove | G49: Witchcliffe | H49: WA | I49: 6286 | J49: 30 | K49: =Table_Household_Alloc[[#This Row],[Unit Entitlement]]/1000 -> 0.03 | L49: =(J49/1000)*232 -> 6.96 | M49: Symo 5.0 | N49: =IF(Table_Household_Alloc[[#This Row],[PV Installed]]="Y",1,0)*Table_Household_Alloc[[#This Row],[Calculated Battery Allocation (kWh)]] -> 6.96 | O49: 5 | P49: Y | Q49: Y | R49: Y | S49: O
A50: 20 | B50: 1B | C50: 50002972 | D50: Family | E50: Nathan Stone | F50: 3 Kyloring Drive | G50: Witchcliffe | H50: WA | I50: 6286 | J50: 59 | K50: =Table_Household_Alloc[[#This Row],[Unit Entitlement]]/1000 -> 0.059 | L50: =(J50/1000)*232 -> 13.688 | M50: Symo 10.0 | N50: =IF(Table_Household_Alloc[[#This Row],[PV Installed]]="Y",1,0)*Table_Household_Alloc[[#This Row],[Calculated Battery Allocation (kWh)]] -> 13.688 | O50: 10 | P50: Y | Q50: Y | R50: Y | S50: O
A51: 21 | B51: 1B | C51: 50002650 | D51: Fam ily | E51: Nicholas Mead & Theresa Brandl | F51: 5 Kyloring Drive | G51: Witchcliffe | H51: WA | I51: 6286 | J51: 59 | K51: =Table_Household_Alloc[[#This Row],[Unit Entitlement]]/1000 -> 0.059 | L51: =(J51/1000)*232 -> 13.688 | M51: Symo 10.0 | N51: =IF(Table_Household_Alloc[[#This Row],[PV Installed]]="Y",1,0)*Table_Household_Alloc[[#This Row],[Calculated Battery Allocation (kWh)]] -> 13.688 | O51: 10 | P51: Y | Q51: Y | R51: Y | S51: O
A52: BESS | B52: 1B | C52: 40002670 | E52: BESS Powerpack 232kWh | K52: =Table_Household_Alloc[[#This Row],[Unit Entitlement]]/1000 -> 0 | N52: =IF(Table_Household_Alloc[[#This Row],[PV Installed]]="Y",1,0)*Table_Household_Alloc[[#This Row],[Calculated Battery Allocation (kWh)]] -> 0
A53: EV | B53: 1B | C53: 40002667 | D53: N/A | E53: EV Charger | G53: Witchcliffe | H53: WA | I53: 6286 | K53: =Table_Household_Alloc[[#This Row],[Unit Entitlement]]/1000 -> 0 | L53: =(J53/1000)*232 -> 0 | N53: =IF(Table_Household_Alloc[[#This Row],[PV Installed]]="Y",1,0)*Table_Household_Alloc[[#This Row],[Calculated Battery Allocation (kWh)]] -> 0 | P53: Y | Q53: N | R53: Y
A54: CS | B54: 1B | C54: 50003399 | D54: N/A | E54: Common Services MSB | G54: Witchcliffe | H54: WA | I54: 6286 | K54: =Table_Household_Alloc[[#This Row],[Unit Entitlement]]/1000 -> 0 | L54: =(J54/1000)*232 -> 0 | N54: =IF(Table_Household_Alloc[[#This Row],[PV Installed]]="Y",1,0)*Table_Household_Alloc[[#This Row],[Calculated Battery Allocation (kWh)]] -> 0 | P54: Y | Q54: N | R54: Y
A55: DB1 | B55: 1B | K55: =Table_Household_Alloc[[#This Row],[Unit Entitlement]]/1000 -> 0 | N55: =IF(Table_Household_Alloc[[#This Row],[PV Installed]]="Y",1,0)*Table_Household_Alloc[[#This Row],[Calculated Battery Allocation (kWh)]] -> 0
A56: DB2 | B56: 1B | K56: =Table_Household_Alloc[[#This Row],[Unit Entitlement]]/1000 -> 0 | N56: =IF(Table_Household_Alloc[[#This Row],[PV Installed]]="Y",1,0)*Table_Household_Alloc[[#This Row],[Calculated Battery Allocation (kWh)]] -> 0
A57: 1 | B57: 1C | C57: 50003397 | E57: Aron Dyer Jodie Passmore | F57: 19 Yornitj Grove | G57: Witchcliffe | H57: WA | I57: 6286 | J57: 42 | K57: =Table_Household_Alloc[[#This Row],[Unit Entitlement]]/1000 -> 0.042 | L57: =(J57/1000)*232 -> 9.744 | M57: Symo 8.2 | N57: =IF(Table_Household_Alloc[[#This Row],[PV Installed]]="Y",1,0)*Table_Household_Alloc[[#This Row],[Calculated Battery Allocation (kWh)]] -> 9.744 | O57: 8.2 | P57: Y | Q57: Y | R57: Y | S57: O | X57: 44381 | Y57: Current
A58: 2 | B58: 1C | C58: 50003402 | E58: Eli Sutton | F58: 21 Yornitj Grove | G58: Witchcliffe | H58: WA | I58: 6286 | J58: 43 | K58: =Table_Household_Alloc[[#This Row],[Unit Entitlement]]/1000 -> 0.043 | L58: =(J58/1000)*232 -> 9.976 | M58: =CONCATENATE("Symo ",Table_Household_Alloc[[#This Row],[Export Capacity (kW)]]) -> Symo 5 | N58: =IF(Table_Household_Alloc[[#This Row],[PV Installed]]="Y",1,0)*Table_Household_Alloc[[#This Row],[Calculated Battery Allocation (kWh)]] -> 9.976 | O58: 5 | P58: Y | Q58: Y | R58: Y | S58: O | X58: 44774 | Y58: Current
A59: 3 | B59: 1C | C59: 50003431 | E59: Shelley Chapman Cherry Chapman | F59: 23 Yornitj Grove | G59: Witchcliffe | H59: WA | I59: 6286 | J59: 44 | K59: =Table_Household_Alloc[[#This Row],[Unit Entitlement]]/1000 -> 0.044 | L59: =(J59/1000)*232 -> 10.208 | M59: =CONCATENATE("Symo ",Table_Household_Alloc[[#This Row],[Export Capacity (kW)]]) -> Symo 8.2 | N59: =IF(Table_Household_Alloc[[#This Row],[PV Installed]]="Y",1,0)*Table_Household_Alloc[[#This Row],[Calculated Battery Allocation (kWh)]] -> 10.208 | O59: 8.2 | P59: Y | Q59: Y | R59: Y | S59: O | X59: 45023 | Y59: Current
A60: 4 | B60: 1C | C60: 50003394 | E60: Jillian Ann Luckhurst | F60: 25 Yornitj Grove | G60: Witchcliffe | H60: WA | I60: 6286 | J60: 45 | K60: =Table_Household_Alloc[[#This Row],[Unit Entitlement]]/1000 -> 0.045 | L60: =(J60/1000)*232 -> 10.44 | M60: =CONCATENATE("Symo ",Table_Household_Alloc[[#This Row],[Export Capacity (kW)]]) -> Symo 5 | N60: =IF(Table_Household_Alloc[[#This Row],[PV Installed]]="Y",1,0)*Table_Household_Alloc[[#This Row],[Calculated Battery Allocation (kWh)]] -> 10.44 | O60: 5 | P60: Y | Q60: Y | R60: Y | S60: O | X60: 45078 | Y60: Current
A61: 5 | B61: 1C | C61: 50003433 | E61: Samuel Vinciullo | F61: 27 Yornitj Grove | G61: Witchcliffe | H61: WA | I61: 6286 | J61: 46 | K61: =Table_Household_Alloc[[#This Row],[Unit Entitlement]]/1000 -> 0.046 | L61: =(J61/1000)*232 -> 10.672 | M61: =CONCATENATE("Symo ",Table_Household_Alloc[[#This Row],[Export Capacity (kW)]]) -> Symo 8.2 | N61: =IF(Table_Household_Alloc[[#This Row],[PV Installed]]="Y",1,0)*Table_Household_Alloc[[#This Row],[Calculated Battery Allocation (kWh)]] -> 10.672 | O61: 8.2 | P61: Y | Q61: Y | R61: Y | S61: O | X61: 44599 | Y61: Current
A62: 6 | B62: 1C | C62: 50003421 | E62: Christopher Paul Martin Vicki Ann Martin | F62: 4 Mannitj Place | G62: Witchcliffe | H62: WA | I62: 6286 | J62: 66 | K62: =Table_Household_Alloc[[#This Row],[Unit Entitlement]]/1000 -> 0.066 | L62: =(J62/1000)*232 -> 15.312 | M62: =CONCATENATE("Symo ",Table_Household_Alloc[[#This Row],[Export Capacity (kW)]]) -> Symo 10 | N62: =IF(Table_Household_Alloc[[#This Row],[PV Installed]]="Y",1,0)*Table_Household_Alloc[[#This Row],[Calculated Battery Allocation (kWh)]] -> 15.312 | O62: 10 | P62: Y | Q62: Y | R62: Y | S62: O | X62: 45020 | Y62: Current
A63: 7 | B63: 1C | C63: 50002953 | E63: Dex Ezekiel, Jeannine Penniment | F63: 6 Mannitj Place | G63: Witchcliffe | H63: WA | I63: 6286 | J63: 66 | K63: =Table_Household_Alloc[[#This Row],[Unit Entitlement]]/1000 -> 0.066 | L63: =(J63/1000)*232 -> 15.312 | N63: =IF(Table_Household_Alloc[[#This Row],[PV Installed]]="Y",1,0)*Table_Household_Alloc[[#This Row],[Calculated Battery Allocation (kWh)]] -> 0 | S63: UC/M/ND
A64: 8 | B64: 1C | C64: 50003395 | E64: Eric Martini Karina Jean Martini | F64: 8 Mannitj Place | G64: Witchcliffe | H64: WA | I64: 6286 | J64: 66 | K64: =Table_Household_Alloc[[#This Row],[Unit Entitlement]]/1000 -> 0.066 | L64: =(J64/1000)*232 -> 15.312 | M64: =CONCATENATE("Symo ",Table_Household_Alloc[[#This Row],[Export Capacity (kW)]]) -> Symo 10 | N64: =IF(Table_Household_Alloc[[#This Row],[PV Installed]]="Y",1,0)*Table_Household_Alloc[[#This Row],[Calculated Battery Allocation (kWh)]] -> 15.312 | O64: 10 | P64: Y | Q64: Y | R64: Y | S64: O | X64: 44682 | Y64: Current
A65: 9 | B65: 1C | C65: 50003435 | E65: Christopher van Etten Emmanuelle van Etten | F65: 10 Mannitj Place | G65: Witchcliffe | H65: WA | I65: 6286 | J65: 66 | K65: =Table_Household_Alloc[[#This Row],[Unit Entitlement]]/1000 -> 0.066 | L65: =(J65/1000)*232 -> 15.312 | N65: =IF(Table_Household_Alloc[[#This Row],[PV Installed]]="Y",1,0)*Table_Household_Alloc[[#This Row],[Calculated Battery Allocation (kWh)]] -> 0 | S65: UC
A66: 10 | B66: 1C | C66: 50002952 | E66: Peter Smith | F66: 32 Kulbardi Way | G66: Witchcliffe | H66: WA | I66: 6286 | J66: 31 | K66: =Table_Household_Alloc[[#This Row],[Unit Entitlement]]/1000 -> 0.031 | L66: =(J66/1000)*232 -> 7.192 | M66: =CONCATENATE("Symo ",Table_Household_Alloc[[#This Row],[Export Capacity (kW)]]) -> Symo 5 | N66: =IF(Table_Household_Alloc[[#This Row],[PV Installed]]="Y",1,0)*Table_Household_Alloc[[#This Row],[Calculated Battery Allocation (kWh)]] -> 7.192 | O66: 5 | P66: Y | Q66: Y | R66: Y | S66: O | X66: 44593 | Y66: Current
A67: 11 | B67: 1C | C67: 50002944 | E67: Peter Andre Grant | F67: 34 Kulbardi Way | G67: Witchcliffe | H67: WA | I67: 6286 | J67: 31 | K67: =Table_Household_Alloc[[#This Row],[Unit Entitlement]]/1000 -> 0.031 | L67: =(J67/1000)*232 -> 7.192 | N67: =IF(Table_Household_Alloc[[#This Row],[PV Installed]]="Y",1,0)*Table_Household_Alloc[[#This Row],[Calculated Battery Allocation (kWh)]] -> 0 | S67: UC/M/ND
A68: 12 | B68: 1C | C68: 3308026898 | E68: Sandra Handy | F68: 36 Kulbardi Way | G68: Witchcliffe | H68: WA | I68: 6286 | J68: 31 | K68: =Table_Household_Alloc[[#This Row],[Unit Entitlement]]/1000 -> 0.031 | L68: =(J68/1000)*232 -> 7.192 | M68: =CONCATENATE("Symo ",Table_Household_Alloc[[#This Row],[Export Capacity (kW)]]) -> Symo 5 | N68: =IF(Table_Household_Alloc[[#This Row],[PV Installed]]="Y",1,0)*Table_Household_Alloc[[#This Row],[Calculated Battery Allocation (kWh)]] -> 7.192 | O68: 5 | P68: N | Q68: Y | R68: Y | S68: O | X68: 45139 | Y68: Current
A69: 13 | B69: 1C | C69: 50003424 | E69: Miles Durand | F69: 38 Kulbardi Way | G69: Witchcliffe | H69: WA | I69: 6286 | J69: 31 | K69: =Table_Household_Alloc[[#This Row],[Unit Entitlement]]/1000 -> 0.031 | L69: =(J69/1000)*232 -> 7.192 | M69: =CONCATENATE("Symo ",Table_Household_Alloc[[#This Row],[Export Capacity (kW)]]) -> Symo 5 | N69: =IF(Table_Household_Alloc[[#This Row],[PV Installed]]="Y",1,0)*Table_Household_Alloc[[#This Row],[Calculated Battery Allocation (kWh)]] -> 7.192 | O69: 5 | P69: Y | Q69: Y | R69: Y | S69: O | X69: 44621 | Y69: Current
A70: 14 | B70: 1C | C70: 50003438 | E70: Lawrence Bycroft Anu Grace | F70: 40 Kulbardi Way | G70: Witchcliffe | H70: WA | I70: 6286 | J70: 37 | K70: =Table_Household_Alloc[[#This Row],[Unit Entitlement]]/1000 -> 0.037 | L70: =(J70/1000)*232 -> 8.584 | M70: =CONCATENATE("Symo ",Table_Household_Alloc[[#This Row],[Export Capacity (kW)]]) -> Symo 5 | N70: =IF(Table_Household_Alloc[[#This Row],[PV Installed]]="Y",1,0)*Table_Household_Alloc[[#This Row],[Calculated Battery Allocation (kWh)]] -> 8.584 | O70: 5 | P70: Y | Q70: Y | R70: Y | S70: O | X70: 44643 | Y70: Current
A71: 15 | B71: 1C | C71: 50003404 | E71: Kaine Grigg (Hudson) | F71: 50 Kulbardi Way | G71: Witchcliffe | H71: WA | I71: 6286 | J71: 69 | K71: =Table_Household_Alloc[[#This Row],[Unit Entitlement]]/1000 -> 0.069 | L71: =(J71/1000)*232 -> 16.008 | M71: =CONCATENATE("Symo ",Table_Household_Alloc[[#This Row],[Export Capacity (kW)]]) -> Symo 8.2 | N71: =IF(Table_Household_Alloc[[#This Row],[PV Installed]]="Y",1,0)*Table_Household_Alloc[[#This Row],[Calculated Battery Allocation (kWh)]] -> 16.008 | O71: 8.2 | P71: Y | Q71: Y | R71: Y | S71: O | X71: 44835 | Y71: Current
A72: 16 | B72: 1C | C72: 50003419 | E72: Veronique Florec | F72: 48 Kulbardi Way | G72: Witchcliffe | H72: WA | I72: 6286 | J72: 69 | K72: =Table_Household_Alloc[[#This Row],[Unit Entitlement]]/1000 -> 0.069 | L72: =(J72/1000)*232 -> 16.008 | M72: =CONCATENATE("Symo ",Table_Household_Alloc[[#This Row],[Export Capacity (kW)]]) -> Symo 10 | N72: =IF(Table_Household_Alloc[[#This Row],[PV Installed]]="Y",1,0)*Table_Household_Alloc[[#This Row],[Calculated Battery Allocation (kWh)]] -> 16.008 | O72: 10 | P72: Y | Q72: Y | R72: Y | S72: O | X72: 45047 | Y72: Current
A73: 17 | B73: 1C | C73: 50003428 | E73: Lars Rueter Katja Blankenheim | F73: 46 Kulbardi Way | G73: Witchcliffe | H73: WA | I73: 6286 | J73: 69 | K73: =Table_Household_Alloc[[#This Row],[Unit Entitlement]]/1000 -> 0.069 | L73: =(J73/1000)*232 -> 16.008 | N73: =IF(Table_Household_Alloc[[#This Row],[PV Installed]]="Y",1,0)*Table_Household_Alloc[[#This Row],[Calculated Battery Allocation (kWh)]] -> 0 | S73: UC/M/ND
A74: 18 | B74: 1C | C74: 50002935 | E74: Amy Steel | F74: 44 Kulbardi Way | G74: Witchcliffe | H74: WA | I74: 6286 | J74: 69 | K74: =Table_Household_Alloc[[#This Row],[Unit Entitlement]]/1000 -> 0.069 | L74: =(J74/1000)*232 -> 16.008 | M74: =CONCATENATE("Symo ",Table_Household_Alloc[[#This Row],[Export Capacity (kW)]]) -> Symo 10 | N74: =IF(Table_Household_Alloc[[#This Row],[PV Installed]]="Y",1,0)*Table_Household_Alloc[[#This Row],[Calculated Battery Allocation (kWh)]] -> 16.008 | O74: 10 | P74: Y | Q74: Y | R74: Y | S74: O | X74: 45481 | Y74: Current
A75: 19 | B75: 1C | C75: 50003417 | E75: Laurence Hansen Janet Anne Hansen | F75: 42 Kulbardi Way | G75: Witchcliffe | H75: WA | I75: 6286 | J75: 79 | K75: =Table_Household_Alloc[[#This Row],[Unit Entitlement]]/1000 -> 0.079 | L75: =(J75/1000)*232 -> 18.328 | M75: =CONCATENATE("Symo ",Table_Household_Alloc[[#This Row],[Export Capacity (kW)]]) -> Symo 10 | N75: =IF(Table_Household_Alloc[[#This Row],[PV Installed]]="Y",1,0)*Table_Household_Alloc[[#This Row],[Calculated Battery Allocation (kWh)]] -> 18.328 | O75: 10 | P75: Y | Q75: Y | R75: Y | S75: O | X75: 44913 | Y75: Current
A76: BESS | B76: 1C | C76: 40002722 | E76: BESS Powerpack 232kWh | K76: =Table_Household_Alloc[[#This Row],[Unit Entitlement]]/1000 -> 0 | N76: =IF(Table_Household_Alloc[[#This Row],[PV Installed]]="Y",1,0)*Table_Household_Alloc[[#This Row],[Calculated Battery Allocation (kWh)]] -> 0
A77: EV | B77: 1C | C77: 40002728 | E77: EV Charger | F77: 10437 Bussell Hwy | G77: Witchcliffe | H77: WA | I77: 6286 | K77: =Table_Household_Alloc[[#This Row],[Unit Entitlement]]/1000 -> 0 | N77: =IF(Table_Household_Alloc[[#This Row],[PV Installed]]="Y",1,0)*Table_Household_Alloc[[#This Row],[Calculated Battery Allocation (kWh)]] -> 0
A78: CS | B78: 1C | C78: 50003429 | E78: Common Services MSB | F78: 10437 Bussell Hwy | G78: Witchcliffe | H78: WA | I78: 6286 | K78: =Table_Household_Alloc[[#This Row],[Unit Entitlement]]/1000 -> 0 | L78: =(J78/1000)*232 -> 0 | N78: =IF(Table_Household_Alloc[[#This Row],[PV Installed]]="Y",1,0)*Table_Household_Alloc[[#This Row],[Calculated Battery Allocation (kWh)]] -> 0
A79: DB1 | B79: 1C | K79: =Table_Household_Alloc[[#This Row],[Unit Entitlement]]/1000 -> 0 | N79: =IF(Table_Household_Alloc[[#This Row],[PV Installed]]="Y",1,0)*Table_Household_Alloc[[#This Row],[Calculated Battery Allocation (kWh)]] -> 0
A80: DB2 | B80: 1C | K80: =Table_Household_Alloc[[#This Row],[Unit Entitlement]]/1000 -> 0 | N80: =IF(Table_Household_Alloc[[#This Row],[PV Installed]]="Y",1,0)*Table_Household_Alloc[[#This Row],[Calculated Battery Allocation (kWh)]] -> 0
A81: 1 | B81: 2A | C81: 50002920 | E81: Megan Donald & Yehuda Harmor | F81: 15 Kulbardi Way | G81: Witchcliffe | H81: WA | I81: 6286 | J81: 40 | K81: =Table_Household_Alloc[[#This Row],[Unit Entitlement]]/1000 -> 0.04 | L81: =J81/1000*232 -> 9.28 | N81: =IF(Table_Household_Alloc[[#This Row],[PV Installed]]="Y",1,0)*Table_Household_Alloc[[#This Row],[Calculated Battery Allocation (kWh)]] -> 0 | S81: UC | T81: 0499 838 958 | U81: 0499 838 830 | V81: tinymegan68@gmail.com
A82: 2 | B82: 2A | C82: 50002903 | E82: LK & MD Hynes | F82: 13 Kulbardi Way | G82: Witchcliffe | H82: WA | I82: 6286 | J82: 40 | K82: =Table_Household_Alloc[[#This Row],[Unit Entitlement]]/1000 -> 0.04 | L82: =J82/1000*232 -> 9.28 | M82: =CONCATENATE("Symo ",Table_Household_Alloc[[#This Row],[Export Capacity (kW)]]) -> Symo 8.2 | N82: =IF(Table_Household_Alloc[[#This Row],[PV Installed]]="Y",1,0)*Table_Household_Alloc[[#This Row],[Calculated Battery Allocation (kWh)]] -> 9.28 | O82: 8.2 | P82: Y | Q82: Y | R82: Y | S82: O | T82: 0411 725 581 | U82: 0478 577 554 | V82: lyndalhynes@hotmail.com | X82: 44986 | Y82: Current
A83: 3 | B83: 2A | E83: Paul John Baker | F83: 11 Kulbardi Way | G83: Witchcliffe | H83: WA | I83: 6286 | J83: 40 | K83: =Table_Household_Alloc[[#This Row],[Unit Entitlement]]/1000 -> 0.04 | L83: =J83/1000*232 -> 9.28 | N83: =IF(Table_Household_Alloc[[#This Row],[PV Installed]]="Y",1,0)*Table_Household_Alloc[[#This Row],[Calculated Battery Allocation (kWh)]] -> 0 | S83: V | T83: 0402 135 100 | V83: theminiguyagain@gmail.com
A84: 4 | B84: 2A | E84: K L Geels | F84: 9 Kulbardi Way | G84: Witchcliffe | H84: WA | I84: 6286 | J84: 40 | K84: =Table_Household_Alloc[[#This Row],[Unit Entitlement]]/1000 -> 0.04 | L84: =J84/1000*232 -> 9.28 | N84: =IF(Table_Household_Alloc[[#This Row],[PV Installed]]="Y",1,0)*Table_Household_Alloc[[#This Row],[Calculated Battery Allocation (kWh)]] -> 0 | S84: V | T84: 44(0)7734364646 | V84: kgeels@gmail.com
A85: 5 | B85: 2A | C85: 50002911 | E85: B & G Hamersma | F85: 7 Kulbardi Way | G85: Witchcliffe | H85: WA | I85: 6286 | J85: 42 | K85: =Table_Household_Alloc[[#This Row],[Unit Entitlement]]/1000 -> 0.042 | L85: =J85/1000*232 -> 9.744 | M85: =CONCATENATE("Symo ",Table_Household_Alloc[[#This Row],[Export Capacity (kW)]]) -> Symo 8.2 | N85: =IF(Table_Household_Alloc[[#This Row],[PV Installed]]="Y",1,0)*Table_Household_Alloc[[#This Row],[Calculated Battery Allocation (kWh)]] -> 9.744 | O85: 8.2 | P85: Y | Q85: Y | R85: Y | S85: O | T85: 0416 499 424 | U85: 0424 482 470 | V85: bouwe.hamersma@gmail.com | X85: 45108 | Y85: Current
A86: 6 | B86: 2A | E86: B & G Garnett | F86: 5 Kulbardi Way | G86: Witchcliffe | H86: WA | I86: 6286 | J86: 41 | K86: =Table_Household_Alloc[[#This Row],[Unit Entitlement]]/1000 -> 0.041 | L86: =J86/1000*232 -> 9.512 | N86: =IF(Table_Household_Alloc[[#This Row],[PV Installed]]="Y",1,0)*Table_Household_Alloc[[#This Row],[Calculated Battery Allocation (kWh)]] -> 0 | S86: V | T86: 0413 209 277 | V86: garnett635@hotmail.com
A87: 7 | B87: 2A | E87: C E Andrews & Y J Marinivich | F87: 3 Kulbardi Way | G87: Witchcliffe | H87: WA | I87: 6286 | J87: 40 | K87: =Table_Household_Alloc[[#This Row],[Unit Entitlement]]/1000 -> 0.04 | L87: =J87/1000*232 -> 9.28 | N87: =IF(Table_Household_Alloc[[#This Row],[PV Installed]]="Y",1,0)*Table_Household_Alloc[[#This Row],[Calculated Battery Allocation (kWh)]] -> 0 | S87: V | T87: 0448 023 265 | U87: 0488 937 149 | V87: yurimarinovich@gmail.com
A88: 8 | B88: 2A | E88: Colin Reburn | F88: 1 Kulbardi Way | G88: Witchcliffe | H88: WA | I88: 6286 | J88: 39 | K88: =Table_Household_Alloc[[#This Row],[Unit Entitlement]]/1000 -> 0.039 | L88: =J88/1000*232 -> 9.048 | N88: =IF(Table_Household_Alloc[[#This Row],[PV Installed]]="Y",1,0)*Table_Household_Alloc[[#This Row],[Calculated Battery Allocation (kWh)]] -> 0 | S88: V | T88: 0435 204 625 | V88: colin@kilmontinplumbing.com
A89: 9 | B89: 2A | C89: 50002909 | E89: N & C Haskell | F89: 23 Wolghine Ave | G89: Witchcliffe | H89: WA | I89: 6286 | J89: 54 | K89: =Table_Household_Alloc[[#This Row],[Unit Entitlement]]/1000 -> 0.054 | L89: =J89/1000*232 -> 12.528 | N89: =IF(Table_Household_Alloc[[#This Row],[PV Installed]]="Y",1,0)*Table_Household_Alloc[[#This Row],[Calculated Battery Allocation (kWh)]] -> 0 | S89: O | T89: 0478 630 993 | U89: 0478 220 964 | V89: nadia.anne@gmail.com | X89: 45139 | Y89: Current
A90: 10 | B90: 2A | E90: Charlotte & Darryl Diaz | F90: 21 Wolghine Ave | G90: Witchcliffe | H90: WA | I90: 6286 | J90: 54 | K90: =Table_Household_Alloc[[#This Row],[Unit Entitlement]]/1000 -> 0.054 | L90: =J90/1000*232 -> 12.528 | N90: =IF(Table_Household_Alloc[[#This Row],[PV Installed]]="Y",1,0)*Table_Household_Alloc[[#This Row],[Calculated Battery Allocation (kWh)]] -> 0 | S90: V | T90: 0415 506 827 | U90: 0449 646 303 | V90: darrylnaidu@gmail.com
A91: 11 | B91: 2A | E91: Simon Alan Naber | F91: 19 Wolghine Ave | G91: Witchcliffe | H91: WA | I91: 6286 | J91: 54 | K91: =Table_Household_Alloc[[#This Row],[Unit Entitlement]]/1000 -> 0.054 | L91: =J91/1000*232 -> 12.528 | N91: =IF(Table_Household_Alloc[[#This Row],[PV Installed]]="Y",1,0)*Table_Household_Alloc[[#This Row],[Calculated Battery Allocation (kWh)]] -> 0 | S91: V | T91: 0449 253 680 | V91: simon@mooreandmoorecafe.com
A92: 12 | B92: 2A | C92: 50002897 | E92: J S C & EP Ford | F92: 17 Wolghine Ave | G92: Witchcliffe | H92: WA | I92: 6286 | J92: 54 | K92: =Table_Household_Alloc[[#This Row],[Unit Entitlement]]/1000 -> 0.054 | L92: =J92/1000*232 -> 12.528 | M92: =CONCATENATE("Symo ",Table_Household_Alloc[[#This Row],[Export Capacity (kW)]]) -> Symo 10 | N92: =IF(Table_Household_Alloc[[#This Row],[PV Installed]]="Y",1,0)*Table_Household_Alloc[[#This Row],[Calculated Battery Allocation (kWh)]] -> 12.528 | O92: 10 | P92: Y | Q92: Y | R92: Y | S92: O | T92: 0414 401 059 | U92: 0432 519 448 | V92: setford.18@gmail.com | X92: 45078 | Y92: Current
A93: 13 | B93: 2A | C93: 50002839 | E93: K V Jarvis & P S Davis | F93: 15 Wolghine Ave | G93: Witchcliffe | H93: WA | I93: 6286 | J93: 56 | K93: =Table_Household_Alloc[[#This Row],[Unit Entitlement]]/1000 -> 0.056 | L93: =J93/1000*232 -> 12.992 | N93: =IF(Table_Household_Alloc[[#This Row],[PV Installed]]="Y",1,0)*Table_Household_Alloc[[#This Row],[Calculated Battery Allocation (kWh)]] -> 0 | P93: Y | R93: Y | S93: O | T93: 0435 280 200 | U93: 0435 280 202 | V93: katevjarvis@hotmail.com | X93: 45261 | Y93: Current
A94: 14 | B94: 2A | C94: 50002863 | E94: A Lillend | F94: 20 Mardo Drive | G94: Witchcliffe | H94: WA | I94: 6286 | J94: 28 | K94: =Table_Household_Alloc[[#This Row],[Unit Entitlement]]/1000 -> 0.028 | L94: =J94/1000*232 -> 6.496 | M94: =CONCATENATE("Symo ",Table_Household_Alloc[[#This Row],[Export Capacity (kW)]]) -> Symo 5 | N94: =IF(Table_Household_Alloc[[#This Row],[PV Installed]]="Y",1,0)*Table_Household_Alloc[[#This Row],[Calculated Battery Allocation (kWh)]] -> 6.496 | O94: 5 | P94: Y | Q94: Y | R94: Y | S94: O | T94: 0466 498 000 | U94: 0449 594 479 | V94: astisup@gmail.com | X94: 45536 | Y94: Current
A95: 15 | B95: 2A | C95: 50002947 | E95: Liz Thomas | F95: 22 Mardo Drive | G95: Witchcliffe | H95: WA | I95: 6286 | J95: 28 | K95: =Table_Household_Alloc[[#This Row],[Unit Entitlement]]/1000 -> 0.028 | L95: =J95/1000*232 -> 6.496 | M95: =CONCATENATE("Symo ",Table_Household_Alloc[[#This Row],[Export Capacity (kW)]]) -> Symo 5 | N95: =IF(Table_Household_Alloc[[#This Row],[PV Installed]]="Y",1,0)*Table_Household_Alloc[[#This Row],[Calculated Battery Allocation (kWh)]] -> 6.496 | O95: 5 | P95: Y | Q95: Y | R95: Y | S95: O | T95: 0421 607 702 | V95: ehmthomas@hotmail.com | X95: 45413 | Y95: Current
A96: 16 | B96: 2A | E96: Helen Downsborough | F96: 24 Mardo Drive | G96: Witchcliffe | H96: WA | I96: 6286 | J96: 28 | K96: =Table_Household_Alloc[[#This Row],[Unit Entitlement]]/1000 -> 0.028 | L96: =J96/1000*232 -> 6.496 | N96: =IF(Table_Household_Alloc[[#This Row],[PV Installed]]="Y",1,0)*Table_Household_Alloc[[#This Row],[Calculated Battery Allocation (kWh)]] -> 0 | S96: V | T96: 042 883 6629 | V96: helendownsborough@bigpond.com
A97: 17 | B97: 2A | C97: 50002902 | E97: Carol Luca | F97: 26 Mardo Drive | G97: Witchcliffe | H97: WA | I97: 6286 | J97: 28 | K97: =Table_Household_Alloc[[#This Row],[Unit Entitlement]]/1000 -> 0.028 | L97: =J97/1000*232 -> 6.496 | M97: =CONCATENATE("Symo ",Table_Household_Alloc[[#This Row],[Export Capacity (kW)]]) -> Symo 5 | N97: =IF(Table_Household_Alloc[[#This Row],[PV Installed]]="Y",1,0)*Table_Household_Alloc[[#This Row],[Calculated Battery Allocation (kWh)]] -> 6.496 | O97: 5 | P97: Y | Q97: Y | R97: Y | S97: O | T97: 0425 823 928 | V97: carolluca8@icloud.com | X97: 45536 | Y97: Current
A98: 18 | B98: 2A | C98: 50002950 | E98: N Rebasti | F98: 28 Mardo Drive | G98: Witchcliffe | H98: WA | I98: 6286 | J98: 28 | K98: =Table_Household_Alloc[[#This Row],[Unit Entitlement]]/1000 -> 0.028 | L98: =J98/1000*232 -> 6.496 | M98: =CONCATENATE("Symo ",Table_Household_Alloc[[#This Row],[Export Capacity (kW)]]) -> Symo 5 | N98: =IF(Table_Household_Alloc[[#This Row],[PV Installed]]="Y",1,0)*Table_Household_Alloc[[#This Row],[Calculated Battery Allocation (kWh)]] -> 6.496 | O98: 5 | P98: Y | Q98: Y | R98: Y | S98: O | T98: 0410 216 361 | U98: 08 9192 7127 | V98: nadreb@hotmail.com | X98: 45536 | Y98: Current
A99: 19 | B99: 2A | C99: 50002936 | E99: T W Oliver | F99: 30 Mardo Drive | G99: Witchcliffe | H99: WA | I99: 6286 | J99: 30 | K99: =Table_Household_Alloc[[#This Row],[Unit Entitlement]]/1000 -> 0.03 | L99: =J99/1000*232 -> 6.96 | M99: =CONCATENATE("Symo ",Table_Household_Alloc[[#This Row],[Export Capacity (kW)]]) -> Symo 5 | N99: =IF(Table_Household_Alloc[[#This Row],[PV Installed]]="Y",1,0)*Table_Household_Alloc[[#This Row],[Calculated Battery Allocation (kWh)]] -> 6.96 | O99: 5 | P99: Y | Q99: Y | R99: Y | S99: O | T99: 0424 205 755 | V99: timoliver33@gmail.com | X99: 45505 | Y99: Current
A100: 20 | B100: 2A | E100: Zac Webb | F100: 32 Mardo Drive | G100: Witchcliffe | H100: WA | I100: 6286 | J100: 59 | K100: =Table_Household_Alloc[[#This Row],[Unit Entitlement]]/1000 -> 0.059 | L100: =J100/1000*232 -> 13.688 | N100: =IF(Table_Household_Alloc[[#This Row],[PV Installed]]="Y",1,0)*Table_Household_Alloc[[#This Row],[Calculated Battery Allocation (kWh)]] -> 0 | S100: V | T100: 0497 685 142 | V100: waalitj_wongi@outlook.com
...

Sheet Amanda Energy
A1: Cluster | B1: Year | C1: Month | D1: Consumption_kWh | E1: Export_kWh | F1: Amanda_consumption_incl_GST | G1: Amanda_export_buyback_incl_GST | H1: Daily_Supply_incl_GST | I1: Other_Fees_incl_GST | J1: Total_incl_GST
A2: 1A | B2: 2025 | C2: 01 | D2: 33.93 | E2: 11281.06 | F2: 10.16 | G2: -434.32 | H2: 170.5 | I2: 15.54 | J2: -238.12
A3: 1A | B3: 2025 | C3: 02 | D3: 9.73 | E3: 10654.83 | F3: 2.92 | G3: -410.21 | H3: 154 | I3: 12.85 | J3: -240.45
A4: 1A | B4: 2025 | C4: 03 | D4: 41.84 | E4: 11239.82 | F4: 12.52 | G4: -432.73 | H4: 170.5 | I4: 16.76 | J4: -232.95
A5: 1B | B5: 2025 | C5: 01 | D5: 12.07 | E5: 17535.52 | F5: 3.62 | G5: -675.11 | H5: 170.5 | I5: 18.04 | J5: -482.96
A6: 1B | B6: 2025 | C6: 02 | D6: 13.33 | E6: 13942.64 | F6: 3.99 | G6: -536.79 | H6: 154 | I6: 16.57 | J6: -362.23
A7: 1B | B7: 2025 | C7: 03 | D7: 14.9 | E7: 14891.96 | F7: 4.46 | G7: -573.34 | H7: 170.5 | I7: 18.59 | J7: -379.8
A8: 1C | B8: 2025 | C8: 01 | D8: 44.48 | E8: 13074.94 | F8: 13.32 | G8: -503.38 | H8: 170.5 | I8: 22.22 | J8: -297.34
A9: 1C | B9: 2025 | C9: 02 | D9: 46.06 | E9: 12380.74 | F9: 13.78 | G9: -476.66 | H9: 154 | I9: 19.29 | J9: -289.59
A10: 1C | B10: 2025 | C10: 03 | D10: 17.99 | E10: 14328.95 | F10: 5.38 | G10: -551.66 | H10: 170.5 | I10: 19.8 | J10: -355.98
A11: 2A | B11: 2025 | C11: 01 | D11: 68.36 | E11: 9864.97 | F11: 21.46 | G11: -379.8 | H11: 178.78 | I11: 0 | J11: -179.55
A12: 2A | B12: 2025 | C12: 02 | D12: 60.15 | E12: 9289.63 | F12: 18.89 | G12: -357.64 | H12: 161.48 | I12: 0 | J12: -177.28
A13: 2B | B13: 2025 | C13: 01 | D13: 25.59 | E13: 13715.2 | F13: 8.04 | G13: -528.04 | H13: 178.78 | I13: 0 | J13: -341.22
... A24: 3C | B24: 2025 | C24: 03 | D24: 219.33 | E24: 5174.58 | F24: 68.86 | G24: -199.22 | H24: 178.78 | I24: 0 | J24: 48.42

Sheet reading-import
A1: Lot | B1: cluster | C1: Meter# | D1: 1/2/2024 | E1: 1/5/2024 | F1: 1/8/2024 | G1: 1/10/2024 | H1: 9/10/2024 | I1: 1/1/2025 | J1: 1/3/2025 | K1: 01/04/2025
A2: 1 | B2: 1A | C2: 50002845 | D2: 0 | E2: 0 | F2: 0 | H2: 0 | I2: 5 | J2: 12 | K2: 31
A3: 2 | B3: 1A | C3: 50002862 | D3: 154 | E3: 193 | F3: 200 | H3: 217 | I3: 252 | J3: 302 | K3: 342
A4: 3 | B4: 1A | C4: 50002872 | D4: 3330 | E4: 4152 | F4: 5885 | G4: 7147 | I4: 8271 | J4: 8830 | K4: 9141
A5: 4 | B5: 1A | C5: 50002869 | D5: 1658.51 | E5: 2242 | F5: 3297.66 | G5: 4012 | I5: 4542 | J5: 4855 | K5: 5037
A6: 5 | B6: 1A | C6: 50002879 | D6: 2500 | E6: 2698 | F6: 3033.57 | G6: 3287 | I6: 3545 | J6: 3673 | K6: 3743
A7: 6 | B7: 1A | C7: 50002865 | D7: 4614 | E7: 5036 | F7: 6545.69 | G7: 7860 | I7: 8639 | J7: 8918 | K7: 9246
A8: 7 | B8: 1A | C8: 50002887 | D8: 5556 | E8: 6178 | F8: 7086 | H8: 7678 | I8: 8272 | J8: 8725 | K8: 8864
A9: 8 | B9: 1A | C9: 50002846 | D9: 17 | E9: 62 | F9: 1347 | G9: 2312 | I9: 3006 | J9: 3404 | K9: 3589
A10: 9 | B10: 1A | C10: 50002885 | D10: 9455 | E10: 10505 | F10: 11763 | H10: 12689 | I10: 13606 | J10: 14226 | K10: 14595
A11: 10 | B11: 1A | C11: 50002850 | D11: 2297 | E11: 2548 | F11: 3196.09 | G11: 3549 | I11: 3930 | J11: 4324 | K11: 4514
A12: 11 | B12: 1A | C12: 50002848 | D12: 1025 | E12: 1059 | F12: 1104.64 | G12: 1138 | I12: 1173 | J12: 1194 | K12: 1203
A13: 12 | B13: 1A | C13: 50002847 | D13: 0 | E13: 0 | F13: 0 | H13: 0 | I13: 34 | J13: 42 | K13: 43
A14: 13 | B14: 1A | C14: 50002739 | D14: 3754 | E14: 4117 | F14: 4598.5 | G14: 4840 | I14: 5168 | J14: 5392 | K14: 5504
A15: 14 | B15: 1A | C15: 50002709 | D15: 0 | E15: 2 | F15: 26 | H15: 95 | I15: 213 | J15: 501 | K15: 667
A16: 15 | B16: 1A | C16: 50002714 | D16: 426 | E16: 570 | F16: 570 | H16: 571 | I16: 571 | J16: 571 | K16: 571
A17: 16 | B17: 1A | C17: 50002855 | D17: 455 | E17: 907 | F17: 1537.61 | G17: 2060 | I17: 2536 | J17: 2846 | K17: 3048
A18: 17 | B18: 1A | C18: 50002877 | D18: 11075 | E18: 12991 | F18: 16647.34 | G18: 18767 | I18: 20977 | J18: 22060 | K18: 22723
A19: 18 | B19: 1A | D19: 0 | E19: 0 | F19: 0 | H19: 0 | I19: 0 | J19: 0
A20: 19 | B20: 1A | C20: 50002864 | D20: 2270 | E20: 2483 | F20: 2819.8 | G20: 3000 | I20: 3203 | J20: 3327 | K20: 3415
A21: 20 | B21: 1A | C21: 50002710 | D21: 2601 | E21: 2781 | F21: 3120.21 | G21: 3389 | I21: 3644 | J21: 3772 | K21: 3852
A22: 21 | B22: 1A | C22: 50002719 | D22: 1225 | E22: 1316 | F22: 1471.61 | G22: 1590 | I22: 1682 | J22: 1735 | K22: 1774
A23: 22 | B23: 1A | C23: 50002876 | D23: 4040 | E23: 4239 | F23: 4589.33 | G23: 4843 | I23: 5052 | J23: 5169 | K23: 5246
A24: 23 | B24: 1A | C24: 50002860 | D24: 2297 | E24: 2429 | F24: 2786.87 | G24: 3041 | I24: 3181 | J24: 3257 | K24: 3312
A25: 24 | B25: 1A | C25: 50002649 | D25: 0 | E25: 0 | F25: 0 | H25: 18 | I25: 27 | J25: 38 | K25: 41
A26: BESS | B26: 1A | C26: 40002686 | D26: 2686.84 | E26: 14090.38 | F26: 32077.16 | G26: 44721 | I26: 59297 | J26: 67826 | K26: 73298
A27: EV | B27: 1A | C27: 40002693 | D27: 0 | E27: 209.39 | F27: 1646.88 | G27: 2831 | I27: 4535 | J27: 6152 | K27: 7172
A28: CS | B28: 1A | C28: 50002858 | D28: 2819.46 | E28: 3565.94 | F28: 4127.37 | G28: 4326 | I28: 4913 | J28: 5343 | K28: 5527
A29: DB1 | B29: 1A | C29: 40002852 | I29: 157 | J29: 166 | K29: 171
A30: DB2 | B30: 1A | C30: 40002693 | I30: 232 | J30: 251 | K30: 262
A31: 1 | B31: 1B | C31: 50003409 | D31: 4530 | E31: 4701 | F31: 5443.32 | H31: 5990.04 | I31: 6200 | J31: 6302 | K31: 6361
A32: 2 | B32: 1B | C32: 50003436 | D32: 1679 | E32: 2331 | F32: 3416.3 | H32: 3923.86 | I32: 4133 | J32: 4305 | K32: 4403
A33: 3 | B33: 1B | C33: 50004064 | D33: 594 | E33: 1137 | F33: 1765.3 | H33: 2232.7 | I33: 2521 | J33: 2701 | K33: 2809
A34: 4 | B34: 1B | C34: 50003414 | D34: 102 | E34: 114 | F34: 126 | H34: 156 | I34: 188 | J34: 268 | K34: 330
A35: 5 | B35: 1B | C35: 50003389 | D35: 10220 | E35: 10700 | F35: 11494.07 | H35: 12012.6 | I35: 12384 | J35: 12657 | K35: 12840
A36: 6 | B36: 1B | C36: 50002969 | D36: 3937 | E36: 4341 | F36: 5453.28 | H36: 6621.05 | I36: 7108 | J36: 7388 | K36: 7527
A37: 7 | B37: 1B | C37: 50002951 | D37: 6063 | E37: 6514 | F37: 7105.58 | H37: 8010.78 | I37: 8532 | J37: 8816 | K37: 8960
A38: 8 | B38: 1B | C38: 50002959 | D38: 2378 | E38: 3049 | F38: 3644.67 | H38: 4022.29 | I38: 4410 | J38: 4764 | K38: 5114
A39: 9 | B39: 1B | D39: 0 | E39: 0 | F39: 0
A40: 10 | B40: 1B | C40: 50003420 | D40: 4776 | E40: 5124 | F40: 5898.31 | H40: 6484.91 | I40: 6876 | J40: 7104 | K40: 7203
A41: 11 | B41: 1B | C41: 50003410 | D41: 14777 | E41: 15333 | F41: 17203.61 | H41: 19213.57 | I41: 20006 | J41: 20313 | K41: 20514
A42: 12 | B42: 1B | C42: 50003418 | D42: 4054 | E42: 4380 | F42: 4732.36 | H42: 5001.61 | I42: 5260 | J42: 5448 | K42: 5560
A43: 13 | B43: 1B | C43: 50002859 | D43: 7149 | E43: 7632 | F43: 8977 | H43: 10306.98 | I43: 10946 | J43: 11250 | K43: 11518
A44: 14 | B44: 1B | C44: 50003396 | D44: 183 | E44: 1359 | F44: 3065.4 | H44: 4143.62 | I44: 4820 | J44: 5206 | K44: 5473
A45: 15 | B45: 1B | C45: 50003401 | D45: 3807 | E45: 4051 | F45: 4461.85 | H45: 4721.91 | I45: 4892 | J45: 5040 | K45: 5128
A46: 16 | B46: 1B | C46: 50003430 | D46: 5421 | E46: 5869 | F46: 6394.51 | H46: 6882.04 | I46: 7246 | J46: 7493 | K46: 7636
A47: 17 | B47: 1B | C47: 50003415 | D47: 4584 | E47: 4804 | F47: 5098 | H47: 5177 | I47: 5345 | J47: 5548 | K47: 5629
A48: 18 | B48: 1B | C48: 50002895 | D48: 2598 | E48: 4059 | F48: 5447 | H48: 6402 | I48: 7710 | J48: 8339 | K48: 8574
A49: 19 | B49: 1B | C49: 50003432 | D49: 2943 | E49: 3111 | F49: 3336.82 | H49: 3477.55 | I49: 3621 | J49: 3734 | K49: 3797
A50: 20 | B50: 1B | C50: 50002972 | D50: 7692 | E50: 8257 | F50: 9309.98 | H50: 10030.08 | I50: 10535 | J50: 10841 | K50: 11032
A51: 21 | B51: 1B | C51: 50002650 | D51: 8532 | E51: 9362 | F51: 10850.49 | H51: 11951.93 | I51: 12589 | J51: 13063 | K51: 13391
A52: BESS | B52: 1B | C52: 40002670 | D52: 2994.53 | E52: 16774.87 | F52: 36287.57 | H52: 53456 | I52: 65774 | J52: 73412 | K52: 78445
A53: EV | B53: 1B | C53: 40002667 | D53: 0 | E53: 573.98 | F53: 2192.17 | H53: 2917.32 | I53: 4038 | J53: 4645 | K53: 5054
A54: CS | B54: 1B | C54: 50003399 | D54: 2962.64 | E54: 4507 | F54: 5116.63 | H54: 5851.25 | I54: 7136 | J54: 8127 | K54: 8705
A55: DB1 | B55: 1B | I55: 129 | J55: 129 | K55: 129
A56: DB2 | B56: 1B | I56: 204 | J56: 204 | K56: 204
A57: 1 | B57: 1C | C57: 50003397 | D57: 6177 | E57: 6575 | F57: 7272.25 | H57: 7838.17 | I57: 8252 | J57: 8549 | K57: 8745
A58: 2 | B58: 1C | C58: 50003402 | D58: 2694 | E58: 2919 | F58: 3307.24 | H58: 3594.1 | I58: 3795 | J58: 3940 | K58: 4028
A59: 3 | B59: 1C | C59: 50003431 | D59: 1847 | E59: 2157 | F59: 2635.52 | H59: 2961.07 | I59: 3227 | J59: 3414 | K59: 3513
A60: 4 | B60: 1C | C60: 50003394 | D60: 1137 | E60: 1399 | F60: 1985.58 | H60: 2578.83 | I60: 2811 | J60: 2944 | K60: 3033
A61: 5 | B61: 1C | C61: 50003433 | D61: 3232 | E61: 4074 | F61: 4889.35 | H61: 5089.98 | I61: 6084 | J61: 6727 | K61: 6998
A62: 6 | B62: 1C | C62: 50003421 | D62: 3268 | E62: 3601 | F62: 4367.83 | H62: 5046.41 | I62: 5469 | J62: 5726 | K62: 5889
A63: 7 | B63: 1C | C63: 50002953 | D63: 119 | E63: 134 | F63: 144 | H63: 160 | I63: 164 | J63: 164 | K63: 166
A64: 8 | B64: 1C | C64: 50003395 | D64: 9469 | E64: 9976 | F64: 10886 | H64: 11948.49 | I64: 12726 | J64: 13095 | K64: 13279
A65: 9 | B65: 1C | C65: 50003435 | D65: 0 | F65: 0 | H65: 5 | I65: 76 | J65: 135 | K65: 158
A66: 10 | B66: 1C | C66: 50002952 | D66: 5326 | E66: 5685 | F66: 6174.26 | H66: 6481.42 | I66: 6735 | J66: 6900 | K66: 6989
A67: 11 | B67: 1C | C67: 50002944 | D67: 0 | E67: 0 | F67: 7 | H67: 24 | I67: 36 | J67: 149 | K67: 149
A68: 12 | B68: 1C | C68: 3308026898 | D68: 5 | E68: 145 | F68: 644 | H68: 1411.81 | I68: 1704.76 | J68: 1835.49 | K68: 1900.16
A69: 13 | B69: 1C | C69: 50003424 | D69: 4602 | E69: 4723 | F69: 5053.76 | H69: 5542.59 | I69: 6030 | J69: 6168 | K69: 6221
A70: 14 | B70: 1C | C70: 50003438 | D70: 10279 | E70: 10681 | F70: 11670.13 | H70: 12371.82 | I70: 12736 | J70: 13010 | K70: 13164
A71: 15 | B71: 1C | C71: 50003404 | D71: 4850 | E71: 5295 | F71: 5967.28 | H71: 6566.27 | I71: 7111 | J71: 7404 | K71: 7561
A72: 16 | B72: 1C | C72: 50003419 | D72: 4762 | E72: 5338 | F72: 6243.76 | H72: 6963.45 | I72: 7360 | J72: 7627 | K72: 7763
A73: 17 | B73: 1C | C73: 50003428 | D73: 6 | E73: 14 | F73: 48 | H73: 195 | I73: 227 | J73: 279 | K73: 586
A74: 18 | B74: 1C | C74: 50002935 | D74: 0 | F74: 881.37 | H74: 2710.92 | I74: 4379 | J74: 5697 | K74: 6007
A75: 19 | B75: 1C | C75: 50003417 | D75: 6873 | E75: 7464 | F75: 8646.84 | H75: 9744.86 | I75: 10411 | J75: 10756 | K75: 10951
A76: BESS | B76: 1C | C76: 40002722 | D76: 1886.05 | E76: 11537.28 | F76: 24413.85 | H76: 36340.52 | I76: 42252 | J76: 47738 | K76: 50626
A77: EV | B77: 1C | C77: 40002728 | D77: 0 | E77: 0 | F77: 0 | H77: 0 | I77: 7349 | J77: 9137 | K77: 10363
A78: CS | B78: 1C | C78: 50003429 | D78: 1885.1 | E78: 2434.68 | F78: 2817.94 | H78: 3213.91 | I78: 3640 | J78: 4070 | K78: 4295
A79: DB1 | B79: 1C | C79: 50003406 | I79: 149 | J79: 162 | K79: 168
A80: DB2 | B80: 1C | C80: 50003408 | I80: 128 | J80: 143 | K80: 151
A81: 1 | B81: 2A | C81: 50002920 | E81: 0 | G81: 7 | I81: 17 | K81: 42
A82: 2 | B82: 2A | C82: 50002903 | E82: 3112 | G82: 3903 | I82: 4264 | J82: 4504 | K82: 4655
A83: 3 | B83: 2A | E83: 0 | G83: 0
A84: 4 | B84: 2A | E84: 0 | G84: 0
A85: 5 | B85: 2A | C85: 50002911 | E85: 3539 | G85: 6860 | I85: 7368 | J85: 7592 | K85: 7728
A86: 6 | B86: 2A | E86: 0 | G86: 0
A87: 7 | B87: 2A | E87: 0 | G87: 0 | K87: 0
A88: 8 | B88: 2A | E88: 0 | G88: 0
A89: 9 | B89: 2A | C89: 50002909 | E89: 11631 | G89: 16215 | I89: 18671 | J89: 20407 | K89: 21306
A90: 10 | B90: 2A | E90: 0 | G90: 0
A91: 11 | B91: 2A | E91: 0 | G91: 0
A92: 12 | B92: 2A | C92: 50002897 | E92: 5181 | G92: 6991 | I92: 7897 | J92: 8462 | K92: 8807
A93: 13 | B93: 2A | C93: 50002839 | E93: 1740 | G93: 3194 | I93: 3610 | J93: 3840 | K93: 3997
A94: 14 | B94: 2A | C94: 50002863 | E94: 1157 | G94: 2480 | I94: 2707 | J94: 2843 | K94: 2927
A95: 15 | B95: 2A | C95: 50002947 | E95: 131 | G95: 1108 | I95: 1489 | J95: 1726 | K95: 1885
A96: 16 | B96: 2A | E96: 0 | G96: 0
A97: 17 | B97: 2A | C97: 50002902 | E97: 1331 | G97: 2233 | I97: 2464 | J97: 2630 | K97: 2713
A98: 18 | B98: 2A | C98: 50002950 | E98: 1201 | G98: 2088 | I98: 2302 | J98: 2449 | K98: 2527
A99: 19 | B99: 2A | C99: 50002936 | E99: 1265 | G99: 3040 | I99: 3568 | J99: 3832 | K99: 4004
A100: 20 | B100: 2A | E100: 0 | G100: 0
...

Sheet reading-export
A1: Lot | B1: cluster | C1: Meter# | D1: 1/2/2024 | E1: 1/5/2024 | F1: 1/8/2024 | G1: 1/10/2024 | H1: 9/10/2024 | I1: 1/1/2025 | J1: 1/3/2025 | K1: 01/04/2025 | L1: 01/05/2025
A2: 1 | B2: 1A | C2: 50002845 | D2: 0 | E2: 0 | J2: 0
A3: 2 | B3: 1A | C3: 50002862 | D3: 0 | E3: 0 | J3: 0
A4: 3 | B4: 1A | C4: 50002872 | D4: 0 | E4: 0 | G4: 0 | I4: 0 | J4: 0 | K4: 0
A5: 4 | B5: 1A | C5: 50002869 | D5: 1100 | E5: 3828 | F5: 5318.8 | G5: 6465 | I5: 9031 | J5: 10612 | K5: 11476
A6: 5 | B6: 1A | C6: 50002879 | D6: 4250 | E6: 7203 | F6: 8765.43 | G6: 10052 | I6: 12884 | J6: 14647 | K6: 15571
A7: 6 | B7: 1A | C7: 50002865 | D7: 5911 | E7: 10438 | F7: 12556.76 | G7: 14094 | I7: 18121 | J7: 20965 | K7: 22324
A8: 7 | B8: 1A | C8: 50002887 | D8: 0 | E8: 0 | J8: 0
A9: 8 | B9: 1A | C9: 50002846 | D9: 0 | E9: 0 | G9: 0 | I9: 2569 | J9: 4165 | K9: 5027
A10: 9 | B10: 1A | C10: 50002885 | D10: 0 | E10: 0 | J10: 0
A11: 10 | B11: 1A | D11: 12347 | E11: 15095 | F11: 16643.58 | G11: 17815 | I11: 20316 | J11: 21130 | K11: 22009
A12: 11 | B12: 1A | C12: 50002848 | D12: 13447 | E12: 16509 | F12: 18262.11 | G12: 19650 | I12: 22593 | J12: 24391 | K12: 25470
A13: 12 | B13: 1A | C13: 50002847 | D13: 0 | E13: 0 | J13: 0
A14: 13 | B14: 1A | C14: 50002739 | D14: 25717 | E14: 30627 | F14: 33475.85 | G14: 36023 | I14: 41072 | J14: 44319 | K14: 46143
A15: 14 | B15: 1A | C15: 50002709 | D15: 0 | E15: 0 | J15: 2399 | K15: 3999
A16: 15 | B16: 1A | C16: 50002714 | D16: 0 | E16: 0 | J16: 0
A17: 16 | B17: 1A | C17: 50002855 | D17: 0 | E17: 2568 | F17: 4134.29 | G17: 5245 | I17: 7804 | J17: 9378 | K17: 10186
A18: 17 | B18: 1A | C18: 50002877 | D18: 4293 | E18: 7088 | F18: 8027 | G18: 9059 | I18: 12029 | J18: 14003 | K18: 14923
A19: 18 | B19: 1A | D19: 0 | E19: 0 | J19: 0
A20: 19 | B20: 1A | C20: 50002864 | D20: 26703 | E20: 32368 | F20: 35423.8 | G20: 38020 | I20: 43757 | J20: 47349 | K20: 49180
A21: 20 | B21: 1A | C21: 50002710 | D21: 3903 | E21: 6356 | F21: 7464.47 | G21: 8589 | I21: 11511 | J21: 13341 | K21: 14162
A22: 21 | B22: 1A | C22: 50002719 | D22: 4515 | E22: 7478 | F22: 9166.34 | G22: 10489 | I22: 13350 | J22: 15149 | K22: 16096
A23: 22 | B23: 1A | C23: 50002876 | D23: 4040 | E23: 6783 | F23: 8314.63 | G23: 9617 | I23: 12269 | J23: 13938 | K23: 14832
A24: 23 | B24: 1A | C24: 50002860 | D24: 5498 | E24: 8307 | F24: 9976.39 | G24: 11307 | I24: 14010 | J24: 15720 | K24: 16609
A25: 24 | B25: 1A | C25: 50002649 | D25: 0 | E25: 0 | J25: 0
A26: BESS | B26: 1A | C26: 40002686 | D26: 1833.14 | E26: 11017.34 | F26: 26071.13 | G26: 36413 | I26: 48306 | J26: 55361 | K26: 59831
A27: EV | B27: 1A | C27: 40002693 | D27: 0 | E27: 0 | F27: 0 | K27: 0
A28: CS | B28: 1A | C28: 50002858 | D28: 0 | E28: 0 | F28: 0 | G28: 0 | I28: 0 | J28: 0 | K28: 0
A29: DB1 | B29: 1A | C29: 40002852
A30: DB2 | B30: 1A | C30: 40002693
A31: 1 | B31: 1B | C31: 50003409 | D31: 3498 | E31: 5938 | F31: 7210.69 | H31: 8291.68 | I31: 10303 | J31: 11728 | K31: 12488
A32: 2 | B32: 1B | C32: 50003436 | D32: 265 | E32: 4070 | F32: 5442.96 | H32: 7233.44 | I32: 11104 | J32: 13586 | K32: 14779
A33: 3 | B33: 1B | C33: 50004064 | D33: 0 | E33: 0 | F33: 684.6 | H33: 1696.37 | I33: 3777 | J33: 5275 | K33: 5973
A34: 4 | B34: 1B | C34: 50003414 | D34: 0 | E34: 0 | F34: 458 | H34: 1460.91 | I34: 4228 | J34: 5871 | K34: 6615
A35: 5 | B35: 1B | C35: 50003389 | D35: 5814 | E35: 9155 | F35: 10239.42 | H35: 11614.69 | I35: 15198 | J35: 17553 | K35: 18600
A36: 6 | B36: 1B | C36: 50002969 | D36: 854 | E36: 4535 | F36: 5754.6 | H36: 7410.18 | I36: 11083 | J36: 13497 | K36: 14615
A37: 7 | B37: 1B | C37: 50002951 | D37: 3559 | E37: 5963 | F37: 7249.59 | H37: 8203.86 | I37: 10036 | J37: 11379 | K37: 12093
A38: 8 | B38: 1B | C38: 50002959 | D38: 17 | E38: 2480 | F38: 3838.25 | H38: 5415.75 | I38: 8407 | J38: 10346 | K38: 11149
A39: 9 | B39: 1B | D39: 0 | E39: 0 | F39: 0
A40: 10 | B40: 1B | C40: 50003420 | D40: 12138 | E40: 14501 | F40: 15561 | H40: 16512.4 | I40: 18452 | J40: 19803 | K40: 20554
A41: 11 | B41: 1B | C41: 50003410 | D41: 3886 | E41: 7001 | F41: 8634.89 | H41: 9978.43 | I41: 12683 | J41: 14556 | K41: 15620
A42: 12 | B42: 1B | C42: 50003418 | D42: 7374 | E42: 12649 | F42: 15529.02 | H42: 18068.36 | I42: 22544 | J42: 25441 | K42: 26958
A43: 13 | B43: 1B | C43: 50002859 | D43: 7339 | E43: 12702 | F43: 15409 | H43: 17371.93 | I43: 21569 | J43: 24315 | K43: 25704
A44: 14 | B44: 1B | C44: 50003396 | D44: 0 | E44: 2 | F44: 1827.01 | H44: 4120.68 | I44: 8268 | J44: 10948 | K44: 12390
A45: 15 | B45: 1B | C45: 50003401 | D45: 3840 | E45: 6062 | F45: 6901.57 | H45: 7887.39 | I45: 10135 | J45: 11621 | K45: 12299
A46: 16 | B46: 1B | C46: 50003430 | D46: 3504 | E46: 6007 | F46: 7399.42 | H46: 8490.27 | I46: 10472 | J46: 11911 | K46: 12675
A47: 17 | B47: 1B | C47: 50003415 | D47: 10794 | E47: 12766 | F47: 13535 | H47: 14606 | I47: 16887 | J47: 18209 | K47: 18878
A48: 18 | B48: 1B | C48: 50002895 | D48: 0 | E48: 0 | F48: 0 | H48: 0 | J48: 702 | K48: 1345
A49: 19 | B49: 1B | C49: 50003432 | D49: 3403 | E49: 5961 | F49: 7410.45 | H49: 8570.52 | I49: 10481 | J49: 11806 | K49: 12573
A50: 20 | B50: 1B | C50: 50002972 | D50: 24099 | E50: 29256 | F50: 31484.53 | H50: 33564.89 | I50: 37964 | J50: 40923 | K50: 42471
A51: 21 | B51: 1B | C51: 50002650 | D51: 24156 | E51: 28297 | F51: 29924.37 | H51: 31896.88 | I51: 36318 | J51: 39181 | K51: 40534
A52: BESS | B52: 1B | C52: 40002670 | D52: 2093.81 | E52: 13451.22 | F52: 29901.46 | H52: 44114.54 | I52: 53961 | J52: 60162 | K52: 64245
A53: EV | B53: 1B | C53: 40002667 | D53: 0 | E53: 0 | F53: 0 | H53: 0 | I53: 0 | J53: 0 | K53: 0
A54: CS | B54: 1B | C54: 50003399 | D54: 0 | E54: 0 | F54: 0 | H54: 0 | I54: 0 | J54: 0 | K54: 0
A55: DB1 | B55: 1B
A56: DB2 | B56: 1B
A57: 1 | B57: 1C | C57: 50003397 | D57: 22466 | E57: 26592 | F57: 28434.59 | H57: 30242.14 | I57: 33585 | J57: 36147 | K57: 37477
A58: 2 | B58: 1C | C58: 50003402 | D58: 7976 | E58: 10495 | F58: 11875.44 | H58: 13112.99 | I58: 15113 | J58: 16602 | K58: 17462
A59: 3 | B59: 1C | C59: 50003431 | D59: 8104 | E59: 11934 | F59: 13449.26 | H59: 15190.17 | I59: 18755 | J59: 21422 | K59: 22749
A60: 4 | B60: 1C | C60: 50003394 | D60: 5365 | E60: 7545 | F60: 8389.8 | H60: 9245.87 | I60: 11256 | J60: 12825 | K60: 13492
A61: 5 | B61: 1C | C61: 50003433 | D61: 23221 | E61: 26772 | F61: 28547.9 | H61: 29022.8 | I61: 34752 | J61: 37400 | K61: 38690
A62: 6 | B62: 1C | C62: 50003421 | D62: 1616 | E62: 6999 | F62: 9599.41 | H62: 11712.14 | I62: 15827 | J62: 18997 | K62: 20723
A63: 7 | B63: 1C | C63: 50002953 | D63: 141 | E63: 141 | F63: 141 | H63: 141 | I63: 142 | J63: 142 | K63: 142
A64: 8 | B64: 1C | C64: 50003395 | D64: 27333 | E64: 32684 | F64: 35790 | H64: 38188.55 | I64: 41841 | J64: 44296 | K64: 46064
A65: 9 | B65: 1C | C65: 50003435 | D65: 0
A66: 10 | B66: 1C | C66: 50002952 | D66: 3264 | E66: 5676 | F66: 7004.47 | H66: 8189.7 | I66: 10088 | J66: 11546 | K66: 12402
A67: 11 | B67: 1C | C67: 50002944 | D67: 0
A68: 12 | B68: 1C | C68: 3308026898 | D68: 0 | E68: 0 | F68: 187.42 | H68: 1255.9 | I68: 3279.89 | J68: 4812.19 | K68: 5683.79
A69: 13 | B69: 1C | C69: 50003424 | D69: 3791 | E69: 6015 | F69: 7169 | H69: 7899.89 | I69: 9864 | J69: 11307 | K69: 12061
A70: 14 | B70: 1C | C70: 50003438 | D70: 5315 | E70: 5695 | F70: 6442.82 | H70: 7320.62 | I70: 9306 | J70: 10855 | K70: 11592
A71: 15 | B71: 1C | C71: 50003404 | D71: 5083 | E71: 9362 | F71: 11609.07 | H71: 13649.03 | I71: 16919 | J71: 19466 | K71: 20916
A72: 16 | B72: 1C | C72: 50003419 | D72: 7655 | E72: 13525 | F72: 16903.4 | H72: 19713.42 | I72: 24215 | J72: 27788 | K72: 29752
A73: 17 | B73: 1C | C73: 50003428 | D73: 0
A74: 18 | B74: 1C | C74: 50002935 | D74: 0 | F74: 1 | H74: 705.36 | I74: 4017 | J74: 5995 | K74: 7545
A75: 19 | B75: 1C | C75: 50003417 | D75: 10388 | E75: 15762 | F75: 18813.23 | H75: 21239.96 | I75: 25220 | J75: 28182 | K75: 29966
A76: BESS | B76: 1C | C76: 40002722 | D76: 1185.25 | E76: 8547.62 | F76: 19040.97 | H76: 29007.26 | I76: 33894 | J76: 38471 | K76: 40865
A77: EV | B77: 1C | C77: 40002728 | D77: 0 | E77: 0 | F77: 0 | H77: 0
A78: CS | B78: 1C | C78: 50003429 | D78: 0 | E78: 0 | F78: 0 | H78: 0 | I78: 0 | J78: 0 | K78: 0
A79: DB1 | B79: 1C | C79: 50003406
A80: DB2 | B80: 1C | C80: 50003408
A81: 1 | B81: 2A | E81: 0 | G81: 0
A82: 2 | B82: 2A | C82: 50002903 | E82: 9441 | G82: 14105 | I82: 18618 | J82: 21526 | K82: 23084
A83: 3 | B83: 2A | E83: 0 | G83: 0
A84: 4 | B84: 2A | E84: 0 | G84: 0
A85: 5 | B85: 2A | C85: 50002911 | E85: 2 | G85: 3604 | I85: 7727 | J85: 10460 | K85: 12017
A86: 6 | B86: 2A | E86: 0 | G86: 0
A87: 7 | B87: 2A | E87: 0 | G87: 0
A88: 8 | B88: 2A | E88: 0 | G88: 0
A89: 9 | B89: 2A | E89: 2249 | G89: 4489 | I89: 6566 | J89: 7871 | K89: 8616
A90: 10 | B90: 2A | E90: 0 | G90: 0
A91: 11 | B91: 2A | E91: 0 | G91: 0
A92: 12 | B92: 2A | C92: 50002897 | E92: 3431 | G92: 8948 | I92: 14259 | J92: 17674 | K92: 19526
A93: 13 | B93: 2A | C93: 50002839 | E93: 7 | G93: 602 | I93: 4288 | J93: 6624 | K93: 7752
A94: 14 | B94: 2A | C94: 50002863 | E94: 0 | G94: 1026 | I94: 3860 | J94: 5667 | K94: 6631
A95: 15 | B95: 2A | C95: 50002947 | E95: 377 | G95: 2687 | I95: 5304 | J95: 7046 | K95: 7940
A96: 16 | B96: 2A | E96: 0 | G96: 0
A97: 17 | B97: 2A | C97: 50002902 | E97: 0 | G97: 469 | I97: 3363 | J97: 5183 | K97: 6184
A98: 18 | B98: 2A | C98: 50002950 | E98: 0 | G98: 455 | I98: 1434 | J98: 2524 | K98: 3517
A99: 19 | B99: 2A | C99: 50002936 | E99: 0 | G99: 784 | I99: 3488 | J99: 5300
A100: 20 | B100: 2A | E100: 0 | G100: 0
...

Sheet Tariff Rates
B1: P2P Charge Rate (Inc. GST) | C1: P2P Export Rate (Inc. GST) | D1: Common Charge Rate (Inc. GST) | E1: Grid Import Rate (Inc. GST) | F1: Grid Export Rate (Inc. GST) | G1: EV Charger Sale to consumer Rate (Inc. GST) | H1: Chargefox Commission take on EV Consumption % (Inc. GST) | I1: Chargefox Commission (Inc GST) | J1: P2P Energy Invasion Charge (Inc. GST) | K1: P2P Energy Borrow Revenue (Inc. GST) | L1: P2P rate for lots with no export (Inc. GST)
A2: c/kWh | B2: 22 | C2: -22 | D2: 22 | E2: 30 | F2: =-3.5*1.1 -> -3.85 | G2: -65 | H2: -0.05 | I2: =-G2*H2 -> -3.25 | J2: 2 | K2: -2 | L2: 36
A3: $/kWh | B3: =B2/100 -> 0.22 | C3: =C2/100 -> -0.22 | D3: =D2/100 -> 0.22 | E3: 0.3 | F3: =F2/100 -> -0.0385 | G3: =G2/100 -> -0.65 | H3: -0.05 | I3: =I2/100 -> -0.0325 | J3: =J2/100 -> 0.02 | K3: =K2/100 -> -0.02 | L3: =L2/100 -> 0.36
B6: SwitchdIn Cost ($ inc. GST) | C6: Chargefox Daily Supply Charge/cluster | D6: Element47 Embedded Network Daily Supply Charges
A7: $/yr | B7: 55 | C7: 858 | D7: 80.3
A8: $/day | B8: =B7/365 -> 0.15068493 | C8: =C7/365 -> 2.3506849 | D8: =D7/365 -> 0.22
B10: Element47 Invoicing Fee
A11: $/Invoice | B11: 1.1

Sheet Energy billing Mastersheet_fml
B1: 1C | C1: billing period | F1: =DATE(2025,F2,1) -> 45658 | H1: =DATE(2025,H2+1,0) -> 45747
F2: 01 | G2: 02 | H2: 03
C3: Number of Days | F3: =DAY(DATE(2024,F2+1,0)) -> 31 | G3: =DAY(DATE(2024,G2+1,0)) -> 29 | H3: =DAY(DATE(2024,H2+1,0)) -> 31 | I3: =N3 -> 90 | J3: =N3 -> 90 | K3: =N3 -> 90 | L3: =N3 -> 90 | M3: 1 | N3: =H1-F1+1 -> 90 | P3: Import data | R3: Consumption Energy | AE3: Battery Loss and common services | AQ3: Export data | BK3: EV Charger Reconcillation | BQ3: Combined
A4: Lot | B4: Name | C4: Meter Numbers | D4: Percentage of Unit Entitlement (%) | E4: Stage of Dev. | F4: Amanda Energy Daily Supply Charge ($) | G4: Amanda Energy Daily Supply Charge ($)2 | H4: Amanda Energy Daily Supply Charge ($)3 | I4: Amanda Energy Other fees ($) | J4: SwitchdIn Cost Daily Supply Charge ($) | K4: Chargefox Daily Supply Charge ($) | L4: Element47 Embedded Network Daily Supply Charges | M4: Element47 Embedded Network Invoicing Fees | N4: Total supply | O4: 1st day of reporting period: import | P4: Last day of reporting period: import | Q4: Total Consumption Import (kWh) | R4: Total Daily Average Consumptio for Billing Period (kWh) | S4: Percentage of Total Import for Billing Period (%) | T4: Daily Battery allowance based on UE% (kWh) | U4: Applicable Battery Allowance Daily Consumption (kWh) | V4: Unused Daily Allowance (kWh) | W4: Unused Daily Allowance % | X4: P2P Import Consumption within Battery Allowance(kWh) | Y4: Energy Exceeding Battery Allowance (kWh) | Z4: Energy Exceeding Battery Allowance % | AA4: Total Cluster Energy Balance for P2P Trading (kWh) | AB4: P2P Import Consumption over Battery Allowance based on Energy Exceeding Allowance % (kWh) | AC4: Total P2P import (kWh) | AD4: Energy Import from Grid (kWh) | AE4: P2P import% | AF4: Cluster's Total Battery Loss (kWh) | AG4: Axillary Battery Losses based upon P2P import % (kWh) | AH4: Cluster's Total Common Services (kWh) | AI4: Common Services based on Split per Unit Entitlement % to battery (kWh) | AJ4: Axillary Battery Loss Charges at P2P Rates based upon P2P import % ($) | AK4: Common Services Cost Split per Unit Entitlement at P2P rate ($) | AL4: P2P Import Cost ($) | AM4: Exceeding Battery Allowance P2P Fee ($) | AN4: Import From Grid Cost ($) | AO4: Total Consumption Cost/Lot | AP4: 1st day of reporting period: export | AQ4: Last day of reporting period: export | AR4: Total Lot Export (kWh) | AS4: Percentage of Total export for Billing Period (%) | AT4: Total Energy Export P2P to battery (kWh) | AU4: Total Cluster Energy Balance for P2P Trading (kWh)2 | AV4: Borrowed Allowance Based on Unused Daily Allowance % (kWh) | AW4: Axillary Battery Losses based upon Adjusted % total export (kWh) | AX4: Common Service based upon % total export to battery (kWh) | AY4: EV Charger based upon % total export to battery (kWh) | AZ4: Therotical Energy Export to Grid (kWh) | BA4: Energy Losses When Export to Grid (kWh) | BB4: Energy Losses When Export to Grid based up % total export (kWh) | BC4: Energy Export to Grid after Losses (kWh) | BD4: Axillary Battery Losses based upon % total export ($) | BE4: Common Service Earning based upon % total export to Load ($) | BF4: EV Charger based upon % total export ($) | BG4: P2P Export Earnings ($) | BH4: Passive Compensation ($) | BI4: Grid Export Earnings ($) | BJ4: Total Export Earnings Per Lot After P2P Battery Energy Storage and Use ($) | BK4: EV Charger Income from Sales Equitable Distribution on UE ($) | BL4: Chargefox Commission on EV Charge Consumption Sales Cost Split by Unit Entitlement ($) | BM4: EV Charger Cost of Electricity Supply at P2P Rates ($) | BN4: Total EV Charger Operating Cost ($) | BO4: Total EV Charger Revenue ($) | BP4: EV Charger Profit per lot owner ($) | BQ4: Energy Invoice Total Charges or Revenue $ | BR4: Date issued | BS4: Date Paid | BT4: Lot
A5: 1 | B5: {=INDEX(Table_Household_Alloc[Owner],MATCH(1,(Table_Household_Alloc[Lot]=A5)*(Table_Household_Alloc[cluster]=$B$1),0))} -> Aron Dyer Jodie Passmore | C5: {=INDEX(Reading_import[Meter'#],MATCH(1,(Table_Household_Alloc[Lot]=A5)*(Table_Household_Alloc[cluster]=$B$1),0))} -> 50003397 | D5: {=INDEX(Table_Household_Alloc[UE % over Cluster],MATCH(1,(Table_Household_Alloc[Lot]=A5)*(Table_Household_Alloc[cluster]=$B$1),0))} -> 0.042 | E5: {=INDEX(Table_Household_Alloc[Stage of Dev.],MATCH(1,(Table_Household_Alloc[Lot]=A5)*(Table_Household_Alloc[cluster]=$B$1),0))} -> O | F5: {=INDEX(Amanda_energy[Daily_Supply_incl_GST],MATCH(1,(Amanda_energy[Cluster]=$B$1)*(Amanda_energy[Month]=$F$2),0))/MAX($A:$A)} -> 8.9736842 | G5: {=INDEX(Amanda_energy[Daily_Supply_incl_GST],MATCH(1,(Amanda_energy[Cluster]=$B$1)*(Amanda_energy[Month]=$G$2),0))/MAX($A:$A)} -> 8.1052632 | H5: {=INDEX(Amanda_energy[Daily_Supply_incl_GST],MATCH(1,(Amanda_energy[Cluster]=$B$1)*(Amanda_energy[Month]=$H$2),0))/MAX($A:$A)} -> 8.9736842 | I5: =$J$38/MAX($A:$A) -> 3.2268421 | J5: ='Tariff Rates'!$B$8*$J$3 -> 13.561644 | K5: ='Tariff Rates'!$C$8*Table1[[#This Row],[Percentage of Unit Entitlement (%)]]*'Energy billing Mastersheet_fml'!$K$3 -> 8.885589 | L5: =$L$3*'Tariff Rates'!$D$8*IF(Table1[[#This Row],[Stage of Dev.]]="V",0,1) -> 19.8 | M5: 1.1 | N5: =SUM(F5:M5) -> 72.626707 | O5: {=INDEX(Reading_import[1/1/2025],MATCH(1,(Reading_import[Lot]=A5)*(Reading_import[cluster]=$B$1),0))} -> 8252 | P5: {=INDEX(Reading_import[01/04/2025],MATCH(1,(Reading_import[Lot]=A5)*(Reading_import[cluster]=$B$1),0))} -> 8745 | Q5: =Table1[[#This Row],[Last day of reporting period: import]]-Table1[[#This Row],[1st day of reporting period: import]] -> 493 | R5: =Q5/$N$3 -> 5.4777778 | S5: =Q5/$Q$30 -> 0.063478574 | T5: =IF(Table1[[#This Row],[Stage of Dev.]]="V",0,233*Table1[[#This Row],[Percentage of Unit Entitlement (%)]]) -> 9.786 | U5: =IF(T5>R5,R5,T5) -> 5.4777778 | V5: =Table1[[#This Row],[Daily Battery allowance based on UE% (kWh)]]-Table1[[#This Row],[Applicable Battery Allowance Daily Consumption (kWh)]] -> 4.3082222 | W5: =Table1[[#This Row],[Unused Daily Allowance (kWh)]]/$V$30 -> 0.028968962 | X5: =IF(Table1[[#This Row],[Applicable Battery Allowance Daily Consumption (kWh)]]>Table1[[#This Row],[Total Daily Average Consumptio for Billing Period (kWh)]],Table1[[#This Row],[Total Consumption Import (kWh)]],U5*$N$3) -> 493 | Y5: =IF(Table1[[#This Row],[Applicable Battery Allowance Daily Consumption (kWh)]]>0,ABS(Q5-X5),0) -> 0 | Z5: =IFERROR(Table1[[#This Row],[Energy Exceeding Battery Allowance (kWh)]]/$Y$30,0) -> 0 | AA5: =IF($Y$30-$E$38>0,$Y$30-$E$38,0) -> 72.54 | AB5: =IFERROR(Table1[[#This Row],[Total Cluster Energy Balance for P2P Trading (kWh)]]*Table1[[#This Row],[Energy Exceeding Battery Allowance %]],0) -> 0 | AC5: =Table1[[#This Row],[P2P Import Consumption within Battery Allowance(kWh)]]+Table1[[#This Row],[P2P Import Consumption over Battery Allowance based on Energy Exceeding Allowance % (kWh)]] -> 493 | AD5: =Table1[[#This Row],[Total Consumption Import (kWh)]]-Table1[[#This Row],[Total P2P import (kWh)]] -> 0 | AE5: =IFERROR(Table1[[#This Row],[Total P2P import (kWh)]]/$AC$30,0) -> 0.064378215 | AF5: =($Q$24-$AR$24) -> 1403 | AG5: =AF5*AE5 -> 90.322635 | AH5: =SUM($Q$26:$Q$28) -> 697 | AI5: =Table1[[#This Row],[Cluster''s Total Common Services (kWh)]]*Table1[[#This Row],[Percentage of Unit Entitlement (%)]] -> 29.274 | AJ5: =AG5*'Tariff Rates'!$B$3 -> 19.87098 | AK5: =Table1[[#This Row],[Common Services based on Split per Unit Entitlement % to battery (kWh)]]*'Tariff Rates'!$B$3 -> 6.44028 | AL5: =Table1[[#This Row],[Total P2P import (kWh)]]*IF(Table1[[#This Row],[Total Lot Export (kWh)]]=0,'Tariff Rates'!$L$3,'Tariff Rates'!$B$3) -> 108.46 | AM5: =Table1[[#This Row],[P2P Import Consumption over Battery Allowance based on Energy Exceeding Allowance % (kWh)]]*'Tariff Rates'!$J$3 -> 0 | AN5: =Table1[[#This Row],[Energy Import from Grid (kWh)]]*'Tariff Rates'!$E$3 -> 0 | AO5: =SUM(AJ5:AN5) -> 134.77126 | AP5: {=INDEX(Reading_export[1/1/2025],MATCH(1,(Reading_export[Lot]=A5)*(Reading_export[cluster]=$B$1),0))} -> 33585 | AQ5: {=INDEX(Reading_export[01/04/2025],MATCH(1,(Reading_export[Lot]=A5)*(Reading_export[cluster]=$B$1),0))} -> 37477 | AR5: =Table1[[#This Row],[Last day of reporting period: export]]-Table1[[#This Row],[1st day of reporting period: export]] -> 3892 | AS5: =AR5/$AR$30 -> 0.074081265 | AT5: =Table1[[#This Row],[Percentage of Total export for Billing Period (%)]]*$AC$30 -> 567.3047 | AU5: =IF($Y$30-$E$38>0,$Y$30-$E$38,0) -> 72.54 | AV5: =IFERROR(Table1[[#This Row],[Total Cluster Energy Balance for P2P Trading (kWh)2]]*Table1[[#This Row],[Unused Daily Allowance %]],0) -> 2.1014085 | AW5: =AS5*AF5 -> 103.93601 | AX5: =Table1[[#This Row],[Cluster''s Total Common Services (kWh)]]*Table1[[#This Row],[Percentage of Total export for Billing Period (%)]] -> 51.634642 | AY5: =$Q$25*Table1[[#This Row],[Percentage of Total export for Billing Period (%)]] -> 223.28093 | AZ5: =Table1[[#This Row],[Total Lot Export (kWh)]]-Table1[[#This Row],[Total Energy Export P2P to battery (kWh)]]-Table1[[#This Row],[Axillary Battery Losses based upon Adjusted % total export (kWh)]]-Table1[[#This Row],[Common Service based upon % total export to battery (kWh)]]-Table1[[#This Row],[EV Charger based upon % total export to battery (kWh)]] -> 2945.8437 | BA5: =IFERROR(IF($AZ$30-$F$38>0,$AZ$30-$F$38,0),0) -> 0 | BB5: =Table1[[#This Row],[Energy Losses When Export to Grid (kWh)]]*Table1[[#This Row],[Percentage of Total export for Billing Period (%)]] -> 0 | BC5: =Table1[[#This Row],[Therotical Energy Export to Grid (kWh)]]-Table1[[#This Row],[Energy Losses When Export to Grid based up % total export (kWh)]] -> 2945.8437 | BD5: =AW5*'Tariff Rates'!$C$3 -> -22.865923 | BE5: =Table1[[#This Row],[Common Service based upon % total export to battery (kWh)]]*'Tariff Rates'!$C$3 -> -11.359621 | BF5: =Table1[[#This Row],[EV Charger based upon % total export to battery (kWh)]]*'Tariff Rates'!$C$3 -> -49.121805 | BG5: =AT5*'Tariff Rates'!$C$3 -> -124.80703 | BH5: =Table1[[#This Row],[Borrowed Allowance Based on Unused Daily Allowance % (kWh)]]*'Tariff Rates'!$K$3 -> -0.04202817 | BI5: =BC5*'Tariff Rates'!$F$3 -> -113.41498 | BJ5: =SUM(BD5:BI5) -> -321.61139 | BK5: =$D$43*Table1[[#This Row],[Percentage of Unit Entitlement (%)]] -> 0 | BL5: =BK5*'Tariff Rates'!$H$3 -> 0 | BM5: =($Q$25)*Table1[[#This Row],[Percentage of Unit Entitlement (%)]]*'Tariff Rates'!$B$3 -> 27.84936 | BN5: =SUM(BM5,BL5) -> 27.84936 | BO5: =BK5 -> 0 | BP5: =BO5+BN5 -> 27.84936 | BQ5: =AO5+BJ5+N5+BP5 -> -86.364067 | BT5: 1
A6: 2 | B6: {=INDEX(Table_Household_Alloc[Owner],MATCH(1,(Table_Household_Alloc[Lot]=A6)*(Table_Household_Alloc[cluster]=$B$1),0))} -> Eli Sutton | C6: {=INDEX(Reading_import[Meter'#],MATCH(1,(Table_Household_Alloc[Lot]=A6)*(Table_Household_Alloc[cluster]=$B$1),0))} -> 50003402 | D6: {=INDEX(Table_Household_Alloc[UE % over Cluster],MATCH(1,(Table_Household_Alloc[Lot]=A6)*(Table_Household_Alloc[cluster]=$B$1),0))} -> 0.043 | E6: {=INDEX(Table_Household_Alloc[Stage of Dev.],MATCH(1,(Table_Household_Alloc[Lot]=A6)*(Table_Household_Alloc[cluster]=$B$1),0))} -> O | F6: {=INDEX(Amanda_energy[Daily_Supply_incl_GST],MATCH(1,(Amanda_energy[Cluster]=$B$1)*(Amanda_energy[Month]=$F$2),0))/MAX($A:$A)} -> 8.9736842 | G6: {=INDEX(Amanda_energy[Daily_Supply_incl_GST],MATCH(1,(Amanda_energy[Cluster]=$B$1)*(Amanda_energy[Month]=$G$2),0))/MAX($A:$A)} -> 8.1052632 | H6: {=INDEX(Amanda_energy[Daily_Supply_incl_GST],MATCH(1,(Amanda_energy[Cluster]=$B$1)*(Amanda_energy[Month]=$H$2),0))/MAX($A:$A)} -> 8.9736842 | I6: =$J$38/MAX($A:$A) -> 3.2268421 | J6: ='Tariff Rates'!$B$8*$J$3 -> 13.561644 | K6: ='Tariff Rates'!$C$8*Table1[[#This Row],[Percentage of Unit Entitlement (%)]]*'Energy billing Mastersheet_fml'!$K$3 -> 9.0971507 | L6: =$L$3*'Tariff Rates'!$D$8*IF(Table1[[#This Row],[Stage of Dev.]]="V",0,1) -> 19.8 | M6: 1.1 | N6: =SUM(F6:M6) -> 72.838268 | O6: {=INDEX(Reading_import[1/1/2025],MATCH(1,(Reading_import[Lot]=A6)*(Reading_import[cluster]=$B$1),0))} -> 3795 | P6: {=INDEX(Reading_import[01/04/2025],MATCH(1,(Reading_import[Lot]=A6)*(Reading_import[cluster]=$B$1),0))} -> 4028 | Q6: =Table1[[#This Row],[Last day of reporting period: import]]-Table1[[#This Row],[1st day of reporting period: import]] -> 233 | R6: =Q6/$N$3 -> 2.5888889 | S6: =Q6/$Q$30 -> 0.03000103 | T6: =IF(Table1[[#This Row],[Stage of Dev.]]="V",0,233*Table1[[#This Row],[Percentage of Unit Entitlement (%)]]) -> 10.019 | U6: =IF(T6>R6,R6,T6) -> 2.5888889 | V6: =Table1[[#This Row],[Daily Battery allowance based on UE% (kWh)]]-Table1[[#This Row],[Applicable Battery Allowance Daily Consumption (kWh)]] -> 7.4301111 | W6: =Table1[[#This Row],[Unused Daily Allowance (kWh)]]/$V$30 -> 0.049960888 | X6: =IF(Table1[[#This Row],[Applicable Battery Allowance Daily Consumption (kWh)]]>Table1[[#This Row],[Total Daily Average Consumptio for Billing Period (kWh)]],Table1[[#This Row],[Total Consumption Import (kWh)]],U6*$N$3) -> 233 | Y6: =IF(Table1[[#This Row],[Applicable Battery Allowance Daily Consumption (kWh)]]>0,ABS(Q6-X6),0) -> 0 | Z6: =IFERROR(Table1[[#This Row],[Energy Exceeding Battery Allowance (kWh)]]/$Y$30,0) -> 0 | AA6: =IF($Y$30-$E$38>0,$Y$30-$E$38,0) -> 72.54 | AB6: =IFERROR(Table1[[#This Row],[Total Cluster Energy Balance for P2P Trading (kWh)]]*Table1[[#This Row],[Energy Exceeding Battery Allowance %]],0) -> 0 | AC6: =Table1[[#This Row],[P2P Import Consumption within Battery Allowance(kWh)]]+Table1[[#This Row],[P2P Import Consumption over Battery Allowance based on Energy Exceeding Allowance % (kWh)]] -> 233 | AD6: =Table1[[#This Row],[Total Consumption Import (kWh)]]-Table1[[#This Row],[Total P2P import (kWh)]] -> 0 | AE6: =IFERROR(Table1[[#This Row],[Total P2P import (kWh)]]/$AC$30,0) -> 0.030426215 | AF6: =($Q$24-$AR$24) -> 1403 | AG6: =AF6*AE6 -> 42.68798 | AH6: =SUM($Q$26:$Q$28) -> 697 | AI6: =Table1[[#This Row],[Cluster''s Total Common Services (kWh)]]*Table1[[#This Row],[Percentage of Unit Entitlement (%)]] -> 29.971 | AJ6: =AG6*'Tariff Rates'!$B$3 -> 9.3913556 | AK6: =Table1[[#This Row],[Common Services based on Split per Unit Entitlement % to battery (kWh)]]*'Tariff Rates'!$B$3 -> 6.59362 | AL6: =Table1[[#This Row],[Total P2P import (kWh)]]*IF(Table1[[#This Row],[Total Lot Export (kWh)]]=0,'Tariff Rates'!$L$3,'Tariff Rates'!$B$3) -> 51.26 | AM6: =Table1[[#This Row],[P2P Import Consumption over Battery Allowance based on Energy Exceeding Allowance % (kWh)]]*'Tariff Rates'!$J$3 -> 0 | AN6: =Table1[[#This Row],[Energy Import from Grid (kWh)]]*'Tariff Rates'!$E$3 -> 0 | AO6: =SUM(AJ6:AN6) -> 67.244976 | AP6: {=INDEX(Reading_export[1/1/2025],MATCH(1,(Reading_export[Lot]=A6)*(Reading_export[cluster]=$B$1),0))} -> 15113 | AQ6: {=INDEX(Reading_export[01/04/2025],MATCH(1,(Reading_export[Lot]=A6)*(Reading_export[cluster]=$B$1),0))} -> 17462 | AR6: =Table1[[#This Row],[Last day of reporting period: export]]-Table1[[#This Row],[1st day of reporting period: export]] -> 2349 | AS6: =AR6/$AR$30 -> 0.044711431 | AT6: =Table1[[#This Row],[Percentage of Total export for Billing Period (%)]]*$AC$30 -> 342.39433 | AU6: =IF($Y$30-$E$38>0,$Y$30-$E$38,0) -> 72.54 | AV6: =IFERROR(Table1[[#This Row],[Total Cluster Energy Balance for P2P Trading (kWh)2]]*Table1[[#This Row],[Unused Daily Allowance %]],0) -> 3.6241628 | AW6: =AS6*AF6 -> 62.730138 | AX6: =Table1[[#This Row],[Cluster''s Total Common Services (kWh)]]*Table1[[#This Row],[Percentage of Total export for Billing Period (%)]] -> 31.163868 | AY6: =$Q$25*Table1[[#This Row],[Percentage of Total export for Billing Period (%)]] -> 134.76025 | AZ6: =Table1[[#This Row],[Total Lot Export (kWh)]]-Table1[[#This Row],[Total Energy Export P2P to battery (kWh)]]-Table1[[#This Row],[Axillary Battery Losses based upon Adjusted % total export (kWh)]]-Table1[[#This Row],[Common Service based upon % total export to battery (kWh)]]-Table1[[#This Row],[EV Charger based upon % total export to battery (kWh)]] -> 1777.9514 | BA6: =IFERROR(IF($AZ$30-$F$38>0,$AZ$30-$F$38,0),0) -> 0 | BB6: =Table1[[#This Row],[Energy Losses When Export to Grid (kWh)]]*Table1[[#This Row],[Percentage of Total export for Billing Period (%)]] -> 0 | BC6: =Table1[[#This Row],[Therotical Energy Export to Grid (kWh)]]-Table1[[#This Row],[Energy Losses When Export to Grid based up % total export (kWh)]] -> 1777.9514 | BD6: =AW6*'Tariff Rates'!$C$3 -> -13.80063 | BE6: =Table1[[#This Row],[Common Service based upon % total export to battery (kWh)]]*'Tariff Rates'!$C$3 -> -6.8560509 | BF6: =Table1[[#This Row],[EV Charger based upon % total export to battery (kWh)]]*'Tariff Rates'!$C$3 -> -29.647256 | BG6: =AT6*'Tariff Rates'!$C$3 -> -75.326752 | BH6: =Table1[[#This Row],[Borrowed Allowance Based on Unused Daily Allowance % (kWh)]]*'Tariff Rates'!$K$3 -> -0.072483256 | BI6: =BC6*'Tariff Rates'!$F$3 -> -68.451129 | BJ6: =SUM(BD6:BI6) -> -194.1543 | BK6: =$D$43*Table1[[#This Row],[Percentage of Unit Entitlement (%)]] -> 0 | BL6: =BK6*'Tariff Rates'!$H$3 -> 0 | BM6: =($Q$25)*Table1[[#This Row],[Percentage of Unit Entitlement (%)]]*'Tariff Rates'!$B$3 -> 28.51244 | BN6: =SUM(BM6,BL6) -> 28.51244 | BO6: =BK6 -> 0 | BP6: =BO6+BN6 -> 28.51244 | BQ6: =AO6+BJ6+N6+BP6 -> -25.558618 | BT6: 2
A7: 3 | B7: {=INDEX(Table_Household_Alloc[Owner],MATCH(1,(Table_Household_Alloc[Lot]=A7)*(Table_Household_Alloc[cluster]=$B$1),0))} -> Shelley Chapman Cherry Chapman | C7: {=INDEX(Reading_import[Meter'#],MATCH(1,(Table_Household_Alloc[Lot]=A7)*(Table_Household_Alloc[cluster]=$B$1),0))} -> 50003431 | D7: {=INDEX(Table_Household_Alloc[UE % over Cluster],MATCH(1,(Table_Household_Alloc[Lot]=A7)*(Table_Household_Alloc[cluster]=$B$1),0))} -> 0.044 | E7: {=INDEX(Table_Household_Alloc[Stage of Dev.],MATCH(1,(Table_Household_Alloc[Lot]=A7)*(Table_Household_Alloc[cluster]=$B$1),0))} -> O | F7: {=INDEX(Amanda_energy[Daily_Supply_incl_GST],MATCH(1,(Amanda_energy[Cluster]=$B$1)*(Amanda_energy[Month]=$F$2),0))/MAX($A:$A)} -> 8.9736842 | G7: {=INDEX(Amanda_energy[Daily_Supply_incl_GST],MATCH(1,(Amanda_energy[Cluster]=$B$1)*(Amanda_energy[Month]=$G$2),0))/MAX($A:$A)} -> 8.1052632 | H7: {=INDEX(Amanda_energy[Daily_Supply_incl_GST],MATCH(1,(Amanda_energy[Cluster]=$B$1)*(Amanda_energy[Month]=$H$2),0))/MAX($A:$A)} -> 8.9736842 | I7: =$J$38/MAX($A:$A) -> 3.2268421 | J7: ='Tariff Rates'!$B$8*$J$3 -> 13.561644 | K7: ='Tariff Rates'!$C$8*Table1[[#This Row],[Percentage of Unit Entitlement (%)]]*'Energy billing Mastersheet_fml'!$K$3 -> 9.3087123 | L7: =$L$3*'Tariff Rates'!$D$8*IF(Table1[[#This Row],[Stage of Dev.]]="V",0,1) -> 19.8 | M7: 1.1 | N7: =SUM(F7:M7) -> 73.04983 | O7: {=INDEX(Reading_import[1/1/2025],MATCH(1,(Reading_import[Lot]=A7)*(Reading_import[cluster]=$B$1),0))} -> 3227 | P7: {=INDEX(Reading_import[01/04/2025],MATCH(1,(Reading_import[Lot]=A7)*(Reading_import[cluster]=$B$1),0))} -> 3513 | Q7: =Table1[[#This Row],[Last day of reporting period: import]]-Table1[[#This Row],[1st day of reporting period: import]] -> 286 | R7: =Q7/$N$3 -> 3.1777778 | S7: =Q7/$Q$30 -> 0.036825299 | T7: =IF(Table1[[#This Row],[Stage of Dev.]]="V",0,233*Table1[[#This Row],[Percentage of Unit Entitlement (%)]]) -> 10.252 | U7: =IF(T7>R7,R7,T7) -> 3.1777778 | V7: =Table1[[#This Row],[Daily Battery allowance based on UE% (kWh)]]-Table1[[#This Row],[Applicable Battery Allowance Daily Consumption (kWh)]] -> 7.0742222 | W7: =Table1[[#This Row],[Unused Daily Allowance (kWh)]]/$V$30 -> 0.047567852 | X7: =IF(Table1[[#This Row],[Applicable Battery Allowance Daily Consumption (kWh)]]>Table1[[#This Row],[Total Daily Average Consumptio for Billing Period (kWh)]],Table1[[#This Row],[Total Consumption Import (kWh)]],U7*$N$3) -> 286 | Y7: =IF(Table1[[#This Row],[Applicable Battery Allowance Daily Consumption (kWh)]]>0,ABS(Q7-X7),0) -> 0 | Z7: =IFERROR(Table1[[#This Row],[Energy Exceeding Battery Allowance (kWh)]]/$Y$30,0) -> 0 | AA7: =IF($Y$30-$E$38>0,$Y$30-$E$38,0) -> 72.54 | AB7: =IFERROR(Table1[[#This Row],[Total Cluster Energy Balance for P2P Trading (kWh)]]*Table1[[#This Row],[Energy Exceeding Battery Allowance %]],0) -> 0 | AC7: =Table1[[#This Row],[P2P Import Consumption within Battery Allowance(kWh)]]+Table1[[#This Row],[P2P Import Consumption over Battery Allowance based on Energy Exceeding Allowance % (kWh)]] -> 286 | AD7: =Table1[[#This Row],[Total Consumption Import (kWh)]]-Table1[[#This Row],[Total P2P import (kWh)]] -> 0 | AE7: =IFERROR(Table1[[#This Row],[Total P2P import (kWh)]]/$AC$30,0) -> 0.0373472 | AF7: =($Q$24-$AR$24) -> 1403 | AG7: =AF7*AE7 -> 52.398121 | AH7: =SUM($Q$26:$Q$28) -> 697 | AI7: =Table1[[#This Row],[Cluster''s Total Common Services (kWh)]]*Table1[[#This Row],[Percentage of Unit Entitlement (%)]] -> 30.668 | AJ7: =AG7*'Tariff Rates'!$B$3 -> 11.527587 | AK7: =Table1[[#This Row],[Common Services based on Split per Unit Entitlement % to battery (kWh)]]*'Tariff Rates'!$B$3 -> 6.74696 | AL7: =Table1[[#This Row],[Total P2P import (kWh)]]*IF(Table1[[#This Row],[Total Lot Export (kWh)]]=0,'Tariff Rates'!$L$3,'Tariff Rates'!$B$3) -> 62.92 | AM7: =Table1[[#This Row],[P2P Import Consumption over Battery Allowance based on Energy Exceeding Allowance % (kWh)]]*'Tariff Rates'!$J$3 -> 0 | AN7: =Table1[[#This Row],[Energy Import from Grid (kWh)]]*'Tariff Rates'!$E$3 -> 0 | AO7: =SUM(AJ7:AN7) -> 81.194547 | AP7: {=INDEX(Reading_export[1/1/2025],MATCH(1,(Reading_export[Lot]=A7)*(Reading_export[cluster]=$B$1),0))} -> 18755 | AQ7: {=INDEX(Reading_export[01/04/2025],MATCH(1,(Reading_export[Lot]=A7)*(Reading_export[cluster]=$B$1),0))} -> 22749 | AR7: =Table1[[#This Row],[Last day of reporting period: export]]-Table1[[#This Row],[1st day of reporting period: export]] -> 3994 | AS7: =AR7/$AR$30 -> 0.076022757 | AT7: =Table1[[#This Row],[Percentage of Total export for Billing Period (%)]]*$AC$30 -> 582.17239 | AU7: =IF($Y$30-$E$38>0,$Y$30-$E$38,0) -> 72.54 | AV7: =IFERROR(Table1[[#This Row],[Total Cluster Energy Balance for P2P Trading (kWh)2]]*Table1[[#This Row],[Unused Daily Allowance %]],0) -> 3.450572 | AW7: =AS7*AF7 -> 106.65993 | AX7: =Table1[[#This Row],[Cluster''s Total Common Services (kWh)]]*Table1[[#This Row],[Percentage of Total export for Billing Period (%)]] -> 52.987862 | AY7: =$Q$25*Table1[[#This Row],[Percentage of Total export for Billing Period (%)]] -> 229.13259 | AZ7: =Table1[[#This Row],[Total Lot Export (kWh)]]-Table1[[#This Row],[Total Energy Export P2P to battery (kWh)]]-Table1[[#This Row],[Axillary Battery Losses based upon Adjusted % total export (kWh)]]-Table1[[#This Row],[Common Service based upon % total export to battery (kWh)]]-Table1[[#This Row],[EV Charger based upon % total export to battery (kWh)]] -> 3023.0472 | BA7: =IFERROR(IF($AZ$30-$F$38>0,$AZ$30-$F$38,0),0) -> 0 | BB7: =Table1[[#This Row],[Energy Losses When Export to Grid (kWh)]]*Table1[[#This Row],[Percentage of Total export for Billing Period (%)]] -> 0 | BC7: =Table1[[#This Row],[Therotical Energy Export to Grid (kWh)]]-Table1[[#This Row],[Energy Losses When Export to Grid based up % total export (kWh)]] -> 3023.0472 | BD7: =AW7*'Tariff Rates'!$C$3 -> -23.465184 | BE7: =Table1[[#This Row],[Common Service based upon % total export to battery (kWh)]]*'Tariff Rates'!$C$3 -> -11.65733 | BF7: =Table1[[#This Row],[EV Charger based upon % total export to battery (kWh)]]*'Tariff Rates'!$C$3 -> -50.40917 | BG7: =AT7*'Tariff Rates'!$C$3 -> -128.07793 | BH7: =Table1[[#This Row],[Borrowed Allowance Based on Unused Daily Allowance % (kWh)]]*'Tariff Rates'!$K$3 -> -0.06901144 | BI7: =BC7*'Tariff Rates'!$F$3 -> -116.38732 | BJ7: =SUM(BD7:BI7) -> -330.06594 | BK7: =$D$43*Table1[[#This Row],[Percentage of Unit Entitlement (%)]] -> 0 | BL7: =BK7*'Tariff Rates'!$H$3 -> 0 | BM7: =($Q$25)*Table1[[#This Row],[Percentage of Unit Entitlement (%)]]*'Tariff Rates'!$B$3 -> 29.17552 | BN7: =SUM(BM7,BL7) -> 29.17552 | BO7: =BK7 -> 0 | BP7: =BO7+BN7 -> 29.17552 | BQ7: =AO7+BJ7+N7+BP7 -> -146.64604 | BT7: 3
A8: 4 | B8: {=INDEX(Table_Household_Alloc[Owner],MATCH(1,(Table_Household_Alloc[Lot]=A8)*(Table_Household_Alloc[cluster]=$B$1),0))} -> Jillian Ann Luckhurst | C8: {=INDEX(Reading_import[Meter'#],MATCH(1,(Table_Household_Alloc[Lot]=A8)*(Table_Household_Alloc[cluster]=$B$1),0))} -> 50003394 | D8: {=INDEX(Table_Household_Alloc[UE % over Cluster],MATCH(1,(Table_Household_Alloc[Lot]=A8)*(Table_Household_Alloc[cluster]=$B$1),0))} -> 0.045 | E8: {=INDEX(Table_Household_Alloc[Stage of Dev.],MATCH(1,(Table_Household_Alloc[Lot]=A8)*(Table_Household_Alloc[cluster]=$B$1),0))} -> O | F8: {=INDEX(Amanda_energy[Daily_Supply_incl_GST],MATCH(1,(Amanda_energy[Cluster]=$B$1)*(Amanda_energy[Month]=$F$2),0))/MAX($A:$A)} -> 8.9736842 | G8: {=INDEX(Amanda_energy[Daily_Supply_incl_GST],MATCH(1,(Amanda_energy[Cluster]=$B$1)*(Amanda_energy[Month]=$G$2),0))/MAX($A:$A)} -> 8.1052632 | H8: {=INDEX(Amanda_energy[Daily_Supply_incl_GST],MATCH(1,(Amanda_energy[Cluster]=$B$1)*(Amanda_energy[Month]=$H$2),0))/MAX($A:$A)} -> 8.9736842 | I8: =$J$38/MAX($A:$A) -> 3.2268421 | J8: ='Tariff Rates'!$B$8*$J$3 -> 13.561644 | K8: ='Tariff Rates'!$C$8*Table1[[#This Row],[Percentage of Unit Entitlement (%)]]*'Energy billing Mastersheet_fml'!$K$3 -> 9.520274 | L8: =$L$3*'Tariff Rates'!$D$8*IF(Table1[[#This Row],[Stage of Dev.]]="V",0,1) -> 19.8 | M8: 1.1 | N8: =SUM(F8:M8) -> 73.261391 | O8: {=INDEX(Reading_import[1/1/2025],MATCH(1,(Reading_import[Lot]=A8)*(Reading_import[cluster]=$B$1),0))} -> 2811 | P8: {=INDEX(Reading_import[01/04/2025],MATCH(1,(Reading_import[Lot]=A8)*(Reading_import[cluster]=$B$1),0))} -> 3033 | Q8: =Table1[[#This Row],[Last day of reporting period: import]]-Table1[[#This Row],[1st day of reporting period: import]] -> 222 | R8: =Q8/$N$3 -> 2.4666667 | S8: =Q8/$Q$30 -> 0.028584672 | T8: =IF(Table1[[#This Row],[Stage of Dev.]]="V",0,233*Table1[[#This Row],[Percentage of Unit Entitlement (%)]]) -> 10.485 | U8: =IF(T8>R8,R8,T8) -> 2.4666667 | V8: =Table1[[#This Row],[Daily Battery allowance based on UE% (kWh)]]-Table1[[#This Row],[Applicable Battery Allowance Daily Consumption (kWh)]] -> 8.0183333 | W8: =Table1[[#This Row],[Unused Daily Allowance (kWh)]]/$V$30 -> 0.053916159 | X8: =IF(Table1[[#This Row],[Applicable Battery Allowance Daily Consumption (kWh)]]>Table1[[#This Row],[Total Daily Average Consumptio for Billing Period (kWh)]],Table1[[#This Row],[Total Consumption Import (kWh)]],U8*$N$3) -> 222 | Y8: =IF(Table1[[#This Row],[Applicable Battery Allowance Daily Consumption (kWh)]]>0,ABS(Q8-X8),0) -> 0 | Z8: =IFERROR(Table1[[#This Row],[Energy Exceeding Battery Allowance (kWh)]]/$Y$30,0) -> 0 | AA8: =IF($Y$30-$E$38>0,$Y$30-$E$38,0) -> 72.54 | AB8: =IFERROR(Table1[[#This Row],[Total Cluster Energy Balance for P2P Trading (kWh)]]*Table1[[#This Row],[Energy Exceeding Battery Allowance %]],0) -> 0 | AC8: =Table1[[#This Row],[P2P Import Consumption within Battery Allowance(kWh)]]+Table1[[#This Row],[P2P Import Consumption over Battery Allowance based on Energy Exceeding Allowance % (kWh)]] -> 222 | AD8: =Table1[[#This Row],[Total Consumption Import (kWh)]]-Table1[[#This Row],[Total P2P import (kWh)]] -> 0 | AE8: =IFERROR(Table1[[#This Row],[Total P2P import (kWh)]]/$AC$30,0) -> 0.028989784 | AF8: =($Q$24-$AR$24) -> 1403 | AG8: =AF8*AE8 -> 40.672667 | AH8: =SUM($Q$26:$Q$28) -> 697 | AI8: =Table1[[#This Row],[Cluster''s Total Common Services (kWh)]]*Table1[[#This Row],[Percentage of Unit Entitlement (%)]] -> 31.365 | AJ8: =AG8*'Tariff Rates'!$B$3 -> 8.9479868 | AK8: =Table1[[#This Row],[Common Services based on Split per Unit Entitlement % to battery (kWh)]]*'Tariff Rates'!$B$3 -> 6.9003 | AL8: =Table1[[#This Row],[Total P2P import (kWh)]]*IF(Table1[[#This Row],[Total Lot Export (kWh)]]=0,'Tariff Rates'!$L$3,'Tariff Rates'!$B$3) -> 48.84 | AM8: =Table1[[#This Row],[P2P Import Consumption over Battery Allowance based on Energy Exceeding Allowance % (kWh)]]*'Tariff Rates'!$J$3 -> 0 | AN8: =Table1[[#This Row],[Energy Import from Grid (kWh)]]*'Tariff Rates'!$E$3 -> 0 | AO8: =SUM(AJ8:AN8) -> 64.688287 | AP8: {=INDEX(Reading_export[1/1/2025],MATCH(1,(Reading_export[Lot]=A8)*(Reading_export[cluster]=$B$1),0))} -> 11256 | AQ8: {=INDEX(Reading_export[01/04/2025],MATCH(1,(Reading_export[Lot]=A8)*(Reading_export[cluster]=$B$1),0))} -> 13492 | AR8: =Table1[[#This Row],[Last day of reporting period: export]]-Table1[[#This Row],[1st day of reporting period: export]] -> 2236 | AS8: =AR8/$AR$30 -> 0.042560562 | AT8: =Table1[[#This Row],[Percentage of Total export for Billing Period (%)]]*$AC$30 -> 325.92325 | AU8: =IF($Y$30-$E$38>0,$Y$30-$E$38,0) -> 72.54 | AV8: =IFERROR(Table1[[#This Row],[Total Cluster Energy Balance for P2P Trading (kWh)2]]*Table1[[#This Row],[Unused Daily Allowance %]],0) -> 3.9110782 | AW8: =AS8*AF8 -> 59.712469 | AX8: =Table1[[#This Row],[Cluster''s Total Common Services (kWh)]]*Table1[[#This Row],[Percentage of Total export for Billing Period (%)]] -> 29.664712 | AY8: =$Q$25*Table1[[#This Row],[Percentage of Total export for Billing Period (%)]] -> 128.27753 | AZ8: =Table1[[#This Row],[Total Lot Export (kWh)]]-Table1[[#This Row],[Total Energy Export P2P to battery (kWh)]]-Table1[[#This Row],[Axillary Battery Losses based upon Adjusted % total export (kWh)]]-Table1[[#This Row],[Common Service based upon % total export to battery (kWh)]]-Table1[[#This Row],[EV Charger based upon % total export to battery (kWh)]] -> 1692.422 | BA8: =IFERROR(IF($AZ$30-$F$38>0,$AZ$30-$F$38,0),0) -> 0 | BB8: =Table1[[#This Row],[Energy Losses When Export to Grid (kWh)]]*Table1[[#This Row],[Percentage of Total export for Billing Period (%)]] -> 0 | BC8: =Table1[[#This Row],[Therotical Energy Export to Grid (kWh)]]-Table1[[#This Row],[Energy Losses When Export to Grid based up % total export (kWh)]] -> 1692.422 | BD8: =AW8*'Tariff Rates'!$C$3 -> -13.136743 | BE8: =Table1[[#This Row],[Common Service based upon % total export to battery (kWh)]]*'Tariff Rates'!$C$3 -> -6.5262366 | BF8: =Table1[[#This Row],[EV Charger based upon % total export to battery (kWh)]]*'Tariff Rates'!$C$3 -> -28.221058 | BG8: =AT8*'Tariff Rates'!$C$3 -> -71.703116 | BH8: =Table1[[#This Row],[Borrowed Allowance Based on Unused Daily Allowance % (kWh)]]*'Tariff Rates'!$K$3 -> -0.078221564 | BI8: =BC8*'Tariff Rates'!$F$3 -> -65.158248 | BJ8: =SUM(BD8:BI8) -> -184.82362 | BK8: =$D$43*Table1[[#This Row],[Percentage of Unit Entitlement (%)]] -> 0 | BL8: =BK8*'Tariff Rates'!$H$3 -> 0 | BM8: =($Q$25)*Table1[[#This Row],[Percentage of Unit Entitlement (%)]]*'Tariff Rates'!$B$3 -> 29.8386 | BN8: =SUM(BM8,BL8) -> 29.8386 | BO8: =BK8 -> 0 | BP8: =BO8+BN8 -> 29.8386 | BQ8: =AO8+BJ8+N8+BP8 -> -17.035344 | BT8: 4
A9: 5 | B9: {=INDEX(Table_Household_Alloc[Owner],MATCH(1,(Table_Household_Alloc[Lot]=A9)*(Table_Household_Alloc[cluster]=$B$1),0))} -> Samuel Vinciullo | C9: {=INDEX(Reading_import[Meter'#],MATCH(1,(Table_Household_Alloc[Lot]=A9)*(Table_Household_Alloc[cluster]=$B$1),0))} -> 50003433 | D9: {=INDEX(Table_Household_Alloc[UE % over Cluster],MATCH(1,(Table_Household_Alloc[Lot]=A9)*(Table_Household_Alloc[cluster]=$B$1),0))} -> 0.046 | E9: {=INDEX(Table_Household_Alloc[Stage of Dev.],MATCH(1,(Table_Household_Alloc[Lot]=A9)*(Table_Household_Alloc[cluster]=$B$1),0))} -> O | F9: {=INDEX(Amanda_energy[Daily_Supply_incl_GST],MATCH(1,(Amanda_energy[Cluster]=$B$1)*(Amanda_energy[Month]=$F$2),0))/MAX($A:$A)} -> 8.9736842 | G9: {=INDEX(Amanda_energy[Daily_Supply_incl_GST],MATCH(1,(Amanda_energy[Cluster]=$B$1)*(Amanda_energy[Month]=$G$2),0))/MAX($A:$A)} -> 8.1052632 | H9: {=INDEX(Amanda_energy[Daily_Supply_incl_GST],MATCH(1,(Amanda_energy[Cluster]=$B$1)*(Amanda_energy[Month]=$H$2),0))/MAX($A:$A)} -> 8.9736842 | I9: =$J$38/MAX($A:$A) -> 3.2268421 | J9: ='Tariff Rates'!$B$8*$J$3 -> 13.561644 | K9: ='Tariff Rates'!$C$8*Table1[[#This Row],[Percentage of Unit Entitlement (%)]]*'Energy billing Mastersheet_fml'!$K$3 -> 9.7318356 | L9: =$L$3*'Tariff Rates'!$D$8*IF(Table1[[#This Row],[Stage of Dev.]]="V",0,1) -> 19.8 | M9: 1.1 | N9: =SUM(F9:M9) -> 73.472953 | O9: {=INDEX(Reading_import[1/1/2025],MATCH(1,(Reading_import[Lot]=A9)*(Reading_import[cluster]=$B$1),0))} -> 6084 | P9: {=INDEX(Reading_import[01/04/2025],MATCH(1,(Reading_import[Lot]=A9)*(Reading_import[cluster]=$B$1),0))} -> 6998 | Q9: =Table1[[#This Row],[Last day of reporting period: import]]-Table1[[#This Row],[1st day of reporting period: import]] -> 914 | R9: =Q9/$N$3 -> 10.155556 | S9: =Q9/$Q$30 -> 0.11768644 | T9: =IF(Table1[[#This Row],[Stage of Dev.]]="V",0,233*Table1[[#This Row],[Percentage of Unit Entitlement (%)]]) -> 10.718 | U9: =IF(T9>R9,R9,T9) -> 10.155556 | V9: =Table1[[#This Row],[Daily Battery allowance based on UE% (kWh)]]-Table1[[#This Row],[Applicable Battery Allowance Daily Consumption (kWh)]] -> 0.56244444 | W9: =Table1[[#This Row],[Unused Daily Allowance (kWh)]]/$V$30 -> 0.0037819386 | X9: =IF(Table1[[#This Row],[Applicable Battery Allowance Daily Consumption (kWh)]]>Table1[[#This Row],[Total Daily Average Consumptio for Billing Period (kWh)]],Table1[[#This Row],[Total Consumption Import (kWh)]],U9*$N$3) -> 914 | Y9: =IF(Table1[[#This Row],[Applicable Battery Allowance Daily Consumption (kWh)]]>0,ABS(Q9-X9),0) -> 0 | Z9: =IFERROR(Table1[[#This Row],[Energy Exceeding Battery Allowance (kWh)]]/$Y$30,0) -> 0 | AA9: =IF($Y$30-$E$38>0,$Y$30-$E$38,0) -> 72.54 | AB9: =IFERROR(Table1[[#This Row],[Total Cluster Energy Balance for P2P Trading (kWh)]]*Table1[[#This Row],[Energy Exceeding Battery Allowance %]],0) -> 0 | AC9: =Table1[[#This Row],[P2P Import Consumption within Battery Allowance(kWh)]]+Table1[[#This Row],[P2P Import Consumption over Battery Allowance based on Energy Exceeding Allowance % (kWh)]] -> 914 | AD9: =Table1[[#This Row],[Total Consumption Import (kWh)]]-Table1[[#This Row],[Total P2P import (kWh)]] -> 0 | AE9: =IFERROR(Table1[[#This Row],[Total P2P import (kWh)]]/$AC$30,0) -> 0.11935434 | AF9: =($Q$24-$AR$24) -> 1403 | AG9: =AF9*AE9 -> 167.45414 | AH9: =SUM($Q$26:$Q$28) -> 697 | AI9: =Table1[[#This Row],[Cluster''s Total Common Services (kWh)]]*Table1[[#This Row],[Percentage of Unit Entitlement (%)]] -> 32.062 | AJ9: =AG9*'Tariff Rates'!$B$3 -> 36.83991 | AK9: =Table1[[#This Row],[Common Services based on Split per Unit Entitlement % to battery (kWh)]]*'Tariff Rates'!$B$3 -> 7.05364 | AL9: =Table1[[#This Row],[Total P2P import (kWh)]]*IF(Table1[[#This Row],[Total Lot Export (kWh)]]=0,'Tariff Rates'!$L$3,'Tariff Rates'!$B$3) -> 201.08 | AM9: =Table1[[#This Row],[P2P Import Consumption over Battery Allowance based on Energy Exceeding Allowance % (kWh)]]*'Tariff Rates'!$J$3 -> 0 | AN9: =Table1[[#This Row],[Energy Import from Grid (kWh)]]*'Tariff Rates'!$E$3 -> 0 | AO9: =SUM(AJ9:AN9) -> 244.97355 | AP9: {=INDEX(Reading_export[1/1/2025],MATCH(1,(Reading_export[Lot]=A9)*(Reading_export[cluster]=$B$1),0))} -> 34752 | AQ9: {=INDEX(Reading_export[01/04/2025],MATCH(1,(Reading_export[Lot]=A9)*(Reading_export[cluster]=$B$1),0))} -> 38690 | AR9: =Table1[[#This Row],[Last day of reporting period: export]]-Table1[[#This Row],[1st day of reporting period: export]] -> 3938 | AS9: =AR9/$AR$30 -> 0.07495684 | AT9: =Table1[[#This Row],[Percentage of Total export for Billing Period (%)]]*$AC$30 -> 574.00974 | AU9: =IF($Y$30-$E$38>0,$Y$30-$E$38,0) -> 72.54 | AV9: =IFERROR(Table1[[#This Row],[Total Cluster Energy Balance for P2P Trading (kWh)2]]*Table1[[#This Row],[Unused Daily Allowance %]],0) -> 0.27434183 | AW9: =AS9*AF9 -> 105.16445 | AX9: =Table1[[#This Row],[Cluster''s Total Common Services (kWh)]]*Table1[[#This Row],[Percentage of Total export for Billing Period (%)]] -> 52.244917 | AY9: =$Q$25*Table1[[#This Row],[Percentage of Total export for Billing Period (%)]] -> 225.91992 | AZ9: =Table1[[#This Row],[Total Lot Export (kWh)]]-Table1[[#This Row],[Total Energy Export P2P to battery (kWh)]]-Table1[[#This Row],[Axillary Battery Losses based upon Adjusted % total export (kWh)]]-Table1[[#This Row],[Common Service based upon % total export to battery (kWh)]]-Table1[[#This Row],[EV Charger based upon % total export to battery (kWh)]] -> 2980.661 | BA9: =IFERROR(IF($AZ$30-$F$38>0,$AZ$30-$F$38,0),0) -> 0 | BB9: =Table1[[#This Row],[Energy Losses When Export to Grid (kWh)]]*Table1[[#This Row],[Percentage of Total export for Billing Period (%)]] -> 0 | BC9: =Table1[[#This Row],[Therotical Energy Export to Grid (kWh)]]-Table1[[#This Row],[Energy Losses When Export to Grid based up % total export (kWh)]] -> 2980.661 | BD9: =AW9*'Tariff Rates'!$C$3 -> -23.136178 | BE9: =Table1[[#This Row],[Common Service based upon % total export to battery (kWh)]]*'Tariff Rates'!$C$3 -> -11.493882 | BF9: =Table1[[#This Row],[EV Charger based upon % total export to battery (kWh)]]*'Tariff Rates'!$C$3 -> -49.702381 | BG9: =AT9*'Tariff Rates'!$C$3 -> -126.28214 | BH9: =Table1[[#This Row],[Borrowed Allowance Based on Unused Daily Allowance % (kWh)]]*'Tariff Rates'!$K$3 -> -0.0054868365 | BI9: =BC9*'Tariff Rates'!$F$3 -> -114.75545 | BJ9: =SUM(BD9:BI9) -> -325.37552 | BK9: =$D$43*Table1[[#This Row],[Percentage of Unit Entitlement (%)]] -> 0 | BL9: =BK9*'Tariff Rates'!$H$3 -> 0 | BM9: =($Q$25)*Table1[[#This Row],[Percentage of Unit Entitlement (%)]]*'Tariff Rates'!$B$3 -> 30.50168 | BN9: =SUM(BM9,BL9) -> 30.50168 | BO9: =BK9 -> 0 | BP9: =BO9+BN9 -> 30.50168 | BQ9: =AO9+BJ9+N9+BP9 -> 23.572665 | BT9: 5
A10: 6 | B10: {=INDEX(Table_Household_Alloc[Owner],MATCH(1,(Table_Household_Alloc[Lot]=A10)*(Table_Household_Alloc[cluster]=$B$1),0))} -> Christopher Paul Martin Vicki Ann Martin | C10: {=INDEX(Reading_import[Meter'#],MATCH(1,(Table_Household_Alloc[Lot]=A10)*(Table_Household_Alloc[cluster]=$B$1),0))} -> 50003421 | D10: {=INDEX(Table_Household_Alloc[UE % over Cluster],MATCH(1,(Table_Household_Alloc[Lot]=A10)*(Table_Household_Alloc[cluster]=$B$1),0))} -> 0.066 | E10: {=INDEX(Table_Household_Alloc[Stage of Dev.],MATCH(1,(Table_Household_Alloc[Lot]=A10)*(Table_Household_Alloc[cluster]=$B$1),0))} -> O | F10: {=INDEX(Amanda_energy[Daily_Supply_incl_GST],MATCH(1,(Amanda_energy[Cluster]=$B$1)*(Amanda_energy[Month]=$F$2),0))/MAX($A:$A)} -> 8.9736842 | G10: {=INDEX(Amanda_energy[Daily_Supply_incl_GST],MATCH(1,(Amanda_energy[Cluster]=$B$1)*(Amanda_energy[Month]=$G$2),0))/MAX($A:$A)} -> 8.1052632 | H10: {=INDEX(Amanda_energy[Daily_Supply_incl_GST],MATCH(1,(Amanda_energy[Cluster]=$B$1)*(Amanda_energy[Month]=$H$2),0))/MAX($A:$A)} -> 8.9736842 | I10: =$J$38/MAX($A:$A) -> 3.2268421 | J10: ='Tariff Rates'!$B$8*$J$3 -> 13.561644 | K10: ='Tariff Rates'!$C$8*Table1[[#This Row],[Percentage of Unit Entitlement (%)]]*'Energy billing Mastersheet_fml'!$K$3 -> 13.963068 | L10: =$L$3*'Tariff Rates'!$D$8*IF(Table1[[#This Row],[Stage of Dev.]]="V",0,1) -> 19.8 | M10: 1.1 | N10: =SUM(F10:M10) -> 77.704186 | O10: {=INDEX(Reading_import[1/1/2025],MATCH(1,(Reading_import[Lot]=A10)*(Reading_import[cluster]=$B$1),0))} -> 5469 | P10: {=INDEX(Reading_import[01/04/2025],MATCH(1,(Reading_import[Lot]=A10)*(Reading_import[cluster]=$B$1),0))} -> 5889 | Q10: =Table1[[#This Row],[Last day of reporting period: import]]-Table1[[#This Row],[1st day of reporting period: import]] -> 420 | R10: =Q10/$N$3 -> 4.6666667 | S10: =Q10/$Q$30 -> 0.05407911 | T10: =IF(Table1[[#This Row],[Stage of Dev.]]="V",0,233*Table1[[#This Row],[Percentage of Unit Entitlement (%)]]) -> 15.378 | U10: =IF(T10>R10,R10,T10) -> 4.6666667 | V10: =Table1[[#This Row],[Daily Battery allowance based on UE% (kWh)]]-Table1[[#This Row],[Applicable Battery Allowance Daily Consumption (kWh)]] -> 10.711333 | W10: =Table1[[#This Row],[Unused Daily Allowance (kWh)]]/$V$30 -> 0.072024189 | X10: =IF(Table1[[#This Row],[Applicable Battery Allowance Daily Consumption (kWh)]]>Table1[[#This Row],[Total Daily Average Consumptio for Billing Period (kWh)]],Table1[[#This Row],[Total Consumption Import (kWh)]],U10*$N$3) -> 420 | Y10: =IF(Table1[[#This Row],[Applicable Battery Allowance Daily Consumption (kWh)]]>0,ABS(Q10-X10),0) -> 0 | Z10: =IFERROR(Table1[[#This Row],[Energy Exceeding Battery Allowance (kWh)]]/$Y$30,0) -> 0 | AA10: =IF($Y$30-$E$38>0,$Y$30-$E$38,0) -> 72.54 | AB10: =IFERROR(Table1[[#This Row],[Total Cluster Energy Balance for P2P Trading (kWh)]]*Table1[[#This Row],[Energy Exceeding Battery Allowance %]],0) -> 0 | AC10: =Table1[[#This Row],[P2P Import Consumption within Battery Allowance(kWh)]]+Table1[[#This Row],[P2P Import Consumption over Battery Allowance based on Energy Exceeding Allowance % (kWh)]] -> 420 | AD10: =Table1[[#This Row],[Total Consumption Import (kWh)]]-Table1[[#This Row],[Total P2P import (kWh)]] -> 0 | AE10: =IFERROR(Table1[[#This Row],[Total P2P import (kWh)]]/$AC$30,0) -> 0.054845538 | AF10: =($Q$24-$AR$24) -> 1403 | AG10: =AF10*AE10 -> 76.94829 | AH10: =SUM($Q$26:$Q$28) -> 697 | AI10: =Table1[[#This Row],[Cluster''s Total Common Services (kWh)]]*Table1[[#This Row],[Percentage of Unit Entitlement (%)]] -> 46.002 | AJ10: =AG10*'Tariff Rates'!$B$3 -> 16.928624 | AK10: =Table1[[#This Row],[Common Services based on Split per Unit Entitlement % to battery (kWh)]]*'Tariff Rates'!$B$3 -> 10.12044 | AL10: =Table1[[#This Row],[Total P2P import (kWh)]]*IF(Table1[[#This Row],[Total Lot Export (kWh)]]=0,'Tariff Rates'!$L$3,'Tariff Rates'!$B$3) -> 92.4 | AM10: =Table1[[#This Row],[P2P Import Consumption over Battery Allowance based on Energy Exceeding Allowance % (kWh)]]*'Tariff Rates'!$J$3 -> 0 | AN10: =Table1[[#This Row],[Energy Import from Grid (kWh)]]*'Tariff Rates'!$E$3 -> 0 | AO10: =SUM(AJ10:AN10) -> 119.44906 | AP10: {=INDEX(Reading_export[1/1/2025],MATCH(1,(Reading_export[Lot]=A10)*(Reading_export[cluster]=$B$1),0))} -> 15827 | AQ10: {=INDEX(Reading_export[01/04/2025],MATCH(1,(Reading_export[Lot]=A10)*(Reading_export[cluster]=$B$1),0))} -> 20723 | AR10: =Table1[[#This Row],[Last day of reporting period: export]]-Table1[[#This Row],[1st day of reporting period: export]] -> 4896 | AS10: =AR10/$AR$30 -> 0.093191642 | AT10: =Table1[[#This Row],[Percentage of Total export for Billing Period (%)]]*$AC$30 -> 713.64948 | AU10: =IF($Y$30-$E$38>0,$Y$30-$E$38,0) -> 72.54 | AV10: =IFERROR(Table1[[#This Row],[Total Cluster Energy Balance for P2P Trading (kWh)2]]*Table1[[#This Row],[Unused Daily Allowance %]],0) -> 5.2246347 | AW10: =AS10*AF10 -> 130.74787 | AX10: =Table1[[#This Row],[Cluster''s Total Common Services (kWh)]]*Table1[[#This Row],[Percentage of Total export for Billing Period (%)]] -> 64.954575 | AY10: =$Q$25*Table1[[#This Row],[Percentage of Total export for Billing Period (%)]] -> 280.87961 | AZ10: =Table1[[#This Row],[Total Lot Export (kWh)]]-Table1[[#This Row],[Total Energy Export P2P to battery (kWh)]]-Table1[[#This Row],[Axillary Battery Losses based upon Adjusted % total export (kWh)]]-Table1[[#This Row],[Common Service based upon % total export to battery (kWh)]]-Table1[[#This Row],[EV Charger based upon % total export to battery (kWh)]] -> 3705.7685 | BA10: =IFERROR(IF($AZ$30-$F$38>0,$AZ$30-$F$38,0),0) -> 0 | BB10: =Table1[[#This Row],[Energy Losses When Export to Grid (kWh)]]*Table1[[#This Row],[Percentage of Total export for Billing Period (%)]] -> 0 | BC10: =Table1[[#This Row],[Therotical Energy Export to Grid (kWh)]]-Table1[[#This Row],[Energy Losses When Export to Grid based up % total export (kWh)]] -> 3705.7685 | BD10: =AW10*'Tariff Rates'!$C$3 -> -28.764532 | BE10: =Table1[[#This Row],[Common Service based upon % total export to battery (kWh)]]*'Tariff Rates'!$C$3 -> -14.290006 | BF10: =Table1[[#This Row],[EV Charger based upon % total export to battery (kWh)]]*'Tariff Rates'!$C$3 -> -61.793514 | BG10: =AT10*'Tariff Rates'!$C$3 -> -157.00289 | BH10: =Table1[[#This Row],[Borrowed Allowance Based on Unused Daily Allowance % (kWh)]]*'Tariff Rates'!$K$3 -> -0.10449269 | BI10: =BC10*'Tariff Rates'!$F$3 -> -142.67209 | BJ10: =SUM(BD10:BI10) -> -404.62752 | BK10: =$D$43*Table1[[#This Row],[Percentage of Unit Entitlement (%)]] -> 0 | BL10: =BK10*'Tariff Rates'!$H$3 -> 0 | BM10: =($Q$25)*Table1[[#This Row],[Percentage of Unit Entitlement (%)]]*'Tariff Rates'!$B$3 -> 43.76328 | BN10: =SUM(BM10,BL10) -> 43.76328 | BO10: =BK10 -> 0 | BP10: =BO10+BN10 -> 43.76328 | BQ10: =AO10+BJ10+N10+BP10 -> -163.71099 | BT10: 6
A11: 7 | B11: {=INDEX(Table_Household_Alloc[Owner],MATCH(1,(Table_Household_Alloc[Lot]=A11)*(Table_Household_Alloc[cluster]=$B$1),0))} -> Dex Ezekiel, Jeannine Penniment | C11: {=INDEX(Reading_import[Meter'#],MATCH(1,(Table_Household_Alloc[Lot]=A11)*(Table_Household_Alloc[cluster]=$B$1),0))} -> 50002953 | D11: {=INDEX(Table_Household_Alloc[UE % over Cluster],MATCH(1,(Table_Household_Alloc[Lot]=A11)*(Table_Household_Alloc[cluster]=$B$1),0))} -> 0.066 | E11: {=INDEX(Table_Household_Alloc[Stage of Dev.],MATCH(1,(Table_Household_Alloc[Lot]=A11)*(Table_Household_Alloc[cluster]=$B$1),0))} -> UC/M/ND | F11: {=INDEX(Amanda_energy[Daily_Supply_incl_GST],MATCH(1,(Amanda_energy[Cluster]=$B$1)*(Amanda_energy[Month]=$F$2),0))/MAX($A:$A)} -> 8.9736842 | G11: {=INDEX(Amanda_energy[Daily_Supply_incl_GST],MATCH(1,(Amanda_energy[Cluster]=$B$1)*(Amanda_energy[Month]=$G$2),0))/MAX($A:$A)} -> 8.1052632 | H11: {=INDEX(Amanda_energy[Daily_Supply_incl_GST],MATCH(1,(Amanda_energy[Cluster]=$B$1)*(Amanda_energy[Month]=$H$2),0))/MAX($A:$A)} -> 8.9736842 | I11: =$J$38/MAX($A:$A) -> 3.2268421 | J11: ='Tariff Rates'!$B$8*$J$3 -> 13.561644 | K11: ='Tariff Rates'!$C$8*Table1[[#This Row],[Percentage of Unit Entitlement (%)]]*'Energy billing Mastersheet_fml'!$K$3 -> 13.963068 | L11: =$L$3*'Tariff Rates'!$D$8*IF(Table1[[#This Row],[Stage of Dev.]]="V",0,1) -> 19.8 | M11: 1.1 | N11: =SUM(F11:M11) -> 77.704186 | O11: {=INDEX(Reading_import[1/1/2025],MATCH(1,(Reading_import[Lot]=A11)*(Reading_import[cluster]=$B$1),0))} -> 164 | P11: {=INDEX(Reading_import[01/04/2025],MATCH(1,(Reading_import[Lot]=A11)*(Reading_import[cluster]=$B$1),0))} -> 166 | Q11: =Table1[[#This Row],[Last day of reporting period: import]]-Table1[[#This Row],[1st day of reporting period: import]] -> 2 | R11: =Q11/$N$3 -> 0.022222222 | S11: =Q11/$Q$30 -> 0.00025751957 | T11: =IF(Table1[[#This Row],[Stage of Dev.]]="V",0,233*Table1[[#This Row],[Percentage of Unit Entitlement (%)]]) -> 15.378 | U11: =IF(T11>R11,R11,T11) -> 0.022222222 | V11: =Table1[[#This Row],[Daily Battery allowance based on UE% (kWh)]]-Table1[[#This Row],[Applicable Battery Allowance Daily Consumption (kWh)]] -> 15.355778 | W11: =Table1[[#This Row],[Unused Daily Allowance (kWh)]]/$V$30 -> 0.10325395 | X11: =IF(Table1[[#This Row],[Applicable Battery Allowance Daily Consumption (kWh)]]>Table1[[#This Row],[Total Daily Average Consumptio for Billing Period (kWh)]],Table1[[#This Row],[Total Consumption Import (kWh)]],U11*$N$3) -> 2 | Y11: =IF(Table1[[#This Row],[Applicable Battery Allowance Daily Consumption (kWh)]]>0,ABS(Q11-X11),0) -> 0 | Z11: =IFERROR(Table1[[#This Row],[Energy Exceeding Battery Allowance (kWh)]]/$Y$30,0) -> 0 | AA11: =IF($Y$30-$E$38>0,$Y$30-$E$38,0) -> 72.54 | AB11: =IFERROR(Table1[[#This Row],[Total Cluster Energy Balance for P2P Trading (kWh)]]*Table1[[#This Row],[Energy Exceeding Battery Allowance %]],0) -> 0 | AC11: =Table1[[#This Row],[P2P Import Consumption within Battery Allowance(kWh)]]+Table1[[#This Row],[P2P Import Consumption over Battery Allowance based on Energy Exceeding Allowance % (kWh)]] -> 2 | AD11: =Table1[[#This Row],[Total Consumption Import (kWh)]]-Table1[[#This Row],[Total P2P import (kWh)]] -> 0 | AE11: =IFERROR(Table1[[#This Row],[Total P2P import (kWh)]]/$AC$30,0) -> 0.00026116923 | AF11: =($Q$24-$AR$24) -> 1403 | AG11: =AF11*AE11 -> 0.36642043 | AH11: =SUM($Q$26:$Q$28) -> 697 | AI11: =Table1[[#This Row],[Cluster''s Total Common Services (kWh)]]*Table1[[#This Row],[Percentage of Unit Entitlement (%)]] -> 46.002 | AJ11: =AG11*'Tariff Rates'!$B$3 -> 0.080612494 | AK11: =Table1[[#This Row],[Common Services based on Split per Unit Entitlement % to battery (kWh)]]*'Tariff Rates'!$B$3 -> 10.12044 | AL11: =Table1[[#This Row],[Total P2P import (kWh)]]*IF(Table1[[#This Row],[Total Lot Export (kWh)]]=0,'Tariff Rates'!$L$3,'Tariff Rates'!$B$3) -> 0.72 | AM11: =Table1[[#This Row],[P2P Import Consumption over Battery Allowance based on Energy Exceeding Allowance % (kWh)]]*'Tariff Rates'!$J$3 -> 0 | AN11: =Table1[[#This Row],[Energy Import from Grid (kWh)]]*'Tariff Rates'!$E$3 -> 0 | AO11: =SUM(AJ11:AN11) -> 10.921052 | AP11: {=INDEX(Reading_export[1/1/2025],MATCH(1,(Reading_export[Lot]=A11)*(Reading_export[cluster]=$B$1),0))} -> 142 | AQ11: {=INDEX(Reading_export[01/04/2025],MATCH(1,(Reading_export[Lot]=A11)*(Reading_export[cluster]=$B$1),0))} -> 142 | AR11: =Table1[[#This Row],[Last day of reporting period: export]]-Table1[[#This Row],[1st day of reporting period: export]] -> 0 | AS11: =AR11/$AR$30 -> 0 | AT11: =Table1[[#This Row],[Percentage of Total export for Billing Period (%)]]*$AC$30 -> 0 | AU11: =IF($Y$30-$E$38>0,$Y$30-$E$38,0) -> 72.54 | AV11: =IFERROR(Table1[[#This Row],[Total Cluster Energy Balance for P2P Trading (kWh)2]]*Table1[[#This Row],[Unused Daily Allowance %]],0) -> 7.4900413 | AW11: =AS11*AF11 -> 0 | AX11: =Table1[[#This Row],[Cluster''s Total Common Services (kWh)]]*Table1[[#This Row],[Percentage of Total export for Billing Period (%)]] -> 0 | AY11: =$Q$25*Table1[[#This Row],[Percentage of Total export for Billing Period (%)]] -> 0 | AZ11: =Table1[[#This Row],[Total Lot Export (kWh)]]-Table1[[#This Row],[Total Energy Export P2P to battery (kWh)]]-Table1[[#This Row],[Axillary Battery Losses based upon Adjusted % total export (kWh)]]-Table1[[#This Row],[Common Service based upon % total export to battery (kWh)]]-Table1[[#This Row],[EV Charger based upon % total export to battery (kWh)]] -> 0 | BA11: =IFERROR(IF($AZ$30-$F$38>0,$AZ$30-$F$38,0),0) -> 0 | BB11: =Table1[[#This Row],[Energy Losses When Export to Grid (kWh)]]*Table1[[#This Row],[Percentage of Total export for Billing Period (%)]] -> 0 | BC11: =Table1[[#This Row],[Therotical Energy Export to Grid (kWh)]]-Table1[[#This Row],[Energy Losses When Export to Grid based up % total export (kWh)]] -> 0 | BD11: =AW11*'Tariff Rates'!$C$3 -> 0 | BE11: =Table1[[#This Row],[Common Service based upon % total export to battery (kWh)]]*'Tariff Rates'!$C$3 -> 0 | BF11: =Table1[[#This Row],[EV Charger based upon % total export to battery (kWh)]]*'Tariff Rates'!$C$3 -> 0 | BG11: =AT11*'Tariff Rates'!$C$3 -> 0 | BH11: =Table1[[#This Row],[Borrowed Allowance Based on Unused Daily Allowance % (kWh)]]*'Tariff Rates'!$K$3 -> -0.14980083 | BI11: =BC11*'Tariff Rates'!$F$3 -> 0 | BJ11: =SUM(BD11:BI11) -> -0.14980083 | BK11: =$D$43*Table1[[#This Row],[Percentage of Unit Entitlement (%)]] -> 0 | BL11: =BK11*'Tariff Rates'!$H$3 -> 0 | BM11: =($Q$25)*Table1[[#This Row],[Percentage of Unit Entitlement (%)]]*'Tariff Rates'!$B$3 -> 43.76328 | BN11: =SUM(BM11,BL11) -> 43.76328 | BO11: =BK11 -> 0 | BP11: =BO11+BN11 -> 43.76328 | BQ11: =AO11+BJ11+N11+BP11 -> 132.23872 | BT11: 7
A12: 8 | B12: {=INDEX(Table_Household_Alloc[Owner],MATCH(1,(Table_Household_Alloc[Lot]=A12)*(Table_Household_Alloc[cluster]=$B$1),0))} -> Eric Martini Karina Jean Martini | C12: {=INDEX(Reading_import[Meter'#],MATCH(1,(Table_Household_Alloc[Lot]=A12)*(Table_Household_Alloc[cluster]=$B$1),0))} -> 50003395 | D12: {=INDEX(Table_Household_Alloc[UE % over Cluster],MATCH(1,(Table_Household_Alloc[Lot]=A12)*(Table_Household_Alloc[cluster]=$B$1),0))} -> 0.066 | E12: {=INDEX(Table_Household_Alloc[Stage of Dev.],MATCH(1,(Table_Household_Alloc[Lot]=A12)*(Table_Household_Alloc[cluster]=$B$1),0))} -> O | F12: {=INDEX(Amanda_energy[Daily_Supply_incl_GST],MATCH(1,(Amanda_energy[Cluster]=$B$1)*(Amanda_energy[Month]=$F$2),0))/MAX($A:$A)} -> 8.9736842 | G12: {=INDEX(Amanda_energy[Daily_Supply_incl_GST],MATCH(1,(Amanda_energy[Cluster]=$B$1)*(Amanda_energy[Month]=$G$2),0))/MAX($A:$A)} -> 8.1052632 | H12: {=INDEX(Amanda_energy[Daily_Supply_incl_GST],MATCH(1,(Amanda_energy[Cluster]=$B$1)*(Amanda_energy[Month]=$H$2),0))/MAX($A:$A)} -> 8.9736842 | I12: =$J$38/MAX($A:$A) -> 3.2268421 | J12: ='Tariff Rates'!$B$8*$J$3 -> 13.561644 | K12: ='Tariff Rates'!$C$8*Table1[[#This Row],[Percentage of Unit Entitlement (%)]]*'Energy billing Mastersheet_fml'!$K$3 -> 13.963068 | L12: =$L$3*'Tariff Rates'!$D$8*IF(Table1[[#This Row],[Stage of Dev.]]="V",0,1) -> 19.8 | M12: 1.1 | N12: =SUM(F12:M12) -> 77.704186 | O12: {=INDEX(Reading_import[1/1/2025],MATCH(1,(Reading_import[Lot]=A12)*(Reading_import[cluster]=$B$1),0))} -> 12726 | P12: {=INDEX(Reading_import[01/04/2025],MATCH(1,(Reading_import[Lot]=A12)*(Reading_import[cluster]=$B$1),0))} -> 13279 | Q12: =Table1[[#This Row],[Last day of reporting period: import]]-Table1[[#This Row],[1st day of reporting period: import]] -> 553 | R12: =Q12/$N$3 -> 6.1444444 | S12: =Q12/$Q$30 -> 0.071204162 | T12: =IF(Table1[[#This Row],[Stage of Dev.]]="V",0,233*Table1[[#This Row],[Percentage of Unit Entitlement (%)]]) -> 15.378 | U12: =IF(T12>R12,R12,T12) -> 6.1444444 | V12: =Table1[[#This Row],[Daily Battery allowance based on UE% (kWh)]]-Table1[[#This Row],[Applicable Battery Allowance Daily Consumption (kWh)]] -> 9.2335556 | W12: =Table1[[#This Row],[Unused Daily Allowance (kWh)]]/$V$30 -> 0.062087448 | X12: =IF(Table1[[#This Row],[Applicable Battery Allowance Daily Consumption (kWh)]]>Table1[[#This Row],[Total Daily Average Consumptio for Billing Period (kWh)]],Table1[[#This Row],[Total Consumption Import (kWh)]],U12*$N$3) -> 553 | Y12: =IF(Table1[[#This Row],[Applicable Battery Allowance Daily Consumption (kWh)]]>0,ABS(Q12-X12),0) -> 0 | Z12: =IFERROR(Table1[[#This Row],[Energy Exceeding Battery Allowance (kWh)]]/$Y$30,0) -> 0 | AA12: =IF($Y$30-$E$38>0,$Y$30-$E$38,0) -> 72.54 | AB12: =IFERROR(Table1[[#This Row],[Total Cluster Energy Balance for P2P Trading (kWh)]]*Table1[[#This Row],[Energy Exceeding Battery Allowance %]],0) -> 0 | AC12: =Table1[[#This Row],[P2P Import Consumption within Battery Allowance(kWh)]]+Table1[[#This Row],[P2P Import Consumption over Battery Allowance based on Energy Exceeding Allowance % (kWh)]] -> 553 | AD12: =Table1[[#This Row],[Total Consumption Import (kWh)]]-Table1[[#This Row],[Total P2P import (kWh)]] -> 0 | AE12: =IFERROR(Table1[[#This Row],[Total P2P import (kWh)]]/$AC$30,0) -> 0.072213292 | AF12: =($Q$24-$AR$24) -> 1403 | AG12: =AF12*AE12 -> 101.31525 | AH12: =SUM($Q$26:$Q$28) -> 697 | AI12: =Table1[[#This Row],[Cluster''s Total Common Services (kWh)]]*Table1[[#This Row],[Percentage of Unit Entitlement (%)]] -> 46.002 | AJ12: =AG12*'Tariff Rates'!$B$3 -> 22.289355 | AK12: =Table1[[#This Row],[Common Services based on Split per Unit Entitlement % to battery (kWh)]]*'Tariff Rates'!$B$3 -> 10.12044 | AL12: =Table1[[#This Row],[Total P2P import (kWh)]]*IF(Table1[[#This Row],[Total Lot Export (kWh)]]=0,'Tariff Rates'!$L$3,'Tariff Rates'!$B$3) -> 121.66 | AM12: =Table1[[#This Row],[P2P Import Consumption over Battery Allowance based on Energy Exceeding Allowance % (kWh)]]*'Tariff Rates'!$J$3 -> 0 | AN12: =Table1[[#This Row],[Energy Import from Grid (kWh)]]*'Tariff Rates'!$E$3 -> 0 | AO12: =SUM(AJ12:AN12) -> 154.06979 | AP12: {=INDEX(Reading_export[1/1/2025],MATCH(1,(Reading_export[Lot]=A12)*(Reading_export[cluster]=$B$1),0))} -> 41841 | AQ12: {=INDEX(Reading_export[01/04/2025],MATCH(1,(Reading_export[Lot]=A12)*(Reading_export[cluster]=$B$1),0))} -> 46064 | AR12: =Table1[[#This Row],[Last day of reporting period: export]]-Table1[[#This Row],[1st day of reporting period: export]] -> 4223 | AS12: =AR12/$AR$30 -> 0.080381598 | AT12: =Table1[[#This Row],[Percentage of Total export for Billing Period (%)]]*$AC$30 -> 615.55183 | AU12: =IF($Y$30-$E$38>0,$Y$30-$E$38,0) -> 72.54 | AV12: =IFERROR(Table1[[#This Row],[Total Cluster Energy Balance for P2P Trading (kWh)2]]*Table1[[#This Row],[Unused Daily Allowance %]],0) -> 4.5038235 | AW12: =AS12*AF12 -> 112.77538 | AX12: =Table1[[#This Row],[Cluster''s Total Common Services (kWh)]]*Table1[[#This Row],[Percentage of Total export for Billing Period (%)]] -> 56.025974 | AY12: =$Q$25*Table1[[#This Row],[Percentage of Total export for Billing Period (%)]] -> 242.27014 | AZ12: =Table1[[#This Row],[Total Lot Export (kWh)]]-Table1[[#This Row],[Total Energy Export P2P to battery (kWh)]]-Table1[[#This Row],[Axillary Battery Losses based upon Adjusted % total export (kWh)]]-Table1[[#This Row],[Common Service based upon % total export to battery (kWh)]]-Table1[[#This Row],[EV Charger based upon % total export to battery (kWh)]] -> 3196.3767 | BA12: =IFERROR(IF($AZ$30-$F$38>0,$AZ$30-$F$38,0),0) -> 0 | BB12: =Table1[[#This Row],[Energy Losses When Export to Grid (kWh)]]*Table1[[#This Row],[Percentage of Total export for Billing Period (%)]] -> 0 | BC12: =Table1[[#This Row],[Therotical Energy Export to Grid (kWh)]]-Table1[[#This Row],[Energy Losses When Export to Grid based up % total export (kWh)]] -> 3196.3767 | BD12: =AW12*'Tariff Rates'!$C$3 -> -24.810584 | BE12: =Table1[[#This Row],[Common Service based upon % total export to battery (kWh)]]*'Tariff Rates'!$C$3 -> -12.325714 | BF12: =Table1[[#This Row],[EV Charger based upon % total export to battery (kWh)]]*'Tariff Rates'!$C$3 -> -53.29943 | BG12: =AT12*'Tariff Rates'!$C$3 -> -135.4214 | BH12: =Table1[[#This Row],[Borrowed Allowance Based on Unused Daily Allowance % (kWh)]]*'Tariff Rates'!$K$3 -> -0.090076469 | BI12: =BC12*'Tariff Rates'!$F$3 -> -123.0605 | BJ12: =SUM(BD12:BI12) -> -349.00771 | BK12: =$D$43*Table1[[#This Row],[Percentage of Unit Entitlement (%)]] -> 0 | BL12: =BK12*'Tariff Rates'!$H$3 -> 0 | BM12: =($Q$25)*Table1[[#This Row],[Percentage of Unit Entitlement (%)]]*'Tariff Rates'!$B$3 -> 43.76328 | BN12: =SUM(BM12,BL12) -> 43.76328 | BO12: =BK12 -> 0 | BP12: =BO12+BN12 -> 43.76328 | BQ12: =AO12+BJ12+N12+BP12 -> -73.470449 | BT12: 8
A13: 9 | B13: {=INDEX(Table_Household_Alloc[Owner],MATCH(1,(Table_Household_Alloc[Lot]=A13)*(Table_Household_Alloc[cluster]=$B$1),0))} -> Christopher van Etten Emmanuelle van Etten | C13: {=INDEX(Reading_import[Meter'#],MATCH(1,(Table_Household_Alloc[Lot]=A13)*(Table_Household_Alloc[cluster]=$B$1),0))} -> 50003435 | D13: {=INDEX(Table_Household_Alloc[UE % over Cluster],MATCH(1,(Table_Household_Alloc[Lot]=A13)*(Table_Household_Alloc[cluster]=$B$1),0))} -> 0.066 | E13: {=INDEX(Table_Household_Alloc[Stage of Dev.],MATCH(1,(Table_Household_Alloc[Lot]=A13)*(Table_Household_Alloc[cluster]=$B$1),0))} -> UC | F13: {=INDEX(Amanda_energy[Daily_Supply_incl_GST],MATCH(1,(Amanda_energy[Cluster]=$B$1)*(Amanda_energy[Month]=$F$2),0))/MAX($A:$A)} -> 8.9736842 | G13: {=INDEX(Amanda_energy[Daily_Supply_incl_GST],MATCH(1,(Amanda_energy[Cluster]=$B$1)*(Amanda_energy[Month]=$G$2),0))/MAX($A:$A)} -> 8.1052632 | H13: {=INDEX(Amanda_energy[Daily_Supply_incl_GST],MATCH(1,(Amanda_energy[Cluster]=$B$1)*(Amanda_energy[Month]=$H$2),0))/MAX($A:$A)} -> 8.9736842 | I13: =$J$38/MAX($A:$A) -> 3.2268421 | J13: ='Tariff Rates'!$B$8*$J$3 -> 13.561644 | K13: ='Tariff Rates'!$C$8*Table1[[#This Row],[Percentage of Unit Entitlement (%)]]*'Energy billing Mastersheet_fml'!$K$3 -> 13.963068 | L13: =$L$3*'Tariff Rates'!$D$8*IF(Table1[[#This Row],[Stage of Dev.]]="V",0,1) -> 19.8 | M13: 1.1 | N13: =SUM(F13:M13) -> 77.704186 | O13: {=INDEX(Reading_import[1/1/2025],MATCH(1,(Reading_import[Lot]=A13)*(Reading_import[cluster]=$B$1),0))} -> 76 | P13: {=INDEX(Reading_import[01/04/2025],MATCH(1,(Reading_import[Lot]=A13)*(Reading_import[cluster]=$B$1),0))} -> 158 | Q13: =Table1[[#This Row],[Last day of reporting period: import]]-Table1[[#This Row],[1st day of reporting period: import]] -> 82 | R13: =Q13/$N$3 -> 0.91111111 | S13: =Q13/$Q$30 -> 0.010558302 | T13: =IF(Table1[[#This Row],[Stage of Dev.]]="V",0,233*Table1[[#This Row],[Percentage of Unit Entitlement (%)]]) -> 15.378 | U13: =IF(T13>R13,R13,T13) -> 0.91111111 | V13: =Table1[[#This Row],[Daily Battery allowance based on UE% (kWh)]]-Table1[[#This Row],[Applicable Battery Allowance Daily Consumption (kWh)]] -> 14.466889 | W13: =Table1[[#This Row],[Unused Daily Allowance (kWh)]]/$V$30 -> 0.097276959 | X13: =IF(Table1[[#This Row],[Applicable Battery Allowance Daily Consumption (kWh)]]>Table1[[#This Row],[Total Daily Average Consumptio for Billing Period (kWh)]],Table1[[#This Row],[Total Consumption Import (kWh)]],U13*$N$3) -> 82 | Y13: =IF(Table1[[#This Row],[Applicable Battery Allowance Daily Consumption (kWh)]]>0,ABS(Q13-X13),0) -> 0 | Z13: =IFERROR(Table1[[#This Row],[Energy Exceeding Battery Allowance (kWh)]]/$Y$30,0) -> 0 | AA13: =IF($Y$30-$E$38>0,$Y$30-$E$38,0) -> 72.54 | AB13: =IFERROR(Table1[[#This Row],[Total Cluster Energy Balance for P2P Trading (kWh)]]*Table1[[#This Row],[Energy Exceeding Battery Allowance %]],0) -> 0 | AC13: =Table1[[#This Row],[P2P Import Consumption within Battery Allowance(kWh)]]+Table1[[#This Row],[P2P Import Consumption over Battery Allowance based on Energy Exceeding Allowance % (kWh)]] -> 82 | AD13: =Table1[[#This Row],[Total Consumption Import (kWh)]]-Table1[[#This Row],[Total P2P import (kWh)]] -> 0 | AE13: =IFERROR(Table1[[#This Row],[Total P2P import (kWh)]]/$AC$30,0) -> 0.010707938 | AF13: =($Q$24-$AR$24) -> 1403 | AG13: =AF13*AE13 -> 15.023238 | AH13: =SUM($Q$26:$Q$28) -> 697 | AI13: =Table1[[#This Row],[Cluster''s Total Common Services (kWh)]]*Table1[[#This Row],[Percentage of Unit Entitlement (%)]] -> 46.002 | AJ13: =AG13*'Tariff Rates'!$B$3 -> 3.3051123 | AK13: =Table1[[#This Row],[Common Services based on Split per Unit Entitlement % to battery (kWh)]]*'Tariff Rates'!$B$3 -> 10.12044 | AL13: =Table1[[#This Row],[Total P2P import (kWh)]]*IF(Table1[[#This Row],[Total Lot Export (kWh)]]=0,'Tariff Rates'!$L$3,'Tariff Rates'!$B$3) -> 29.52 | AM13: =Table1[[#This Row],[P2P Import Consumption over Battery Allowance based on Energy Exceeding Allowance % (kWh)]]*'Tariff Rates'!$J$3 -> 0 | AN13: =Table1[[#This Row],[Energy Import from Grid (kWh)]]*'Tariff Rates'!$E$3 -> 0 | AO13: =SUM(AJ13:AN13) -> 42.945552 | AP13: {=INDEX(Reading_export[1/1/2025],MATCH(1,(Reading_export[Lot]=A13)*(Reading_export[cluster]=$B$1),0))} -> 0 | AQ13: {=INDEX(Reading_export[01/04/2025],MATCH(1,(Reading_export[Lot]=A13)*(Reading_export[cluster]=$B$1),0))} -> 0 | AR13: =Table1[[#This Row],[Last day of reporting period: export]]-Table1[[#This Row],[1st day of reporting period: export]] -> 0 | AS13: =AR13/$AR$30 -> 0 | AT13: =Table1[[#This Row],[Percentage of Total export for Billing Period (%)]]*$AC$30 -> 0 | AU13: =IF($Y$30-$E$38>0,$Y$30-$E$38,0) -> 72.54 | AV13: =IFERROR(Table1[[#This Row],[Total Cluster Energy Balance for P2P Trading (kWh)2]]*Table1[[#This Row],[Unused Daily Allowance %]],0) -> 7.0564706 | AW13: =AS13*AF13 -> 0 | AX13: =Table1[[#This Row],[Cluster''s Total Common Services (kWh)]]*Table1[[#This Row],[Percentage of Total export for Billing Period (%)]] -> 0 | AY13: =$Q$25*Table1[[#This Row],[Percentage of Total export for Billing Period (%)]] -> 0 | AZ13: =Table1[[#This Row],[Total Lot Export (kWh)]]-Table1[[#This Row],[Total Energy Export P2P to battery (kWh)]]-Table1[[#This Row],[Axillary Battery Losses based upon Adjusted % total export (kWh)]]-Table1[[#This Row],[Common Service based upon % total export to battery (kWh)]]-Table1[[#This Row],[EV Charger based upon % total export to battery (kWh)]] -> 0 | BA13: =IFERROR(IF($AZ$30-$F$38>0,$AZ$30-$F$38,0),0) -> 0 | BB13: =Table1[[#This Row],[Energy Losses When Export to Grid (kWh)]]*Table1[[#This Row],[Percentage of Total export for Billing Period (%)]] -> 0 | BC13: =Table1[[#This Row],[Therotical Energy Export to Grid (kWh)]]-Table1[[#This Row],[Energy Losses When Export to Grid based up % total export (kWh)]] -> 0 | BD13: =AW13*'Tariff Rates'!$C$3 -> 0 | BE13: =Table1[[#This Row],[Common Service based upon % total export to battery (kWh)]]*'Tariff Rates'!$C$3 -> 0 | BF13: =Table1[[#This Row],[EV Charger based upon % total export to battery (kWh)]]*'Tariff Rates'!$C$3 -> 0 | BG13: =AT13*'Tariff Rates'!$C$3 -> 0 | BH13: =Table1[[#This Row],[Borrowed Allowance Based on Unused Daily Allowance % (kWh)]]*'Tariff Rates'!$K$3 -> -0.14112941 | BI13: =BC13*'Tariff Rates'!$F$3 -> 0 | BJ13: =SUM(BD13:BI13) -> -0.14112941 | BK13: =$D$43*Table1[[#This Row],[Percentage of Unit Entitlement (%)]] -> 0 | BL13: =BK13*'Tariff Rates'!$H$3 -> 0 | BM13: =($Q$25)*Table1[[#This Row],[Percentage of Unit Entitlement (%)]]*'Tariff Rates'!$B$3 -> 43.76328 | BN13: =SUM(BM13,BL13) -> 43.76328 | BO13: =BK13 -> 0 | BP13: =BO13+BN13 -> 43.76328 | BQ13: =AO13+BJ13+N13+BP13 -> 164.27189 | BT13: 9
A14: 10 | B14: {=INDEX(Table_Household_Alloc[Owner],MATCH(1,(Table_Household_Alloc[Lot]=A14)*(Table_Household_Alloc[cluster]=$B$1),0))} -> Peter Smith | C14: {=INDEX(Reading_import[Meter'#],MATCH(1,(Table_Household_Alloc[Lot]=A14)*(Table_Household_Alloc[cluster]=$B$1),0))} -> 50002952 | D14: {=INDEX(Table_Household_Alloc[UE % over Cluster],MATCH(1,(Table_Household_Alloc[Lot]=A14)*(Table_Household_Alloc[cluster]=$B$1),0))} -> 0.031 | E14: {=INDEX(Table_Household_Alloc[Stage of Dev.],MATCH(1,(Table_Household_Alloc[Lot]=A14)*(Table_Household_Alloc[cluster]=$B$1),0))} -> O | F14: {=INDEX(Amanda_energy[Daily_Supply_incl_GST],MATCH(1,(Amanda_energy[Cluster]=$B$1)*(Amanda_energy[Month]=$F$2),0))/MAX($A:$A)} -> 8.9736842 | G14: {=INDEX(Amanda_energy[Daily_Supply_incl_GST],MATCH(1,(Amanda_energy[Cluster]=$B$1)*(Amanda_energy[Month]=$G$2),0))/MAX($A:$A)} -> 8.1052632 | H14: {=INDEX(Amanda_energy[Daily_Supply_incl_GST],MATCH(1,(Amanda_energy[Cluster]=$B$1)*(Amanda_energy[Month]=$H$2),0))/MAX($A:$A)} -> 8.9736842 | I14: =$J$38/MAX($A:$A) -> 3.2268421 | J14: ='Tariff Rates'!$B$8*$J$3 -> 13.561644 | K14: ='Tariff Rates'!$C$8*Table1[[#This Row],[Percentage of Unit Entitlement (%)]]*'Energy billing Mastersheet_fml'!$K$3 -> 6.558411 | L14: =$L$3*'Tariff Rates'!$D$8*IF(Table1[[#This Row],[Stage of Dev.]]="V",0,1) -> 19.8 | M14: 1.1 | N14: =SUM(F14:M14) -> 70.299528 | O14: {=INDEX(Reading_import[1/1/2025],MATCH(1,(Reading_import[Lot]=A14)*(Reading_import[cluster]=$B$1),0))} -> 6735 | P14: {=INDEX(Reading_import[01/04/2025],MATCH(1,(Reading_import[Lot]=A14)*(Reading_import[cluster]=$B$1),0))} -> 6989 | Q14: =Table1[[#This Row],[Last day of reporting period: import]]-Table1[[#This Row],[1st day of reporting period: import]] -> 254 | R14: =Q14/$N$3 -> 2.8222222 | S14: =Q14/$Q$30 -> 0.032704986 | T14: =IF(Table1[[#This Row],[Stage of Dev.]]="V",0,233*Table1[[#This Row],[Percentage of Unit Entitlement (%)]]) -> 7.223 | U14: =IF(T14>R14,R14,T14) -> 2.8222222 | V14: =Table1[[#This Row],[Daily Battery allowance based on UE% (kWh)]]-Table1[[#This Row],[Applicable Battery Allowance Daily Consumption (kWh)]] -> 4.4007778 | W14: =Table1[[#This Row],[Unused Daily Allowance (kWh)]]/$V$30 -> 0.029591316 | X14: =IF(Table1[[#This Row],[Applicable Battery Allowance Daily Consumption (kWh)]]>Table1[[#This Row],[Total Daily Average Consumptio for Billing Period (kWh)]],Table1[[#This Row],[Total Consumption Import (kWh)]],U14*$N$3) -> 254 | Y14: =IF(Table1[[#This Row],[Applicable Battery Allowance Daily Consumption (kWh)]]>0,ABS(Q14-X14),0) -> 2.8421709e-14 | Z14: =IFERROR(Table1[[#This Row],[Energy Exceeding Battery Allowance (kWh)]]/$Y$30,0) -> 1.5696531e-16 | AA14: =IF($Y$30-$E$38>0,$Y$30-$E$38,0) -> 72.54 | AB14: =IFERROR(Table1[[#This Row],[Total Cluster Energy Balance for P2P Trading (kWh)]]*Table1[[#This Row],[Energy Exceeding Battery Allowance %]],0) -> 1.1386264e-14 | AC14: =Table1[[#This Row],[P2P Import Consumption within Battery Allowance(kWh)]]+Table1[[#This Row],[P2P Import Consumption over Battery Allowance based on Energy Exceeding Allowance % (kWh)]] -> 254 | AD14: =Table1[[#This Row],[Total Consumption Import (kWh)]]-Table1[[#This Row],[Total P2P import (kWh)]] -> 0 | AE14: =IFERROR(Table1[[#This Row],[Total P2P import (kWh)]]/$AC$30,0) -> 0.033168492 | AF14: =($Q$24-$AR$24) -> 1403 | AG14: =AF14*AE14 -> 46.535394 | AH14: =SUM($Q$26:$Q$28) -> 697 | AI14: =Table1[[#This Row],[Cluster''s Total Common Services (kWh)]]*Table1[[#This Row],[Percentage of Unit Entitlement (%)]] -> 21.607 | AJ14: =AG14*'Tariff Rates'!$B$3 -> 10.237787 | AK14: =Table1[[#This Row],[Common Services based on Split per Unit Entitlement % to battery (kWh)]]*'Tariff Rates'!$B$3 -> 4.75354 | AL14: =Table1[[#This Row],[Total P2P import (kWh)]]*IF(Table1[[#This Row],[Total Lot Export (kWh)]]=0,'Tariff Rates'!$L$3,'Tariff Rates'!$B$3) -> 55.88 | AM14: =Table1[[#This Row],[P2P Import Consumption over Battery Allowance based on Energy Exceeding Allowance % (kWh)]]*'Tariff Rates'!$J$3 -> 2.2772528e-16 | AN14: =Table1[[#This Row],[Energy Import from Grid (kWh)]]*'Tariff Rates'!$E$3 -> 0 | AO14: =SUM(AJ14:AN14) -> 70.871327 | AP14: {=INDEX(Reading_export[1/1/2025],MATCH(1,(Reading_export[Lot]=A14)*(Reading_export[cluster]=$B$1),0))} -> 10088 | AQ14: {=INDEX(Reading_export[01/04/2025],MATCH(1,(Reading_export[Lot]=A14)*(Reading_export[cluster]=$B$1),0))} -> 12402 | AR14: =Table1[[#This Row],[Last day of reporting period: export]]-Table1[[#This Row],[1st day of reporting period: export]] -> 2314 | AS14: =AR14/$AR$30 -> 0.044045233 | AT14: =Table1[[#This Row],[Percentage of Total export for Billing Period (%)]]*$AC$30 -> 337.29267 | AU14: =IF($Y$30-$E$38>0,$Y$30-$E$38,0) -> 72.54 | AV14: =IFERROR(Table1[[#This Row],[Total Cluster Energy Balance for P2P Trading (kWh)2]]*Table1[[#This Row],[Unused Daily Allowance %]],0) -> 2.1465541 | AW14: =AS14*AF14 -> 61.795462 | AX14: =Table1[[#This Row],[Cluster''s Total Common Services (kWh)]]*Table1[[#This Row],[Percentage of Total export for Billing Period (%)]] -> 30.699527 | AY14: =$Q$25*Table1[[#This Row],[Percentage of Total export for Billing Period (%)]] -> 132.75233 | AZ14: =Table1[[#This Row],[Total Lot Export (kWh)]]-Table1[[#This Row],[Total Energy Export P2P to battery (kWh)]]-Table1[[#This Row],[Axillary Battery Losses based upon Adjusted % total export (kWh)]]-Table1[[#This Row],[Common Service based upon % total export to battery (kWh)]]-Table1[[#This Row],[EV Charger based upon % total export to battery (kWh)]] -> 1751.46 | BA14: =IFERROR(IF($AZ$30-$F$38>0,$AZ$30-$F$38,0),0) -> 0 | BB14: =Table1[[#This Row],[Energy Losses When Export to Grid (kWh)]]*Table1[[#This Row],[Percentage of Total export for Billing Period (%)]] -> 0 | BC14: =Table1[[#This Row],[Therotical Energy Export to Grid (kWh)]]-Table1[[#This Row],[Energy Losses When Export to Grid based up % total export (kWh)]] -> 1751.46 | BD14: =AW14*'Tariff Rates'!$C$3 -> -13.595002 | BE14: =Table1[[#This Row],[Common Service based upon % total export to battery (kWh)]]*'Tariff Rates'!$C$3 -> -6.753896 | BF14: =Table1[[#This Row],[EV Charger based upon % total export to battery (kWh)]]*'Tariff Rates'!$C$3 -> -29.205513 | BG14: =AT14*'Tariff Rates'!$C$3 -> -74.204387 | BH14: =Table1[[#This Row],[Borrowed Allowance Based on Unused Daily Allowance % (kWh)]]*'Tariff Rates'!$K$3 -> -0.042931081 | BI14: =BC14*'Tariff Rates'!$F$3 -> -67.43121 | BJ14: =SUM(BD14:BI14) -> -191.23294 | BK14: =$D$43*Table1[[#This Row],[Percentage of Unit Entitlement (%)]] -> 0 | BL14: =BK14*'Tariff Rates'!$H$3 -> 0 | BM14: =($Q$25)*Table1[[#This Row],[Percentage of Unit Entitlement (%)]]*'Tariff Rates'!$B$3 -> 20.55548 | BN14: =SUM(BM14,BL14) -> 20.55548 | BO14: =BK14 -> 0 | BP14: =BO14+BN14 -> 20.55548 | BQ14: =AO14+BJ14+N14+BP14 -> -29.506604 | BT14: 10
A15: 11 | B15: {=INDEX(Table_Household_Alloc[Owner],MATCH(1,(Table_Household_Alloc[Lot]=A15)*(Table_Household_Alloc[cluster]=$B$1),0))} -> Peter Andre Grant | C15: {=INDEX(Reading_import[Meter'#],MATCH(1,(Table_Household_Alloc[Lot]=A15)*(Table_Household_Alloc[cluster]=$B$1),0))} -> 50002944 | D15: {=INDEX(Table_Household_Alloc[UE % over Cluster],MATCH(1,(Table_Household_Alloc[Lot]=A15)*(Table_Household_Alloc[cluster]=$B$1),0))} -> 0.031 | E15: {=INDEX(Table_Household_Alloc[Stage of Dev.],MATCH(1,(Table_Household_Alloc[Lot]=A15)*(Table_Household_Alloc[cluster]=$B$1),0))} -> UC/M/ND | F15: {=INDEX(Amanda_energy[Daily_Supply_incl_GST],MATCH(1,(Amanda_energy[Cluster]=$B$1)*(Amanda_energy[Month]=$F$2),0))/MAX($A:$A)} -> 8.9736842 | G15: {=INDEX(Amanda_energy[Daily_Supply_incl_GST],MATCH(1,(Amanda_energy[Cluster]=$B$1)*(Amanda_energy[Month]=$G$2),0))/MAX($A:$A)} -> 8.1052632 | H15: {=INDEX(Amanda_energy[Daily_Supply_incl_GST],MATCH(1,(Amanda_energy[Cluster]=$B$1)*(Amanda_energy[Month]=$H$2),0))/MAX($A:$A)} -> 8.9736842 | I15: =$J$38/MAX($A:$A) -> 3.2268421 | J15: ='Tariff Rates'!$B$8*$J$3 -> 13.561644 | K15: ='Tariff Rates'!$C$8*Table1[[#This Row],[Percentage of Unit Entitlement (%)]]*'Energy billing Mastersheet_fml'!$K$3 -> 6.558411 | L15: =$L$3*'Tariff Rates'!$D$8*IF(Table1[[#This Row],[Stage of Dev.]]="V",0,1) -> 19.8 | M15: 1.1 | N15: =SUM(F15:M15) -> 70.299528 | O15: {=INDEX(Reading_import[1/1/2025],MATCH(1,(Reading_import[Lot]=A15)*(Reading_import[cluster]=$B$1),0))} -> 36 | P15: {=INDEX(Reading_import[01/04/2025],MATCH(1,(Reading_import[Lot]=A15)*(Reading_import[cluster]=$B$1),0))} -> 149 | Q15: =Table1[[#This Row],[Last day of reporting period: import]]-Table1[[#This Row],[1st day of reporting period: import]] -> 113 | R15: =Q15/$N$3 -> 1.2555556 | S15: =Q15/$Q$30 -> 0.014549856 | T15: =IF(Table1[[#This Row],[Stage of Dev.]]="V",0,233*Table1[[#This Row],[Percentage of Unit Entitlement (%)]]) -> 7.223 | U15: =IF(T15>R15,R15,T15) -> 1.2555556 | V15: =Table1[[#This Row],[Daily Battery allowance based on UE% (kWh)]]-Table1[[#This Row],[Applicable Battery Allowance Daily Consumption (kWh)]] -> 5.9674444 | W15: =Table1[[#This Row],[Unused Daily Allowance (kWh)]]/$V$30 -> 0.040125756 | X15: =IF(Table1[[#This Row],[Applicable Battery Allowance Daily Consumption (kWh)]]>Table1[[#This Row],[Total Daily Average Consumptio for Billing Period (kWh)]],Table1[[#This Row],[Total Consumption Import (kWh)]],U15*$N$3) -> 113 | Y15: =IF(Table1[[#This Row],[Applicable Battery Allowance Daily Consumption (kWh)]]>0,ABS(Q15-X15),0) -> 0 | Z15: =IFERROR(Table1[[#This Row],[Energy Exceeding Battery Allowance (kWh)]]/$Y$30,0) -> 0 | AA15: =IF($Y$30-$E$38>0,$Y$30-$E$38,0) -> 72.54 | AB15: =IFERROR(Table1[[#This Row],[Total Cluster Energy Balance for P2P Trading (kWh)]]*Table1[[#This Row],[Energy Exceeding Battery Allowance %]],0) -> 0 | AC15: =Table1[[#This Row],[P2P Import Consumption within Battery Allowance(kWh)]]+Table1[[#This Row],[P2P Import Consumption over Battery Allowance based on Energy Exceeding Allowance % (kWh)]] -> 113 | AD15: =Table1[[#This Row],[Total Consumption Import (kWh)]]-Table1[[#This Row],[Total P2P import (kWh)]] -> 0 | AE15: =IFERROR(Table1[[#This Row],[Total P2P import (kWh)]]/$AC$30,0) -> 0.014756061 | AF15: =($Q$24-$AR$24) -> 1403 | AG15: =AF15*AE15 -> 20.702754 | AH15: =SUM($Q$26:$Q$28) -> 697 | AI15: =Table1[[#This Row],[Cluster''s Total Common Services (kWh)]]*Table1[[#This Row],[Percentage of Unit Entitlement (%)]] -> 21.607 | AJ15: =AG15*'Tariff Rates'!$B$3 -> 4.5546059 | AK15: =Table1[[#This Row],[Common Services based on Split per Unit Entitlement % to battery (kWh)]]*'Tariff Rates'!$B$3 -> 4.75354 | AL15: =Table1[[#This Row],[Total P2P import (kWh)]]*IF(Table1[[#This Row],[Total Lot Export (kWh)]]=0,'Tariff Rates'!$L$3,'Tariff Rates'!$B$3) -> 40.68 | AM15: =Table1[[#This Row],[P2P Import Consumption over Battery Allowance based on Energy Exceeding Allowance % (kWh)]]*'Tariff Rates'!$J$3 -> 0 | AN15: =Table1[[#This Row],[Energy Import from Grid (kWh)]]*'Tariff Rates'!$E$3 -> 0 | AO15: =SUM(AJ15:AN15) -> 49.988146 | AP15: {=INDEX(Reading_export[1/1/2025],MATCH(1,(Reading_export[Lot]=A15)*(Reading_export[cluster]=$B$1),0))} -> 0 | AQ15: {=INDEX(Reading_export[01/04/2025],MATCH(1,(Reading_export[Lot]=A15)*(Reading_export[cluster]=$B$1),0))} -> 0 | AR15: =Table1[[#This Row],[Last day of reporting period: export]]-Table1[[#This Row],[1st day of reporting period: export]] -> 0 | AS15: =AR15/$AR$30 -> 0 | AT15: =Table1[[#This Row],[Percentage of Total export for Billing Period (%)]]*$AC$30 -> 0 | AU15: =IF($Y$30-$E$38>0,$Y$30-$E$38,0) -> 72.54 | AV15: =IFERROR(Table1[[#This Row],[Total Cluster Energy Balance for P2P Trading (kWh)2]]*Table1[[#This Row],[Unused Daily Allowance %]],0) -> 2.9107223 | AW15: =AS15*AF15 -> 0 | AX15: =Table1[[#This Row],[Cluster''s Total Common Services (kWh)]]*Table1[[#This Row],[Percentage of Total export for Billing Period (%)]] -> 0 | AY15: =$Q$25*Table1[[#This Row],[Percentage of Total export for Billing Period (%)]] -> 0 | AZ15: =Table1[[#This Row],[Total Lot Export (kWh)]]-Table1[[#This Row],[Total Energy Export P2P to battery (kWh)]]-Table1[[#This Row],[Axillary Battery Losses based upon Adjusted % total export (kWh)]]-Table1[[#This Row],[Common Service based upon % total export to battery (kWh)]]-Table1[[#This Row],[EV Charger based upon % total export to battery (kWh)]] -> 0 | BA15: =IFERROR(IF($AZ$30-$F$38>0,$AZ$30-$F$38,0),0) -> 0 | BB15: =Table1[[#This Row],[Energy Losses When Export to Grid (kWh)]]*Table1[[#This Row],[Percentage of Total export for Billing Period (%)]] -> 0 | BC15: =Table1[[#This Row],[Therotical Energy Export to Grid (kWh)]]-Table1[[#This Row],[Energy Losses When Export to Grid based up % total export (kWh)]] -> 0 | BD15: =AW15*'Tariff Rates'!$C$3 -> 0 | BE15: =Table1[[#This Row],[Common Service based upon % total export to battery (kWh)]]*'Tariff Rates'!$C$3 -> 0 | BF15: =Table1[[#This Row],[EV Charger based upon % total export to battery (kWh)]]*'Tariff Rates'!$C$3 -> 0 | BG15: =AT15*'Tariff Rates'!$C$3 -> 0 | BH15: =Table1[[#This Row],[Borrowed Allowance Based on Unused Daily Allowance % (kWh)]]*'Tariff Rates'!$K$3 -> -0.058214447 | BI15: =BC15*'Tariff Rates'!$F$3 -> 0 | BJ15: =SUM(BD15:BI15) -> -0.058214447 | BK15: =$D$43*Table1[[#This Row],[Percentage of Unit Entitlement (%)]] -> 0 | BL15: =BK15*'Tariff Rates'!$H$3 -> 0 | BM15: =($Q$25)*Table1[[#This Row],[Percentage of Unit Entitlement (%)]]*'Tariff Rates'!$B$3 -> 20.55548 | BN15: =SUM(BM15,BL15) -> 20.55548 | BO15: =BK15 -> 0 | BP15: =BO15+BN15 -> 20.55548 | BQ15: =AO15+BJ15+N15+BP15 -> 140.78494 | BT15: 11
A16: 12 | B16: {=INDEX(Table_Household_Alloc[Owner],MATCH(1,(Table_Household_Alloc[Lot]=A16)*(Table_Household_Alloc[cluster]=$B$1),0))} -> Sandra Handy | C16: {=INDEX(Reading_import[Meter'#],MATCH(1,(Table_Household_Alloc[Lot]=A16)*(Table_Household_Alloc[cluster]=$B$1),0))} -> 3308026898 | D16: {=INDEX(Table_Household_Alloc[UE % over Cluster],MATCH(1,(Table_Household_Alloc[Lot]=A16)*(Table_Household_Alloc[cluster]=$B$1),0))} -> 0.031 | E16: {=INDEX(Table_Household_Alloc[Stage of Dev.],MATCH(1,(Table_Household_Alloc[Lot]=A16)*(Table_Household_Alloc[cluster]=$B$1),0))} -> O | F16: {=INDEX(Amanda_energy[Daily_Supply_incl_GST],MATCH(1,(Amanda_energy[Cluster]=$B$1)*(Amanda_energy[Month]=$F$2),0))/MAX($A:$A)} -> 8.9736842 | G16: {=INDEX(Amanda_energy[Daily_Supply_incl_GST],MATCH(1,(Amanda_energy[Cluster]=$B$1)*(Amanda_energy[Month]=$G$2),0))/MAX($A:$A)} -> 8.1052632 | H16: {=INDEX(Amanda_energy[Daily_Supply_incl_GST],MATCH(1,(Amanda_energy[Cluster]=$B$1)*(Amanda_energy[Month]=$H$2),0))/MAX($A:$A)} -> 8.9736842 | I16: =$J$38/MAX($A:$A) -> 3.2268421 | J16: ='Tariff Rates'!$B$8*$J$3 -> 13.561644 | K16: ='Tariff Rates'!$C$8*Table1[[#This Row],[Percentage of Unit Entitlement (%)]]*'Energy billing Mastersheet_fml'!$K$3 -> 6.558411 | L16: =$L$3*'Tariff Rates'!$D$8*IF(Table1[[#This Row],[Stage of Dev.]]="V",0,1) -> 19.8 | M16: 1.1 | N16: =SUM(F16:M16) -> 70.299528 | O16: {=INDEX(Reading_import[1/1/2025],MATCH(1,(Reading_import[Lot]=A16)*(Reading_import[cluster]=$B$1),0))} -> 1704.76 | P16: {=INDEX(Reading_import[01/04/2025],MATCH(1,(Reading_import[Lot]=A16)*(Reading_import[cluster]=$B$1),0))} -> 1900.16 | Q16: =Table1[[#This Row],[Last day of reporting period: import]]-Table1[[#This Row],[1st day of reporting period: import]] -> 195.4 | R16: =Q16/$N$3 -> 2.1711111 | S16: =Q16/$Q$30 -> 0.025159662 | T16: =IF(Table1[[#This Row],[Stage of Dev.]]="V",0,233*Table1[[#This Row],[Percentage of Unit Entitlement (%)]]) -> 7.223 | U16: =IF(T16>R16,R16,T16) -> 2.1711111 | V16: =Table1[[#This Row],[Daily Battery allowance based on UE% (kWh)]]-Table1[[#This Row],[Applicable Battery Allowance Daily Consumption (kWh)]] -> 5.0518889 | W16: =Table1[[#This Row],[Unused Daily Allowance (kWh)]]/$V$30 -> 0.033969459 | X16: =IF(Table1[[#This Row],[Applicable Battery Allowance Daily Consumption (kWh)]]>Table1[[#This Row],[Total Daily Average Consumptio for Billing Period (kWh)]],Table1[[#This Row],[Total Consumption Import (kWh)]],U16*$N$3) -> 195.4 | Y16: =IF(Table1[[#This Row],[Applicable Battery Allowance Daily Consumption (kWh)]]>0,ABS(Q16-X16),0) -> 0 | Z16: =IFERROR(Table1[[#This Row],[Energy Exceeding Battery Allowance (kWh)]]/$Y$30,0) -> 0 | AA16: =IF($Y$30-$E$38>0,$Y$30-$E$38,0) -> 72.54 | AB16: =IFERROR(Table1[[#This Row],[Total Cluster Energy Balance for P2P Trading (kWh)]]*Table1[[#This Row],[Energy Exceeding Battery Allowance %]],0) -> 0 | AC16: =Table1[[#This Row],[P2P Import Consumption within Battery Allowance(kWh)]]+Table1[[#This Row],[P2P Import Consumption over Battery Allowance based on Energy Exceeding Allowance % (kWh)]] -> 195.4 | AD16: =Table1[[#This Row],[Total Consumption Import (kWh)]]-Table1[[#This Row],[Total P2P import (kWh)]] -> 0 | AE16: =IFERROR(Table1[[#This Row],[Total P2P import (kWh)]]/$AC$30,0) -> 0.025516234 | AF16: =($Q$24-$AR$24) -> 1403 | AG16: =AF16*AE16 -> 35.799276 | AH16: =SUM($Q$26:$Q$28) -> 697 | AI16: =Table1[[#This Row],[Cluster''s Total Common Services (kWh)]]*Table1[[#This Row],[Percentage of Unit Entitlement (%)]] -> 21.607 | AJ16: =AG16*'Tariff Rates'!$B$3 -> 7.8758407 | AK16: =Table1[[#This Row],[Common Services based on Split per Unit Entitlement % to battery (kWh)]]*'Tariff Rates'!$B$3 -> 4.75354 | AL16: =Table1[[#This Row],[Total P2P import (kWh)]]*IF(Table1[[#This Row],[Total Lot Export (kWh)]]=0,'Tariff Rates'!$L$3,'Tariff Rates'!$B$3) -> 42.988 | AM16: =Table1[[#This Row],[P2P Import Consumption over Battery Allowance based on Energy Exceeding Allowance % (kWh)]]*'Tariff Rates'!$J$3 -> 0 | AN16: =Table1[[#This Row],[Energy Import from Grid (kWh)]]*'Tariff Rates'!$E$3 -> 0 | AO16: =SUM(AJ16:AN16) -> 55.617381 | AP16: {=INDEX(Reading_export[1/1/2025],MATCH(1,(Reading_export[Lot]=A16)*(Reading_export[cluster]=$B$1),0))} -> 3279.89 | AQ16: {=INDEX(Reading_export[01/04/2025],MATCH(1,(Reading_export[Lot]=A16)*(Reading_export[cluster]=$B$1),0))} -> 5683.79 | AR16: =Table1[[#This Row],[Last day of reporting period: export]]-Table1[[#This Row],[1st day of reporting period: export]] -> 2403.9 | AS16: =AR16/$AR$30 -> 0.045756411 | AT16: =Table1[[#This Row],[Percentage of Total export for Billing Period (%)]]*$AC$30 -> 350.39665 | AU16: =IF($Y$30-$E$38>0,$Y$30-$E$38,0) -> 72.54 | AV16: =IFERROR(Table1[[#This Row],[Total Cluster Energy Balance for P2P Trading (kWh)2]]*Table1[[#This Row],[Unused Daily Allowance %]],0) -> 2.4641446 | AW16: =AS16*AF16 -> 64.196245 | AX16: =Table1[[#This Row],[Cluster''s Total Common Services (kWh)]]*Table1[[#This Row],[Percentage of Total export for Billing Period (%)]] -> 31.892219 | AY16: =$Q$25*Table1[[#This Row],[Percentage of Total export for Billing Period (%)]] -> 137.90982 | AZ16: =Table1[[#This Row],[Total Lot Export (kWh)]]-Table1[[#This Row],[Total Energy Export P2P to battery (kWh)]]-Table1[[#This Row],[Axillary Battery Losses based upon Adjusted % total export (kWh)]]-Table1[[#This Row],[Common Service based upon % total export to battery (kWh)]]-Table1[[#This Row],[EV Charger based upon % total export to battery (kWh)]] -> 1819.5051 | BA16: =IFERROR(IF($AZ$30-$F$38>0,$AZ$30-$F$38,0),0) -> 0 | BB16: =Table1[[#This Row],[Energy Losses When Export to Grid (kWh)]]*Table1[[#This Row],[Percentage of Total export for Billing Period (%)]] -> 0 | BC16: =Table1[[#This Row],[Therotical Energy Export to Grid (kWh)]]-Table1[[#This Row],[Energy Losses When Export to Grid based up % total export (kWh)]] -> 1819.5051 | BD16: =AW16*'Tariff Rates'!$C$3 -> -14.123174 | BE16: =Table1[[#This Row],[Common Service based upon % total export to battery (kWh)]]*'Tariff Rates'!$C$3 -> -7.0162881 | BF16: =Table1[[#This Row],[EV Charger based upon % total export to battery (kWh)]]*'Tariff Rates'!$C$3 -> -30.340161 | BG16: =AT16*'Tariff Rates'!$C$3 -> -77.087263 | BH16: =Table1[[#This Row],[Borrowed Allowance Based on Unused Daily Allowance % (kWh)]]*'Tariff Rates'!$K$3 -> -0.049282891 | BI16: =BC16*'Tariff Rates'!$F$3 -> -70.050945 | BJ16: =SUM(BD16:BI16) -> -198.66711 | BK16: =$D$43*Table1[[#This Row],[Percentage of Unit Entitlement (%)]] -> 0 | BL16: =BK16*'Tariff Rates'!$H$3 -> 0 | BM16: =($Q$25)*Table1[[#This Row],[Percentage of Unit Entitlement (%)]]*'Tariff Rates'!$B$3 -> 20.55548 | BN16: =SUM(BM16,BL16) -> 20.55548 | BO16: =BK16 -> 0 | BP16: =BO16+BN16 -> 20.55548 | BQ16: =AO16+BJ16+N16+BP16 -> -52.194725 | BT16: 12
... A23: 19 | B23: {=INDEX(Table_Household_Alloc[Owner],MATCH(1,(Table_Household_Alloc[Lot]=A23)*(Table_Household_Alloc[cluster]=$B$1),0))} -> Laurence Hansen Janet Anne Hansen | C23: {=INDEX(Reading_import[Meter'#],MATCH(1,(Table_Household_Alloc[Lot]=A23)*(Table_Household_Alloc[cluster]=$B$1),0))} -> 50003417 | D23: {=INDEX(Table_Household_Alloc[UE % over Cluster],MATCH(1,(Table_Household_Alloc[Lot]=A23)*(Table_Household_Alloc[cluster]=$B$1),0))} -> 0.079 | E23: {=INDEX(Table_Household_Alloc[Stage of Dev.],MATCH(1,(Table_Household_Alloc[Lot]=A23)*(Table_Household_Alloc[cluster]=$B$1),0))} -> O | F23: {=INDEX(Amanda_energy[Daily_Supply_incl_GST],MATCH(1,(Amanda_energy[Cluster]=$B$1)*(Amanda_energy[Month]=$F$2),0))/MAX($A:$A)} -> 8.9736842 | G23: {=INDEX(Amanda_energy[Daily_Supply_incl_GST],MATCH(1,(Amanda_energy[Cluster]=$B$1)*(Amanda_energy[Month]=$G$2),0))/MAX($A:$A)} -> 8.1052632 | H23: {=INDEX(Amanda_energy[Daily_Supply_incl_GST],MATCH(1,(Amanda_energy[Cluster]=$B$1)*(Amanda_energy[Month]=$H$2),0))/MAX($A:$A)} -> 8.9736842 | I23: =$J$38/MAX($A:$A) -> 3.2268421 | J23: ='Tariff Rates'!$B$8*$J$3 -> 13.561644 | K23: ='Tariff Rates'!$C$8*Table1[[#This Row],[Percentage of Unit Entitlement (%)]]*'Energy billing Mastersheet_fml'!$K$3 -> 16.71337 | L23: =$L$3*'Tariff Rates'!$D$8*IF(Table1[[#This Row],[Stage of Dev.]]="V",0,1) -> 19.8 | M23: 1.1 | N23: =SUM(F23:M23) -> 80.454487 | O23: {=INDEX(Reading_import[1/1/2025],MATCH(1,(Reading_import[Lot]=A23)*(Reading_import[cluster]=$B$1),0))} -> 10411 | P23: {=INDEX(Reading_import[01/04/2025],MATCH(1,(Reading_import[Lot]=A23)*(Reading_import[cluster]=$B$1),0))} -> 10951 | Q23: =Table1[[#This Row],[Last day of reporting period: import]]-Table1[[#This Row],[1st day of reporting period: import]] -> 540 | R23: =Q23/$N$3 -> 6 | S23: =Q23/$Q$30 -> 0.069530284 | T23: =IF(Table1[[#This Row],[Stage of Dev.]]="V",0,233*Table1[[#This Row],[Percentage of Unit Entitlement (%)]]) -> 18.407 | U23: =IF(T23>R23,R23,T23) -> 6 | V23: =Table1[[#This Row],[Daily Battery allowance based on UE% (kWh)]]-Table1[[#This Row],[Applicable Battery Allowance Daily Consumption (kWh)]] -> 12.407 | W23: =Table1[[#This Row],[Unused Daily Allowance (kWh)]]/$V$30 -> 0.083426039 | X23: =IF(Table1[[#This Row],[Applicable Battery Allowance Daily Consumption (kWh)]]>Table1[[#This Row],[Total Daily Average Consumptio for Billing Period (kWh)]],Table1[[#This Row],[Total Consumption Import (kWh)]],U23*$N$3) -> 540 | Y23: =IF(Table1[[#This Row],[Applicable Battery Allowance Daily Consumption (kWh)]]>0,ABS(Q23-X23),0) -> 0 | Z23: =IFERROR(Table1[[#This Row],[Energy Exceeding Battery Allowance (kWh)]]/$Y$30,0) -> 0 | AA23: =IF($Y$30-$E$38>0,$Y$30-$E$38,0) -> 72.54 | AB23: =IFERROR(Table1[[#This Row],[Total Cluster Energy Balance for P2P Trading (kWh)]]*Table1[[#This Row],[Energy Exceeding Battery Allowance %]],0) -> 0 | AC23: =Table1[[#This Row],[P2P Import Consumption within Battery Allowance(kWh)]]+Table1[[#This Row],[P2P Import Consumption over Battery Allowance based on Energy Exceeding Allowance % (kWh)]] -> 540 | AD23: =Table1[[#This Row],[Total Consumption Import (kWh)]]-Table1[[#This Row],[Total P2P import (kWh)]] -> 0 | AE23: =IFERROR(Table1[[#This Row],[Total P2P import (kWh)]]/$AC$30,0) -> 0.070515692 | AF23: =($Q$24-$AR$24) -> 1403 | AG23: =AF23*AE23 -> 98.933515 | AH23: =SUM($Q$26:$Q$28) -> 697 | AI23: =Table1[[#This Row],[Cluster''s Total Common Services (kWh)]]*Table1[[#This Row],[Percentage of Unit Entitlement (%)]] -> 55.063 | AJ23: =AG23*'Tariff Rates'!$B$3 -> 21.765373 | AK23: =Table1[[#This Row],[Common Services based on Split per Unit Entitlement % to battery (kWh)]]*'Tariff Rates'!$B$3 -> 12.11386 | AL23: =Table1[[#This Row],[Total P2P import (kWh)]]*IF(Table1[[#This Row],[Total Lot Export (kWh)]]=0,'Tariff Rates'!$L$3,'Tariff Rates'!$B$3) -> 118.8 | AM23: =Table1[[#This Row],[P2P Import Consumption over Battery Allowance based on Energy Exceeding Allowance % (kWh)]]*'Tariff Rates'!$J$3 -> 0 | AN23: =Table1[[#This Row],[Energy Import from Grid (kWh)]]*'Tariff Rates'!$E$3 -> 0 | AO23: =SUM(AJ23:AN23) -> 152.67923 | AP23: {=INDEX(Reading_export[1/1/2025],MATCH(1,(Reading_export[Lot]=A23)*(Reading_export[cluster]=$B$1),0))} -> 25220 | AQ23: {=INDEX(Reading_export[01/04/2025],MATCH(1,(Reading_export[Lot]=A23)*(Reading_export[cluster]=$B$1),0))} -> 29966 | AR23: =Table1[[#This Row],[Last day of reporting period: export]]-Table1[[#This Row],[1st day of reporting period: export]] -> 4746 | AS23: =AR23/$AR$30 -> 0.090336506 | AT23: =Table1[[#This Row],[Percentage of Total export for Billing Period (%)]]*$AC$30 -> 691.78522 | AU23: =IF($Y$30-$E$38>0,$Y$30-$E$38,0) -> 72.54 | AV23: =IFERROR(Table1[[#This Row],[Total Cluster Energy Balance for P2P Trading (kWh)2]]*Table1[[#This Row],[Unused Daily Allowance %]],0) -> 6.0517249 | AW23: =AS23*AF23 -> 126.74212 | AX23: =Table1[[#This Row],[Cluster''s Total Common Services (kWh)]]*Table1[[#This Row],[Percentage of Total export for Billing Period (%)]] -> 62.964545 | AY23: =$Q$25*Table1[[#This Row],[Percentage of Total export for Billing Period (%)]] -> 272.27423 | AZ23: =Table1[[#This Row],[Total Lot Export (kWh)]]-Table1[[#This Row],[Total Energy Export P2P to battery (kWh)]]-Table1[[#This Row],[Axillary Battery Losses based upon Adjusted % total export (kWh)]]-Table1[[#This Row],[Common Service based upon % total export to battery (kWh)]]-Table1[[#This Row],[EV Charger based upon % total export to battery (kWh)]] -> 3592.2339 | BA23: =IFERROR(IF($AZ$30-$F$38>0,$AZ$30-$F$38,0),0) -> 0 | BB23: =Table1[[#This Row],[Energy Losses When Export to Grid (kWh)]]*Table1[[#This Row],[Percentage of Total export for Billing Period (%)]] -> 0 | BC23: =Table1[[#This Row],[Therotical Energy Export to Grid (kWh)]]-Table1[[#This Row],[Energy Losses When Export to Grid based up % total export (kWh)]] -> 3592.2339 | BD23: =AW23*'Tariff Rates'!$C$3 -> -27.883266 | BE23: =Table1[[#This Row],[Common Service based upon % total export to battery (kWh)]]*'Tariff Rates'!$C$3 -> -13.8522 | BF23: =Table1[[#This Row],[EV Charger based upon % total export to battery (kWh)]]*'Tariff Rates'!$C$3 -> -59.900331 | BG23: =AT23*'Tariff Rates'!$C$3 -> -152.19275 | BH23: =Table1[[#This Row],[Borrowed Allowance Based on Unused Daily Allowance % (kWh)]]*'Tariff Rates'!$K$3 -> -0.1210345 | BI23: =BC23*'Tariff Rates'!$F$3 -> -138.301 | BJ23: =SUM(BD23:BI23) -> -392.25058 | BK23: =$D$43*Table1[[#This Row],[Percentage of Unit Entitlement (%)]] -> 0 | BL23: =BK23*'Tariff Rates'!$H$3 -> 0 | BM23: =($Q$25)*Table1[[#This Row],[Percentage of Unit Entitlement (%)]]*'Tariff Rates'!$B$3 -> 52.38332 | BN23: =SUM(BM23,BL23) -> 52.38332 | BO23: =BK23 -> 0 | BP23: =BO23+BN23 -> 52.38332 | BQ23: =AO23+BJ23+N23+BP23 -> -106.73354 | BT23: 16
A24: BESS | B24: BESS Powerpack 232kWh | C24: {=INDEX(Reading_import[Meter'#],MATCH(1,(Table_Household_Alloc[Lot]=A24)*(Table_Household_Alloc[cluster]=$B$1),0))} -> 40002722 | O24: {=INDEX(Reading_import[1/1/2025],MATCH(1,(Reading_import[Lot]=A24)*(Reading_import[cluster]=$B$1),0))} -> 42252 | P24: {=INDEX(Reading_import[01/04/2025],MATCH(1,(Reading_import[Lot]=A24)*(Reading_import[cluster]=$B$1),0))} -> 50626 | Q24: =Table1[[#This Row],[Last day of reporting period: import]]-Table1[[#This Row],[1st day of reporting period: import]] -> 8374 | AP24: {=INDEX(Reading_export[1/1/2025],MATCH(1,(Reading_export[Lot]=A24)*(Reading_export[cluster]=$B$1),0))} -> 33894 | AQ24: {=INDEX(Reading_export[01/04/2025],MATCH(1,(Reading_export[Lot]=A24)*(Reading_export[cluster]=$B$1),0))} -> 40865 | AR24: =Table1[[#This Row],[Last day of reporting period: export]]-Table1[[#This Row],[1st day of reporting period: export]] -> 6971 | BR24: data swapped | BT24: BESS
A25: EV | B25: EV Charger | C25: {=INDEX(Reading_import[Meter'#],MATCH(1,(Table_Household_Alloc[Lot]=A25)*(Table_Household_Alloc[cluster]=$B$1),0))} -> 40002728 | O25: {=INDEX(Reading_import[1/1/2025],MATCH(1,(Reading_import[Lot]=A25)*(Reading_import[cluster]=$B$1),0))} -> 7349 | P25: {=INDEX(Reading_import[01/04/2025],MATCH(1,(Reading_import[Lot]=A25)*(Reading_import[cluster]=$B$1),0))} -> 10363 | Q25: =Table1[[#This Row],[Last day of reporting period: import]]-Table1[[#This Row],[1st day of reporting period: import]] -> 3014 | AP25: {=INDEX(Reading_export[1/1/2025],MATCH(1,(Reading_export[Lot]=A25)*(Reading_export[cluster]=$B$1),0))} -> 0 | AQ25: {=INDEX(Reading_export[01/04/2025],MATCH(1,(Reading_export[Lot]=A25)*(Reading_export[cluster]=$B$1),0))} -> 0 | AR25: =Table1[[#This Row],[Last day of reporting period: export]]-Table1[[#This Row],[1st day of reporting period: export]] -> 0 | BT25: EV
A26: CS | B26: Common Services MSB | C26: {=INDEX(Reading_import[Meter'#],MATCH(1,(Table_Household_Alloc[Lot]=A26)*(Table_Household_Alloc[cluster]=$B$1),0))} -> 50003429 | O26: {=INDEX(Reading_import[1/1/2025],MATCH(1,(Reading_import[Lot]=A26)*(Reading_import[cluster]=$B$1),0))} -> 3640 | P26: {=INDEX(Reading_import[01/04/2025],MATCH(1,(Reading_import[Lot]=A26)*(Reading_import[cluster]=$B$1),0))} -> 4295 | Q26: =Table1[[#This Row],[Last day of reporting period: import]]-Table1[[#This Row],[1st day of reporting period: import]] -> 655 | AP26: {=INDEX(Reading_export[1/1/2025],MATCH(1,(Reading_export[Lot]=A26)*(Reading_export[cluster]=$B$1),0))} -> 0 | AQ26: {=INDEX(Reading_export[01/04/2025],MATCH(1,(Reading_export[Lot]=A26)*(Reading_export[cluster]=$B$1),0))} -> 0 | AR26: =Table1[[#This Row],[Last day of reporting period: export]]-Table1[[#This Row],[1st day of reporting period: export]] -> 0 | BT26: CS
A27: DB1 | B27: Common Services DB1 | O27: {=INDEX(Reading_import[1/1/2025],MATCH(1,(Reading_import[Lot]=A27)*(Reading_import[cluster]=$B$1),0))} -> 149 | P27: {=INDEX(Reading_import[01/04/2025],MATCH(1,(Reading_import[Lot]=A27)*(Reading_import[cluster]=$B$1),0))} -> 168 | Q27: =Table1[[#This Row],[Last day of reporting period: import]]-Table1[[#This Row],[1st day of reporting period: import]] -> 19 | BT27: DB1
A28: DB2 | B28: Common Services DB2 | O28: {=INDEX(Reading_import[1/1/2025],MATCH(1,(Reading_import[Lot]=A28)*(Reading_import[cluster]=$B$1),0))} -> 128 | P28: {=INDEX(Reading_import[01/04/2025],MATCH(1,(Reading_import[Lot]=A28)*(Reading_import[cluster]=$B$1),0))} -> 151 | Q28: =Table1[[#This Row],[Last day of reporting period: import]]-Table1[[#This Row],[1st day of reporting period: import]] -> 23 | BT28: DB2
A29: CP | B29: Strata consumption Site Check Meter | BT29: CP
D30: =SUM(D5:D23) -> 1 | E30: =SUM(E5:E23) -> 0 | F30: =SUM(F5:F23) -> 170.5 | H30: =SUM(H5:H23) -> 170.5 | I30: =SUM(I5:I23) -> 61.31 | J30: =SUM(J5:J23) -> 257.67123 | K30: =SUM(K5:K23) -> 211.56164 | L30: =SUM(L5:L23) -> 376.2 | M30: =SUM(M5:M23) -> 20.9 | N30: =SUM(N5:N23) -> 1422.6429 | Q30: =SUM(Q5:Q23) -> 7766.4 | S30: =SUM(S5:S23) -> 1 | T30: =SUM(T5:T23) -> 233 | V30: =SUM(V5:V23) -> 148.71856 | W30: =SUM(W5:W23) -> 1 | X30: =SUM(X5:X23) -> 7585.33 | Y30: =SUM(Y5:Y23) -> 181.07 | Z30: =SUM(Z5:Z23) -> 1 | AB30: =SUM(AB5:AB29) -> 72.54 | AC30: =SUM(AC5:AC29) -> 7657.87 | AD30: =SUM(AD5:AD29) -> 108.53 | AE30: =SUM(AE5:AE23) -> 1 | AG30: =SUM(AG5:AG23) -> 1403 | AI30: =SUM(AI5:AI23) -> 697 | AJ30: =SUM(AJ5:AJ29) -> 308.66 | AK30: =SUM(AK5:AK29) -> 153.34 | AL30: =SUM(AL5:AL29) -> 1762.5714 | AM30: =SUM(AM5:AM29) -> 1.4508 | AN30: =SUM(AN5:AN29) -> 32.559 | AO30: =SUM(AO5:AO29) -> 2258.5812 | AR30: =SUM(AR5:AR23) -> 52536.9 | AS30: =SUM(AS5:AS23) -> 1 | AT30: =SUM(AT5:AT23) -> 7657.87 | AV30: =SUM(AV5:AV23) -> 72.54 | AW30: =SUM(AW5:AW23) -> 1403 | AX30: =SUM(AX5:AX23) -> 697 | AY30: =SUM(AY5:AY23) -> 3014 | AZ30: =SUM(AZ5:AZ23) -> 39765.03 | BB30: =SUM(BB5:BB23) -> 0 | BC30: =SUM(BC5:BC23) -> 39765.03 | BD30: =SUM(BD5:BD23) -> -308.66 | BE30: =SUM(BE5:BE23) -> -153.34 | BF30: =SUM(BF5:BF23) -> -663.08 | BG30: =SUM(BG5:BG23) -> -1684.7314 | BH30: =SUM(BH5:BH23) -> -1.4508 | BI30: =SUM(BI5:BI23) -> -1530.9537 | ... BP30: =SUM(BP5:BP23) -> 663.08
L31: =COUNTIF(L5:L23,">0") -> 19 | M31: =COUNTIF(M5:M23,">0") -> 19
AA32: = Total Energy exceeding allowance - Actual amanda energy import | AL32: Teants with 0 export will be charge at higher rate for their consumption
B34: Amanda enegery | C34: Year | D34: Month | E34: Consumption_kWh | F34: Export_kWh | G34: Amanda_consumption_incl_GST | H34: Amanda_export_buyback_incl_GST | I34: Daily_Supply_incl_GST | J34: Other_Fees_incl_GST | K34: Total_incl_GST
B35: =B1 -> 1C | C35: 2025 | D35: =F2 -> 01 | E35: {=INDEX(Amanda_energy[Consumption_kWh],MATCH(1,(Amanda_energy[Cluster]=$B$1)*(Amanda_energy[Month]=$D35),0))} -> 44.48 | F35: {=INDEX(Amanda_energy[Export_kWh],MATCH(1,(Amanda_energy[Cluster]=$B$1)*(Amanda_energy[Month]=$D35),0))} -> 13074.94 | G35: {=INDEX(Amanda_energy[Amanda_consumption_incl_GST],MATCH(1,(Amanda_energy[Cluster]=$B$1)*(Amanda_energy[Month]=$D35),0))} -> 13.32 | H35: {=INDEX(Amanda_energy[Amanda_export_buyback_incl_GST],MATCH(1,(Amanda_energy[Cluster]=$B$1)*(Amanda_energy[Month]=$D35),0))} -> -503.38 | I35: {=INDEX(Amanda_energy[Daily_Supply_incl_GST],MATCH(1,(Amanda_energy[Cluster]=$B$1)*(Amanda_energy[Month]=$D35),0))} -> 170.5 | J35: {=INDEX(Amanda_energy[Other_Fees_incl_GST],MATCH(1,(Amanda_energy[Cluster]=$B$1)*(Amanda_energy[Month]=$D35),0))} -> 22.22 | K35: {=INDEX(Amanda_energy[Total_incl_GST],MATCH(1,(Amanda_energy[Cluster]=$B$1)*(Amanda_energy[Month]=$D35),0))} -> -297.34
B36: =B35 -> 1C | C36: 2025 | D36: =G2 -> 02 | E36: {=INDEX(Amanda_energy[Consumption_kWh],MATCH(1,(Amanda_energy[Cluster]=$B$1)*(Amanda_energy[Month]=$D36),0))} -> 46.06 | F36: {=INDEX(Amanda_energy[Export_kWh],MATCH(1,(Amanda_energy[Cluster]=$B$1)*(Amanda_energy[Month]=$D36),0))} -> 12380.74 | G36: {=INDEX(Amanda_energy[Amanda_consumption_incl_GST],MATCH(1,(Amanda_energy[Cluster]=$B$1)*(Amanda_energy[Month]=$D36),0))} -> 13.78 | H36: {=INDEX(Amanda_energy[Amanda_export_buyback_incl_GST],MATCH(1,(Amanda_energy[Cluster]=$B$1)*(Amanda_energy[Month]=$D36),0))} -> -476.66 | I36: {=INDEX(Amanda_energy[Daily_Supply_incl_GST],MATCH(1,(Amanda_energy[Cluster]=$B$1)*(Amanda_energy[Month]=$D36),0))} -> 154 | J36: {=INDEX(Amanda_energy[Other_Fees_incl_GST],MATCH(1,(Amanda_energy[Cluster]=$B$1)*(Amanda_energy[Month]=$D36),0))} -> 19.29 | K36: {=INDEX(Amanda_energy[Total_incl_GST],MATCH(1,(Amanda_energy[Cluster]=$B$1)*(Amanda_energy[Month]=$D36),0))} -> -289.59
B37: =B35 -> 1C | C37: 2025 | D37: =H2 -> 03 | E37: {=INDEX(Amanda_energy[Consumption_kWh],MATCH(1,(Amanda_energy[Cluster]=$B$1)*(Amanda_energy[Month]=$D37),0))} -> 17.99 | F37: {=INDEX(Amanda_energy[Export_kWh],MATCH(1,(Amanda_energy[Cluster]=$B$1)*(Amanda_energy[Month]=$D37),0))} -> 14328.95 | G37: {=INDEX(Amanda_energy[Amanda_consumption_incl_GST],MATCH(1,(Amanda_energy[Cluster]=$B$1)*(Amanda_energy[Month]=$D37),0))} -> 5.38 | H37: {=INDEX(Amanda_energy[Amanda_export_buyback_incl_GST],MATCH(1,(Amanda_energy[Cluster]=$B$1)*(Amanda_energy[Month]=$D37),0))} -> -551.66 | I37: {=INDEX(Amanda_energy[Daily_Supply_incl_GST],MATCH(1,(Amanda_energy[Cluster]=$B$1)*(Amanda_energy[Month]=$D37),0))} -> 170.5 | J37: {=INDEX(Amanda_energy[Other_Fees_incl_GST],MATCH(1,(Amanda_energy[Cluster]=$B$1)*(Amanda_energy[Month]=$D37),0))} -> 19.8 | K37: {=INDEX(Amanda_energy[Total_incl_GST],MATCH(1,(Amanda_energy[Cluster]=$B$1)*(Amanda_energy[Month]=$D37),0))} -> -355.98
B38: Total | E38: =SUM(E35:E37) -> 108.53 | F38: =SUM(F35:F37) -> 39784.63 | G38: =SUM(G35:G37) -> 32.48 | H38: =SUM(H35:H37) -> -1531.7 | I38: =SUM(I35:I37) -> 495 | J38: =SUM(J35:J37) -> 61.31 | K38: =SUM(K35:K37) -> -942.91
G39: =G38/E38 -> 0.29927209 | H39: =H38/F38 -> -0.038499793
B40: Month | C40: EV Charger KWh/month total | D40: Chargefox Revenue | E40: Chargefox Revenue -5%
B43: Total | C43: =SUM(C41:C42) -> 0 | D43: =SUM(D41:D42) -> 0 | E43: =SUM(E41:E42) -> 0
C44: =C43/Q25 -> 0
B46: Strata reconcilation table | C46: $ Incl. GST
B47: Residents supply charge | C47: =N30 -> 1422.6429
B48: Amanda buyback | C48: =SUM(H38)*-1 -> 1531.7
B49: Residents energy consumption | C49: =AO30 -> 2258.5812
B50: EV Charger operation cost | C50: =BN30 -> 663.08
B51: ChargeFox Income | C51: =E43*-1 -> 0
B52: Strata total income | C52: =SUM(C47:C51) -> 5876.0041
B53: Total payout to resident for exporting | C53: =BJ30 -> -4342.2159
B54: Total payout to resident for EV charger revenue | C54: =BO30 -> 0
B55: Total payout to Amanda Energy | C55: =(G38+J38+I38)*-1 -> -588.79
B56: Total payout to supply (SwichDin, E47, ChargeFox) | C56: =SUM(J30:M30)*-1 -> -866.33288
B57: Strata total payout | C57: =SUM(C53:C56) -> -5797.3387
B58: P2P subsidies for residents without solar panels | C58: =AL30+BG30 -> 77.84
B59: Variance | C59: =C52+C57-C58 -> 0.825345
B60: Variance % | C60: =C59/C52 -> 0.00014046025

Sheet Energy billing Mastersheet
B1: 1C | C1: billing period | F1: 45658 | H1: 45747
F2: 01 | G2: 02 | H2: 03
C3: Number of Days | F3: 31 | G3: 29 | H3: 31 | I3: 90 | J3: 90 | K3: 90 | L3: 90 | M3: 1 | N3: 90 | P3: Import data | R3: Consumption Energy | AE3: Battery Loss and common services | AQ3: Export data | BK3: EV Charger Reconcillation | BQ3: Combined
A4: Lot | B4: Name | C4: Meter Numbers | D4: Percentage of Unit Entitlement (%) | E4: Stage of Dev. | F4: Amanda Energy Daily Supply Charge ($) | G4: Amanda Energy Daily Supply Charge ($)2 | H4: Amanda Energy Daily Supply Charge ($)3 | I4: Amanda Energy Other fees ($) | J4: SwitchdIn Cost Daily Supply Charge ($) | K4: Chargefox Daily Supply Charge ($) | L4: Element47 Embedded Network Daily Supply Charges | M4: Element47 Embedded Network Invoicing Fees | N4: Total supply | O4: 1st day of reporting period: import | P4: Last day of reporting period: import | Q4: Total Consumption Import (kWh) | R4: Total Daily Average Consumptio for Billing Period (kWh) | S4: Percentage of Total Import for Billing Period (%) | T4: Daily Battery allowance based on UE% (kWh) | U4: Applicable Battery Allowance Daily Consumption (kWh) | V4: Unused Daily Allowance (kWh) | W4: Unused Daily Allowance % | X4: P2P Import Consumption within Battery Allowance(kWh) | Y4: Energy Exceeding Battery Allowance (kWh) | Z4: Energy Exceeding Battery Allowance % | AA4: Total Cluster Energy Balance for P2P Trading (kWh) | AB4: P2P Import Consumption over Battery Allowance based on Energy Exceeding Allowance % (kWh) | AC4: Total P2P import (kWh) | AD4: Energy Import from Grid (kWh) | AE4: P2P import% | AF4: Cluster's Total Battery Loss (kWh) | AG4: Axillary Battery Losses based upon P2P import % (kWh) | AH4: Cluster's Total Common Services (kWh) | AI4: Common Services based on Split per Unit Entitlement % to battery (kWh) | AJ4: Axillary Battery Loss Charges at P2P Rates based upon P2P import % ($) | AK4: Common Services Cost Split per Unit Entitlement at P2P rate ($) | AL4: P2P Import Cost ($) | AM4: Exceeding Battery Allowance P2P Fee ($) | AN4: Import From Grid Cost ($) | AO4: Total Consumption Cost/Lot | AP4: 1st day of reporting period: export | AQ4: Last day of reporting period: export | AR4: Total Lot Export (kWh) | AS4: Percentage of Total export for Billing Period (%) | AT4: Total Energy Export P2P to battery (kWh) | AU4: Total Cluster Energy Balance for P2P Trading (kWh)2 | AV4: Borrowed Allowance Based on Unused Daily Allowance % (kWh) | AW4: Axillary Battery Losses based upon Adjusted % total export (kWh) | AX4: Common Service based upon % total export to battery (kWh) | AY4: EV Charger based upon % total export to battery (kWh) | AZ4: Therotical Energy Export to Grid (kWh) | BA4: Energy Losses When Export to Grid (kWh) | BB4: Energy Losses When Export to Grid based up % total export (kWh) | BC4: Energy Export to Grid after Losses (kWh) | BD4: Axillary Battery Losses based upon % total export ($) | BE4: Common Service Earning based upon % total export to Load ($) | BF4: EV Charger based upon % total export ($) | BG4: P2P Export Earnings ($) | BH4: Passive Compensation ($) | BI4: Grid Export Earnings ($) | BJ4: Total Export Earnings Per Lot After P2P Battery Energy Storage and Use ($) | BK4: EV Charger Income from Sales Equitable Distribution on UE ($) | BL4: Chargefox Commission on EV Charge Consumption Sales Cost Split by Unit Entitlement ($) | BM4: EV Charger Cost of Electricity Supply at P2P Rates ($) | BN4: Total EV Charger Operating Cost ($) | BO4: Total EV Charger Revenue ($) | BP4: EV Charger Profit per lot owner ($) | BQ4: Energy Invoice Total Charges or Revenue $ | BR4: Date issued | BS4: Date Paid | BT4: Lot
A5: 1 | B5: Aron Dyer Jodie Passmore | C5: 50003397 | D5: 0.042 | E5: O | F5: 8.9736842 | G5: 8.1052632 | H5: 8.9736842 | I5: 3.2268421 | J5: 13.561644 | K5: 8.885589 | L5: 19.8 | M5: 1.1 | N5: 72.626707 | O5: 8252 | P5: 8745 | Q5: 493 | R5: 5.4777778 | S5: 0.063478574 | T5: 9.786 | U5: 5.4777778 | V5: 4.3082222 | W5: 0.028968962 | X5: 493 | Y5: 0 | Z5: 0 | AA5: 72.54 | AB5: 0 | AC5: 493 | AD5: 0 | AE5: 0.064378215 | AF5: 1403 | AG5: 90.322635 | AH5: 697 | AI5: 29.274 | AJ5: 19.87098 | AK5: 6.44028 | AL5: 108.46 | AM5: 0 | AN5: 0 | AO5: 134.77126 | AP5: 33585 | AQ5: 37477 | AR5: 3892 | AS5: 0.074081265 | AT5: 567.3047 | AU5: 72.54 | AV5: 2.1014085 | AW5: 103.93601 | AX5: 51.634642 | AY5: 223.28093 | AZ5: 2945.8437 | BA5: 0 | BB5: 0 | BC5: 2945.8437 | BD5: -22.865923 | BE5: -11.359621 | BF5: -49.121805 | BG5: -124.80703 | BH5: -0.04202817 | BI5: -113.41498 | BJ5: -321.61139 | BK5: -30.42984 | BL5: 1.521492 | BM5: 27.84936 | BN5: 29.370852 | BO5: -30.42984 | BP5: -1.058988 | BQ5: -115.27242 | BT5: 1
A6: 2 | B6: Eli Sutton | C6: 50003402 | D6: 0.043 | E6: O | F6: 8.9736842 | G6: 8.1052632 | H6: 8.9736842 | I6: 3.2268421 | J6: 13.561644 | K6: 9.0971507 | L6: 19.8 | M6: 1.1 | N6: 72.838268 | O6: 3795 | P6: 4028 | Q6: 233 | R6: 2.5888889 | S6: 0.03000103 | T6: 10.019 | U6: 2.5888889 | V6: 7.4301111 | W6: 0.049960888 | X6: 233 | Y6: 0 | Z6: 0 | AA6: 72.54 | AB6: 0 | AC6: 233 | AD6: 0 | AE6: 0.030426215 | AF6: 1403 | AG6: 42.68798 | AH6: 697 | AI6: 29.971 | AJ6: 9.3913556 | AK6: 6.59362 | AL6: 51.26 | AM6: 0 | AN6: 0 | AO6: 67.244976 | AP6: 15113 | AQ6: 17462 | AR6: 2349 | AS6: 0.044711431 | AT6: 342.39433 | AU6: 72.54 | AV6: 3.6241628 | AW6: 62.730138 | AX6: 31.163868 | AY6: 134.76025 | AZ6: 1777.9514 | BA6: 0 | BB6: 0 | BC6: 1777.9514 | BD6: -13.80063 | BE6: -6.8560509 | BF6: -29.647256 | BG6: -75.326752 | BH6: -0.072483256 | BI6: -68.451129 | BJ6: -194.1543 | BK6: -31.15436 | BL6: 1.557718 | BM6: 28.51244 | BN6: 30.070158 | BO6: -31.15436 | BP6: -1.084202 | BQ6: -55.15526 | BT6: 2
A7: 3 | B7: Shelley Chapman Cherry Chapman | C7: 50003431 | D7: 0.044 | E7: O | F7: 8.9736842 | G7: 8.1052632 | H7: 8.9736842 | I7: 3.2268421 | J7: 13.561644 | K7: 9.3087123 | L7: 19.8 | M7: 1.1 | N7: 73.04983 | O7: 3227 | P7: 3513 | Q7: 286 | R7: 3.1777778 | S7: 0.036825299 | T7: 10.252 | U7: 3.1777778 | V7: 7.0742222 | W7: 0.047567852 | X7: 286 | Y7: 0 | Z7: 0 | AA7: 72.54 | AB7: 0 | AC7: 286 | AD7: 0 | AE7: 0.0373472 | AF7: 1403 | AG7: 52.398121 | AH7: 697 | AI7: 30.668 | AJ7: 11.527587 | AK7: 6.74696 | AL7: 62.92 | AM7: 0 | AN7: 0 | AO7: 81.194547 | AP7: 18755 | AQ7: 22749 | AR7: 3994 | AS7: 0.076022757 | AT7: 582.17239 | AU7: 72.54 | AV7: 3.450572 | AW7: 106.65993 | AX7: 52.987862 | AY7: 229.13259 | AZ7: 3023.0472 | BA7: 0 | BB7: 0 | BC7: 3023.0472 | BD7: -23.465184 | BE7: -11.65733 | BF7: -50.40917 | BG7: -128.07793 | BH7: -0.06901144 | BI7: -116.38732 | BJ7: -330.06594 | BK7: -31.87888 | BL7: 1.593944 | BM7: 29.17552 | BN7: 30.769464 | BO7: -31.87888 | BP7: -1.109416 | BQ7: -176.93098 | BT7: 3
A8: 4 | B8: Jillian Ann Luckhurst | C8: 50003394 | D8: 0.045 | E8: O | F8: 8.9736842 | G8: 8.1052632 | H8: 8.9736842 | I8: 3.2268421 | J8: 13.561644 | K8: 9.520274 | L8: 19.8 | M8: 1.1 | N8: 73.261391 | O8: 2811 | P8: 3033 | Q8: 222 | R8: 2.4666667 | S8: 0.028584672 | T8: 10.485 | U8: 2.4666667 | V8: 8.0183333 | W8: 0.053916159 | X8: 222 | Y8: 0 | Z8: 0 | AA8: 72.54 | AB8: 0 | AC8: 222 | AD8: 0 | AE8: 0.028989784 | AF8: 1403 | AG8: 40.672667 | AH8: 697 | AI8: 31.365 | AJ8: 8.9479868 | AK8: 6.9003 | AL8: 48.84 | AM8: 0 | AN8: 0 | AO8: 64.688287 | AP8: 11256 | AQ8: 13492 | AR8: 2236 | AS8: 0.042560562 | AT8: 325.92325 | AU8: 72.54 | AV8: 3.9110782 | AW8: 59.712469 | AX8: 29.664712 | AY8: 128.27753 | AZ8: 1692.422 | BA8: 0 | BB8: 0 | BC8: 1692.422 | BD8: -13.136743 | BE8: -6.5262366 | BF8: -28.221058 | BG8: -71.703116 | BH8: -0.078221564 | BI8: -65.158248 | BJ8: -184.82362 | BK8: -32.6034 | BL8: 1.63017 | BM8: 29.8386 | BN8: 31.46877 | BO8: -32.6034 | BP8: -1.13463 | BQ8: -48.008574 | BT8: 4
A9: 5 | B9: Samuel Vinciullo | C9: 50003433 | D9: 0.046 | E9: O | F9: 8.9736842 | G9: 8.1052632 | H9: 8.9736842 | I9: 3.2268421 | J9: 13.561644 | K9: 9.7318356 | L9: 19.8 | M9: 1.1 | N9: 73.472953 | O9: 6084 | P9: 6998 | Q9: 914 | R9: 10.155556 | S9: 0.11768644 | T9: 10.718 | U9: 10.155556 | V9: 0.56244444 | W9: 0.0037819386 | X9: 914 | Y9: 0 | Z9: 0 | AA9: 72.54 | AB9: 0 | AC9: 914 | AD9: 0 | AE9: 0.11935434 | AF9: 1403 | AG9: 167.45414 | AH9: 697 | AI9: 32.062 | AJ9: 36.83991 | AK9: 7.05364 | AL9: 201.08 | AM9: 0 | AN9: 0 | AO9: 244.97355 | AP9: 34752 | AQ9: 38690 | AR9: 3938 | AS9: 0.07495684 | AT9: 574.00974 | AU9: 72.54 | AV9: 0.27434183 | AW9: 105.16445 | AX9: 52.244917 | AY9: 225.91992 | AZ9: 2980.661 | BA9: 0 | BB9: 0 | BC9: 2980.661 | BD9: -23.136178 | BE9: -11.493882 | BF9: -49.702381 | BG9: -126.28214 | BH9: -0.0054868365 | BI9: -114.75545 | BJ9: -325.37552 | BK9: -33.32792 | BL9: 1.666396 | BM9: 30.50168 | BN9: 32.168076 | BO9: -33.32792 | BP9: -1.159844 | BQ9: -8.088859 | BT9: 5
A10: 6 | B10: Christopher Paul Martin Vicki Ann Martin | C10: 50003421 | D10: 0.066 | E10: O | F10: 8.9736842 | G10: 8.1052632 | H10: 8.9736842 | I10: 3.2268421 | J10: 13.561644 | K10: 13.963068 | L10: 19.8 | M10: 1.1 | N10: 77.704186 | O10: 5469 | P10: 5889 | Q10: 420 | R10: 4.6666667 | S10: 0.05407911 | T10: 15.378 | U10: 4.6666667 | V10: 10.711333 | W10: 0.072024189 | X10: 420 | Y10: 0 | Z10: 0 | AA10: 72.54 | AB10: 0 | AC10: 420 | AD10: 0 | AE10: 0.054845538 | AF10: 1403 | AG10: 76.94829 | AH10: 697 | AI10: 46.002 | AJ10: 16.928624 | AK10: 10.12044 | AL10: 92.4 | AM10: 0 | AN10: 0 | AO10: 119.44906 | AP10: 15827 | AQ10: 20723 | AR10: 4896 | AS10: 0.093191642 | AT10: 713.64948 | AU10: 72.54 | AV10: 5.2246347 | AW10: 130.74787 | AX10: 64.954575 | AY10: 280.87961 | AZ10: 3705.7685 | BA10: 0 | BB10: 0 | BC10: 3705.7685 | BD10: -28.764532 | BE10: -14.290006 | BF10: -61.793514 | BG10: -157.00289 | BH10: -0.10449269 | BI10: -142.67209 | BJ10: -404.62752 | BK10: -47.81832 | BL10: 2.390916 | BM10: 43.76328 | BN10: 46.154196 | BO10: -47.81832 | BP10: -1.664124 | BQ10: -209.13839 | BT10: 6
A11: 7 | B11: Dex Ezekiel, Jeannine Penniment | C11: 50002953 | D11: 0.066 | E11: UC/M/ND | F11: 8.9736842 | G11: 8.1052632 | H11: 8.9736842 | I11: 3.2268421 | J11: 13.561644 | K11: 13.963068 | L11: 19.8 | M11: 1.1 | N11: 77.704186 | O11: 164 | P11: 166 | Q11: 2 | R11: 0.022222222 | S11: 0.00025751957 | T11: 15.378 | U11: 0.022222222 | V11: 15.355778 | W11: 0.10325395 | X11: 2 | Y11: 0 | Z11: 0 | AA11: 72.54 | AB11: 0 | AC11: 2 | AD11: 0 | AE11: 0.00026116923 | AF11: 1403 | AG11: 0.36642043 | AH11: 697 | AI11: 46.002 | AJ11: 0.080612494 | AK11: 10.12044 | AL11: 0.72 | AM11: 0 | AN11: 0 | AO11: 10.921052 | AP11: 142 | AQ11: 142 | AR11: 0 | AS11: 0 | AT11: 0 | AU11: 72.54 | AV11: 7.4900413 | AW11: 0 | AX11: 0 | AY11: 0 | AZ11: 0 | BA11: 0 | BB11: 0 | BC11: 0 | BD11: 0 | BE11: 0 | BF11: 0 | BG11: 0 | BH11: -0.14980083 | BI11: 0 | BJ11: -0.14980083 | BK11: -47.81832 | BL11: 2.390916 | BM11: 43.76328 | BN11: 46.154196 | BO11: -47.81832 | BP11: -1.664124 | BQ11: 86.811314 | BT11: 7
A12: 8 | B12: Eric Martini Karina Jean Martini | C12: 50003395 | D12: 0.066 | E12: O | F12: 8.9736842 | G12: 8.1052632 | H12: 8.9736842 | I12: 3.2268421 | J12: 13.561644 | K12: 13.963068 | L12: 19.8 | M12: 1.1 | N12: 77.704186 | O12: 12726 | P12: 13279 | Q12: 553 | R12: 6.1444444 | S12: 0.071204162 | T12: 15.378 | U12: 6.1444444 | V12: 9.2335556 | W12: 0.062087448 | X12: 553 | Y12: 0 | Z12: 0 | AA12: 72.54 | AB12: 0 | AC12: 553 | AD12: 0 | AE12: 0.072213292 | AF12: 1403 | AG12: 101.31525 | AH12: 697 | AI12: 46.002 | AJ12: 22.289355 | AK12: 10.12044 | AL12: 121.66 | AM12: 0 | AN12: 0 | AO12: 154.06979 | AP12: 41841 | AQ12: 46064 | AR12: 4223 | AS12: 0.080381598 | AT12: 615.55183 | AU12: 72.54 | AV12: 4.5038235 | AW12: 112.77538 | AX12: 56.025974 | AY12: 242.27014 | AZ12: 3196.3767 | BA12: 0 | BB12: 0 | BC12: 3196.3767 | BD12: -24.810584 | BE12: -12.325714 | BF12: -53.29943 | BG12: -135.4214 | BH12: -0.090076469 | BI12: -123.0605 | BJ12: -349.00771 | BK12: -47.81832 | BL12: 2.390916 | BM12: 43.76328 | BN12: 46.154196 | BO12: -47.81832 | BP12: -1.664124 | BQ12: -118.89785 | BT12: 8
A13: 9 | B13: Christopher van Etten Emmanuelle van Etten | C13: 50003435 | D13: 0.066 | E13: UC | F13: 8.9736842 | G13: 8.1052632 | H13: 8.9736842 | I13: 3.2268421 | J13: 13.561644 | K13: 13.963068 | L13: 19.8 | M13: 1.1 | N13: 77.704186 | O13: 76 | P13: 158 | Q13: 82 | R13: 0.91111111 | S13: 0.010558302 | T13: 15.378 | U13: 0.91111111 | V13: 14.466889 | W13: 0.097276959 | X13: 82 | Y13: 0 | Z13: 0 | AA13: 72.54 | AB13: 0 | AC13: 82 | AD13: 0 | AE13: 0.010707938 | AF13: 1403 | AG13: 15.023238 | AH13: 697 | AI13: 46.002 | AJ13: 3.3051123 | AK13: 10.12044 | AL13: 29.52 | AM13: 0 | AN13: 0 | AO13: 42.945552 | AP13: 0 | AQ13: 0 | AR13: 0 | AS13: 0 | AT13: 0 | AU13: 72.54 | AV13: 7.0564706 | AW13: 0 | AX13: 0 | AY13: 0 | AZ13: 0 | BA13: 0 | BB13: 0 | BC13: 0 | BD13: 0 | BE13: 0 | BF13: 0 | BG13: 0 | BH13: -0.14112941 | BI13: 0 | BJ13: -0.14112941 | BK13: -47.81832 | BL13: 2.390916 | BM13: 43.76328 | BN13: 46.154196 | BO13: -47.81832 | BP13: -1.664124 | BQ13: 118.84448 | BT13: 9
A14: 10 | B14: Peter Smith | C14: 50002952 | D14: 0.031 | E14: O | F14: 8.9736842 | G14: 8.1052632 | H14: 8.9736842 | I14: 3.2268421 | J14: 13.561644 | K14: 6.558411 | L14: 19.8 | M14: 1.1 | N14: 70.299528 | O14: 6735 | P14: 6989 | Q14: 254 | R14: 2.8222222 | S14: 0.032704986 | T14: 7.223 | U14: 2.8222222 | V14: 4.4007778 | W14: 0.029591316 | X14: 254 | Y14: 2.8421709e-14 | Z14: 1.5696531e-16 | AA14: 72.54 | AB14: 1.1386264e-14 | AC14: 254 | AD14: 0 | AE14: 0.033168492 | AF14: 1403 | AG14: 46.535394 | AH14: 697 | AI14: 21.607 | AJ14: 10.237787 | AK14: 4.75354 | AL14: 55.88 | AM14: 2.2772528e-16 | AN14: 0 | AO14: 70.871327 | AP14: 10088 | AQ14: 12402 | AR14: 2314 | AS14: 0.044045233 | AT14: 337.29267 | AU14: 72.54 | AV14: 2.1465541 | AW14: 61.795462 | AX14: 30.699527 | AY14: 132.75233 | AZ14: 1751.46 | BA14: 0 | BB14: 0 | BC14: 1751.46 | BD14: -13.595002 | BE14: -6.753896 | BF14: -29.205513 | BG14: -74.204387 | BH14: -0.042931081 | BI14: -67.43121 | BJ14: -191.23294 | BK14: -22.46012 | BL14: 1.123006 | BM14: 20.55548 | BN14: 21.678486 | BO14: -22.46012 | BP14: -0.781634 | BQ14: -50.843718 | BT14: 10
A15: 11 | B15: Peter Andre Grant | C15: 50002944 | D15: 0.031 | E15: UC/M/ND | F15: 8.9736842 | G15: 8.1052632 | H15: 8.9736842 | I15: 3.2268421 | J15: 13.561644 | K15: 6.558411 | L15: 19.8 | M15: 1.1 | N15: 70.299528 | O15: 36 | P15: 149 | Q15: 113 | R15: 1.2555556 | S15: 0.014549856 | T15: 7.223 | U15: 1.2555556 | V15: 5.9674444 | W15: 0.040125756 | X15: 113 | Y15: 0 | Z15: 0 | AA15: 72.54 | AB15: 0 | AC15: 113 | AD15: 0 | AE15: 0.014756061 | AF15: 1403 | AG15: 20.702754 | AH15: 697 | AI15: 21.607 | AJ15: 4.5546059 | AK15: 4.75354 | AL15: 40.68 | AM15: 0 | AN15: 0 | AO15: 49.988146 | AP15: 0 | AQ15: 0 | AR15: 0 | AS15: 0 | AT15: 0 | AU15: 72.54 | AV15: 2.9107223 | AW15: 0 | AX15: 0 | AY15: 0 | AZ15: 0 | BA15: 0 | BB15: 0 | BC15: 0 | BD15: 0 | BE15: 0 | BF15: 0 | BG15: 0 | BH15: -0.058214447 | BI15: 0 | BJ15: -0.058214447 | BK15: -22.46012 | BL15: 1.123006 | BM15: 20.55548 | BN15: 21.678486 | BO15: -22.46012 | BP15: -0.781634 | BQ15: 119.44783 | BT15: 11
A16: 12 | B16: Sandra Handy | C16: 3308026898 | D16: 0.031 | E16: O | F16: 8.9736842 | G16: 8.1052632 | H16: 8.9736842 | I16: 3.2268421 | J16: 13.561644 | K16: 6.558411 | L16: 19.8 | M16: 1.1 | N16: 70.299528 | O16: 1704.76 | P16: 1900.16 | Q16: 195.4 | R16: 2.1711111 | S16: 0.025159662 | T16: 7.223 | U16: 2.1711111 | V16: 5.0518889 | W16: 0.033969459 | X16: 195.4 | Y16: 0 | Z16: 0 | AA16: 72.54 | AB16: 0 | AC16: 195.4 | AD16: 0 | AE16: 0.025516234 | AF16: 1403 | AG16: 35.799276 | AH16: 697 | AI16: 21.607 | AJ16: 7.8758407 | AK16: 4.75354 | AL16: 42.988 | AM16: 0 | AN16: 0 | AO16: 55.617381 | AP16: 3279.89 | AQ16: 5683.79 | AR16: 2403.9 | AS16: 0.045756411 | AT16: 350.39665 | AU16: 72.54 | AV16: 2.4641446 | AW16: 64.196245 | AX16: 31.892219 | AY16: 137.90982 | AZ16: 1819.5051 | BA16: 0 | BB16: 0 | BC16: 1819.5051 | BD16: -14.123174 | BE16: -7.0162881 | BF16: -30.340161 | BG16: -77.087263 | BH16: -0.049282891 | BI16: -70.050945 | BJ16: -198.66711 | BK16: -22.46012 | BL16: 1.123006 | BM16: 20.55548 | BN16: 21.678486 | BO16: -22.46012 | BP16: -0.781634 | BQ16: -73.531839 | BT16: 12
... A23: 19 | B23: Laurence Hansen Janet Anne Hansen | C23: 50003417 | D23: 0.079 | E23: O | F23: 8.9736842 | G23: 8.1052632 | H23: 8.9736842 | I23: 3.2268421 | J23: 13.561644 | K23: 16.71337 | L23: 19.8 | M23: 1.1 | N23: 80.454487 | O23: 10411 | P23: 10951 | Q23: 540 | R23: 6 | S23: 0.069530284 | T23: 18.407 | U23: 6 | V23: 12.407 | W23: 0.083426039 | X23: 540 | Y23: 0 | Z23: 0 | AA23: 72.54 | AB23: 0 | AC23: 540 | AD23: 0 | AE23: 0.070515692 | AF23: 1403 | AG23: 98.933515 | AH23: 697 | AI23: 55.063 | AJ23: 21.765373 | AK23: 12.11386 | AL23: 118.8 | AM23: 0 | AN23: 0 | AO23: 152.67923 | AP23: 25220 | AQ23: 29966 | AR23: 4746 | AS23: 0.090336506 | AT23: 691.78522 | AU23: 72.54 | AV23: 6.0517249 | AW23: 126.74212 | AX23: 62.964545 | AY23: 272.27423 | AZ23: 3592.2339 | BA23: 0 | BB23: 0 | BC23: 3592.2339 | BD23: -27.883266 | BE23: -13.8522 | BF23: -59.900331 | BG23: -152.19275 | BH23: -0.1210345 | BI23: -138.301 | BJ23: -392.25058 | BK23: -57.23708 | BL23: 2.861854 | BM23: 52.38332 | BN23: 55.245174 | BO23: -57.23708 | BP23: -1.991906 | BQ23: -161.10877 | BT23: 16
A24: BESS | B24: BESS Powerpack 232kWh | C24: 40002722 | O24: 42252 | P24: 50626 | Q24: 8374 | AP24: 33894 | AQ24: 40865 | AR24: 6971 | BR24: data swapped | BT24: BESS
A25: EV | B25: EV Charger | C25: 40002728 | O25: 7349 | P25: 10363 | Q25: 3014 | AP25: 0 | AQ25: 0 | AR25: 0 | BT25: EV
A26: CS | B26: Common Services MSB | C26: 50003429 | O26: 3640 | P26: 4295 | Q26: 655 | AP26: 0 | AQ26: 0 | AR26: 0 | BT26: CS
A27: DB1 | B27: Common Services DB1 | O27: 149 | P27: 168 | Q27: 19 | BT27: DB1
A28: DB2 | B28: Common Services DB2 | O28: 128 | P28: 151 | Q28: 23 | BT28: DB2
A29: CP | B29: Strata consumption Site Check Meter | BT29: CP
D30: 1 | E30: 0 | F30: 170.5 | H30: 170.5 | I30: 61.31 | J30: 257.67123 | K30: 211.56164 | L30: 376.2 | M30: 20.9 | N30: 1422.6429 | Q30: 7766.4 | S30: 1 | T30: 233 | V30: 148.71856 | W30: 1 | X30: 7585.33 | Y30: 181.07 | Z30: 1 | AB30: 72.54 | AC30: 7657.87 | AD30: 108.53 | AE30: 1 | AG30: 1403 | AI30: 697 | AJ30: 308.66 | AK30: 153.34 | AL30: 1762.5714 | AM30: 1.4508 | AN30: 32.559 | AO30: 2258.5812 | AR30: 52536.9 | AS30: 1 | AT30: 7657.87 | AV30: 72.54 | AW30: 1403 | AX30: 697 | AY30: 3014 | AZ30: 39765.03 | BB30: 0 | BC30: 39765.03 | BD30: -308.66 | BE30: -153.34 | BF30: -663.08 | BG30: -1684.7314 | BH30: -1.4508 | BI30: -1530.9537 | BJ30: -4342.2159 | BK30: -724.52 | BL30: 36.226 | BM30: 663.08 | BN30: 699.306 | BO30: -724.52 | BP30: -25.214
L31: 19 | M31: 19
AA32: = Total Energy exceeding allowance - Actual amanda energy import | AL32: Teants with 0 export will be charge at higher rate for their consumption
B34: Amanda enegery | C34: Year | D34: Month | E34: Consumption_kWh | F34: Export_kWh | G34: Amanda_consumption_incl_GST | H34: Amanda_export_buyback_incl_GST | I34: Daily_Supply_incl_GST | J34: Other_Fees_incl_GST | K34: Total_incl_GST
B35: 1C | C35: 2025 | D35: 01 | E35: 44.48 | F35: 13074.94 | G35: 13.32 | H35: -503.38 | I35: 170.5 | J35: 22.22 | K35: -297.34
B36: 1C | C36: 2025 | D36: 02 | E36: 46.06 | F36: 12380.74 | G36: 13.78 | H36: -476.66 | I36: 154 | J36: 19.29 | K36: -289.59
B37: 1C | C37: 2025 | D37: 03 | E37: 17.99 | F37: 14328.95 | G37: 5.38 | H37: -551.66 | I37: 170.5 | J37: 19.8 | K37: -355.98
B38: Total | E38: 108.53 | F38: 39784.63 | G38: 32.48 | H38: -1531.7 | I38: 495 | J38: 61.31 | K38: -942.91
G39: 0.29927209 | H39: -0.038499793
B40: Month | C40: EV Charger KWh/month total | D40: Chargefox Revenue | E40: Chargefox Revenue -5%
B41: 45658 | C41: 514.2 | D41: -200.44 | E41: -190.42
B42: 45689 | C42: 669.75 | D42: -252.66 | E42: -240.03
B43: 45717 | C43: 735.27 | D43: -271.42 | E43: -257.58
B44: Total | C44: 1919.22 | D44: -724.52 | E44: -688.29
C45: 0.63676841
B47: Strata reconcilation table | C47: $ Incl. GST
B48: Residents supply charge | C48: 1422.6429
B49: Amanda buyback | C49: 1531.7
B50: Residents energy consumption | C50: 2258.5812
B51: EV Charger operation cost | C51: 699.306
B52: ChargeFox Income | C52: 688.29
B53: Strata total income | C53: 6600.5201
B54: Total payout to resident for exporting | C54: -4342.2159
B55: Total payout to resident for EV charger revenue | C55: -724.52
B56: Total payout to Amanda Energy | C56: -588.79
B57: Total payout to supply (SwichDin, E47, ChargeFox) | C57: -866.33288
B58: Strata total payout | C58: -6521.8587
B59: P2P subsidies for residents without solar panels | C59: 77.84
... B61: Variance % | C61: 0.00012443641

Sheet Lot 1
A2: The Owners of Cluster 1C Witchcliffe Ecovillage Survey Strata 77786 | B2: TAX INVOICE
A3: ABN: 80 608 251 481
A5: C/- Cluster 1C Strata | B5: DATE: | E5: 45784
A6: 10437 Bussell Highway | B6: Invoice # | E6: 1C1/0325
A7: Witchcliffe WA 6286 | B7: Cluster | E7: 1C
A8: Email: wevcluster1c@gmail.com | B8: Lot Number | E8: 1
B9: Lot Meter Number # | E9: 50003397
A10: Addressee:- | B10: Unit Entitlement | E10: 42
A11: Aron Dyer Jodie Passmore | B11: Unit Entitlement % | E11: 0.042
A12: 19 Yornitj Grove | B12: Billing period | C12: 45658 | E12: 45747
A13: Witchcliffe WA 6286 | B13: Billing period days | E13: 90
A15: Items | B15: Charge Rate ($ Inc. GST) | C15: Usage | E15: Amount due ($ Inc. GST)
A16: Supply charge
A17: Amanda Energy Daily Supply Charge 1/01/25 - 31/01/25 | B17: $8.97368 | C17: 1 | D17: Unit | E17: $8.97
A18: Amanda Energy Daily Supply Charge 1/02/25 - 28/02/25 | B18: $8.10526 | C18: 1 | D18: Unit | E18: $8.11
A19: Amanda Energy Daily Supply Charge 1/03/25 - 31/03/25 | B19: $8.97368 | C19: 1 | D19: Unit | E19: $8.97
A20: Amanda Energy Other Fees | B20: $3.22684 | C20: 1 | D20: Unit | E20: $3.23
A21: Element47 Embedded Network Daily Supply Charges | B21: $0.22000 | C21: 90 | D21: Days | E21: $19.80
A22: Element47 Embedded Network Invoicing Fees | B22: $1.10000 | C22: 1 | D22: Unit | E22: $1.10
A23: Chargefox EV Charger Network Fixed Fees Equitable Split % of Unit Entitlement | B23: $0.09873 | C23: 90 | D23: Days | E23: $8.89
A24: SwitchdIn Supply Charge | B24: $0.15068 | C24: 90 | D24: Days | E24: $13.56
A25: Total Daily Supply Charge | B25: $0.80696 | C25: 90 | D25: Days | E25: $72.63
A26: Common Services Charges
A27: Common Services Fees Equitable Split % of Unit Entitlement kWh | B27: $0.22000 | C27: 29.274 | D27: kWh | E27: $6.44
A28: Common Services Reimbursement based on P2P export % kWh | B28: $(0.22000) | C28: 51.6346 | D28: kWh | E28: $(11.36)
A29: Import Battery Loss Allocation based on P2P import % kWh | B29: $0.22000 | C29: 90.3226 | D29: kWh | E29: $19.87
A30: Export of Solar PV Battery Loss Reimbursement based on P2P export % kWh | B30: $(0.22000) | C30: 103.936 | D30: kWh | E30: $(22.87)
A31: Community EV Charger Variable Income Equitable Split % of Unit Entitlement kWh | B31: $(0.24038) | C31: 126.588 | D31: kWh | E31: $(30.43)
A32: Community EV Charger Variable Cost of Electricity Supply Equitable Split % of Unit Entitlement kWh | B32: $0.22000 | C32: 126.588 | D32: kWh | E32: $27.85
A33: Community EV Charger Reimbursement based on P2P export % kWh | B33: $(0.22000) | C33: 223.2809 | D33: kWh | E33: $(49.12)
A34: Community EV Charger Chargefox Commission Cost Equitable Split % of Unit Entitlement kWh | B34: $0.01202 | C34: 126.588 | D34: kWh | E34: $1.52
A35: Total Common Services Charges | B35: $(0.64550) | C35: 90 | D35: Days | E35: $(58.10)
A36: Imported energy
A37: Import Peer to Peer kWh | B37: $0.22000 | C37: 493 | D37: kWh | E37: $108.46
A38: P2P Import Consumption over Battery Allowance kWh | B38: $- | C38: 0 | D38: kWh | E38: $-
A39: Import From Grid kWh | B39: $- | C39: 0 | D39: kWh | E39: $-
A40: Total Imported Energy | B40: $1.20511 | C40: 90 | D40: Days | E40: $108.46
A41: Exported energy
A42: Export Peer to Peer kWh | B42: $(0.22000) | C42: 567.3047 | D42: kWh | E42: $(124.81)
A43: P2P Borrowed Allowance Passive Compensation kWh | B43: $(0.02000) | C43: 2.1014 | D43: kWh | E43: $(0.04)
