Workbook
Name ColumnTitle1: #REF!
Name ColumnTitleRegion1..B11.1: #REF!
Name Company_Name: #REF!
Name Profit_table: #REF!
Name RowTitleRegion1..D5: #REF!

Sheet Insutrcution for whole process
A1: check box | B1: Instruction for whole process
A2: FALSE | B2: 0. save as a new file
A3: FALSE | B3: 1. check detail for strata rep contacts, update if necessary
A4: FALSE | B4: 2. check detail for strata roll contacts, update if neccssary
A5: FALSE | B5: 3. update Amanda Energy bills using python code | C5: get invoice pdf from amanda energy | D5: get_Amanda_inovice.py | E5: output.csv
A6: FALSE | B6: 4. update auto meter reading (SwitchDin) | C6: download data from billing dashboard | D6: process_meter_data.py | E6: formatted data
A7: FALSE | B7: 5. update manual meter reading | C7: request manual meter reading ahead of time | D7: January 1st | E7: April 1st | F7: July 1st | G7: October 1st
A8: FALSE | B8: 6. check Tariff Rates, update if necessary
A9: FALSE | B9: 7. update master billing sheet to current billing cycle: | C9: cluster name and billing month
A10: FALSE | B10: 8. check supply table as follow, remove supply charge as request.
A11: FALSE | B11: 9. run VB code
A12: FALSE | B12: 10. Hide sensitve info sheet
B14: Instruction for VB code:
A15: FALSE | B15: 1. open tab 'Developer'
A16: FALSE | B16: 2. choose 'Visual Basic'
A17: FALSE | B17: 3. add module
A18: FALSE | B18: 4. copy and paste VB code | F18: Sub GenerateDynamicLotSheets() Dim wsTemplate As Worksheet Dim newSheet As Worksheet Dim strataRoll As Worksheet Dim clusterValue As String Dim maxLotNo As Long Dim rng As Range Dim cell As Range Dim i As Long ' Define the template sheet and reference sheet Set wsTemplate = ThisWorkbook.Sheets("Lot 1") Set strataRoll = ThisWorkbook.Sheets("Strata Roll") ' Get the Cluster value from D7 of the template sheet clusterValue = wsTemplate.Range("E7").Value ' Initialize the maximum Lot No maxLotNo = 0 ' Search "Strata Roll" for the maximum Lot No matching the Cluster value With strataRoll Set rng = .Range("A2", .Cells(.Rows.Count, "A").End(xlUp)) ' Assume data starts from A2 For Each cell In rng ' Check if the corresponding row's Cluster matches the target Cluster If .Cells(cell.Row, "B").Value = clusterValue Then ' Ensure the cell value in column A is numeric before comparing If IsNumeric(cell.Value) Then ' Compare the numeric Lot No directly If CLng(cell.Value) > maxLotNo Then maxLotNo = CLng(cell.Value) End If End If End If Next cell End With ' Check if any Lot No was found for the given Cluster If maxLotNo = 0 Then MsgBox "No Lot No found for Cluster value " & clusterValue & "!", vbExclamation Exit Sub End If ' Generate worksheets for Lot 2 to maxLotNo For i = 2 To maxLotNo ' Copy the template sheet wsTemplate.Copy After:=ThisWorkbook.Sheets(ThisWorkbook.Sheets.Count) Set newSheet = ThisWorkbook.Sheets(ThisWorkbook.Sheets.Count) ' Rename the new sheet newSheet.Name = "Lot " & i ' Update the Lot No in the new sheet (e.g., D8 cell) newSheet.Range("E8").Value = i Next i MsgBox "Successfully created Lot 2 to Lot " & maxLotNo & " worksheets!", vbInformation End Sub
A19: FALSE | B19: 5. run
A20: FALSE | B20: 6. remove VB code
B22: Invoicing table
B23: Cluster | C23: Account setup fee | D23: Q1 | E23: Q2 | F23: Q3 | G23: Q4 | H23: Jan-Feb | I23: Mar | J23: Redundant Invoices | K23: Contract Update
B24: 1A | C24: 1018 | D24: self- issued | E24: self- issued | F24: self- issued | G24: 1077 | H24: 1091 | J24: 1039 for Q1-Q3 | K24: Signed
B25: 1B | C25: 1019 | D25: self- issued | E25: self- issued | F25: self- issued | G25: 1069 | H25: 1092 | J25: 1043 for Q1-Q3 | K25: Weekend | M25: paid
B26: 1C | C26: 1020 | D26: 1044 | E26: 1044 | F26: 1044 | G26: 1070 | H26: 1093 | K26: Signed | M26: not paid
B27: 2A | C27: 1021 | D27: self- issued | E27: self- issued | F27: self- issued | G27: 1071 | J27: 1045 for Q2-Q3 | K27: Holiday | M27: Credit Note allocated
B28: 2B | C28: 1022 | D28: self- issued | E28: 1046 | F28: 1046 | G28: 1082 | H28: 1094 | K28: Weekend | M28: self- issued
B29: 3A | C29: 1023 | D29: self- issued | E29: 1047 | F29: 1047 | G29: 1081 | K29: Weekend
B30: 3B | C30: 1024 | D30: self- issued | E30: 1083 | F30: 1083 | G30: 1083 | H30: 1095 | J30: 1048 for Q2-Q3 | K30: FIFO working
B32: Supply charge table
B33: Cluster | C33: Amanda energy supply charge | D33: SwitchDin | E33: ChargeFox | F33: EV charger cost of electricy @P2P rate | G33: P2P trade rate for lots with export | H33: P2P rate for lots with no export | I33: Agreement and action items | J33: BESS status | K33: billing cycle | L33: P2P borrow/lend
B34: 1A | C34: Included | D34: Not included | E34: Not included | F34: Included | G34: 0.22$/kwh | H34: 0.36$/kwh | I34: July 1st 2025 | J34: ON | K34: quarterly | L34: 2
B35: 1B | C35: Included | D35: Not included Till May 2025 | E35: Not included | F35: Included (customer cannled on 30/04/2025) | G35: 0.22$/kwh | H35: 0.22$/kwh | I35: July 1st 2025 | J35: ON | K35: quarterly | L35: 2
B36: 1C | C36: Included | D36: Included | E36: Included | F36: Included | G36: 0.22$/kwh | H36: 0.22$/kwh | J36: ON | K36: quarterly | L36: 2
B37: 2A | C37: Included | D37: Not included | E37: Not included | G37: 0.22$/kwh | H37: 0.22$/kwh | I37: July 1st 2025 | J37: ON | K37: quarterly | L37: 2
B38: 2B | C38: Included | D38: Included | E38: Not included | G38: 0.22$/kwh | H38: 0.22$/kwh | I38: July 1st 2025 | J38: ON | K38: quarterly | L38: 2
B39: 3A | C39: Not included | D39: Not included | E39: Not included | G39: 0.22$/kwh | H39: 0.22$/kwh | I39: July 1st 2025 | J39: ON | K39: quarterly | L39: 0
B40: 3B | C40: Not included | D40: Not included | E40: Not included | G40: 0.22$/kwh | H40: 0.22$/kwh | I40: July 1st 2025 | J40: ON | K40: quarterly | L40: 0
B41: FALSE | C41: FALSE | D41: FALSE | E41: FALSE | F41: FALSE | G41: FALSE | H41: FALSE | I41: FALSE | J41: FALSE | K41: FALSE | L41: FALSE

Sheet strata rep contacts
A1: Cluster | B1: Strata company name | C1: ABN | D1: Parcel Address | E1: Energy Representative | F1: Energy Representative email | G1: Strata Council Chair | H1: Strata Council Email | I1: Energy supply charge incl in strata fees | J1: Cluster battery | K1: Invividual lot battery | L1: number of lots | M1: Account Name | N1: BSB | O1: Account #
A2: 1A | B2: The Owners of Cluster 1A Witchcliffe Ecovillage Survey Strata 77784 | C2: ABN: 29 857 461 927 | D2: Lot 10, 10347 Bussell Hwy Witchcliffe WA | E2: Peter Froehlich (lot 13) | F2: froehlich.fp@gmail.com | G2: to be confirmed by strata | H2: wevcluster1a@gmail.com | J2: ✓ | M2: Owners Cluster 1A | N2: 633-000 | O2: 209 071 927
B3: 24 Lots | E3: Lindy Dunlop | F3: lindyjdunlop@hotmail.com | L3: 24
A4: 1B | B4: The Owners of Cluster 1B Witchcliffe Ecovillage Survey Strata 77785 | C4: ABN: 31 962 028 201 | D4: Lot 17, 10347 Bussell Hwy Witchcliffe WA | E4: Paul Wilkinson (lot 12) | F4: mail2paul07@gmail.com | G4: to be confirmed by strata | H4: wevcluster1b@gmail.com | J4: ✓ | M4: 1B Admin Fund | N4: 633000 | O4: 208 200 014
B5: 21 Lots | L5: 21
A6: 1C | B6: The Owners of Cluster 1C Witchcliffe Ecovillage Survey Strata 77786 | C6: ABN: 80 608 251 481 | D6: Lot 11, 10347 Bussell Hwy Witchcliffe WA | E6: Laurence Hansen (Lot 19) | F6: logs1@iinet.net.au | G6: to be confirmed by strata | H6: wevcluster1c@gmail.com | J6: ✓ | M6: WEV Cluster 1C Strata Account | N6: 633 000 | O6: 216 423 913
B7: 19 Lots | L7: 19
A9: 2A | B9: The Owners of Cluster 2A Witchcliffe Ecovillage Survey Strata 77787 | C9: ABN: 38 248 842 277 | D9: Lot 7 10347 Bussell Hwy Witchcliffe WA | E9: Bouwe Hamersma (Lot 5) | F9: bouwe.hamersma@gmail.com | G9: to be confirmed by strata | H9: wevcluster2a@gmail.com | J9: ✓ | M9: 2A ADMIN FUND | N9: 306-188 | O9: 352588
B10: 23 Lots | L10: 23
A11: 2B | B11: The Owners of Cluster 2B Witchcliffe Ecovillage Survey Strata 77788 | C11: ABN: 64 989 501 940 | D11: Lot 8, 10347 Bussell Hwy Witchcliffe WA | E11: Alison Askew (Lot 10) | F11: alisonaskew123@gmail.com | G11: to be confirmed by strata | H11: wevcluster2b@gmail.com | J11: ✓ | M11: The Owners of Cluster 2B Witchcliffe | N11: 633000 | O11: 209 181 437
B12: 22 Lots | L12: 22
A14: 3A | B14: The Owners of Cluster 3A Witchcliffe Ecovillage Survey Strata 77790 | C14: ABN: 22315195710 | D14: 2 Karrack Crescent, Witchcliffe WA | E14: Elaine Clocherty (Lot 15) | F14: elaineclocherty@gmail.com | G14: to be confirmed by strata | H14: wevcluster3a@gmail.com | I14: ✓ | J14: ✓ | M14: WEV Cluster 3A Strata | N14: 633 000 | O14: 223 075 870
B15: 27 Lots | L15: 27
A16: 3B | B16: The Owners of Cluster 3B Witchcliffe Ecovillage Survey Strata 77791 | C16: ABN: 11801467982 | D16: 3 Karrack Crescent, Witchcliffe WA | E16: Jason McHattan (Lot13) | F16: jasonmchattan@gmail.com | G16: to be confirmed by strata | H16: wevcluster3b@gmail.com | I16: ✓ | J16: ✓ | M16: 3B Admin Fund | N16: 306-412 | O16: 0020794
B17: 19 Lots | E17: Tim Thomson (Lot 8) | F17: timjcthomson@gmail.com | L17: 19
B18: The Owners of Cluster 3C Witchcliffe Ecovillage Survey Strata 83347 | C18: ABN: 86675221914 | D18: Lot 18 Karrack Crescent Witchcliffe WA | E18: ?? | G18: to be confirmed by strata | H18: wevcluster3c@gmail.com | I18: ✓ | K18: ✓
B19: 15 Short Stay | L19: 15
B21: The Owners of Cluster 4A Witchcliffe Ecovillage Survey Strata 85752 | C21: ABN: 33 677 155 303 | D21: 22 Gnuraren Grove, Witchcliffe WA | E21: ?? | G21: Caroline Bannister (Lot18) | H21: wevcluster4a@gmail.com | I21: ✓ | K21: ✓
B22: 26 lots | L22: 26
B23: The Owners of Cluster 4B Witchcliffe Ecovillage Survey Strata 85753 | C23: ABN: 24 266 141 390 | D23: 23 Mulal Avenue, Witchcliffe WA | E23: Manuel Mall (Lot 3) | F23: carolinandmanuel@gmail.com | G23: Jenny Challen (Lot 9) | H23: wevcluster4b@gmail.com | I23: ✓ | K23: ✓
B24: 20 lots | E24: Jenny Challen (Lot 9) | F24: jenny@challen.com.au | L24: 20

Sheet strata roll
A1: Lot | B1: cluster | C1: Meter# | D1: Block Type | E1: Owner | F1: Street Address | G1: Suburb | H1: State | I1: Post Code | J1: Unit Entitlement | K1: UE % over Cluster | L1: Calculated Battery Allocation (kWh) | M1: Inverter Model | N1: Applied Battery Allocation (kWh) | O1: Export Capacity (kW) | P1: Energy Meter Installed | Q1: PV Installed | R1: Functional Droplet | S1: Stage of Dev. | T1: Phone 1 | U1: Phone 2 | V1: Email | W1: Meter Number | X1: Occupant 1 Start Date | Y1: Occupant 1 End date | Z1: Inverter start date
A2: 1 | B2: 1A | D2: Cottage | E2: Mead Family trust | F2: 1 Yornitj Grove | G2: Witchcliffe | H2: WA | I2: 6286 | J2: 36 | K2: 0.036 | L2: 8.352 | N2: 0 | P2: Y | Q2: N | R2: N | S2: UC | T2: 0 | U2: 0.72 | V2: 0457 578 078 | W2: 0476919881 | X2: nicholasjamesmead@gmail.co | Z2: 45292 | AA2: Current
A3: 2 | B3: 1A | D3: Cottage | E3: Margareta Roeck | F3: 3 Yornitj Grove | G3: Witchcliffe | H3: WA | I3: 6286 | J3: 36 | K3: 0.036 | L3: 8.352 | N3: 0 | P3: Y | Q3: N | R3: N | S3: UC | T3: 0 | U3: 0.72 | V3: 0416732634 | X3: maroeck@gmail.com | Z3: 45292 | AA3: Current
A4: 3 | B4: 1A | C4: 50002872 | D4: Cottage | E4: Battigielli | F4: 5 Yornitj Grove | G4: Witchcliffe | H4: WA | I4: 6286 | J4: 37 | K4: 0.037 | L4: 8.584 | N4: 0 | P4: Y | Q4: N | R4: N | S4: O | T4: 0 | U4: 0.72 | V4: 0424154036 | X4: emailalexhughes@gmail.com | Z4: 45292 | AA4: Current
A5: 4 | B5: 1A | C5: 50002869 | D5: Cottage | E5: Paul Jurjevich & Trish Rushton | F5: 7 Yornitj Grove | G5: Witchcliffe | H5: WA | I5: 6286 | J5: 38 | K5: 0.038 | L5: 8.816 | M5: Symo 5.0 | N5: 8.816 | O5: 6.64 | P5: Y | Q5: Y | R5: Y | S5: O | T5: 4.7808 | U5: 0.72 | V5: 0412261482 | W5: 0403732723 | X5: mulloway9@icloud.com | Z5: 45292 | AA5: Current
A6: 5 | B6: 1A | C6: 50002879 | D6: Cottage | E6: Dwyer | F6: 9 Yornitj Grove | G6: Witchcliffe | H6: WA | I6: 6286 | J6: 39 | K6: 0.039 | L6: 9.048 | M6: Symo 5.0 | N6: 9.048 | O6: 6.4 | P6: Y | Q6: Y | R6: Y | S6: O | T6: 4.608 | U6: 0.72 | V6: 0408744572 | W6: 0437286462 | X6: mammoth@iinet.net.au | Z6: 45292 | AA6: Current
A7: 6 | B7: 1A | C7: 50002865 | D7: Cottage | E7: Gillespie | F7: 11 Yornitj Grove | G7: Witchcliffe | H7: WA | I7: 6286 | J7: 39 | K7: 0.039 | L7: 9.048 | M7: Symo 8.2 | N7: 9.048 | O7: 10.88 | P7: Y | Q7: Y | R7: Y | S7: O | T7: 7.8336 | U7: 0.72 | V7: 0417950370 | W7: 0429196637 | X7: barbaragillespie@iinet.net.au | Z7: 45292 | AA7: Current
A8: 7 | B8: 1A | D8: Cottage | E8: Rio & Alix Healey-­‐Diaz | F8: 13 Yornitj Grove | G8: Witchcliffe | H8: WA | I8: 6286 | J8: 37 | K8: 0.037 | L8: 8.584 | N8: 0 | P8: Y | Q8: N | R8: N | S8: O | T8: 0 | U8: 0.72 | V8: 0425890670 | X8: alixward@gmail.com | Z8: 45292 | AA8: Current
A9: 8 | B9: 1A | C9: 50002846 | D9: Cottage | E9: Marcus Browne & Sook-­‐JaRebecchi | F9: 15 Yornitj Grove | G9: Witchcliffe | H9: WA | I9: 6286 | J9: 36 | K9: 0.036 | L9: 8.352 | M9: Symo 5.0 | N9: 8.352 | O9: 6.6 | P9: Y | Q9: Y | R9: Y | S9: O | T9: 4.752 | U9: 0.72 | V9: 0433290368 | W9: 0448279836 | X9: marcus@mishack.com.au | Z9: 45292 | AA9: Current
A10: 9 | B10: 1A | D10: Cottage | E10: Jasmine Heah | F10: 17 Yornitj Grove | G10: Witchcliffe | H10: WA | I10: 6286 | J10: 36 | K10: 0.036 | L10: 8.352 | N10: 0 | P10: Y | Q10: N | R10: N | S10: O | T10: 0 | U10: 0.72 | V10: 0408323274 | X10: jasmine_heah@hotmail.com | Z10: 45292 | AA10: Current
A11: 10 | B11: 1A | D11: Family | E11: Pernille Stent | F11: 51 Mardo Drive | G11: Witchcliffe | H11: WA | I11: 6286 | J11: 53 | K11: 0.053 | L11: 12.296 | M11: Symo 5.0 | N11: 12.296 | O11: 6.4 | P11: Y | Q11: Y | R11: Y | S11: O | T11: 4.608 | U11: 0.72 | V11: 0410416005 | X11: pernille@designbutton.net.au | Z11: 45292 | AA11: Current
A12: 11 | B12: 1A | C12: 50002848 | D12: Family | E12: Levi Holden | F12: 49 Mardo Drive | G12: Witchcliffe | H12: WA | I12: 6286 | J12: 52 | K12: 0.052 | L12: 12.064 | M12: Symo 5.0 | N12: 12.064 | O12: 6.4 | P12: Y | Q12: Y | R12: Y | S12: O | T12: 4.608 | U12: 0.72 | V12: 0427444150 | X12: levi.holden@optusnet.com.au | Z12: 45292 | AA12: Current
A13: 12 | B13: 1A | D13: Family | E13: Matt & Kate Shaw | F13: 47 Mardo Drive | G13: Witchcliffe | H13: WA | I13: 6286 | J13: 52 | K13: 0.052 | L13: 12.064 | N13: 0 | P13: Y | Q13: N | R13: N | S13: UC | T13: 0 | U13: 0.72 | V13: 0428088590 | W13: 0431001084 | X13: shaw76@hotmail.co.uk | Z13: 45292 | AA13: Current
A14: 13 | B14: 1A | C14: 50002739 | D14: Family | E14: Peter Froehlich & Lydia Walzel | F14: 45 Mardo Drive | G14: Witchcliffe | H14: WA | I14: 6286 | J14: 52 | K14: 0.052 | L14: 12.064 | M14: Symo 10.0 | N14: 12.064 | O14: 12.8 | P14: Y | Q14: Y | R14: Y | S14: O | T14: 9.216 | U14: 0.72 | V14: 0418946078 | W14: 0419928925 | X14: froehlich.fp@gmail.com | Z14: 45292 | AA14: Current
A15: 14 | B15: 1A | D15: Family | E15: Priscila Goncalves | F15: 43 Mardo Drive | G15: Witchcliffe | H15: WA | I15: 6286 | J15: 52 | K15: 0.052 | L15: 12.064 | M15: Symo 10.0 | N15: 12.064 | O15: 13.2 | P15: Y | Q15: Y | R15: N | S15: UC | T15: 9.504 | U15: 0.72 | V15: 0475716267 | W15: 0475716400 | X15: diego.barneche@ymail.com | Z15: 45292 | AA15: Current
A16: 15 | B16: 1A | D16: Family | E16: Jeﬀ & Jo Thierfelder | F16: 41 Mardo Drive | G16: Witchcliffe | H16: WA | I16: 6286 | J16: 53 | K16: 0.053 | L16: 12.296 | N16: 0 | P16: Y | Q16: N | R16: N | S16: UC | T16: 0 | U16: 0.72 | V16: 0409770316 | W16: 0421589548 | X16: jeﬀ.thierfelder@iinet.net.au | Z16: 45292 | AA16: Current
A17: 16 | B17: 1A | C17: 50002855 | D17: Family | E17: Libby Davy | F17: 3 Mannitj Place | G17: Witchcliffe | H17: WA | I17: 6286 | J17: 55 | K17: 0.055 | L17: 12.76 | M17: Symo 5.0 | N17: 12.76 | O17: 6.6 | P17: Y | Q17: Y | R17: Y | S17: O | T17: 4.752 | U17: 0.72 | V17: 0413993452 | X17: libby@humanbells.com | Z17: 45292 | AA17: Current
A18: 17 | B18: 1A | C18: 50002877 | D18: Family | E18: Henry & Jo Weldon | F18: 5 Mannitj Place | G18: Witchcliffe | H18: WA | I18: 6286 | J18: 55 | K18: 0.055 | L18: 12.76 | M18: Symo 8.2 | N18: 12.76 | O18: 10.9 | P18: Y | Q18: Y | R18: Y | S18: O | T18: 7.848 | U18: 0.72 | V18: 0407076552 | W18: 0407388196 | X18: henryweldon90@gmail.com | Z18: 45292 | AA18: Current
A19: 18 | B19: 1A | D19: Family | E19: Liz Kirk | F19: 7 Mannitj Place | G19: Witchcliffe | H19: WA | I19: 6286 | J19: 55 | K19: 0.055 | L19: 12.76 | N19: 0 | Q19: N | R19: N | S19: V | T19: 0 | U19: 0.72 | V19: 0408751379 | X19: lizk@beyondergo.com.au | Z19: 45292 | AA19: Current
A20: 19 | B20: 1A | C20: 50002864 | D20: Family | E20: Lindy Dunlop | F20: 9 Mannitj Place | G20: Witchcliffe | H20: WA | I20: 6286 | J20: 55 | K20: 0.055 | L20: 12.76 | M20: Symo 10.0 | N20: 12.76 | O20: 12.8 | P20: Y | Q20: Y | R20: Y | S20: O | T20: 9.216 | U20: 0.72 | V20: 0493385725 | X20: lindyjdunlop@hotmail.com | Z20: 45292 | AA20: Current
A21: 20 | B21: 1A | C21: 50002710 | D21: Groupie | E21: Elke Light | F21: 30 Kulbardi Way | G21: Witchcliffe | H21: WA | I21: 6286 | J21: 26 | K21: 0.026 | L21: 6.032 | M21: Symo 5.0 | N21: 6.032 | O21: 6.4 | P21: Y | Q21: Y | R21: Y | S21: O | T21: 4.608 | U21: 0.72 | V21: 0439968661 | X21: lightelke@gmail.com | Z21: 45292 | AA21: Current
A22: 21 | B22: 1A | C22: 50002719 | D22: Groupie | E22: Deborah Woodman | F22: 28 Kulbardi Way | G22: Witchcliffe | H22: WA | I22: 6286 | J22: 26 | K22: 0.026 | L22: 6.032 | M22: Symo 5.0 | N22: 6.032 | O22: 6.4 | P22: Y | Q22: Y | R22: Y | S22: O | T22: 4.608 | U22: 0.72 | V22: 0456121155 | X22: woodmandj55@gmail.com | Z22: 45292 | AA22: Current
A23: 22 | B23: 1A | C23: 50002876 | D23: Groupie | E23: Carrie & Warrick Goldsmith | F23: 26 Kulbardi Way | G23: Witchcliffe | H23: WA | I23: 6286 | J23: 26 | K23: 0.026 | L23: 6.032 | M23: Symo 5.0 | N23: 6.032 | O23: 6.4 | P23: Y | Q23: Y | R23: Y | S23: O | T23: 4.608 | U23: 0.72 | V23: 0499270453 | W23: 0447110831 | X23: carrieandwarrick@gmail.com | Z23: 45292 | AA23: Current
A24: 23 | B24: 1A | C24: 50002860 | D24: Groupie | E24: Clyde Huxtable | F24: 24 Kulbardi Way | G24: Witchcliffe | H24: WA | I24: 6286 | J24: 26 | K24: 0.026 | L24: 6.032 | M24: Symo 5.0 | N24: 6.032 | O24: 6.4 | P24: Y | Q24: Y | R24: Y | S24: O | T24: 4.608 | U24: 0.72 | V24: 0406351722 | X24: hotfire1948@hotmail.com | Z24: 45292 | AA24: Current
A25: 24 | B25: 1A | D25: Groupie | E25: Helen Rose | F25: 22 Kulbardi Way | G25: Witchcliffe | H25: WA | I25: 6286 | J25: 28 | K25: 0.028 | L25: 6.496 | N25: 0 | P25: Y | Q25: N | R25: N | S25: UC | T25: 0 | U25: 0.72 | V25: 0437445630 | X25: rosebunch5@gmail.com | Z25: 45292 | AA25: Current
A26: BESS | B26: 1A | C26: 40002686 | E26: BESS Powerpack 232kWh | J26: 1000 | K26: 1 | N26: 0 | T26: 0 | U26: 0.72
A27: EV | B27: 1A | C27: 40002693 | D27: N/A | E27: EV Charger | G27: Witchcliffe | H27: WA | I27: 6286 | K27: 0 | L27: 0 | N27: 0 | P27: Y | Q27: N | R27: Y | T27: 0 | U27: 0.72
A28: CS | B28: 1A | D28: N/A | E28: Common Services MSB | G28: Witchcliffe | H28: WA | I28: 6286 | K28: 0 | L28: 0 | N28: 0 | P28: Y | Q28: N | R28: Y | T28: 0 | U28: 0.72
A29: DB1 | B29: 1A | K29: 0 | N29: 0 | T29: 0
A30: DB2 | B30: 1A | K30: 0 | N30: 0 | T30: 0
A31: 1 | B31: 1B | C31: 50003409 | D31: Cottage | E31: Susan Gibson | F31: 78 Kulbardi Way | G31: Witchcliffe | H31: WA | I31: 6286 | J31: 42 | K31: =Table_Household_Alloc[[#This Row],[Unit Entitlement]]/1000 -> 0.042 | L31: =(J31/1000)*232 -> 9.744 | M31: Symo 5.0 | N31: =IF(Table_Household_Alloc[[#This Row],[PV Installed]]="Y",1,0)*Table_Household_Alloc[[#This Row],[Calculated Battery Allocation (kWh)]] -> 9.744 | O31: 5 | P31: Y | Q31: Y | R31: Y | S31: O
A32: 2 | B32: 1B | C32: 50003436 | D32: Cottage | E32: Karen Majer & Boyd Wykes | F32: 76 Kulbardi Way | G32: Witchcliffe | H32: WA | I32: 6286 | J32: 43 | K32: =Table_Household_Alloc[[#This Row],[Unit Entitlement]]/1000 -> 0.043 | L32: =(J32/1000)*232 -> 9.976 | M32: Symo 8.2 | N32: =IF(Table_Household_Alloc[[#This Row],[PV Installed]]="Y",1,0)*Table_Household_Alloc[[#This Row],[Calculated Battery Allocation (kWh)]] -> 9.976 | O32: 8.2 | P32: Y | Q32: Y | R32: Y | S32: O
A33: 3 | B33: 1B | C33: 50004064 | D33: Cottage | E33: Susan Hardy | F33: 74 Kulbardi Way | G33: Witchcliffe | H33: WA | I33: 6286 | J33: 43 | K33: =Table_Household_Alloc[[#This Row],[Unit Entitlement]]/1000 -> 0.043 | L33: =(J33/1000)*232 -> 9.976 | M33: Symo 5.0 | N33: =IF(Table_Household_Alloc[[#This Row],[PV Installed]]="Y",1,0)*Table_Household_Alloc[[#This Row],[Calculated Battery Allocation (kWh)]] -> 9.976 | O33: 5 | P33: Y | Q33: Y | R33: Y | S33: O
A34: 4 | B34: 1B | C34: 50003414 | D34: Cottage | E34: Jennie McCormack | F34: 72 Kulbardi Way | G34: Witchcliffe | H34: WA | I34: 6286 | J34: 45 | K34: =Table_Household_Alloc[[#This Row],[Unit Entitlement]]/1000 -> 0.045 | L34: =(J34/1000)*232 -> 10.44 | M34: Symo 5.0 | N34: =IF(Table_Household_Alloc[[#This Row],[PV Installed]]="Y",1,0)*Table_Household_Alloc[[#This Row],[Calculated Battery Allocation (kWh)]] -> 10.44 | O34: 5 | P34: Y | Q34: Y | R34: Y | S34: O
A35: 5 | B35: 1B | C35: 50003389 | D35: Cottage | E35: Michael & Britta Sorensen | F35: 70 Kulbardi Way | G35: Witchcliffe | H35: WA | I35: 6286 | J35: 46 | K35: =Table_Household_Alloc[[#This Row],[Unit Entitlement]]/1000 -> 0.046 | L35: =(J35/1000)*232 -> 10.672 | M35: Symo 8.2 | N35: =IF(Table_Household_Alloc[[#This Row],[PV Installed]]="Y",1,0)*Table_Household_Alloc[[#This Row],[Calculated Battery Allocation (kWh)]] -> 10.672 | O35: 8.2 | P35: Y | Q35: Y | R35: Y | S35: O
A36: 6 | B36: 1B | C36: 50002969 | D36: Cottage | E36: Toni Aslett | F36: 68 Kulbardi Way | G36: Witchcliffe | H36: WA | I36: 6286 | J36: 50 | K36: =Table_Household_Alloc[[#This Row],[Unit Entitlement]]/1000 -> 0.05 | L36: =(J36/1000)*232 -> 11.6 | M36: Symo 8.2 | N36: =IF(Table_Household_Alloc[[#This Row],[PV Installed]]="Y",1,0)*Table_Household_Alloc[[#This Row],[Calculated Battery Allocation (kWh)]] -> 11.6 | O36: 8.2 | P36: Y | Q36: Y | R36: Y | S36: O
A37: 7 | B37: 1B | C37: 50002951 | D37: Cottage | E37: Bridget Bolitho | F37: 66 Kulbardi Way | G37: Witchcliffe | H37: WA | I37: 6286 | J37: 52 | K37: =Table_Household_Alloc[[#This Row],[Unit Entitlement]]/1000 -> 0.052 | L37: =(J37/1000)*232 -> 12.064 | M37: Symo 5.0 | N37: =IF(Table_Household_Alloc[[#This Row],[PV Installed]]="Y",1,0)*Table_Household_Alloc[[#This Row],[Calculated Battery Allocation (kWh)]] -> 12.064 | O37: 5 | P37: Y | Q37: Y | R37: Y | S37: O
A38: 8 | B38: 1B | C38: 50002959 | D38: Family | E38: Shereen & Hamish Jolly | F38: 64 Kulbardi Way | G38: Witchcliffe | H38: WA | I38: 6286 | J38: 69 | K38: =Table_Household_Alloc[[#This Row],[Unit Entitlement]]/1000 -> 0.069 | L38: =(J38/1000)*232 -> 16.008 | M38: Symo 6.0 | N38: =IF(Table_Household_Alloc[[#This Row],[PV Installed]]="Y",1,0)*Table_Household_Alloc[[#This Row],[Calculated Battery Allocation (kWh)]] -> 16.008 | O38: 6 | P38: Y | Q38: Y | R38: Y | S38: O
A39: 9 | B39: 1B | D39: Family | E39: Phillip Crockford & Wendy Davis | F39: 62 Kulbardi Way | G39: Witchcliffe | H39: WA | I39: 6286 | J39: 55 | K39: =Table_Household_Alloc[[#This Row],[Unit Entitlement]]/1000 -> 0.055 | L39: =(J39/1000)*232 -> 12.76 | M39: Symo 10.0 | N39: =IF(Table_Household_Alloc[[#This Row],[PV Installed]]="Y",1,0)*Table_Household_Alloc[[#This Row],[Calculated Battery Allocation (kWh)]] -> 0 | P39: N | Q39: N | R39: N | S39: V
A40: 10 | B40: 1B | C40: 50003420 | D40: Family | E40: Stefan & Jennifer Widmer | F40: 60 Kulbardi Way | G40: Witchcliffe | H40: WA | I40: 6286 | J40: 57 | K40: =Table_Household_Alloc[[#This Row],[Unit Entitlement]]/1000 -> 0.057 | L40: =(J40/1000)*232 -> 13.224 | M40: Symo 5.0 | N40: =IF(Table_Household_Alloc[[#This Row],[PV Installed]]="Y",1,0)*Table_Household_Alloc[[#This Row],[Calculated Battery Allocation (kWh)]] -> 13.224 | O40: 5 | P40: Y | Q40: Y | R40: Y | S40: O
A41: 11 | B41: 1B | C41: 50003410 | D41: Family | E41: Hannah & Peter Flack | F41: 58 Kulbardi Way | G41: Witchcliffe | H41: WA | I41: 6286 | J41: 59 | K41: =Table_Household_Alloc[[#This Row],[Unit Entitlement]]/1000 -> 0.059 | L41: =(J41/1000)*232 -> 13.688 | M41: Symo 6.0 | N41: =IF(Table_Household_Alloc[[#This Row],[PV Installed]]="Y",1,0)*Table_Household_Alloc[[#This Row],[Calculated Battery Allocation (kWh)]] -> 13.688 | O41: 6 | P41: Y | Q41: Y | R41: Y | S41: O
A42: 12 | B42: 1B | C42: 50003418 | D42: Family | E42: Paul & Nicole Wilkinson | F42: 56 Kulbardi Way | G42: Witchcliffe | H42: WA | I42: 6286 | J42: 60 | K42: =Table_Household_Alloc[[#This Row],[Unit Entitlement]]/1000 -> 0.06 | L42: =(J42/1000)*232 -> 13.92 | M42: Symo 10.0 | N42: =IF(Table_Household_Alloc[[#This Row],[PV Installed]]="Y",1,0)*Table_Household_Alloc[[#This Row],[Calculated Battery Allocation (kWh)]] -> 13.92 | O42: 10 | P42: Y | Q42: Y | R42: Y | S42: O
A43: 13 | B43: 1B | C43: 50002859 | D43: Family | E43: Stephen & Dicy Hall | F43: 54 Kulbardi Way | G43: Witchcliffe | H43: WA | I43: 6286 | J43: 60 | K43: =Table_Household_Alloc[[#This Row],[Unit Entitlement]]/1000 -> 0.06 | L43: =(J43/1000)*232 -> 13.92 | M43: Symo 10.0 | N43: =IF(Table_Household_Alloc[[#This Row],[PV Installed]]="Y",1,0)*Table_Household_Alloc[[#This Row],[Calculated Battery Allocation (kWh)]] -> 13.92 | O43: 10 | P43: Y | Q43: Y | R43: Y | S43: O
A44: 14 | B44: 1B | C44: 50003396 | D44: Family | E44: Craig & Julie Headford | F44: 52 Kulbardi Way | G44: Witchcliffe | H44: WA | I44: 6286 | J44: 63 | K44: =Table_Household_Alloc[[#This Row],[Unit Entitlement]]/1000 -> 0.063 | L44: =(J44/1000)*232 -> 14.616 | M44: Symo 10.0 | N44: =IF(Table_Household_Alloc[[#This Row],[PV Installed]]="Y",1,0)*Table_Household_Alloc[[#This Row],[Calculated Battery Allocation (kWh)]] -> 14.616 | O44: 10 | P44: Y | Q44: Y | R44: Y | S44: O
A45: 15 | B45: 1B | C45: 50003401 | D45: Groupie | E45: Jema McCabe | F45: 18 Yornitj Grove | G45: Witchcliffe | H45: WA | I45: 6286 | J45: 27 | K45: =Table_Household_Alloc[[#This Row],[Unit Entitlement]]/1000 -> 0.027 | L45: =(J45/1000)*232 -> 6.264 | M45: Symo 5.0 | N45: =IF(Table_Household_Alloc[[#This Row],[PV Installed]]="Y",1,0)*Table_Household_Alloc[[#This Row],[Calculated Battery Allocation (kWh)]] -> 6.264 | O45: 5 | P45: Y | Q45: Y | R45: N | S45: O
A46: 16 | B46: 1B | C46: 50003430 | D46: Groupie | E46: Colin & Filomena Dear | F46: 20 Yornitj Grove | G46: Witchcliffe | H46: WA | I46: 6286 | J46: 27 | K46: =Table_Household_Alloc[[#This Row],[Unit Entitlement]]/1000 -> 0.027 | L46: =(J46/1000)*232 -> 6.264 | M46: Symo 5.0 | N46: =IF(Table_Household_Alloc[[#This Row],[PV Installed]]="Y",1,0)*Table_Household_Alloc[[#This Row],[Calculated Battery Allocation (kWh)]] -> 6.264 | O46: 5 | P46: Y | Q46: Y | R46: Y | S46: O
A47: 17 | B47: 1B | C47: 50003415 | D47: Groupie | E47: Candice & Bryn Papalia | F47: 22 Yornitj Grove | G47: Witchcliffe | H47: WA | I47: 6286 | J47: 27 | K47: =Table_Household_Alloc[[#This Row],[Unit Entitlement]]/1000 -> 0.027 | L47: =(J47/1000)*232 -> 6.264 | M47: Symo 5.0 | N47: =IF(Table_Household_Alloc[[#This Row],[PV Installed]]="Y",1,0)*Table_Household_Alloc[[#This Row],[Calculated Battery Allocation (kWh)]] -> 6.264 | O47: 5 | P47: Y | Q47: Y | R47: N | S47: O
A48: 18 | B48: 1B | D48: Groupie | E48: Chloe Dignam | F48: 24 Yornitj Grove | G48: Witchcliffe | H48: WA | I48: 6286 | J48: 27 | K48: =Table_Household_Alloc[[#This Row],[Unit Entitlement]]/1000 -> 0.027 | L48: =(J48/1000)*232 -> 6.264 | M48: Symo 5.0 | N48: =IF(Table_Household_Alloc[[#This Row],[PV Installed]]="Y",1,0)*Table_Household_Alloc[[#This Row],[Calculated Battery Allocation (kWh)]] -> 0 | P48: Y | Q48: N | R48: N | S48: UC
A49: 19 | B49: 1B | C49: 50003432 | D49: Groupie | E49: Alex Jolly | F49: 26 Yornitj Grove | G49: Witchcliffe | H49: WA | I49: 6286 | J49: 30 | K49: =Table_Household_Alloc[[#This Row],[Unit Entitlement]]/1000 -> 0.03 | L49: =(J49/1000)*232 -> 6.96 | M49: Symo 5.0 | N49: =IF(Table_Household_Alloc[[#This Row],[PV Installed]]="Y",1,0)*Table_Household_Alloc[[#This Row],[Calculated Battery Allocation (kWh)]] -> 6.96 | O49: 5 | P49: Y | Q49: Y | R49: Y | S49: O
A50: 20 | B50: 1B | C50: 50002972 | D50: Family | E50: Nathan Stone | F50: 3 Kyloring Drive | G50: Witchcliffe | H50: WA | I50: 6286 | J50: 59 | K50: =Table_Household_Alloc[[#This Row],[Unit Entitlement]]/1000 -> 0.059 | L50: =(J50/1000)*232 -> 13.688 | M50: Symo 10.0 | N50: =IF(Table_Household_Alloc[[#This Row],[PV Installed]]="Y",1,0)*Table_Household_Alloc[[#This Row],[Calculated Battery Allocation (kWh)]] -> 13.688 | O50: 10 | P50: Y | Q50: Y | R50: Y | S50: O
A51: 21 | B51: 1B | C51: 50002650 | D51: Fam ily | E51: Nicholas Mead & Theresa Brandl | F51: 5 Kyloring Drive | G51: Witchcliffe | H51: WA | I51: 6286 | J51: 59 | K51: =Table_Household_Alloc[[#This Row],[Unit Entitlement]]/1000 -> 0.059 | L51: =(J51/1000)*232 -> 13.688 | M51: Symo 10.0 | N51: =IF(Table_Household_Alloc[[#This Row],[PV Installed]]="Y",1,0)*Table_Household_Alloc[[#This Row],[Calculated Battery Allocation (kWh)]] -> 13.688 | O51: 10 | P51: Y | Q51: Y | R51: Y | S51: O
A52: BESS | B52: 1B | C52: 40002670 | E52: BESS Powerpack 232kWh | K52: =Table_Household_Alloc[[#This Row],[Unit Entitlement]]/1000 -> 0 | N52: =IF(Table_Household_Alloc[[#This Row],[PV Installed]]="Y",1,0)*Table_Household_Alloc[[#This Row],[Calculated Battery Allocation (kWh)]] -> 0
A53: EV | B53: 1B | C53: 40002667 | D53: N/A | E53: EV Charger | G53: Witchcliffe | H53: WA | I53: 6286 | K53: =Table_Household_Alloc[[#This Row],[Unit Entitlement]]/1000 -> 0 | L53: =(J53/1000)*232 -> 0 | N53: =IF(Table_Household_Alloc[[#This Row],[PV Installed]]="Y",1,0)*Table_Household_Alloc[[#This Row],[Calculated Battery Allocation (kWh)]] -> 0 | P53: Y | Q53: N | R53: Y
A54: CS | B54: 1B | C54: 50003399 | D54: N/A | E54: Common Services MSB | G54: Witchcliffe | H54: WA | I54: 6286 | K54: =Table_Household_Alloc[[#This Row],[Unit Entitlement]]/1000 -> 0 | L54: =(J54/1000)*232 -> 0 | N54: =IF(Table_Household_Alloc[[#This Row],[PV Installed]]="Y",1,0)*Table_Household_Alloc[[#This Row],[Calculated Battery Allocation (kWh)]] -> 0 | P54: Y | Q54: N | R54: Y
A55: DB1 | B55: 1B | K55: =Table_Household_Alloc[[#This Row],[Unit Entitlement]]/1000 -> 0 | N55: =IF(Table_Household_Alloc[[#This Row],[PV Installed]]="Y",1,0)*Table_Household_Alloc[[#This Row],[Calculated Battery Allocation (kWh)]] -> 0
A56: DB2 | B56: 1B | K56: =Table_Household_Alloc[[#This Row],[Unit Entitlement]]/1000 -> 0 | N56: =IF(Table_Household_Alloc[[#This Row],[PV Installed]]="Y",1,0)*Table_Household_Alloc[[#This Row],[Calculated Battery Allocation (kWh)]] -> 0
A57: 1 | B57: 1C | C57: 50003397 | E57: Aron Dyer Jodie Passmore | F57: 19 Yornitj Grove | G57: Witchcliffe | H57: WA | I57: 6286 | J57: 42 | K57: =Table_Household_Alloc[[#This Row],[Unit Entitlement]]/1000 -> 0.042 | L57: =(J57/1000)*232 -> 9.744 | M57: Symo 8.2 | N57: =IF(Table_Household_Alloc[[#This Row],[PV Installed]]="Y",1,0)*Table_Household_Alloc[[#This Row],[Calculated Battery Allocation (kWh)]] -> 9.744 | O57: 8.2 | P57: Y | Q57: Y | R57: Y | S57: O | X57: 44381 | Y57: Current
A58: 2 | B58: 1C | C58: 50003402 | E58: Eli Sutton | F58: 21 Yornitj Grove | G58: Witchcliffe | H58: WA | I58: 6286 | J58: 43 | K58: =Table_Household_Alloc[[#This Row],[Unit Entitlement]]/1000 -> 0.043 | L58: =(J58/1000)*232 -> 9.976 | M58: =CONCATENATE("Symo ",Table_Household_Alloc[[#This Row],[Export Capacity (kW)]]) -> Symo 5 | N58: =IF(Table_Household_Alloc[[#This Row],[PV Installed]]="Y",1,0)*Table_Household_Alloc[[#This Row],[Calculated Battery Allocation (kWh)]] -> 9.976 | O58: 5 | P58: Y | Q58: Y | R58: Y | S58: O | X58: 44774 | Y58: Current
A59: 3 | B59: 1C | C59: 50003431 | E59: Shelley Chapman Cherry Chapman | F59: 23 Yornitj Grove | G59: Witchcliffe | H59: WA | I59: 6286 | J59: 44 | K59: =Table_Household_Alloc[[#This Row],[Unit Entitlement]]/1000 -> 0.044 | L59: =(J59/1000)*232 -> 10.208 | M59: =CONCATENATE("Symo ",Table_Household_Alloc[[#This Row],[Export Capacity (kW)]]) -> Symo 8.2 | N59: =IF(Table_Household_Alloc[[#This Row],[PV Installed]]="Y",1,0)*Table_Household_Alloc[[#This Row],[Calculated Battery Allocation (kWh)]] -> 10.208 | O59: 8.2 | P59: Y | Q59: Y | R59: Y | S59: O | X59: 45023 | Y59: Current
A60: 4 | B60: 1C | C60: 50003394 | E60: Jillian Ann Luckhurst | F60: 25 Yornitj Grove | G60: Witchcliffe | H60: WA | I60: 6286 | J60: 45 | K60: =Table_Household_Alloc[[#This Row],[Unit Entitlement]]/1000 -> 0.045 | L60: =(J60/1000)*232 -> 10.44 | M60: =CONCATENATE("Symo ",Table_Household_Alloc[[#This Row],[Export Capacity (kW)]]) -> Symo 5 | N60: =IF(Table_Household_Alloc[[#This Row],[PV Installed]]="Y",1,0)*Table_Household_Alloc[[#This Row],[Calculated Battery Allocation (kWh)]] -> 10.44 | O60: 5 | P60: Y | Q60: Y | R60: Y | S60: O | X60: 45078 | Y60: Current
A61: 5 | B61: 1C | C61: 50003433 | E61: Samuel Vinciullo | F61: 27 Yornitj Grove | G61: Witchcliffe | H61: WA | I61: 6286 | J61: 46 | K61: =Table_Household_Alloc[[#This Row],[Unit Entitlement]]/1000 -> 0.046 | L61: =(J61/1000)*232 -> 10.672 | M61: =CONCATENATE("Symo ",Table_Household_Alloc[[#This Row],[Export Capacity (kW)]]) -> Symo 8.2 | N61: =IF(Table_Household_Alloc[[#This Row],[PV Installed]]="Y",1,0)*Table_Household_Alloc[[#This Row],[Calculated Battery Allocation (kWh)]] -> 10.672 | O61: 8.2 | P61: Y | Q61: Y | R61: Y | S61: O | X61: 44599 | Y61: Current
A62: 6 | B62: 1C | C62: 50003421 | E62: Christopher Paul Martin Vicki Ann Martin | F62: 4 Mannitj Place | G62: Witchcliffe | H62: WA | I62: 6286 | J62: 66 | K62: =Table_Household_Alloc[[#This Row],[Unit Entitlement]]/1000 -> 0.066 | L62: =(J62/1000)*232 -> 15.312 | M62: =CONCATENATE("Symo ",Table_Household_Alloc[[#This Row],[Export Capacity (kW)]]) -> Symo 10 | N62: =IF(Table_Household_Alloc[[#This Row],[PV Installed]]="Y",1,0)*Table_Household_Alloc[[#This Row],[Calculated Battery Allocation (kWh)]] -> 15.312 | O62: 10 | P62: Y | Q62: Y | R62: Y | S62: O | X62: 45020 | Y62: Current
A63: 7 | B63: 1C | C63: 50002953 | E63: Dex Ezekiel, Jeannine Penniment | F63: 6 Mannitj Place | G63: Witchcliffe | H63: WA | I63: 6286 | J63: 66 | K63: =Table_Household_Alloc[[#This Row],[Unit Entitlement]]/1000 -> 0.066 | L63: =(J63/1000)*232 -> 15.312 | N63: =IF(Table_Household_Alloc[[#This Row],[PV Installed]]="Y",1,0)*Table_Household_Alloc[[#This Row],[Calculated Battery Allocation (kWh)]] -> 0 | S63: UC/M/ND
A64: 8 | B64: 1C | C64: 50003395 | E64: Eric Martini Karina Jean Martini | F64: 8 Mannitj Place | G64: Witchcliffe | H64: WA | I64: 6286 | J64: 66 | K64: =Table_Household_Alloc[[#This Row],[Unit Entitlement]]/1000 -> 0.066 | L64: =(J64/1000)*232 -> 15.312 | M64: =CONCATENATE("Symo ",Table_Household_Alloc[[#This Row],[Export Capacity (kW)]]) -> Symo 10 | N64: =IF(Table_Household_Alloc[[#This Row],[PV Installed]]="Y",1,0)*Table_Household_Alloc[[#This Row],[Calculated Battery Allocation (kWh)]] -> 15.312 | O64: 10 | P64: Y | Q64: Y | R64: Y | S64: O | X64: 44682 | Y64: Current
A65: 9 | B65: 1C | C65: 50003435 | E65: Christopher van Etten Emmanuelle van Etten | F65: 10 Mannitj Place | G65: Witchcliffe | H65: WA | I65: 6286 | J65: 66 | K65: =Table_Household_Alloc[[#This Row],[Unit Entitlement]]/1000 -> 0.066 | L65: =(J65/1000)*232 -> 15.312 | N65: =IF(Table_Household_Alloc[[#This Row],[PV Installed]]="Y",1,0)*Table_Household_Alloc[[#This Row],[Calculated Battery Allocation (kWh)]] -> 0 | S65: UC
A66: 10 | B66: 1C | C66: 50002952 | E66: Peter Smith | F66: 32 Kulbardi Way | G66: Witchcliffe | H66: WA | I66: 6286 | J66: 31 | K66: =Table_Household_Alloc[[#This Row],[Unit Entitlement]]/1000 -> 0.031 | L66: =(J66/1000)*232 -> 7.192 | M66: =CONCATENATE("Symo ",Table_Household_Alloc[[#This Row],[Export Capacity (kW)]]) -> Symo 5 | N66: =IF(Table_Household_Alloc[[#This Row],[PV Installed]]="Y",1,0)*Table_Household_Alloc[[#This Row],[Calculated Battery Allocation (kWh)]] -> 7.192 | O66: 5 | P66: Y | Q66: Y | R66: Y | S66: O | X66: 44593 | Y66: Current
A67: 11 | B67: 1C | C67: 50002944 | E67: Peter Andre Grant | F67: 34 Kulbardi Way | G67: Witchcliffe | H67: WA | I67: 6286 | J67: 31 | K67: =Table_Household_Alloc[[#This Row],[Unit Entitlement]]/1000 -> 0.031 | L67: =(J67/1000)*232 -> 7.192 | N67: =IF(Table_Household_Alloc[[#This Row],[PV Installed]]="Y",1,0)*Table_Household_Alloc[[#This Row],[Calculated Battery Allocation (kWh)]] -> 0 | S67: UC/M/ND
A68: 12 | B68: 1C | C68: 3308026898 | E68: Sandra Handy | F68: 36 Kulbardi Way | G68: Witchcliffe | H68: WA | I68: 6286 | J68: 31 | K68: =Table_Household_Alloc[[#This Row],[Unit Entitlement]]/1000 -> 0.031 | L68: =(J68/1000)*232 -> 7.192 | M68: =CONCATENATE("Symo ",Table_Household_Alloc[[#This Row],[Export Capacity (kW)]]) -> Symo 5 | N68: =IF(Table_Household_Alloc[[#This Row],[PV Installed]]="Y",1,0)*Table_Household_Alloc[[#This Row],[Calculated Battery Allocation (kWh)]] -> 7.192 | O68: 5 | P68: N | Q68: Y | R68: Y | S68: O | X68: 45139 | Y68: Current
A69: 13 | B69: 1C | C69: 50003424 | E69: Miles Durand | F69: 38 Kulbardi Way | G69: Witchcliffe | H69: WA | I69: 6286 | J69: 31 | K69: =Table_Household_Alloc[[#This Row],[Unit Entitlement]]/1000 -> 0.031 | L69: =(J69/1000)*232 -> 7.192 | M69: =CONCATENATE("Symo ",Table_Household_Alloc[[#This Row],[Export Capacity (kW)]]) -> Symo 5 | N69: =IF(Table_Household_Alloc[[#This Row],[PV Installed]]="Y",1,0)*Table_Household_Alloc[[#This Row],[Calculated Battery Allocation (kWh)]] -> 7.192 | O69: 5 | P69: Y | Q69: Y | R69: Y | S69: O | X69: 44621 | Y69: Current
A70: 14 | B70: 1C | C70: 50003438 | E70: Lawrence Bycroft Anu Grace | F70: 40 Kulbardi Way | G70: Witchcliffe | H70: WA | I70: 6286 | J70: 37 | K70: =Table_Household_Alloc[[#This Row],[Unit Entitlement]]/1000 -> 0.037 | L70: =(J70/1000)*232 -> 8.584 | M70: =CONCATENATE("Symo ",Table_Household_Alloc[[#This Row],[Export Capacity (kW)]]) -> Symo 5 | N70: =IF(Table_Household_Alloc[[#This Row],[PV Installed]]="Y",1,0)*Table_Household_Alloc[[#This Row],[Calculated Battery Allocation (kWh)]] -> 8.584 | O70: 5 | P70: Y | Q70: Y | R70: Y | S70: O | X70: 44643 | Y70: Current
A71: 15 | B71: 1C | C71: 50003404 | E71: Kaine Grigg (Hudson) | F71: 50 Kulbardi Way | G71: Witchcliffe | H71: WA | I71: 6286 | J71: 69 | K71: =Table_Household_Alloc[[#This Row],[Unit Entitlement]]/1000 -> 0.069 | L71: =(J71/1000)*232 -> 16.008 | M71: =CONCATENATE("Symo ",Table_Household_Alloc[[#This Row],[Export Capacity (kW)]]) -> Symo 8.2 | N71: =IF(Table_Household_Alloc[[#This Row],[PV Installed]]="Y",1,0)*Table_Household_Alloc[[#This Row],[Calculated Battery Allocation (kWh)]] -> 16.008 | O71: 8.2 | P71: Y | Q71: Y | R71: Y | S71: O | X71: 44835 | Y71: Current
A72: 16 | B72: 1C | C72: 50003419 | E72: Veronique Florec | F72: 48 Kulbardi Way | G72: Witchcliffe | H72: WA | I72: 6286 | J72: 69 | K72: =Table_Household_Alloc[[#This Row],[Unit Entitlement]]/1000 -> 0.069 | L72: =(J72/1000)*232 -> 16.008 | M72: =CONCATENATE("Symo ",Table_Household_Alloc[[#This Row],[Export Capacity (kW)]]) -> Symo 10 | N72: =IF(Table_Household_Alloc[[#This Row],[PV Installed]]="Y",1,0)*Table_Household_Alloc[[#This Row],[Calculated Battery Allocation (kWh)]] -> 16.008 | O72: 10 | P72: Y | Q72: Y | R72: Y | S72: O | X72: 45047 | Y72: Current
A73: 17 | B73: 1C | C73: 50003428 | E73: Lars Rueter Katja Blankenheim | F73: 46 Kulbardi Way | G73: Witchcliffe | H73: WA | I73: 6286 | J73: 69 | K73: =Table_Household_Alloc[[#This Row],[Unit Entitlement]]/1000 -> 0.069 | L73: =(J73/1000)*232 -> 16.008 | N73: =IF(Table_Household_Alloc[[#This Row],[PV Installed]]="Y",1,0)*Table_Household_Alloc[[#This Row],[Calculated Battery Allocation (kWh)]] -> 0 | S73: UC/M/ND
A74: 18 | B74: 1C | C74: 50002935 | E74: Amy Steel | F74: 44 Kulbardi Way | G74: Witchcliffe | H74: WA | I74: 6286 | J74: 69 | K74: =Table_Household_Alloc[[#This Row],[Unit Entitlement]]/1000 -> 0.069 | L74: =(J74/1000)*232 -> 16.008 | M74: =CONCATENATE("Symo ",Table_Household_Alloc[[#This Row],[Export Capacity (kW)]]) -> Symo 10 | N74: =IF(Table_Household_Alloc[[#This Row],[PV Installed]]="Y",1,0)*Table_Household_Alloc[[#This Row],[Calculated Battery Allocation (kWh)]] -> 16.008 | O74: 10 | P74: Y | Q74: Y | R74: Y | S74: O | X74: 45481 | Y74: Current
A75: 19 | B75: 1C | C75: 50003417 | E75: Laurence Hansen Janet Anne Hansen | F75: 42 Kulbardi Way | G75: Witchcliffe | H75: WA | I75: 6286 | J75: 79 | K75: =Table_Household_Alloc[[#This Row],[Unit Entitlement]]/1000 -> 0.079 | L75: =(J75/1000)*232 -> 18.328 | M75: =CONCATENATE("Symo ",Table_Household_Alloc[[#This Row],[Export Capacity (kW)]]) -> Symo 10 | N75: =IF(Table_Household_Alloc[[#This Row],[PV Installed]]="Y",1,0)*Table_Household_Alloc[[#This Row],[Calculated Battery Allocation (kWh)]] -> 18.328 | O75: 10 | P75: Y | Q75: Y | R75: Y | S75: O | X75: 44913 | Y75: Current
A76: BESS | B76: 1C | C76: 40002722 | E76: BESS Powerpack 232kWh | K76: =Table_Household_Alloc[[#This Row],[Unit Entitlement]]/1000 -> 0 | N76: =IF(Table_Household_Alloc[[#This Row],[PV Installed]]="Y",1,0)*Table_Household_Alloc[[#This Row],[Calculated Battery Allocation (kWh)]] -> 0
A77: EV | B77: 1C | C77: 40002728 | E77: EV Charger | F77: 10437 Bussell Hwy | G77: Witchcliffe | H77: WA | I77: 6286 | K77: =Table_Household_Alloc[[#This Row],[Unit Entitlement]]/1000 -> 0 | N77: =IF(Table_Household_Alloc[[#This Row],[PV Installed]]="Y",1,0)*Table_Household_Alloc[[#This Row],[Calculated Battery Allocation (kWh)]] -> 0
A78: CS | B78: 1C | C78: 50003429 | E78: Common Services MSB | F78: 10437 Bussell Hwy | G78: Witchcliffe | H78: WA | I78: 6286 | K78: =Table_Household_Alloc[[#This Row],[Unit Entitlement]]/1000 -> 0 | L78: =(J78/1000)*232 -> 0 | N78: =IF(Table_Household_Alloc[[#This Row],[PV Installed]]="Y",1,0)*Table_Household_Alloc[[#This Row],[Calculated Battery Allocation (kWh)]] -> 0
A79: DB1 | B79: 1C | K79: =Table_Household_Alloc[[#This Row],[Unit Entitlement]]/1000 -> 0 | N79: =IF(Table_Household_Alloc[[#This Row],[PV Installed]]="Y",1,0)*Table_Household_Alloc[[#This Row],[Calculated Battery Allocation (kWh)]] -> 0
A80: DB2 | B80: 1C | K80: =Table_Household_Alloc[[#This Row],[Unit Entitlement]]/1000 -> 0 | N80: =IF(Table_Household_Alloc[[#This Row],[PV Installed]]="Y",1,0)*Table_Household_Alloc[[#This Row],[Calculated Battery Allocation (kWh)]] -> 0
A81: 1 | B81: 2A | C81: 50002920 | E81: Megan Donald & Yehuda Harmor | F81: 15 Kulbardi Way | G81: Witchcliffe | H81: WA | I81: 6286 | J81: 40 | K81: =Table_Household_Alloc[[#This Row],[Unit Entitlement]]/1000 -> 0.04 | L81: =J81/1000*232 -> 9.28 | N81: =IF(Table_Household_Alloc[[#This Row],[PV Installed]]="Y",1,0)*Table_Household_Alloc[[#This Row],[Calculated Battery Allocation (kWh)]] -> 0 | S81: UC | T81: 0499 838 958 | U81: 0499 838 830 | V81: tinymegan68@gmail.com
A82: 2 | B82: 2A | C82: 50002903 | E82: LK & MD Hynes | F82: 13 Kulbardi Way | G82: Witchcliffe | H82: WA | I82: 6286 | J82: 40 | K82: =Table_Household_Alloc[[#This Row],[Unit Entitlement]]/1000 -> 0.04 | L82: =J82/1000*232 -> 9.28 | M82: =CONCATENATE("Symo ",Table_Household_Alloc[[#This Row],[Export Capacity (kW)]]) -> Symo 8.2 | N82: =IF(Table_Household_Alloc[[#This Row],[PV Installed]]="Y",1,0)*Table_Household_Alloc[[#This Row],[Calculated Battery Allocation (kWh)]] -> 9.28 | O82: 8.2 | P82: Y | Q82: Y | R82: Y | S82: O | T82: 0411 725 581 | U82: 0478 577 554 | V82: lyndalhynes@hotmail.com | X82: 44986 | Y82: Current
A83: 3 | B83: 2A | E83: Paul John Baker | F83: 11 Kulbardi Way | G83: Witchcliffe | H83: WA | I83: 6286 | J83: 40 | K83: =Table_Household_Alloc[[#This Row],[Unit Entitlement]]/1000 -> 0.04 | L83: =J83/1000*232 -> 9.28 | N83: =IF(Table_Household_Alloc[[#This Row],[PV Installed]]="Y",1,0)*Table_Household_Alloc[[#This Row],[Calculated Battery Allocation (kWh)]] -> 0 | S83: V | T83: 0402 135 100 | V83: theminiguyagain@gmail.com
A84: 4 | B84: 2A | E84: K L Geels | F84: 9 Kulbardi Way | G84: Witchcliffe | H84: WA | I84: 6286 | J84: 40 | K84: =Table_Household_Alloc[[#This Row],[Unit Entitlement]]/1000 -> 0.04 | L84: =J84/1000*232 -> 9.28 | N84: =IF(Table_Household_Alloc[[#This Row],[PV Installed]]="Y",1,0)*Table_Household_Alloc[[#This Row],[Calculated Battery Allocation (kWh)]] -> 0 | S84: V | T84: 44(0)7734364646 | V84: kgeels@gmail.com
A85: 5 | B85: 2A | C85: 50002911 | E85: B & G Hamersma | F85: 7 Kulbardi Way | G85: Witchcliffe | H85: WA | I85: 6286 | J85: 42 | K85: =Table_Household_Alloc[[#This Row],[Unit Entitlement]]/1000 -> 0.042 | L85: =J85/1000*232 -> 9.744 | M85: =CONCATENATE("Symo ",Table_Household_Alloc[[#This Row],[Export Capacity (kW)]]) -> Symo 8.2 | N85: =IF(Table_Household_Alloc[[#This Row],[PV Installed]]="Y",1,0)*Table_Household_Alloc[[#This Row],[Calculated Battery Allocation (kWh)]] -> 9.744 | O85: 8.2 | P85: Y | Q85: Y | R85: Y | S85: O | T85: 0416 499 424 | U85: 0424 482 470 | V85: bouwe.hamersma@gmail.com | X85: 45108 | Y85: Current
A86: 6 | B86: 2A | E86: B & G Garnett | F86: 5 Kulbardi Way | G86: Witchcliffe | H86: WA | I86: 6286 | J86: 41 | K86: =Table_Household_Alloc[[#This Row],[Unit Entitlement]]/1000 -> 0.041 | L86: =J86/1000*232 -> 9.512 | N86: =IF(Table_Household_Alloc[[#This Row],[PV Installed]]="Y",1,0)*Table_Household_Alloc[[#This Row],[Calculated Battery Allocation (kWh)]] -> 0 | S86: V | T86: 0413 209 277 | V86: garnett635@hotmail.com
A87: 7 | B87: 2A | E87: C E Andrews & Y J Marinivich | F87: 3 Kulbardi Way | G87: Witchcliffe | H87: WA | I87: 6286 | J87: 40 | K87: =Table_Household_Alloc[[#This Row],[Unit Entitlement]]/1000 -> 0.04 | L87: =J87/1000*232 -> 9.28 | N87: =IF(Table_Household_Alloc[[#This Row],[PV Installed]]="Y",1,0)*Table_Household_Alloc[[#This Row],[Calculated Battery Allocation (kWh)]] -> 0 | S87: V | T87: 0448 023 265 | U87: 0488 937 149 | V87: yurimarinovich@gmail.com
A88: 8 | B88: 2A | E88: Colin Reburn | F88: 1 Kulbardi Way | G88: Witchcliffe | H88: WA | I88: 6286 | J88: 39 | K88: =Table_Household_Alloc[[#This Row],[Unit Entitlement]]/1000 -> 0.039 | L88: =J88/1000*232 -> 9.048 | N88: =IF(Table_Household_Alloc[[#This Row],[PV Installed]]="Y",1,0)*Table_Household_Alloc[[#This Row],[Calculated Battery Allocation (kWh)]] -> 0 | S88: V | T88: 0435 204 625 | V88: colin@kilmontinplumbing.com
A89: 9 | B89: 2A | C89: 50002909 | E89: N & C Haskell | F89: 23 Wolghine Ave | G89: Witchcliffe | H89: WA | I89: 6286 | J89: 54 | K89: =Table_Household_Alloc[[#This Row],[Unit Entitlement]]/1000 -> 0.054 | L89: =J89/1000*232 -> 12.528 | N89: =IF(Table_Household_Alloc[[#This Row],[PV Installed]]="Y",1,0)*Table_Household_Alloc[[#This Row],[Calculated Battery Allocation (kWh)]] -> 0 | S89: O | T89: 0478 630 993 | U89: 0478 220 964 | V89: nadia.anne@gmail.com | X89: 45139 | Y89: Current
A90: 10 | B90: 2A | E90: Charlotte & Darryl Diaz | F90: 21 Wolghine Ave | G90: Witchcliffe | H90: WA | I90: 6286 | J90: 54 | K90: =Table_Household_Alloc[[#This Row],[Unit Entitlement]]/1000 -> 0.054 | L90: =J90/1000*232 -> 12.528 | N90: =IF(Table_Household_Alloc[[#This Row],[PV Installed]]="Y",1,0)*Table_Household_Alloc[[#This Row],[Calculated Battery Allocation (kWh)]] -> 0 | S90: V | T90: 0415 506 827 | U90: 0449 646 303 | V90: darrylnaidu@gmail.com
A91: 11 | B91: 2A | E91: Simon Alan Naber | F91: 19 Wolghine Ave | G91: Witchcliffe | H91: WA | I91: 6286 | J91: 54 | K91: =Table_Household_Alloc[[#This Row],[Unit Entitlement]]/1000 -> 0.054 | L91: =J91/1000*232 -> 12.528 | N91: =IF(Table_Household_Alloc[[#This Row],[PV Installed]]="Y",1,0)*Table_Household_Alloc[[#This Row],[Calculated Battery Allocation (kWh)]] -> 0 | S91: V | T91: 0449 253 680 | V91: simon@mooreandmoorecafe.com
A92: 12 | B92: 2A | C92: 50002897 | E92: J S C & EP Ford | F92: 17 Wolghine Ave | G92: Witchcliffe | H92: WA | I92: 6286 | J92: 54 | K92: =Table_Household_Alloc[[#This Row],[Unit Entitlement]]/1000 -> 0.054 | L92: =J92/1000*232 -> 12.528 | M92: =CONCATENATE("Symo ",Table_Household_Alloc[[#This Row],[Export Capacity (kW)]]) -> Symo 10 | N92: =IF(Table_Household_Alloc[[#This Row],[PV Installed]]="Y",1,0)*Table_Household_Alloc[[#This Row],[Calculated Battery Allocation (kWh)]] -> 12.528 | O92: 10 | P92: Y | Q92: Y | R92: Y | S92: O | T92: 0414 401 059 | U92: 0432 519 448 | V92: setford.18@gmail.com | X92: 45078 | Y92: Current
A93: 13 | B93: 2A | C93: 50002839 | E93: K V Jarvis & P S Davis | F93: 15 Wolghine Ave | G93: Witchcliffe | H93: WA | I93: 6286 | J93: 56 | K93: =Table_Household_Alloc[[#This Row],[Unit Entitlement]]/1000 -> 0.056 | L93: =J93/1000*232 -> 12.992 | N93: =IF(Table_Household_Alloc[[#This Row],[PV Installed]]="Y",1,0)*Table_Household_Alloc[[#This Row],[Calculated Battery Allocation (kWh)]] -> 0 | P93: Y | R93: Y | S93: O | T93: 0435 280 200 | U93: 0435 280 202 | V93: katevjarvis@hotmail.com | X93: 45261 | Y93: Current
A94: 14 | B94: 2A | C94: 50002863 | E94: A Lillend | F94: 20 Mardo Drive | G94: Witchcliffe | H94: WA | I94: 6286 | J94: 28 | K94: =Table_Household_Alloc[[#This Row],[Unit Entitlement]]/1000 -> 0.028 | L94: =J94/1000*232 -> 6.496 | M94: =CONCATENATE("Symo ",Table_Household_Alloc[[#This Row],[Export Capacity (kW)]]) -> Symo 5 | N94: =IF(Table_Household_Alloc[[#This Row],[PV Installed]]="Y",1,0)*Table_Household_Alloc[[#This Row],[Calculated Battery Allocation (kWh)]] -> 6.496 | O94: 5 | P94: Y | Q94: Y | R94: Y | S94: O | T94: 0466 498 000 | U94: 0449 594 479 | V94: astisup@gmail.com | X94: 45536 | Y94: Current
A95: 15 | B95: 2A | C95: 50002947 | E95: Liz Thomas | F95: 22 Mardo Drive | G95: Witchcliffe | H95: WA | I95: 6286 | J95: 28 | K95: =Table_Household_Alloc[[#This Row],[Unit Entitlement]]/1000 -> 0.028 | L95: =J95/1000*232 -> 6.496 | M95: =CONCATENATE("Symo ",Table_Household_Alloc[[#This Row],[Export Capacity (kW)]]) -> Symo 5 | N95: =IF(Table_Household_Alloc[[#This Row],[PV Installed]]="Y",1,0)*Table_Household_Alloc[[#This Row],[Calculated Battery Allocation (kWh)]] -> 6.496 | O95: 5 | P95: Y | Q95: Y | R95: Y | S95: O | T95: 0421 607 702 | V95: ehmthomas@hotmail.com | X95: 45413 | Y95: Current
A96: 16 | B96: 2A | E96: Helen Downsborough | F96: 24 Mardo Drive | G96: Witchcliffe | H96: WA | I96: 6286 | J96: 28 | K96: =Table_Household_Alloc[[#This Row],[Unit Entitlement]]/1000 -> 0.028 | L96: =J96/1000*232 -> 6.496 | N96: =IF(Table_Household_Alloc[[#This Row],[PV Installed]]="Y",1,0)*Table_Household_Alloc[[#This Row],[Calculated Battery Allocation (kWh)]] -> 0 | S96: V | T96: 042 883 6629 | V96: helendownsborough@bigpond.com
A97: 17 | B97: 2A | C97: 50002902 | E97: Carol Luca | F97: 26 Mardo Drive | G97: Witchcliffe | H97: WA | I97: 6286 | J97: 28 | K97: =Table_Household_Alloc[[#This Row],[Unit Entitlement]]/1000 -> 0.028 | L97: =J97/1000*232 -> 6.496 | M97: =CONCATENATE("Symo ",Table_Household_Alloc[[#This Row],[Export Capacity (kW)]]) -> Symo 5 | N97: =IF(Table_Household_Alloc[[#This Row],[PV Installed]]="Y",1,0)*Table_Household_Alloc[[#This Row],[Calculated Battery Allocation (kWh)]] -> 6.496 | O97: 5 | P97: Y | Q97: Y | R97: Y | S97: O | T97: 0425 823 928 | V97: carolluca8@icloud.com | X97: 45536 | Y97: Current
A98: 18 | B98: 2A | C98: 50002950 | E98: N Rebasti | F98: 28 Mardo Drive | G98: Witchcliffe | H98: WA | I98: 6286 | J98: 28 | K98: =Table_Household_Alloc[[#This Row],[Unit Entitlement]]/1000 -> 0.028 | L98: =J98/1000*232 -> 6.496 | M98: =CONCATENATE("Symo ",Table_Household_Alloc[[#This Row],[Export Capacity (kW)]]) -> Symo 5 | N98: =IF(Table_Household_Alloc[[#This Row],[PV Installed]]="Y",1,0)*Table_Household_Alloc[[#This Row],[Calculated Battery Allocation (kWh)]] -> 6.496 | O98: 5 | P98: Y | Q98: Y | R98: Y | S98: O | T98: 0410 216 361 | U98: 08 9192 7127 | V98: nadreb@hotmail.com | X98: 45536 | Y98: Current
A99: 19 | B99: 2A | C99: 50002936 | E99: T W Oliver | F99: 30 Mardo Drive | G99: Witchcliffe | H99: WA | I99: 6286 | J99: 30 | K99: =Table_Household_Alloc[[#This Row],[Unit Entitlement]]/1000 -> 0.03 | L99: =J99/1000*232 -> 6.96 | M99: =CONCATENATE("Symo ",Table_Household_Alloc[[#This Row],[Export Capacity (kW)]]) -> Symo 5 | N99: =IF(Table_Household_Alloc[[#This Row],[PV Installed]]="Y",1,0)*Table_Household_Alloc[[#This Row],[Calculated Battery Allocation (kWh)]] -> 6.96 | O99: 5 | P99: Y | Q99: Y | R99: Y | S99: O | T99: 0424 205 755 | V99: timoliver33@gmail.com | X99: 45505 | Y99: Current
A100: 20 | B100: 2A | E100: Zac Webb | F100: 32 Mardo Drive | G100: Witchcliffe | H100: WA | I100: 6286 | J100: 59 | K100: =Table_Household_Alloc[[#This Row],[Unit Entitlement]]/1000 -> 0.059 | L100: =J100/1000*232 -> 13.688 | N100: =IF(Table_Household_Alloc[[#This Row],[PV Installed]]="Y",1,0)*Table_Household_Alloc[[#This Row],[Calculated Battery Allocation (kWh)]] -> 0 | S100: V | T100: 0497 685 142 | V100: waalitj_wongi@outlook.com
...

Sheet Amanda Energy
A1: Cluster | B1: Year | C1: Month | D1: Consumption_kWh | E1: Export_kWh | F1: Amanda_consumption_incl_GST | G1: Amanda_export_buyback_incl_GST | H1: Daily_Supply_incl_GST | I1: Other_Fees_incl_GST | J1: Total_incl_GST
A2: 1A | B2: 2025 | C2: 1 | D2: 33.93 | E2: 11281.06 | F2: 10.16 | G2: -434.32 | H2: 170.5 | I2: 15.54 | J2: -238.12
A3: 1A | B3: 2025 | C3: 2 | D3: 9.73 | E3: 10654.83 | F3: 2.92 | G3: -410.21 | H3: 154 | I3: 12.85 | J3: -240.45
A4: 1B | B4: 2025 | C4: 1 | D4: 12.07 | E4: 17535.52 | F4: 3.62 | G4: -675.11 | H4: 170.5 | I4: 18.04 | J4: -482.96
A5: 1B | B5: 2025 | C5: 2 | D5: 13.33 | E5: 13942.64 | F5: 3.99 | G5: -536.79 | H5: 154 | I5: 16.57 | J5: -362.23
A6: 1C | B6: 2025 | C6: 1 | D6: 44.48 | E6: 13074.94 | F6: 13.32 | G6: -503.38 | H6: 170.5 | I6: 22.22 | J6: -297.34
A7: 1C | B7: 2025 | C7: 2 | D7: 46.06 | E7: 12380.74 | F7: 13.78 | G7: -476.66 | H7: 154 | I7: 19.29 | J7: -289.59
A8: 2A | B8: 2025 | C8: 1 | D8: 68.36 | E8: 9864.97 | F8: 21.46 | G8: -379.8 | H8: 178.78 | I8: 0 | J8: -179.55
A9: 2A | B9: 2025 | C9: 2 | D9: 60.15 | E9: 9289.63 | F9: 18.89 | G9: -357.64 | H9: 161.48 | I9: 0 | J9: -177.28
A10: 2B | B10: 2025 | C10: 1 | D10: 25.59 | E10: 13715.2 | F10: 8.04 | G10: -528.04 | H10: 178.78 | I10: 0 | J10: -341.22
A11: 2B | B11: 2025 | C11: 2 | D11: 20.76 | E11: 10080.49 | F11: 6.52 | G11: -388.1 | H11: 161.48 | I11: 0 | J11: -220.1
A12: 3A | B12: 2025 | C12: 1 | D12: 397.4 | E12: 5237.2 | F12: 124.77 | G12: -201.63 | H12: 178.78 | I12: 0 | J12: 101.93
A13: 3A | B13: 2025 | C13: 2 | D13: 1319.47 | E13: 7643.82 | F13: 414.27 | G13: -294.28 | H13: 161.48 | I13: 0 | J13: 281.47
... A17: 3C | B17: 2025 | C17: 2 | D17: 235.52 | E17: 4016 | F17: 73.95 | G17: -154.62 | H17: 161.48 | I17: 0 | J17: 80.82

Sheet reading-import
A1: Lot | B1: cluster | C1: Meter# | D1: 1/2/2024 | E1: 1/5/2024 | F1: 1/8/2024 | G1: 1/10/2024 | H1: 9/10/2024 | I1: 1/1/2025 | J1: 1/3/2025
A2: 1 | B2: 1A | C2: 50002845 | D2: 0 | E2: 0 | F2: 0 | H2: 0 | I2: 5 | J2: 12
A3: 2 | B3: 1A | C3: 50002862 | D3: 154 | E3: 193 | F3: 200 | H3: 217 | I3: 252 | J3: 302
A4: 3 | B4: 1A | C4: 50002872 | D4: 3330 | E4: 4152 | F4: 5885 | G4: 7147 | I4: 8271 | J4: 8830
A5: 4 | B5: 1A | C5: 50002869 | D5: 1658.51 | E5: 2242 | F5: 3297.66 | G5: 4012 | I5: 4542 | J5: 4855
A6: 5 | B6: 1A | C6: 50002879 | D6: 2500 | E6: 2698 | F6: 3033.57 | G6: 3287 | I6: 3545 | J6: 3673
A7: 6 | B7: 1A | C7: 50002865 | D7: 4614 | E7: 5036 | F7: 6545.69 | G7: 7860 | I7: 8639 | J7: 8918
A8: 7 | B8: 1A | C8: 50002887 | D8: 5556 | E8: 6178 | F8: 7086 | H8: 7678 | I8: 8272 | J8: 8725
A9: 8 | B9: 1A | C9: 50002846 | D9: 17 | E9: 62 | F9: 1347 | G9: 2312 | I9: 3006 | J9: 3404
A10: 9 | B10: 1A | C10: 50002885 | D10: 9455 | E10: 10505 | F10: 11763 | H10: 12689 | I10: 13606 | J10: 14226
A11: 10 | B11: 1A | C11: 50002850 | D11: 2297 | E11: 2548 | F11: 3196.09 | G11: 3549 | I11: 3930 | J11: 4324
A12: 11 | B12: 1A | C12: 50002848 | D12: 1025 | E12: 1059 | F12: 1104.64 | G12: 1138 | I12: 1173 | J12: 1194
A13: 12 | B13: 1A | C13: 50002847 | D13: 0 | E13: 0 | F13: 0 | H13: 0 | I13: 34 | J13: 42
A14: 13 | B14: 1A | C14: 50002739 | D14: 3754 | E14: 4117 | F14: 4598.5 | G14: 4840 | I14: 5168 | J14: 5392
A15: 14 | B15: 1A | C15: 50002709 | D15: 0 | E15: 2 | F15: 26 | H15: 95 | I15: 213 | J15: 501
A16: 15 | B16: 1A | C16: 50002714 | D16: 426 | E16: 570 | F16: 570 | H16: 571 | I16: 571 | J16: 571
A17: 16 | B17: 1A | C17: 50002855 | D17: 455 | E17: 907 | F17: 1537.61 | G17: 2060 | I17: 2536 | J17: 2846
A18: 17 | B18: 1A | C18: 50002877 | D18: 11075 | E18: 12991 | F18: 16647.34 | G18: 18767 | I18: 20977 | J18: 22060
A19: 18 | B19: 1A | D19: 0 | E19: 0 | F19: 0 | H19: 0 | I19: 0 | J19: 0
A20: 19 | B20: 1A | C20: 50002864 | D20: 2270 | E20: 2483 | F20: 2819.8 | G20: 3000 | I20: 3203 | J20: 3327
A21: 20 | B21: 1A | C21: 50002710 | D21: 2601 | E21: 2781 | F21: 3120.21 | G21: 3389 | I21: 3644 | J21: 3772
A22: 21 | B22: 1A | C22: 50002719 | D22: 1225 | E22: 1316 | F22: 1471.61 | G22: 1590 | I22: 1682 | J22: 1735
A23: 22 | B23: 1A | C23: 50002876 | D23: 4040 | E23: 4239 | F23: 4589.33 | G23: 4843 | I23: 5052 | J23: 5169
A24: 23 | B24: 1A | C24: 50002860 | D24: 2297 | E24: 2429 | F24: 2786.87 | G24: 3041 | I24: 3181 | J24: 3257
A25: 24 | B25: 1A | C25: 50002649 | D25: 0 | E25: 0 | F25: 0 | H25: 18 | I25: 27 | J25: 38
A26: BESS | B26: 1A | C26: 40002686 | D26: 2686.84 | E26: 14090.38 | F26: 32077.16 | G26: 44721 | I26: 59297 | J26: 67826
A27: EV | B27: 1A | C27: 40002693 | D27: 0 | E27: 209.39 | F27: 1646.88 | G27: 2831 | I27: 4535 | J27: 6152
A28: CS | B28: 1A | C28: 50002858 | D28: 2819.46 | E28: 3565.94 | F28: 4127.37 | G28: 4326 | I28: 4913 | J28: 5343
A29: DB1 | B29: 1A | C29: 40002852 | I29: 157 | J29: 166
A30: DB2 | B30: 1A | C30: 40002693 | I30: 232 | J30: 251
A31: 1 | B31: 1B | C31: 50003409 | D31: 4530 | E31: 4701 | F31: 5443.32 | H31: 5990.04 | I31: 6200 | J31: 6302
A32: 2 | B32: 1B | C32: 50003436 | D32: 1679 | E32: 2331 | F32: 3416.3 | H32: 3923.86 | I32: 4133 | J32: 4305
A33: 3 | B33: 1B | C33: 50004064 | D33: 594 | E33: 1137 | F33: 1765.3 | H33: 2232.7 | I33: 2521 | J33: 2701
A34: 4 | B34: 1B | C34: 50003414 | D34: 102 | E34: 114 | F34: 126 | H34: 156 | I34: 188 | J34: 268
A35: 5 | B35: 1B | C35: 50003389 | D35: 10220 | E35: 10700 | F35: 11494.07 | H35: 12012.6 | I35: 12384 | J35: 12657
A36: 6 | B36: 1B | C36: 50002969 | D36: 3937 | E36: 4341 | F36: 5453.28 | H36: 6621.05 | I36: 7108 | J36: 7388
A37: 7 | B37: 1B | C37: 50002951 | D37: 6063 | E37: 6514 | F37: 7105.58 | H37: 8010.78 | I37: 8532 | J37: 8816
A38: 8 | B38: 1B | C38: 50002959 | D38: 2378 | E38: 3049 | F38: 3644.67 | H38: 4022.29 | I38: 4410 | J38: 4764
A39: 9 | B39: 1B | D39: 0 | E39: 0 | F39: 0
A40: 10 | B40: 1B | C40: 50003420 | D40: 4776 | E40: 5124 | F40: 5898.31 | H40: 6484.91 | I40: 6876 | J40: 7104
A41: 11 | B41: 1B | C41: 50003410 | D41: 14777 | E41: 15333 | F41: 17203.61 | H41: 19213.57 | I41: 20006 | J41: 20313
A42: 12 | B42: 1B | C42: 50003418 | D42: 4054 | E42: 4380 | F42: 4732.36 | H42: 5001.61 | I42: 5260 | J42: 5448
A43: 13 | B43: 1B | C43: 50002859 | D43: 7149 | E43: 7632 | F43: 8977 | H43: 10306.98 | I43: 10946 | J43: 11250
A44: 14 | B44: 1B | C44: 50003396 | D44: 183 | E44: 1359 | F44: 3065.4 | H44: 4143.62 | I44: 4820 | J44: 5206
A45: 15 | B45: 1B | C45: 50003401 | D45: 3807 | E45: 4051 | F45: 4461.85 | H45: 4721.91 | I45: 4892 | J45: 5040
A46: 16 | B46: 1B | C46: 50003430 | D46: 5421 | E46: 5869 | F46: 6394.51 | H46: 6882.04 | I46: 7246 | J46: 7493
A47: 17 | B47: 1B | C47: 50003415 | D47: 4584 | E47: 4804 | F47: 5098 | H47: 5177 | I47: 5345 | J47: 5548
A48: 18 | B48: 1B | C48: 50002895 | D48: 2598 | E48: 4059 | F48: 5447 | H48: 6402 | I48: 7710 | J48: 8339
A49: 19 | B49: 1B | C49: 50003432 | D49: 2943 | E49: 3111 | F49: 3336.82 | H49: 3477.55 | I49: 3621 | J49: 3734
A50: 20 | B50: 1B | C50: 50002972 | D50: 7692 | E50: 8257 | F50: 9309.98 | H50: 10030.08 | I50: 10535 | J50: 10841
A51: 21 | B51: 1B | C51: 50002650 | D51: 8532 | E51: 9362 | F51: 10850.49 | H51: 11951.93 | I51: 12589 | J51: 13063
A52: BESS | B52: 1B | C52: 40002670 | D52: 2994.53 | E52: 16774.87 | F52: 36287.57 | H52: 53456 | I52: 65774 | J52: 73412
A53: EV | B53: 1B | C53: 40002667 | D53: 0 | E53: 573.98 | F53: 2192.17 | H53: 2917.32 | I53: 4038 | J53: 4645
A54: CS | B54: 1B | C54: 50003399 | D54: 2962.64 | E54: 4507 | F54: 5116.63 | H54: 5851.25 | I54: 7136 | J54: 8127
A55: DB1 | B55: 1B | I55: 129 | J55: 129
A56: DB2 | B56: 1B | I56: 204 | J56: 204
A57: 1 | B57: 1C | C57: 50003397 | D57: 6177 | E57: 6575 | F57: 7272.25 | H57: 7838.17 | I57: 8252 | J57: 8549
A58: 2 | B58: 1C | C58: 50003402 | D58: 2694 | E58: 2919 | F58: 3307.24 | H58: 3594.1 | I58: 3795 | J58: 3940
A59: 3 | B59: 1C | C59: 50003431 | D59: 1847 | E59: 2157 | F59: 2635.52 | H59: 2961.07 | I59: 3227 | J59: 3414
A60: 4 | B60: 1C | C60: 50003394 | D60: 1137 | E60: 1399 | F60: 1985.58 | H60: 2578.83 | I60: 2811 | J60: 2944
A61: 5 | B61: 1C | C61: 50003433 | D61: 3232 | E61: 4074 | F61: 4889.35 | H61: 5089.98 | I61: 6084 | J61: 6727
A62: 6 | B62: 1C | C62: 50003421 | D62: 3268 | E62: 3601 | F62: 4367.83 | H62: 5046.41 | I62: 5469 | J62: 5726
A63: 7 | B63: 1C | C63: 50002953 | D63: 119 | E63: 134 | F63: 144 | H63: 160 | I63: 164 | J63: 164
A64: 8 | B64: 1C | C64: 50003395 | D64: 9469 | E64: 9976 | F64: 10886 | H64: 11948.49 | I64: 12726 | J64: 13095
A65: 9 | B65: 1C | C65: 50003435 | D65: 0 | F65: 0 | H65: 5 | I65: 76 | J65: 135
A66: 10 | B66: 1C | C66: 50002952 | D66: 5326 | E66: 5685 | F66: 6174.26 | H66: 6481.42 | I66: 6735 | J66: 6900
A67: 11 | B67: 1C | C67: 50002944 | D67: 0 | E67: 0 | F67: 7 | H67: 24 | I67: 36 | J67: 149
A68: 12 | B68: 1C | C68: 3308026898 | D68: 5 | E68: 145 | F68: 644 | H68: 1411.81 | I68: 1704.76 | J68: 1835.49
A69: 13 | B69: 1C | C69: 50003424 | D69: 4602 | E69: 4723 | F69: 5053.76 | H69: 5542.59 | I69: 6030 | J69: 6168
A70: 14 | B70: 1C | C70: 50003438 | D70: 10279 | E70: 10681 | F70: 11670.13 | H70: 12371.82 | I70: 12736 | J70: 13010
A71: 15 | B71: 1C | C71: 50003404 | D71: 4850 | E71: 5295 | F71: 5967.28 | H71: 6566.27 | I71: 7111 | J71: 7404
A72: 16 | B72: 1C | C72: 50003419 | D72: 4762 | E72: 5338 | F72: 6243.76 | H72: 6963.45 | I72: 7360 | J72: 7627
A73: 17 | B73: 1C | C73: 50003428 | D73: 6 | E73: 14 | F73: 48 | H73: 195 | I73: 227 | J73: 279
A74: 18 | B74: 1C | C74: 50002935 | D74: 0 | F74: 881.37 | H74: 2710.92 | I74: 4379 | J74: 5697
A75: 19 | B75: 1C | C75: 50003417 | D75: 6873 | E75: 7464 | F75: 8646.84 | H75: 9744.86 | I75: 10411 | J75: 10756
A76: BESS | B76: 1C | C76: 40002722 | D76: 1886.05 | E76: 11537.28 | F76: 24413.85 | H76: 36340.52 | I76: 42252 | J76: 47738
A77: EV | B77: 1C | C77: 40002728 | D77: 0 | E77: 0 | F77: 0 | H77: 0 | I77: 7349 | J77: 9137
A78: CS | B78: 1C | C78: 50003429 | D78: 1885.1 | E78: 2434.68 | F78: 2817.94 | H78: 3213.91 | I78: 3640 | J78: 4070
A79: DB1 | B79: 1C | C79: 50003406 | I79: 149 | J79: 162
A80: DB2 | B80: 1C | C80: 50003408 | I80: 128 | J80: 143
A81: 1 | B81: 2A | C81: 50002920 | E81: 0 | G81: 7 | I81: 17
A82: 2 | B82: 2A | C82: 50002903 | E82: 3112 | G82: 3903 | I82: 4264 | J82: 4504
A83: 3 | B83: 2A | E83: 0 | G83: 0
A84: 4 | B84: 2A | E84: 0 | G84: 0
A85: 5 | B85: 2A | C85: 50002911 | E85: 3539 | G85: 6860 | I85: 7368 | J85: 7592
A86: 6 | B86: 2A | E86: 0 | G86: 0
A87: 7 | B87: 2A | E87: 0 | G87: 0
A88: 8 | B88: 2A | E88: 0 | G88: 0
A89: 9 | B89: 2A | C89: 50002909 | E89: 11631 | G89: 16215 | I89: 18671 | J89: 20407
A90: 10 | B90: 2A | E90: 0 | G90: 0
A91: 11 | B91: 2A | E91: 0 | G91: 0
A92: 12 | B92: 2A | C92: 50002897 | E92: 5181 | G92: 6991 | I92: 7897 | J92: 8462
A93: 13 | B93: 2A | C93: 50002839 | E93: 1740 | G93: 3194 | I93: 3610 | J93: 3840
A94: 14 | B94: 2A | C94: 50002863 | E94: 1157 | G94: 2480 | I94: 2707 | J94: 2843
A95: 15 | B95: 2A | C95: 50002947 | E95: 131 | G95: 1108 | I95: 1489 | J95: 1726
A96: 16 | B96: 2A | E96: 0 | G96: 0
A97: 17 | B97: 2A | C97: 50002902 | E97: 1331 | G97: 2233 | I97: 2464 | J97: 2630
A98: 18 | B98: 2A | C98: 50002950 | E98: 1201 | G98: 2088 | I98: 2302 | J98: 2449
A99: 19 | B99: 2A | C99: 50002936 | E99: 1265 | G99: 3040 | I99: 3568 | J99: 3832
A100: 20 | B100: 2A | E100: 0 | G100: 0
...

Sheet reading-export
A1: Lot | B1: cluster | C1: Meter# | D1: 1/2/2024 | E1: 1/5/2024 | F1: 1/8/2024 | G1: 1/10/2024 | H1: 9/10/2024 | I1: 1/1/2025 | J1: 1/3/2025
A2: 1 | B2: 1A | C2: 50002845 | D2: 0 | E2: 0 | J2: 0
A3: 2 | B3: 1A | C3: 50002862 | D3: 0 | E3: 0 | J3: 0
A4: 3 | B4: 1A | C4: 50002872 | D4: 0 | E4: 0 | G4: 0 | I4: 0 | J4: 0
A5: 4 | B5: 1A | C5: 50002869 | D5: 1100 | E5: 3828 | F5: 5318.8 | G5: 6465 | I5: 9031 | J5: 10612
A6: 5 | B6: 1A | C6: 50002879 | D6: 4250 | E6: 7203 | F6: 8765.43 | G6: 10052 | I6: 12884 | J6: 14647
A7: 6 | B7: 1A | C7: 50002865 | D7: 5911 | E7: 10438 | F7: 12556.76 | G7: 14094 | I7: 18121 | J7: 20965
A8: 7 | B8: 1A | C8: 50002887 | D8: 0 | E8: 0 | J8: 0
A9: 8 | B9: 1A | C9: 50002846 | D9: 0 | E9: 0 | G9: 0 | I9: 2569 | J9: 4165
A10: 9 | B10: 1A | C10: 50002885 | D10: 0 | E10: 0 | J10: 0
A11: 10 | B11: 1A | D11: 12347 | E11: 15095 | F11: 16643.58 | G11: 17815 | I11: 20316 | J11: 21130
A12: 11 | B12: 1A | C12: 50002848 | D12: 13447 | E12: 16509 | F12: 18262.11 | G12: 19650 | I12: 22593 | J12: 24391
A13: 12 | B13: 1A | C13: 50002847 | D13: 0 | E13: 0 | J13: 0
A14: 13 | B14: 1A | C14: 50002739 | D14: 25717 | E14: 30627 | F14: 33475.85 | G14: 36023 | I14: 41072 | J14: 44319
A15: 14 | B15: 1A | C15: 50002709 | D15: 0 | E15: 0 | J15: 2399
A16: 15 | B16: 1A | C16: 50002714 | D16: 0 | E16: 0 | J16: 0
A17: 16 | B17: 1A | C17: 50002855 | D17: 0 | E17: 2568 | F17: 4134.29 | G17: 5245 | I17: 7804 | J17: 9378
A18: 17 | B18: 1A | C18: 50002877 | D18: 4293 | E18: 7088 | F18: 8027 | G18: 9059 | I18: 12029 | J18: 14003
A19: 18 | B19: 1A | D19: 0 | E19: 0 | J19: 0
A20: 19 | B20: 1A | C20: 50002864 | D20: 26703 | E20: 32368 | F20: 35423.8 | G20: 38020 | I20: 43757 | J20: 47349
A21: 20 | B21: 1A | C21: 50002710 | D21: 3903 | E21: 6356 | F21: 7464.47 | G21: 8589 | I21: 11511 | J21: 13341
A22: 21 | B22: 1A | C22: 50002719 | D22: 4515 | E22: 7478 | F22: 9166.34 | G22: 10489 | I22: 13350 | J22: 15149
A23: 22 | B23: 1A | C23: 50002876 | D23: 4040 | E23: 6783 | F23: 8314.63 | G23: 9617 | I23: 12269 | J23: 13938
A24: 23 | B24: 1A | C24: 50002860 | D24: 5498 | E24: 8307 | F24: 9976.39 | G24: 11307 | I24: 14010 | J24: 15720
A25: 24 | B25: 1A | C25: 50002649 | D25: 0 | E25: 0 | J25: 0
A26: BESS | B26: 1A | C26: 40002686 | D26: 1833.14 | E26: 11017.34 | F26: 26071.13 | G26: 36413 | I26: 48306 | J26: 55361
A27: EV | B27: 1A | C27: 40002693 | D27: 0 | E27: 0 | F27: 0
A28: CS | B28: 1A | C28: 50002858 | D28: 0 | E28: 0 | F28: 0 | G28: 0 | I28: 0 | J28: 0
A29: DB1 | B29: 1A | C29: 40002852
A30: DB2 | B30: 1A | C30: 40002693
A31: 1 | B31: 1B | C31: 50003409 | D31: 3498 | E31: 5938 | F31: 7210.69 | H31: 8291.68 | I31: 10303 | J31: 11728
A32: 2 | B32: 1B | C32: 50003436 | D32: 265 | E32: 4070 | F32: 5442.96 | H32: 7233.44 | I32: 11104 | J32: 13586
A33: 3 | B33: 1B | C33: 50004064 | D33: 0 | E33: 0 | F33: 684.6 | H33: 1696.37 | I33: 3777 | J33: 5275
A34: 4 | B34: 1B | C34: 50003414 | D34: 0 | E34: 0 | F34: 458 | H34: 1460.91 | I34: 4228 | J34: 5871
A35: 5 | B35: 1B | C35: 50003389 | D35: 5814 | E35: 9155 | F35: 10239.42 | H35: 11614.69 | I35: 15198 | J35: 17553
A36: 6 | B36: 1B | C36: 50002969 | D36: 854 | E36: 4535 | F36: 5754.6 | H36: 7410.18 | I36: 11083 | J36: 13497
A37: 7 | B37: 1B | C37: 50002951 | D37: 3559 | E37: 5963 | F37: 7249.59 | H37: 8203.86 | I37: 10036 | J37: 11379
A38: 8 | B38: 1B | C38: 50002959 | D38: 17 | E38: 2480 | F38: 3838.25 | H38: 5415.75 | I38: 8407 | J38: 10346
A39: 9 | B39: 1B | D39: 0 | E39: 0 | F39: 0
A40: 10 | B40: 1B | C40: 50003420 | D40: 12138 | E40: 14501 | F40: 15561 | H40: 16512.4 | I40: 18452 | J40: 19803
A41: 11 | B41: 1B | C41: 50003410 | D41: 3886 | E41: 7001 | F41: 8634.89 | H41: 9978.43 | I41: 12683 | J41: 14556
A42: 12 | B42: 1B | C42: 50003418 | D42: 7374 | E42: 12649 | F42: 15529.02 | H42: 18068.36 | I42: 22544 | J42: 25441
A43: 13 | B43: 1B | C43: 50002859 | D43: 7339 | E43: 12702 | F43: 15409 | H43: 17371.93 | I43: 21569 | J43: 24315
A44: 14 | B44: 1B | C44: 50003396 | D44: 0 | E44: 2 | F44: 1827.01 | H44: 4120.68 | I44: 8268 | J44: 10948
A45: 15 | B45: 1B | C45: 50003401 | D45: 3840 | E45: 6062 | F45: 6901.57 | H45: 7887.39 | I45: 10135 | J45: 11621
A46: 16 | B46: 1B | C46: 50003430 | D46: 3504 | E46: 6007 | F46: 7399.42 | H46: 8490.27 | I46: 10472 | J46: 11911
A47: 17 | B47: 1B | C47: 50003415 | D47: 10794 | E47: 12766 | F47: 13535 | H47: 14606 | I47: 16887 | J47: 18209
A48: 18 | B48: 1B | C48: 50002895 | D48: 0 | E48: 0 | F48: 0 | H48: 0 | J48: 702
A49: 19 | B49: 1B | C49: 50003432 | D49: 3403 | E49: 5961 | F49: 7410.45 | H49: 8570.52 | I49: 10481 | J49: 11806
A50: 20 | B50: 1B | C50: 50002972 | D50: 24099 | E50: 29256 | F50: 31484.53 | H50: 33564.89 | I50: 37964 | J50: 40923
A51: 21 | B51: 1B | C51: 50002650 | D51: 24156 | E51: 28297 | F51: 29924.37 | H51: 31896.88 | I51: 36318 | J51: 39181
A52: BESS | B52: 1B | C52: 40002670 | D52: 2093.81 | E52: 13451.22 | F52: 29901.46 | H52: 44114.54 | I52: 53961 | J52: 60162
A53: EV | B53: 1B | C53: 40002667 | D53: 0 | E53: 0 | F53: 0 | H53: 0 | I53: 0 | J53: 0
A54: CS | B54: 1B | C54: 50003399 | D54: 0 | E54: 0 | F54: 0 | H54: 0 | I54: 0 | J54: 0
A55: DB1 | B55: 1B
A56: DB2 | B56: 1B
A57: 1 | B57: 1C | C57: 50003397 | D57: 22466 | E57: 26592 | F57: 28434.59 | H57: 30242.14 | I57: 33585 | J57: 36147
A58: 2 | B58: 1C | C58: 50003402 | D58: 7976 | E58: 10495 | F58: 11875.44 | H58: 13112.99 | I58: 15113 | J58: 16602
A59: 3 | B59: 1C | C59: 50003431 | D59: 8104 | E59: 11934 | F59: 13449.26 | H59: 15190.17 | I59: 18755 | J59: 21422
A60: 4 | B60: 1C | C60: 50003394 | D60: 5365 | E60: 7545 | F60: 8389.8 | H60: 9245.87 | I60: 11256 | J60: 12825
A61: 5 | B61: 1C | C61: 50003433 | D61: 23221 | E61: 26772 | F61: 28547.9 | H61: 29022.8 | I61: 34752 | J61: 37400
A62: 6 | B62: 1C | C62: 50003421 | D62: 1616 | E62: 6999 | F62: 9599.41 | H62: 11712.14 | I62: 15827 | J62: 18997
A63: 7 | B63: 1C | C63: 50002953 | D63: 141 | E63: 141 | F63: 141 | H63: 141 | I63: 142 | J63: 142
A64: 8 | B64: 1C | C64: 50003395 | D64: 27333 | E64: 32684 | F64: 35790 | H64: 38188.55 | I64: 41841 | J64: 44296
A65: 9 | B65: 1C | C65: 50003435 | D65: 0
A66: 10 | B66: 1C | C66: 50002952 | D66: 3264 | E66: 5676 | F66: 7004.47 | H66: 8189.7 | I66: 10088 | J66: 11546
A67: 11 | B67: 1C | C67: 50002944 | D67: 0
A68: 12 | B68: 1C | C68: 3308026898 | D68: 0 | E68: 0 | F68: 187.42 | H68: 1255.9 | I68: 3279.89 | J68: 4812.19
A69: 13 | B69: 1C | C69: 50003424 | D69: 3791 | E69: 6015 | F69: 7169 | H69: 7899.89 | I69: 9864 | J69: 11307
A70: 14 | B70: 1C | C70: 50003438 | D70: 5315 | E70: 5695 | F70: 6442.82 | H70: 7320.62 | I70: 9306 | J70: 10855
A71: 15 | B71: 1C | C71: 50003404 | D71: 5083 | E71: 9362 | F71: 11609.07 | H71: 13649.03 | I71: 16919 | J71: 19466
A72: 16 | B72: 1C | C72: 50003419 | D72: 7655 | E72: 13525 | F72: 16903.4 | H72: 19713.42 | I72: 24215 | J72: 27788
A73: 17 | B73: 1C | C73: 50003428 | D73: 0
A74: 18 | B74: 1C | C74: 50002935 | D74: 0 | F74: 1 | H74: 705.36 | I74: 4017 | J74: 5995
A75: 19 | B75: 1C | C75: 50003417 | D75: 10388 | E75: 15762 | F75: 18813.23 | H75: 21239.96 | I75: 25220 | J75: 28182
A76: BESS | B76: 1C | C76: 40002722 | D76: 1185.25 | E76: 8547.62 | F76: 19040.97 | H76: 29007.26 | I76: 33894 | J76: 38471
A77: EV | B77: 1C | C77: 40002728 | D77: 0 | E77: 0 | F77: 0 | H77: 0
A78: CS | B78: 1C | C78: 50003429 | D78: 0 | E78: 0 | F78: 0 | H78: 0 | I78: 0 | J78: 0
A79: DB1 | B79: 1C | C79: 50003406
A80: DB2 | B80: 1C | C80: 50003408
A81: 1 | B81: 2A | E81: 0 | G81: 0
A82: 2 | B82: 2A | C82: 50002903 | E82: 9441 | G82: 14105 | I82: 18618 | J82: 21526
A83: 3 | B83: 2A | E83: 0 | G83: 0
A84: 4 | B84: 2A | E84: 0 | G84: 0
A85: 5 | B85: 2A | C85: 50002911 | E85: 2 | G85: 3604 | I85: 7727 | J85: 10460
A86: 6 | B86: 2A | E86: 0 | G86: 0
A87: 7 | B87: 2A | E87: 0 | G87: 0
A88: 8 | B88: 2A | E88: 0 | G88: 0
A89: 9 | B89: 2A | E89: 2249 | G89: 4489 | I89: 6566 | J89: 7871
A90: 10 | B90: 2A | E90: 0 | G90: 0
A91: 11 | B91: 2A | E91: 0 | G91: 0
A92: 12 | B92: 2A | C92: 50002897 | E92: 3431 | G92: 8948 | I92: 14259 | J92: 17674
A93: 13 | B93: 2A | C93: 50002839 | E93: 7 | G93: 602 | I93: 4288 | J93: 6624
A94: 14 | B94: 2A | C94: 50002863 | E94: 0 | G94: 1026 | I94: 3860 | J94: 5667
A95: 15 | B95: 2A | C95: 50002947 | E95: 377 | G95: 2687 | I95: 5304 | J95: 7046
A96: 16 | B96: 2A | E96: 0 | G96: 0
A97: 17 | B97: 2A | C97: 50002902 | E97: 0 | G97: 469 | I97: 3363 | J97: 5183
A98: 18 | B98: 2A | C98: 50002950 | E98: 0 | G98: 455 | I98: 1434 | J98: 2524
A99: 19 | B99: 2A | C99: 50002936 | E99: 0 | G99: 784 | I99: 3488 | J99: 5300
A100: 20 | B100: 2A | E100: 0 | G100: 0
...

Sheet Tariff Rates
B1: P2P Charge Rate (Inc. GST) | C1: P2P Export Rate (Inc. GST) | D1: Common Charge Rate (Inc. GST) | E1: Grid Import Rate (Inc. GST) | F1: Grid Export Rate (Inc. GST) | G1: EV Charger Sale to consumer Rate (Inc. GST) | H1: Chargefox Commission take on EV Consumption % (Inc. GST) | I1: Chargefox Commission (Inc GST) | J1: P2P Energy Invasion Charge (Inc. GST) | K1: P2P Energy Borrow Revenue (Inc. GST) | L1: P2P rate for lots with no export (Inc. GST)
A2: c/kWh | B2: 22 | C2: -22 | D2: 22 | E2: 30 | F2: =-3.5*1.1 -> -3.85 | G2: -65 | H2: -0.05 | I2: =-G2*H2 -> -3.25 | J2: 2 | K2: -2 | L2: 36
A3: $/kWh | B3: =B2/100 -> 0.22 | C3: =C2/100 -> -0.22 | D3: =D2/100 -> 0.22 | E3: 0.3 | F3: =F2/100 -> -0.0385 | G3: =G2/100 -> -0.65 | H3: -0.05 | I3: =I2/100 -> -0.0325 | J3: =J2/100 -> 0.02 | K3: =K2/100 -> -0.02 | L3: =L2/100 -> 0.36
B6: SwitchdIn Cost ($ inc. GST) | C6: Chargefox Daily Supply Charge/cluster | D6: Element47 Embedded Network Daily Supply Charges
A7: $/yr | B7: 55 | C7: 858 | D7: 80.3
A8: $/day | B8: =B7/365 -> 0.15068493 | C8: =C7/365 -> 2.3506849 | D8: =D7/365 -> 0.22
B10: Element47 Invoicing Fee
A11: $/Invoice | B11: 1.1

Sheet Energy billing Mastersheet
B1: 1A | C1: billing period | F1: =DATE(2025,F2,1) -> 45658 | H1: =DATE(2025,H2+1,0) -> 45747
F2: 1 | G2: 2 | H2: 3
C3: Number of Days | F3: =DAY(DATE(2024,F2+1,0)) -> 31 | G3: =DAY(DATE(2024,G2+1,0)) -> 29 | H3: =DAY(DATE(2024,H2+1,0)) -> 31 | I3: =N3 -> 90 | J3: =N3 -> 90 | K3: =N3 -> 90 | L3: =N3 -> 90 | M3: 1 | N3: =H1-F1+1 -> 90 | P3: Import data | R3: Consumption Energy | AE3: Battery Loss and common services | AQ3: Export data | BK3: EV Charger Reconcillation | BQ3: Combined
A4: Lot | B4: Name | C4: Meter Numbers | D4: Percentage of Unit Entitlement (%) | E4: Stage of Dev. | F4: Amanda Energy Daily Supply Charge ($) | G4: Amanda Energy Daily Supply Charge ($)2 | H4: Amanda Energy Daily Supply Charge ($)3 | I4: Amanda Energy Other fees ($) | J4: SwitchdIn Cost Daily Supply Charge ($) | K4: Chargefox Daily Supply Charge ($) | L4: Element47 Embedded Network Daily Supply Charges | M4: Element47 Embedded Network Invoicing Fees | N4: Total supply | O4: 1st day of reporting period: import | P4: Last day of reporting period: import | Q4: Total Consumption Import (kWh) | R4: Total Daily Average Consumptio for Billing Period (kWh) | S4: Percentage of Total Import for Billing Period (%) | T4: Daily Battery allowance based on UE% (kWh) | U4: Applicable Battery Allowance Daily Consumption (kWh) | V4: Unused Daily Allowance (kWh) | W4: Unused Daily Allowance % | X4: P2P Import Consumption within Battery Allowance(kWh) | Y4: Energy Exceeding Battery Allowance (kWh) | Z4: Energy Exceeding Battery Allowance % | AA4: Total Cluster Energy Balance for P2P Trading (kWh) | AB4: P2P Import Consumption over Battery Allowance based on Energy Exceeding Allowance % (kWh) | AC4: Total P2P import (kWh) | AD4: Energy Import from Grid (kWh) | AE4: P2P import% | AF4: Cluster's Total Battery Loss (kWh) | AG4: Axillary Battery Losses based upon P2P import % (kWh) | AH4: Cluster's Total Common Services (kWh) | AI4: Common Services based on Split per Unit Entitlement % to battery (kWh) | AJ4: Axillary Battery Loss Charges at P2P Rates based upon P2P import % ($) | AK4: Common Services Cost Split per Unit Entitlement at P2P rate ($) | AL4: P2P Import Cost ($) | AM4: Exceeding Battery Allowance P2P Fee ($) | AN4: Import From Grid Cost ($) | AO4: Total Consumption Cost/Lot | AP4: 1st day of reporting period: export | AQ4: Last day of reporting period: export | AR4: Total Lot Export (kWh) | AS4: Percentage of Total export for Billing Period (%) | AT4: Total Energy Export P2P to battery (kWh) | AU4: Total Cluster Energy Balance for P2P Trading (kWh)2 | AV4: Borrowed Allowance Based on Unused Daily Allowance % (kWh) | AW4: Axillary Battery Losses based upon Adjusted % total export (kWh) | AX4: Common Service based upon % total export to battery (kWh) | AY4: EV Charger based upon % total export to battery (kWh) | AZ4: Therotical Energy Export to Grid (kWh) | BA4: Energy Losses When Export to Grid (kWh) | BB4: Energy Losses When Export to Grid based up % total export (kWh) | BC4: Energy Export to Grid after Losses (kWh) | BD4: Axillary Battery Losses based upon % total export ($) | BE4: Common Service Earning based upon % total export to Load ($) | BF4: EV Charger based upon % total export ($) | BG4: P2P Export Earnings ($) | BH4: Passive Compensation ($) | BI4: Grid Export Earnings ($) | BJ4: Total Export Earnings Per Lot After P2P Battery Energy Storage and Use ($) | BK4: EV Charger Income from Sales Equitable Distribution on UE ($) | BL4: Chargefox Commission on EV Charge Consumption Sales Cost Split by Unit Entitlement ($) | BM4: EV Charger Cost of Electricity Supply at P2P Rates ($) | BN4: Total EV Charger Operating Cost ($) | BO4: Total EV Charger Revenue ($) | BP4: EV Charger Profit per lot owner ($) | BQ4: Energy Invoice Total Charges or Revenue $ | BR4: Date issued | BS4: Date Paid | BT4: Lot
A5: 1 | B5: {=INDEX(Table_Household_Alloc[Owner],MATCH(1,(Table_Household_Alloc[Lot]=A5)*(Table_Household_Alloc[cluster]=$B$1),0))} -> Mead Family trust | C5: {=INDEX(Reading_import[Meter'#],MATCH(1,(Table_Household_Alloc[Lot]=A5)*(Table_Household_Alloc[cluster]=$B$1),0))} -> 50002845 | D5: {=INDEX(Table_Household_Alloc[UE % over Cluster],MATCH(1,(Table_Household_Alloc[Lot]=A5)*(Table_Household_Alloc[cluster]=$B$1),0))} -> 0.036 | E5: {=INDEX(Table_Household_Alloc[Stage of Dev.],MATCH(1,(Table_Household_Alloc[Lot]=A5)*(Table_Household_Alloc[cluster]=$B$1),0))} -> UC | F5: {=INDEX(Amanda_energy[Daily_Supply_incl_GST],MATCH(1,(Amanda_energy[Cluster]=$B$1)*(Amanda_energy[Month]=$F$2),0))/MAX($A:$A)} -> 8.1190476 | G5: {=INDEX(Amanda_energy[Daily_Supply_incl_GST],MATCH(1,(Amanda_energy[Cluster]=$B$1)*(Amanda_energy[Month]=$G$2),0))/MAX($A:$A)} -> 7.3333333 | H5: {=INDEX(Amanda_energy[Daily_Supply_incl_GST],MATCH(1,(Amanda_energy[Cluster]=$B$1)*(Amanda_energy[Month]=$H$2),0))/MAX($A:$A)} -> #N/A | I5: =$J$40/MAX($A:$A) -> #N/A | J5: ='Tariff Rates'!$B$8*$J$3 -> 13.561644 | K5: ='Tariff Rates'!$C$8*Table1[[#This Row],[Percentage of Unit Entitlement (%)]]*'Energy billing Mastersheet'!$K$3 -> 7.6162192 | L5: =$L$3*'Tariff Rates'!$D$8*IF(Table1[[#This Row],[Stage of Dev.]]="V",0,1) -> 19.8 | M5: 1.1 | N5: =SUM(F5:M5) -> #N/A | O5: {=INDEX(Reading_import[1/1/2025],MATCH(1,(Reading_import[Lot]=A5)*(Reading_import[cluster]=$B$1),0))} -> 5 | P5: {=INDEX(Reading_import[1/3/2025],MATCH(1,(Reading_import[Lot]=A5)*(Reading_import[cluster]=$B$1),0))} -> 12 | Q5: =Table1[[#This Row],[Last day of reporting period: import]]-Table1[[#This Row],[1st day of reporting period: import]] -> 7 | R5: =Q5/$N$3 -> 0.077777778 | S5: =Q5/$Q$32 -> 0.0012867647 | T5: =IF(Table1[[#This Row],[Stage of Dev.]]="V",0,233*Table1[[#This Row],[Percentage of Unit Entitlement (%)]]) -> 8.388 | U5: =IF(T5>R5,R5,T5) -> 0.077777778 | V5: =Table1[[#This Row],[Daily Battery allowance based on UE% (kWh)]]-Table1[[#This Row],[Applicable Battery Allowance Daily Consumption (kWh)]] -> 8.3102222 | W5: =Table1[[#This Row],[Unused Daily Allowance (kWh)]]/$V$32 -> 0.058895744 | X5: =IF(Table1[[#This Row],[Applicable Battery Allowance Daily Consumption (kWh)]]>Table1[[#This Row],[Total Daily Average Consumptio for Billing Period (kWh)]],Table1[[#This Row],[Total Consumption Import (kWh)]],U5*$N$3) -> 7 | Y5: =IF(Table1[[#This Row],[Applicable Battery Allowance Daily Consumption (kWh)]]>0,ABS(Q5-X5),0) -> 0 | Z5: =IFERROR(Table1[[#This Row],[Energy Exceeding Battery Allowance (kWh)]]/$Y$32,0) -> 0 | AA5: =IF($Y$32-$E$40>0,$Y$32-$E$40,0) -> #N/A | AB5: =IFERROR(Table1[[#This Row],[Total Cluster Energy Balance for P2P Trading (kWh)]]*Table1[[#This Row],[Energy Exceeding Battery Allowance %]],0) -> 0 | AC5: =Table1[[#This Row],[P2P Import Consumption within Battery Allowance(kWh)]]+Table1[[#This Row],[P2P Import Consumption over Battery Allowance based on Energy Exceeding Allowance % (kWh)]] -> 7 | AD5: =Table1[[#This Row],[Total Consumption Import (kWh)]]-Table1[[#This Row],[Total P2P import (kWh)]] -> 0 | AE5: =IFERROR(Table1[[#This Row],[Total P2P import (kWh)]]/$AC$32,0) -> 0.0012867647 | AF5: =($Q$26-$AR$26) -> 1474 | AG5: =AF5*AE5 -> 1.8966912 | AH5: =SUM($Q$28:$Q$30) -> 458 | AI5: =Table1[[#This Row],[Cluster''s Total Common Services (kWh)]]*Table1[[#This Row],[Percentage of Unit Entitlement (%)]] -> 16.488 | AJ5: =AG5*'Tariff Rates'!$B$3 -> 0.41727206 | AK5: =Table1[[#This Row],[Common Services based on Split per Unit Entitlement % to battery (kWh)]]*'Tariff Rates'!$B$3 -> 3.62736 | AL5: =Table1[[#This Row],[Total P2P import (kWh)]]*IF(Table1[[#This Row],[Total Lot Export (kWh)]]=0,'Tariff Rates'!$B$3,'Tariff Rates'!$L$3) -> 1.54 | AM5: =Table1[[#This Row],[P2P Import Consumption over Battery Allowance based on Energy Exceeding Allowance % (kWh)]]*'Tariff Rates'!$J$3 -> 0 | AN5: =Table1[[#This Row],[Energy Import from Grid (kWh)]]*'Tariff Rates'!$E$3 -> 0 | AO5: =SUM(AJ5:AN5) -> 5.5846321 | AP5: {=INDEX(Reading_export[1/1/2025],MATCH(1,(Reading_export[Lot]=A5)*(Reading_export[cluster]=$B$1),0))} -> 0 | AQ5: {=INDEX(Reading_export[1/3/2025],MATCH(1,(Reading_export[Lot]=A5)*(Reading_export[cluster]=$B$1),0))} -> 0 | AR5: =Table1[[#This Row],[Last day of reporting period: export]]-Table1[[#This Row],[1st day of reporting period: export]] -> 0 | AS5: =AR5/$AR$32 -> 0 | AT5: =Table1[[#This Row],[Percentage of Total export for Billing Period (%)]]*$AC$32 -> 0 | AU5: =IF($Y$32-$E$40>0,$Y$32-$E$40,0) -> #N/A | AV5: =IFERROR(Table1[[#This Row],[Total Cluster Energy Balance for P2P Trading (kWh)2]]*Table1[[#This Row],[Unused Daily Allowance %]],0) -> 0 | AW5: =AS5*AF5 -> 0 | AX5: =Table1[[#This Row],[Cluster''s Total Common Services (kWh)]]*Table1[[#This Row],[Percentage of Total export for Billing Period (%)]] -> 0 | AY5: =$Q$27*Table1[[#This Row],[Percentage of Total export for Billing Period (%)]] -> 0 | AZ5: =Table1[[#This Row],[Total Lot Export (kWh)]]-Table1[[#This Row],[Total Energy Export P2P to battery (kWh)]]-Table1[[#This Row],[Axillary Battery Losses based upon Adjusted % total export (kWh)]]-Table1[[#This Row],[Common Service based upon % total export to battery (kWh)]]-Table1[[#This Row],[EV Charger based upon % total export to battery (kWh)]] -> 0 | BA5: =IFERROR(IF($AZ$32-$F$40>0,$AZ$32-$F$40,0),0) -> 0 | BB5: =Table1[[#This Row],[Energy Losses When Export to Grid (kWh)]]*Table1[[#This Row],[Percentage of Total export for Billing Period (%)]] -> 0 | BC5: =Table1[[#This Row],[Therotical Energy Export to Grid (kWh)]]-Table1[[#This Row],[Energy Losses When Export to Grid based up % total export (kWh)]] -> 0 | BD5: =AW5*'Tariff Rates'!$C$3 -> 0 | BE5: =Table1[[#This Row],[Common Service based upon % total export to battery (kWh)]]*'Tariff Rates'!$C$3 -> 0 | BF5: =Table1[[#This Row],[EV Charger based upon % total export to battery (kWh)]]*'Tariff Rates'!$C$3 -> 0 | BG5: =AT5*'Tariff Rates'!$C$3 -> 0 | BH5: =Table1[[#This Row],[Borrowed Allowance Based on Unused Daily Allowance % (kWh)]]*'Tariff Rates'!$K$3 -> 0 | BI5: =BC5*'Tariff Rates'!$F$3 -> 0 | BJ5: =SUM(BD5:BI5) -> 0 | BK5: =$D$45*Table1[[#This Row],[Percentage of Unit Entitlement (%)]] -> 0 | BL5: =BK5*'Tariff Rates'!$H$3 -> 0 | BM5: =($Q$27)*Table1[[#This Row],[Percentage of Unit Entitlement (%)]]*'Tariff Rates'!$B$3 -> 12.80664 | BN5: =SUM(BM5,BL5) -> 12.80664 | BO5: =BK5 -> 0 | BP5: =BO5+BN5 -> 12.80664 | BQ5: =AO5+BJ5+N5+BP5 -> #N/A | BT5: 1
A6: 2 | B6: {=INDEX(Table_Household_Alloc[Owner],MATCH(1,(Table_Household_Alloc[Lot]=A6)*(Table_Household_Alloc[cluster]=$B$1),0))} -> Margareta Roeck | C6: {=INDEX(Reading_import[Meter'#],MATCH(1,(Table_Household_Alloc[Lot]=A6)*(Table_Household_Alloc[cluster]=$B$1),0))} -> 50002862 | D6: {=INDEX(Table_Household_Alloc[UE % over Cluster],MATCH(1,(Table_Household_Alloc[Lot]=A6)*(Table_Household_Alloc[cluster]=$B$1),0))} -> 0.036 | E6: {=INDEX(Table_Household_Alloc[Stage of Dev.],MATCH(1,(Table_Household_Alloc[Lot]=A6)*(Table_Household_Alloc[cluster]=$B$1),0))} -> UC | F6: {=INDEX(Amanda_energy[Daily_Supply_incl_GST],MATCH(1,(Amanda_energy[Cluster]=$B$1)*(Amanda_energy[Month]=$F$2),0))/MAX($A:$A)} -> 8.1190476 | G6: {=INDEX(Amanda_energy[Daily_Supply_incl_GST],MATCH(1,(Amanda_energy[Cluster]=$B$1)*(Amanda_energy[Month]=$G$2),0))/MAX($A:$A)} -> 7.3333333 | H6: {=INDEX(Amanda_energy[Daily_Supply_incl_GST],MATCH(1,(Amanda_energy[Cluster]=$B$1)*(Amanda_energy[Month]=$H$2),0))/MAX($A:$A)} -> #N/A | I6: =$J$40/MAX($A:$A) -> #N/A | J6: ='Tariff Rates'!$B$8*$J$3 -> 13.561644 | K6: ='Tariff Rates'!$C$8*Table1[[#This Row],[Percentage of Unit Entitlement (%)]]*'Energy billing Mastersheet'!$K$3 -> 7.6162192 | L6: =$L$3*'Tariff Rates'!$D$8*IF(Table1[[#This Row],[Stage of Dev.]]="V",0,1) -> 19.8 | M6: 1.1 | N6: =SUM(F6:M6) -> #N/A | O6: {=INDEX(Reading_import[1/1/2025],MATCH(1,(Reading_import[Lot]=A6)*(Reading_import[cluster]=$B$1),0))} -> 252 | P6: {=INDEX(Reading_import[1/3/2025],MATCH(1,(Reading_import[Lot]=A6)*(Reading_import[cluster]=$B$1),0))} -> 302 | Q6: =Table1[[#This Row],[Last day of reporting period: import]]-Table1[[#This Row],[1st day of reporting period: import]] -> 50 | R6: =Q6/$N$3 -> 0.55555556 | S6: =Q6/$Q$32 -> 0.0091911765 | T6: =IF(Table1[[#This Row],[Stage of Dev.]]="V",0,233*Table1[[#This Row],[Percentage of Unit Entitlement (%)]]) -> 8.388 | U6: =IF(T6>R6,R6,T6) -> 0.55555556 | V6: =Table1[[#This Row],[Daily Battery allowance based on UE% (kWh)]]-Table1[[#This Row],[Applicable Battery Allowance Daily Consumption (kWh)]] -> 7.8324444 | W6: =Table1[[#This Row],[Unused Daily Allowance (kWh)]]/$V$32 -> 0.055509664 | X6: =IF(Table1[[#This Row],[Applicable Battery Allowance Daily Consumption (kWh)]]>Table1[[#This Row],[Total Daily Average Consumptio for Billing Period (kWh)]],Table1[[#This Row],[Total Consumption Import (kWh)]],U6*$N$3) -> 50 | Y6: =IF(Table1[[#This Row],[Applicable Battery Allowance Daily Consumption (kWh)]]>0,ABS(Q6-X6),0) -> 0 | Z6: =IFERROR(Table1[[#This Row],[Energy Exceeding Battery Allowance (kWh)]]/$Y$32,0) -> 0 | AA6: =IF($Y$32-$E$40>0,$Y$32-$E$40,0) -> #N/A | AB6: =IFERROR(Table1[[#This Row],[Total Cluster Energy Balance for P2P Trading (kWh)]]*Table1[[#This Row],[Energy Exceeding Battery Allowance %]],0) -> 0 | AC6: =Table1[[#This Row],[P2P Import Consumption within Battery Allowance(kWh)]]+Table1[[#This Row],[P2P Import Consumption over Battery Allowance based on Energy Exceeding Allowance % (kWh)]] -> 50 | AD6: =Table1[[#This Row],[Total Consumption Import (kWh)]]-Table1[[#This Row],[Total P2P import (kWh)]] -> 0 | AE6: =IFERROR(Table1[[#This Row],[Total P2P import (kWh)]]/$AC$32,0) -> 0.0091911765 | AF6: =($Q$26-$AR$26) -> 1474 | AG6: =AF6*AE6 -> 13.547794 | AH6: =SUM($Q$28:$Q$30) -> 458 | AI6: =Table1[[#This Row],[Cluster''s Total Common Services (kWh)]]*Table1[[#This Row],[Percentage of Unit Entitlement (%)]] -> 16.488 | AJ6: =AG6*'Tariff Rates'!$B$3 -> 2.9805147 | AK6: =Table1[[#This Row],[Common Services based on Split per Unit Entitlement % to battery (kWh)]]*'Tariff Rates'!$B$3 -> 3.62736 | AL6: =Table1[[#This Row],[Total P2P import (kWh)]]*IF(Table1[[#This Row],[Total Lot Export (kWh)]]=0,'Tariff Rates'!$B$3,'Tariff Rates'!$L$3) -> 11 | AM6: =Table1[[#This Row],[P2P Import Consumption over Battery Allowance based on Energy Exceeding Allowance % (kWh)]]*'Tariff Rates'!$J$3 -> 0 | AN6: =Table1[[#This Row],[Energy Import from Grid (kWh)]]*'Tariff Rates'!$E$3 -> 0 | AO6: =SUM(AJ6:AN6) -> 17.607875 | AP6: {=INDEX(Reading_export[1/1/2025],MATCH(1,(Reading_export[Lot]=A6)*(Reading_export[cluster]=$B$1),0))} -> 0 | AQ6: {=INDEX(Reading_export[1/3/2025],MATCH(1,(Reading_export[Lot]=A6)*(Reading_export[cluster]=$B$1),0))} -> 0 | AR6: =Table1[[#This Row],[Last day of reporting period: export]]-Table1[[#This Row],[1st day of reporting period: export]] -> 0 | AS6: =AR6/$AR$32 -> 0 | AT6: =Table1[[#This Row],[Percentage of Total export for Billing Period (%)]]*$AC$32 -> 0 | AU6: =IF($Y$32-$E$40>0,$Y$32-$E$40,0) -> #N/A | AV6: =IFERROR(Table1[[#This Row],[Total Cluster Energy Balance for P2P Trading (kWh)2]]*Table1[[#This Row],[Unused Daily Allowance %]],0) -> 0 | AW6: =AS6*AF6 -> 0 | AX6: =Table1[[#This Row],[Cluster''s Total Common Services (kWh)]]*Table1[[#This Row],[Percentage of Total export for Billing Period (%)]] -> 0 | AY6: =$Q$27*Table1[[#This Row],[Percentage of Total export for Billing Period (%)]] -> 0 | AZ6: =Table1[[#This Row],[Total Lot Export (kWh)]]-Table1[[#This Row],[Total Energy Export P2P to battery (kWh)]]-Table1[[#This Row],[Axillary Battery Losses based upon Adjusted % total export (kWh)]]-Table1[[#This Row],[Common Service based upon % total export to battery (kWh)]]-Table1[[#This Row],[EV Charger based upon % total export to battery (kWh)]] -> 0 | BA6: =IFERROR(IF($AZ$32-$F$40>0,$AZ$32-$F$40,0),0) -> 0 | BB6: =Table1[[#This Row],[Energy Losses When Export to Grid (kWh)]]*Table1[[#This Row],[Percentage of Total export for Billing Period (%)]] -> 0 | BC6: =Table1[[#This Row],[Therotical Energy Export to Grid (kWh)]]-Table1[[#This Row],[Energy Losses When Export to Grid based up % total export (kWh)]] -> 0 | BD6: =AW6*'Tariff Rates'!$C$3 -> 0 | BE6: =Table1[[#This Row],[Common Service based upon % total export to battery (kWh)]]*'Tariff Rates'!$C$3 -> 0 | BF6: =Table1[[#This Row],[EV Charger based upon % total export to battery (kWh)]]*'Tariff Rates'!$C$3 -> 0 | BG6: =AT6*'Tariff Rates'!$C$3 -> 0 | BH6: =Table1[[#This Row],[Borrowed Allowance Based on Unused Daily Allowance % (kWh)]]*'Tariff Rates'!$K$3 -> 0 | BI6: =BC6*'Tariff Rates'!$F$3 -> 0 | BJ6: =SUM(BD6:BI6) -> 0 | BK6: =$D$45*Table1[[#This Row],[Percentage of Unit Entitlement (%)]] -> 0 | BL6: =BK6*'Tariff Rates'!$H$3 -> 0 | BM6: =($Q$27)*Table1[[#This Row],[Percentage of Unit Entitlement (%)]]*'Tariff Rates'!$B$3 -> 12.80664 | BN6: =SUM(BM6,BL6) -> 12.80664 | BO6: =BK6 -> 0 | BP6: =BO6+BN6 -> 12.80664 | BQ6: =AO6+BJ6+N6+BP6 -> #N/A | BT6: 2
A7: 3 | B7: {=INDEX(Table_Household_Alloc[Owner],MATCH(1,(Table_Household_Alloc[Lot]=A7)*(Table_Household_Alloc[cluster]=$B$1),0))} -> Battigielli | C7: {=INDEX(Reading_import[Meter'#],MATCH(1,(Table_Household_Alloc[Lot]=A7)*(Table_Household_Alloc[cluster]=$B$1),0))} -> 50002872 | D7: {=INDEX(Table_Household_Alloc[UE % over Cluster],MATCH(1,(Table_Household_Alloc[Lot]=A7)*(Table_Household_Alloc[cluster]=$B$1),0))} -> 0.037 | E7: {=INDEX(Table_Household_Alloc[Stage of Dev.],MATCH(1,(Table_Household_Alloc[Lot]=A7)*(Table_Household_Alloc[cluster]=$B$1),0))} -> O | F7: {=INDEX(Amanda_energy[Daily_Supply_incl_GST],MATCH(1,(Amanda_energy[Cluster]=$B$1)*(Amanda_energy[Month]=$F$2),0))/MAX($A:$A)} -> 8.1190476 | G7: {=INDEX(Amanda_energy[Daily_Supply_incl_GST],MATCH(1,(Amanda_energy[Cluster]=$B$1)*(Amanda_energy[Month]=$G$2),0))/MAX($A:$A)} -> 7.3333333 | H7: {=INDEX(Amanda_energy[Daily_Supply_incl_GST],MATCH(1,(Amanda_energy[Cluster]=$B$1)*(Amanda_energy[Month]=$H$2),0))/MAX($A:$A)} -> #N/A | I7: =$J$40/MAX($A:$A) -> #N/A | J7: ='Tariff Rates'!$B$8*$J$3 -> 13.561644 | K7: ='Tariff Rates'!$C$8*Table1[[#This Row],[Percentage of Unit Entitlement (%)]]*'Energy billing Mastersheet'!$K$3 -> 7.8277808 | L7: =$L$3*'Tariff Rates'!$D$8*IF(Table1[[#This Row],[Stage of Dev.]]="V",0,1) -> 19.8 | M7: 1.1 | N7: =SUM(F7:M7) -> #N/A | O7: {=INDEX(Reading_import[1/1/2025],MATCH(1,(Reading_import[Lot]=A7)*(Reading_import[cluster]=$B$1),0))} -> 8271 | P7: {=INDEX(Reading_import[1/3/2025],MATCH(1,(Reading_import[Lot]=A7)*(Reading_import[cluster]=$B$1),0))} -> 8830 | Q7: =Table1[[#This Row],[Last day of reporting period: import]]-Table1[[#This Row],[1st day of reporting period: import]] -> 559 | R7: =Q7/$N$3 -> 6.2111111 | S7: =Q7/$Q$32 -> 0.10275735 | T7: =IF(Table1[[#This Row],[Stage of Dev.]]="V",0,233*Table1[[#This Row],[Percentage of Unit Entitlement (%)]]) -> 8.621 | U7: =IF(T7>R7,R7,T7) -> 6.2111111 | V7: =Table1[[#This Row],[Daily Battery allowance based on UE% (kWh)]]-Table1[[#This Row],[Applicable Battery Allowance Daily Consumption (kWh)]] -> 2.4098889 | W7: =Table1[[#This Row],[Unused Daily Allowance (kWh)]]/$V$32 -> 0.01707923 | X7: =IF(Table1[[#This Row],[Applicable Battery Allowance Daily Consumption (kWh)]]>Table1[[#This Row],[Total Daily Average Consumptio for Billing Period (kWh)]],Table1[[#This Row],[Total Consumption Import (kWh)]],U7*$N$3) -> 559 | Y7: =IF(Table1[[#This Row],[Applicable Battery Allowance Daily Consumption (kWh)]]>0,ABS(Q7-X7),0) -> 0 | Z7: =IFERROR(Table1[[#This Row],[Energy Exceeding Battery Allowance (kWh)]]/$Y$32,0) -> 0 | AA7: =IF($Y$32-$E$40>0,$Y$32-$E$40,0) -> #N/A | AB7: =IFERROR(Table1[[#This Row],[Total Cluster Energy Balance for P2P Trading (kWh)]]*Table1[[#This Row],[Energy Exceeding Battery Allowance %]],0) -> 0 | AC7: =Table1[[#This Row],[P2P Import Consumption within Battery Allowance(kWh)]]+Table1[[#This Row],[P2P Import Consumption over Battery Allowance based on Energy Exceeding Allowance % (kWh)]] -> 559 | AD7: =Table1[[#This Row],[Total Consumption Import (kWh)]]-Table1[[#This Row],[Total P2P import (kWh)]] -> 0 | AE7: =IFERROR(Table1[[#This Row],[Total P2P import (kWh)]]/$AC$32,0) -> 0.10275735 | AF7: =($Q$26-$AR$26) -> 1474 | AG7: =AF7*AE7 -> 151.46434 | AH7: =SUM($Q$28:$Q$30) -> 458 | AI7: =Table1[[#This Row],[Cluster''s Total Common Services (kWh)]]*Table1[[#This Row],[Percentage of Unit Entitlement (%)]] -> 16.946 | AJ7: =AG7*'Tariff Rates'!$B$3 -> 33.322154 | AK7: =Table1[[#This Row],[Common Services based on Split per Unit Entitlement % to battery (kWh)]]*'Tariff Rates'!$B$3 -> 3.72812 | AL7: =Table1[[#This Row],[Total P2P import (kWh)]]*IF(Table1[[#This Row],[Total Lot Export (kWh)]]=0,'Tariff Rates'!$B$3,'Tariff Rates'!$L$3) -> 122.98 | AM7: =Table1[[#This Row],[P2P Import Consumption over Battery Allowance based on Energy Exceeding Allowance % (kWh)]]*'Tariff Rates'!$J$3 -> 0 | AN7: =Table1[[#This Row],[Energy Import from Grid (kWh)]]*'Tariff Rates'!$E$3 -> 0 | AO7: =SUM(AJ7:AN7) -> 160.03027 | AP7: {=INDEX(Reading_export[1/1/2025],MATCH(1,(Reading_export[Lot]=A7)*(Reading_export[cluster]=$B$1),0))} -> 0 | AQ7: {=INDEX(Reading_export[1/3/2025],MATCH(1,(Reading_export[Lot]=A7)*(Reading_export[cluster]=$B$1),0))} -> 0 | AR7: =Table1[[#This Row],[Last day of reporting period: export]]-Table1[[#This Row],[1st day of reporting period: export]] -> 0 | AS7: =AR7/$AR$32 -> 0 | AT7: =Table1[[#This Row],[Percentage of Total export for Billing Period (%)]]*$AC$32 -> 0 | AU7: =IF($Y$32-$E$40>0,$Y$32-$E$40,0) -> #N/A | AV7: =IFERROR(Table1[[#This Row],[Total Cluster Energy Balance for P2P Trading (kWh)2]]*Table1[[#This Row],[Unused Daily Allowance %]],0) -> 0 | AW7: =AS7*AF7 -> 0 | AX7: =Table1[[#This Row],[Cluster''s Total Common Services (kWh)]]*Table1[[#This Row],[Percentage of Total export for Billing Period (%)]] -> 0 | AY7: =$Q$27*Table1[[#This Row],[Percentage of Total export for Billing Period (%)]] -> 0 | AZ7: =Table1[[#This Row],[Total Lot Export (kWh)]]-Table1[[#This Row],[Total Energy Export P2P to battery (kWh)]]-Table1[[#This Row],[Axillary Battery Losses based upon Adjusted % total export (kWh)]]-Table1[[#This Row],[Common Service based upon % total export to battery (kWh)]]-Table1[[#This Row],[EV Charger based upon % total export to battery (kWh)]] -> 0 | BA7: =IFERROR(IF($AZ$32-$F$40>0,$AZ$32-$F$40,0),0) -> 0 | BB7: =Table1[[#This Row],[Energy Losses When Export to Grid (kWh)]]*Table1[[#This Row],[Percentage of Total export for Billing Period (%)]] -> 0 | BC7: =Table1[[#This Row],[Therotical Energy Export to Grid (kWh)]]-Table1[[#This Row],[Energy Losses When Export to Grid based up % total export (kWh)]] -> 0 | BD7: =AW7*'Tariff Rates'!$C$3 -> 0 | BE7: =Table1[[#This Row],[Common Service based upon % total export to battery (kWh)]]*'Tariff Rates'!$C$3 -> 0 | BF7: =Table1[[#This Row],[EV Charger based upon % total export to battery (kWh)]]*'Tariff Rates'!$C$3 -> 0 | BG7: =AT7*'Tariff Rates'!$C$3 -> 0 | BH7: =Table1[[#This Row],[Borrowed Allowance Based on Unused Daily Allowance % (kWh)]]*'Tariff Rates'!$K$3 -> 0 | BI7: =BC7*'Tariff Rates'!$F$3 -> 0 | BJ7: =SUM(BD7:BI7) -> 0 | BK7: =$D$45*Table1[[#This Row],[Percentage of Unit Entitlement (%)]] -> 0 | BL7: =BK7*'Tariff Rates'!$H$3 -> 0 | BM7: =($Q$27)*Table1[[#This Row],[Percentage of Unit Entitlement (%)]]*'Tariff Rates'!$B$3 -> 13.16238 | BN7: =SUM(BM7,BL7) -> 13.16238 | BO7: =BK7 -> 0 | BP7: =BO7+BN7 -> 13.16238 | BQ7: =AO7+BJ7+N7+BP7 -> #N/A | BT7: 3
A8: 4 | B8: {=INDEX(Table_Household_Alloc[Owner],MATCH(1,(Table_Household_Alloc[Lot]=A8)*(Table_Household_Alloc[cluster]=$B$1),0))} -> Paul Jurjevich & Trish Rushton | C8: {=INDEX(Reading_import[Meter'#],MATCH(1,(Table_Household_Alloc[Lot]=A8)*(Table_Household_Alloc[cluster]=$B$1),0))} -> 50002869 | D8: {=INDEX(Table_Household_Alloc[UE % over Cluster],MATCH(1,(Table_Household_Alloc[Lot]=A8)*(Table_Household_Alloc[cluster]=$B$1),0))} -> 0.038 | E8: {=INDEX(Table_Household_Alloc[Stage of Dev.],MATCH(1,(Table_Household_Alloc[Lot]=A8)*(Table_Household_Alloc[cluster]=$B$1),0))} -> O | F8: {=INDEX(Amanda_energy[Daily_Supply_incl_GST],MATCH(1,(Amanda_energy[Cluster]=$B$1)*(Amanda_energy[Month]=$F$2),0))/MAX($A:$A)} -> 8.1190476 | G8: {=INDEX(Amanda_energy[Daily_Supply_incl_GST],MATCH(1,(Amanda_energy[Cluster]=$B$1)*(Amanda_energy[Month]=$G$2),0))/MAX($A:$A)} -> 7.3333333 | H8: {=INDEX(Amanda_energy[Daily_Supply_incl_GST],MATCH(1,(Amanda_energy[Cluster]=$B$1)*(Amanda_energy[Month]=$H$2),0))/MAX($A:$A)} -> #N/A | I8: =$J$40/MAX($A:$A) -> #N/A | J8: ='Tariff Rates'!$B$8*$J$3 -> 13.561644 | K8: ='Tariff Rates'!$C$8*Table1[[#This Row],[Percentage of Unit Entitlement (%)]]*'Energy billing Mastersheet'!$K$3 -> 8.0393425 | L8: =$L$3*'Tariff Rates'!$D$8*IF(Table1[[#This Row],[Stage of Dev.]]="V",0,1) -> 19.8 | M8: 1.1 | N8: =SUM(F8:M8) -> #N/A | O8: {=INDEX(Reading_import[1/1/2025],MATCH(1,(Reading_import[Lot]=A8)*(Reading_import[cluster]=$B$1),0))} -> 4542 | P8: {=INDEX(Reading_import[1/3/2025],MATCH(1,(Reading_import[Lot]=A8)*(Reading_import[cluster]=$B$1),0))} -> 4855 | Q8: =Table1[[#This Row],[Last day of reporting period: import]]-Table1[[#This Row],[1st day of reporting period: import]] -> 313 | R8: =Q8/$N$3 -> 3.4777778 | S8: =Q8/$Q$32 -> 0.057536765 | T8: =IF(Table1[[#This Row],[Stage of Dev.]]="V",0,233*Table1[[#This Row],[Percentage of Unit Entitlement (%)]]) -> 8.854 | U8: =IF(T8>R8,R8,T8) -> 3.4777778 | V8: =Table1[[#This Row],[Daily Battery allowance based on UE% (kWh)]]-Table1[[#This Row],[Applicable Battery Allowance Daily Consumption (kWh)]] -> 5.3762222 | W8: =Table1[[#This Row],[Unused Daily Allowance (kWh)]]/$V$32 -> 0.038102063 | X8: =IF(Table1[[#This Row],[Applicable Battery Allowance Daily Consumption (kWh)]]>Table1[[#This Row],[Total Daily Average Consumptio for Billing Period (kWh)]],Table1[[#This Row],[Total Consumption Import (kWh)]],U8*$N$3) -> 313 | Y8: =IF(Table1[[#This Row],[Applicable Battery Allowance Daily Consumption (kWh)]]>0,ABS(Q8-X8),0) -> 0 | Z8: =IFERROR(Table1[[#This Row],[Energy Exceeding Battery Allowance (kWh)]]/$Y$32,0) -> 0 | AA8: =IF($Y$32-$E$40>0,$Y$32-$E$40,0) -> #N/A | AB8: =IFERROR(Table1[[#This Row],[Total Cluster Energy Balance for P2P Trading (kWh)]]*Table1[[#This Row],[Energy Exceeding Battery Allowance %]],0) -> 0 | AC8: =Table1[[#This Row],[P2P Import Consumption within Battery Allowance(kWh)]]+Table1[[#This Row],[P2P Import Consumption over Battery Allowance based on Energy Exceeding Allowance % (kWh)]] -> 313 | AD8: =Table1[[#This Row],[Total Consumption Import (kWh)]]-Table1[[#This Row],[Total P2P import (kWh)]] -> 0 | AE8: =IFERROR(Table1[[#This Row],[Total P2P import (kWh)]]/$AC$32,0) -> 0.057536765 | AF8: =($Q$26-$AR$26) -> 1474 | AG8: =AF8*AE8 -> 84.809191 | AH8: =SUM($Q$28:$Q$30) -> 458 | AI8: =Table1[[#This Row],[Cluster''s Total Common Services (kWh)]]*Table1[[#This Row],[Percentage of Unit Entitlement (%)]] -> 17.404 | AJ8: =AG8*'Tariff Rates'!$B$3 -> 18.658022 | AK8: =Table1[[#This Row],[Common Services based on Split per Unit Entitlement % to battery (kWh)]]*'Tariff Rates'!$B$3 -> 3.82888 | AL8: =Table1[[#This Row],[Total P2P import (kWh)]]*IF(Table1[[#This Row],[Total Lot Export (kWh)]]=0,'Tariff Rates'!$B$3,'Tariff Rates'!$L$3) -> 112.68 | AM8: =Table1[[#This Row],[P2P Import Consumption over Battery Allowance based on Energy Exceeding Allowance % (kWh)]]*'Tariff Rates'!$J$3 -> 0 | AN8: =Table1[[#This Row],[Energy Import from Grid (kWh)]]*'Tariff Rates'!$E$3 -> 0 | AO8: =SUM(AJ8:AN8) -> 135.1669 | AP8: {=INDEX(Reading_export[1/1/2025],MATCH(1,(Reading_export[Lot]=A8)*(Reading_export[cluster]=$B$1),0))} -> 9031 | AQ8: {=INDEX(Reading_export[1/3/2025],MATCH(1,(Reading_export[Lot]=A8)*(Reading_export[cluster]=$B$1),0))} -> 10612 | AR8: =Table1[[#This Row],[Last day of reporting period: export]]-Table1[[#This Row],[1st day of reporting period: export]] -> 1581 | AS8: =AR8/$AR$32 -> 0.058968334 | AT8: =Table1[[#This Row],[Percentage of Total export for Billing Period (%)]]*$AC$32 -> 320.78774 | AU8: =IF($Y$32-$E$40>0,$Y$32-$E$40,0) -> #N/A | AV8: =IFERROR(Table1[[#This Row],[Total Cluster Energy Balance for P2P Trading (kWh)2]]*Table1[[#This Row],[Unused Daily Allowance %]],0) -> 0 | AW8: =AS8*AF8 -> 86.919324 | AX8: =Table1[[#This Row],[Cluster''s Total Common Services (kWh)]]*Table1[[#This Row],[Percentage of Total export for Billing Period (%)]] -> 27.007497 | AY8: =$Q$27*Table1[[#This Row],[Percentage of Total export for Billing Period (%)]] -> 95.351796 | AZ8: =Table1[[#This Row],[Total Lot Export (kWh)]]-Table1[[#This Row],[Total Energy Export P2P to battery (kWh)]]-Table1[[#This Row],[Axillary Battery Losses based upon Adjusted % total export (kWh)]]-Table1[[#This Row],[Common Service based upon % total export to battery (kWh)]]-Table1[[#This Row],[EV Charger based upon % total export to battery (kWh)]] -> 1050.9336 | BA8: =IFERROR(IF($AZ$32-$F$40>0,$AZ$32-$F$40,0),0) -> 0 | BB8: =Table1[[#This Row],[Energy Losses When Export to Grid (kWh)]]*Table1[[#This Row],[Percentage of Total export for Billing Period (%)]] -> 0 | BC8: =Table1[[#This Row],[Therotical Energy Export to Grid (kWh)]]-Table1[[#This Row],[Energy Losses When Export to Grid based up % total export (kWh)]] -> 1050.9336 | BD8: =AW8*'Tariff Rates'!$C$3 -> -19.122251 | BE8: =Table1[[#This Row],[Common Service based upon % total export to battery (kWh)]]*'Tariff Rates'!$C$3 -> -5.9416493 | BF8: =Table1[[#This Row],[EV Charger based upon % total export to battery (kWh)]]*'Tariff Rates'!$C$3 -> -20.977395 | BG8: =AT8*'Tariff Rates'!$C$3 -> -70.573302 | BH8: =Table1[[#This Row],[Borrowed Allowance Based on Unused Daily Allowance % (kWh)]]*'Tariff Rates'!$K$3 -> 0 | BI8: =BC8*'Tariff Rates'!$F$3 -> -40.460945 | BJ8: =SUM(BD8:BI8) -> -157.07554 | BK8: =$D$45*Table1[[#This Row],[Percentage of Unit Entitlement (%)]] -> 0 | BL8: =BK8*'Tariff Rates'!$H$3 -> 0 | BM8: =($Q$27)*Table1[[#This Row],[Percentage of Unit Entitlement (%)]]*'Tariff Rates'!$B$3 -> 13.51812 | BN8: =SUM(BM8,BL8) -> 13.51812 | BO8: =BK8 -> 0 | BP8: =BO8+BN8 -> 13.51812 | BQ8: =AO8+BJ8+N8+BP8 -> #N/A | BT8: 4
A9: 5 | B9: {=INDEX(Table_Household_Alloc[Owner],MATCH(1,(Table_Household_Alloc[Lot]=A9)*(Table_Household_Alloc[cluster]=$B$1),0))} -> Dwyer | C9: {=INDEX(Reading_import[Meter'#],MATCH(1,(Table_Household_Alloc[Lot]=A9)*(Table_Household_Alloc[cluster]=$B$1),0))} -> 50002879 | D9: {=INDEX(Table_Household_Alloc[UE % over Cluster],MATCH(1,(Table_Household_Alloc[Lot]=A9)*(Table_Household_Alloc[cluster]=$B$1),0))} -> 0.039 | E9: {=INDEX(Table_Household_Alloc[Stage of Dev.],MATCH(1,(Table_Household_Alloc[Lot]=A9)*(Table_Household_Alloc[cluster]=$B$1),0))} -> O | F9: {=INDEX(Amanda_energy[Daily_Supply_incl_GST],MATCH(1,(Amanda_energy[Cluster]=$B$1)*(Amanda_energy[Month]=$F$2),0))/MAX($A:$A)} -> 8.1190476 | G9: {=INDEX(Amanda_energy[Daily_Supply_incl_GST],MATCH(1,(Amanda_energy[Cluster]=$B$1)*(Amanda_energy[Month]=$G$2),0))/MAX($A:$A)} -> 7.3333333 | H9: {=INDEX(Amanda_energy[Daily_Supply_incl_GST],MATCH(1,(Amanda_energy[Cluster]=$B$1)*(Amanda_energy[Month]=$H$2),0))/MAX($A:$A)} -> #N/A | I9: =$J$40/MAX($A:$A) -> #N/A | J9: ='Tariff Rates'!$B$8*$J$3 -> 13.561644 | K9: ='Tariff Rates'!$C$8*Table1[[#This Row],[Percentage of Unit Entitlement (%)]]*'Energy billing Mastersheet'!$K$3 -> 8.2509041 | L9: =$L$3*'Tariff Rates'!$D$8*IF(Table1[[#This Row],[Stage of Dev.]]="V",0,1) -> 19.8 | M9: 1.1 | N9: =SUM(F9:M9) -> #N/A | O9: {=INDEX(Reading_import[1/1/2025],MATCH(1,(Reading_import[Lot]=A9)*(Reading_import[cluster]=$B$1),0))} -> 3545 | P9: {=INDEX(Reading_import[1/3/2025],MATCH(1,(Reading_import[Lot]=A9)*(Reading_import[cluster]=$B$1),0))} -> 3673 | Q9: =Table1[[#This Row],[Last day of reporting period: import]]-Table1[[#This Row],[1st day of reporting period: import]] -> 128 | R9: =Q9/$N$3 -> 1.4222222 | S9: =Q9/$Q$32 -> 0.023529412 | T9: =IF(Table1[[#This Row],[Stage of Dev.]]="V",0,233*Table1[[#This Row],[Percentage of Unit Entitlement (%)]]) -> 9.087 | U9: =IF(T9>R9,R9,T9) -> 1.4222222 | V9: =Table1[[#This Row],[Daily Battery allowance based on UE% (kWh)]]-Table1[[#This Row],[Applicable Battery Allowance Daily Consumption (kWh)]] -> 7.6647778 | W9: =Table1[[#This Row],[Unused Daily Allowance (kWh)]]/$V$32 -> 0.054321386 | X9: =IF(Table1[[#This Row],[Applicable Battery Allowance Daily Consumption (kWh)]]>Table1[[#This Row],[Total Daily Average Consumptio for Billing Period (kWh)]],Table1[[#This Row],[Total Consumption Import (kWh)]],U9*$N$3) -> 128 | Y9: =IF(Table1[[#This Row],[Applicable Battery Allowance Daily Consumption (kWh)]]>0,ABS(Q9-X9),0) -> 0 | Z9: =IFERROR(Table1[[#This Row],[Energy Exceeding Battery Allowance (kWh)]]/$Y$32,0) -> 0 | AA9: =IF($Y$32-$E$40>0,$Y$32-$E$40,0) -> #N/A | AB9: =IFERROR(Table1[[#This Row],[Total Cluster Energy Balance for P2P Trading (kWh)]]*Table1[[#This Row],[Energy Exceeding Battery Allowance %]],0) -> 0 | AC9: =Table1[[#This Row],[P2P Import Consumption within Battery Allowance(kWh)]]+Table1[[#This Row],[P2P Import Consumption over Battery Allowance based on Energy Exceeding Allowance % (kWh)]] -> 128 | AD9: =Table1[[#This Row],[Total Consumption Import (kWh)]]-Table1[[#This Row],[Total P2P import (kWh)]] -> 0 | AE9: =IFERROR(Table1[[#This Row],[Total P2P import (kWh)]]/$AC$32,0) -> 0.023529412 | AF9: =($Q$26-$AR$26) -> 1474 | AG9: =AF9*AE9 -> 34.682353 | AH9: =SUM($Q$28:$Q$30) -> 458 | AI9: =Table1[[#This Row],[Cluster''s Total Common Services (kWh)]]*Table1[[#This Row],[Percentage of Unit Entitlement (%)]] -> 17.862 | AJ9: =AG9*'Tariff Rates'!$B$3 -> 7.6301176 | AK9: =Table1[[#This Row],[Common Services based on Split per Unit Entitlement % to battery (kWh)]]*'Tariff Rates'!$B$3 -> 3.92964 | AL9: =Table1[[#This Row],[Total P2P import (kWh)]]*IF(Table1[[#This Row],[Total Lot Export (kWh)]]=0,'Tariff Rates'!$B$3,'Tariff Rates'!$L$3) -> 46.08 | AM9: =Table1[[#This Row],[P2P Import Consumption over Battery Allowance based on Energy Exceeding Allowance % (kWh)]]*'Tariff Rates'!$J$3 -> 0 | AN9: =Table1[[#This Row],[Energy Import from Grid (kWh)]]*'Tariff Rates'!$E$3 -> 0 | AO9: =SUM(AJ9:AN9) -> 57.639758 | AP9: {=INDEX(Reading_export[1/1/2025],MATCH(1,(Reading_export[Lot]=A9)*(Reading_export[cluster]=$B$1),0))} -> 12884 | AQ9: {=INDEX(Reading_export[1/3/2025],MATCH(1,(Reading_export[Lot]=A9)*(Reading_export[cluster]=$B$1),0))} -> 14647 | AR9: =Table1[[#This Row],[Last day of reporting period: export]]-Table1[[#This Row],[1st day of reporting period: export]] -> 1763 | AS9: =AR9/$AR$32 -> 0.065756592 | AT9: =Table1[[#This Row],[Percentage of Total export for Billing Period (%)]]*$AC$32 -> 357.71586 | AU9: =IF($Y$32-$E$40>0,$Y$32-$E$40,0) -> #N/A | AV9: =IFERROR(Table1[[#This Row],[Total Cluster Energy Balance for P2P Trading (kWh)2]]*Table1[[#This Row],[Unused Daily Allowance %]],0) -> 0 | AW9: =AS9*AF9 -> 96.925217 | AX9: =Table1[[#This Row],[Cluster''s Total Common Services (kWh)]]*Table1[[#This Row],[Percentage of Total export for Billing Period (%)]] -> 30.116519 | AY9: =$Q$27*Table1[[#This Row],[Percentage of Total export for Billing Period (%)]] -> 106.32841 | AZ9: =Table1[[#This Row],[Total Lot Export (kWh)]]-Table1[[#This Row],[Total Energy Export P2P to battery (kWh)]]-Table1[[#This Row],[Axillary Battery Losses based upon Adjusted % total export (kWh)]]-Table1[[#This Row],[Common Service based upon % total export to battery (kWh)]]-Table1[[#This Row],[EV Charger based upon % total export to battery (kWh)]] -> 1171.914 | BA9: =IFERROR(IF($AZ$32-$F$40>0,$AZ$32-$F$40,0),0) -> 0 | BB9: =Table1[[#This Row],[Energy Losses When Export to Grid (kWh)]]*Table1[[#This Row],[Percentage of Total export for Billing Period (%)]] -> 0 | BC9: =Table1[[#This Row],[Therotical Energy Export to Grid (kWh)]]-Table1[[#This Row],[Energy Losses When Export to Grid based up % total export (kWh)]] -> 1171.914 | BD9: =AW9*'Tariff Rates'!$C$3 -> -21.323548 | BE9: =Table1[[#This Row],[Common Service based upon % total export to battery (kWh)]]*'Tariff Rates'!$C$3 -> -6.6256343 | BF9: =Table1[[#This Row],[EV Charger based upon % total export to battery (kWh)]]*'Tariff Rates'!$C$3 -> -23.39225 | BG9: =AT9*'Tariff Rates'!$C$3 -> -78.69749 | BH9: =Table1[[#This Row],[Borrowed Allowance Based on Unused Daily Allowance % (kWh)]]*'Tariff Rates'!$K$3 -> 0 | BI9: =BC9*'Tariff Rates'!$F$3 -> -45.118689 | BJ9: =SUM(BD9:BI9) -> -175.15761 | BK9: =$D$45*Table1[[#This Row],[Percentage of Unit Entitlement (%)]] -> 0 | BL9: =BK9*'Tariff Rates'!$H$3 -> 0 | BM9: =($Q$27)*Table1[[#This Row],[Percentage of Unit Entitlement (%)]]*'Tariff Rates'!$B$3 -> 13.87386 | BN9: =SUM(BM9,BL9) -> 13.87386 | BO9: =BK9 -> 0 | BP9: =BO9+BN9 -> 13.87386 | BQ9: =AO9+BJ9+N9+BP9 -> #N/A | BT9: 5
A10: 6 | B10: {=INDEX(Table_Household_Alloc[Owner],MATCH(1,(Table_Household_Alloc[Lot]=A10)*(Table_Household_Alloc[cluster]=$B$1),0))} -> Gillespie | C10: {=INDEX(Reading_import[Meter'#],MATCH(1,(Table_Household_Alloc[Lot]=A10)*(Table_Household_Alloc[cluster]=$B$1),0))} -> 50002865 | D10: {=INDEX(Table_Household_Alloc[UE % over Cluster],MATCH(1,(Table_Household_Alloc[Lot]=A10)*(Table_Household_Alloc[cluster]=$B$1),0))} -> 0.039 | E10: {=INDEX(Table_Household_Alloc[Stage of Dev.],MATCH(1,(Table_Household_Alloc[Lot]=A10)*(Table_Household_Alloc[cluster]=$B$1),0))} -> O | F10: {=INDEX(Amanda_energy[Daily_Supply_incl_GST],MATCH(1,(Amanda_energy[Cluster]=$B$1)*(Amanda_energy[Month]=$F$2),0))/MAX($A:$A)} -> 8.1190476 | G10: {=INDEX(Amanda_energy[Daily_Supply_incl_GST],MATCH(1,(Amanda_energy[Cluster]=$B$1)*(Amanda_energy[Month]=$G$2),0))/MAX($A:$A)} -> 7.3333333 | H10: {=INDEX(Amanda_energy[Daily_Supply_incl_GST],MATCH(1,(Amanda_energy[Cluster]=$B$1)*(Amanda_energy[Month]=$H$2),0))/MAX($A:$A)} -> #N/A | I10: =$J$40/MAX($A:$A) -> #N/A | J10: ='Tariff Rates'!$B$8*$J$3 -> 13.561644 | K10: ='Tariff Rates'!$C$8*Table1[[#This Row],[Percentage of Unit Entitlement (%)]]*'Energy billing Mastersheet'!$K$3 -> 8.2509041 | L10: =$L$3*'Tariff Rates'!$D$8*IF(Table1[[#This Row],[Stage of Dev.]]="V",0,1) -> 19.8 | M10: 1.1 | N10: =SUM(F10:M10) -> #N/A | O10: {=INDEX(Reading_import[1/1/2025],MATCH(1,(Reading_import[Lot]=A10)*(Reading_import[cluster]=$B$1),0))} -> 8639 | P10: {=INDEX(Reading_import[1/3/2025],MATCH(1,(Reading_import[Lot]=A10)*(Reading_import[cluster]=$B$1),0))} -> 8918 | Q10: =Table1[[#This Row],[Last day of reporting period: import]]-Table1[[#This Row],[1st day of reporting period: import]] -> 279 | R10: =Q10/$N$3 -> 3.1 | S10: =Q10/$Q$32 -> 0.051286765 | T10: =IF(Table1[[#This Row],[Stage of Dev.]]="V",0,233*Table1[[#This Row],[Percentage of Unit Entitlement (%)]]) -> 9.087 | U10: =IF(T10>R10,R10,T10) -> 3.1 | V10: =Table1[[#This Row],[Daily Battery allowance based on UE% (kWh)]]-Table1[[#This Row],[Applicable Battery Allowance Daily Consumption (kWh)]] -> 5.987 | W10: =Table1[[#This Row],[Unused Daily Allowance (kWh)]]/$V$32 -> 0.042430733 | X10: =IF(Table1[[#This Row],[Applicable Battery Allowance Daily Consumption (kWh)]]>Table1[[#This Row],[Total Daily Average Consumptio for Billing Period (kWh)]],Table1[[#This Row],[Total Consumption Import (kWh)]],U10*$N$3) -> 279 | Y10: =IF(Table1[[#This Row],[Applicable Battery Allowance Daily Consumption (kWh)]]>0,ABS(Q10-X10),0) -> 0 | Z10: =IFERROR(Table1[[#This Row],[Energy Exceeding Battery Allowance (kWh)]]/$Y$32,0) -> 0 | AA10: =IF($Y$32-$E$40>0,$Y$32-$E$40,0) -> #N/A | AB10: =IFERROR(Table1[[#This Row],[Total Cluster Energy Balance for P2P Trading (kWh)]]*Table1[[#This Row],[Energy Exceeding Battery Allowance %]],0) -> 0 | AC10: =Table1[[#This Row],[P2P Import Consumption within Battery Allowance(kWh)]]+Table1[[#This Row],[P2P Import Consumption over Battery Allowance based on Energy Exceeding Allowance % (kWh)]] -> 279 | AD10: =Table1[[#This Row],[Total Consumption Import (kWh)]]-Table1[[#This Row],[Total P2P import (kWh)]] -> 0 | AE10: =IFERROR(Table1[[#This Row],[Total P2P import (kWh)]]/$AC$32,0) -> 0.051286765 | AF10: =($Q$26-$AR$26) -> 1474 | AG10: =AF10*AE10 -> 75.596691 | AH10: =SUM($Q$28:$Q$30) -> 458 | AI10: =Table1[[#This Row],[Cluster''s Total Common Services (kWh)]]*Table1[[#This Row],[Percentage of Unit Entitlement (%)]] -> 17.862 | AJ10: =AG10*'Tariff Rates'!$B$3 -> 16.631272 | AK10: =Table1[[#This Row],[Common Services based on Split per Unit Entitlement % to battery (kWh)]]*'Tariff Rates'!$B$3 -> 3.92964 | AL10: =Table1[[#This Row],[Total P2P import (kWh)]]*IF(Table1[[#This Row],[Total Lot Export (kWh)]]=0,'Tariff Rates'!$B$3,'Tariff Rates'!$L$3) -> 100.44 | AM10: =Table1[[#This Row],[P2P Import Consumption over Battery Allowance based on Energy Exceeding Allowance % (kWh)]]*'Tariff Rates'!$J$3 -> 0 | AN10: =Table1[[#This Row],[Energy Import from Grid (kWh)]]*'Tariff Rates'!$E$3 -> 0 | AO10: =SUM(AJ10:AN10) -> 121.00091 | AP10: {=INDEX(Reading_export[1/1/2025],MATCH(1,(Reading_export[Lot]=A10)*(Reading_export[cluster]=$B$1),0))} -> 18121 | AQ10: {=INDEX(Reading_export[1/3/2025],MATCH(1,(Reading_export[Lot]=A10)*(Reading_export[cluster]=$B$1),0))} -> 20965 | AR10: =Table1[[#This Row],[Last day of reporting period: export]]-Table1[[#This Row],[1st day of reporting period: export]] -> 2844 | AS10: =AR10/$AR$32 -> 0.10607586 | AT10: =Table1[[#This Row],[Percentage of Total export for Billing Period (%)]]*$AC$32 -> 577.0527 | AU10: =IF($Y$32-$E$40>0,$Y$32-$E$40,0) -> #N/A | AV10: =IFERROR(Table1[[#This Row],[Total Cluster Energy Balance for P2P Trading (kWh)2]]*Table1[[#This Row],[Unused Daily Allowance %]],0) -> 0 | AW10: =AS10*AF10 -> 156.35582 | AX10: =Table1[[#This Row],[Cluster''s Total Common Services (kWh)]]*Table1[[#This Row],[Percentage of Total export for Billing Period (%)]] -> 48.582746 | AY10: =$Q$27*Table1[[#This Row],[Percentage of Total export for Billing Period (%)]] -> 171.52467 | AZ10: =Table1[[#This Row],[Total Lot Export (kWh)]]-Table1[[#This Row],[Total Energy Export P2P to battery (kWh)]]-Table1[[#This Row],[Axillary Battery Losses based upon Adjusted % total export (kWh)]]-Table1[[#This Row],[Common Service based upon % total export to battery (kWh)]]-Table1[[#This Row],[EV Charger based upon % total export to battery (kWh)]] -> 1890.4841 | BA10: =IFERROR(IF($AZ$32-$F$40>0,$AZ$32-$F$40,0),0) -> 0 | BB10: =Table1[[#This Row],[Energy Losses When Export to Grid (kWh)]]*Table1[[#This Row],[Percentage of Total export for Billing Period (%)]] -> 0 | BC10: =Table1[[#This Row],[Therotical Energy Export to Grid (kWh)]]-Table1[[#This Row],[Energy Losses When Export to Grid based up % total export (kWh)]] -> 1890.4841 | BD10: =AW10*'Tariff Rates'!$C$3 -> -34.398281 | BE10: =Table1[[#This Row],[Common Service based upon % total export to battery (kWh)]]*'Tariff Rates'!$C$3 -> -10.688204 | BF10: =Table1[[#This Row],[EV Charger based upon % total export to battery (kWh)]]*'Tariff Rates'!$C$3 -> -37.735428 | BG10: =AT10*'Tariff Rates'!$C$3 -> -126.95159 | BH10: =Table1[[#This Row],[Borrowed Allowance Based on Unused Daily Allowance % (kWh)]]*'Tariff Rates'!$K$3 -> 0 | BI10: =BC10*'Tariff Rates'!$F$3 -> -72.783636 | BJ10: =SUM(BD10:BI10) -> -282.55714 | BK10: =$D$45*Table1[[#This Row],[Percentage of Unit Entitlement (%)]] -> 0 | BL10: =BK10*'Tariff Rates'!$H$3 -> 0 | BM10: =($Q$27)*Table1[[#This Row],[Percentage of Unit Entitlement (%)]]*'Tariff Rates'!$B$3 -> 13.87386 | BN10: =SUM(BM10,BL10) -> 13.87386 | BO10: =BK10 -> 0 | BP10: =BO10+BN10 -> 13.87386 | BQ10: =AO10+BJ10+N10+BP10 -> #N/A | BT10: 6
A11: 7 | B11: {=INDEX(Table_Household_Alloc[Owner],MATCH(1,(Table_Household_Alloc[Lot]=A11)*(Table_Household_Alloc[cluster]=$B$1),0))} -> Rio & Alix Healey-­‐Diaz | C11: {=INDEX(Reading_import[Meter'#],MATCH(1,(Table_Household_Alloc[Lot]=A11)*(Table_Household_Alloc[cluster]=$B$1),0))} -> 50002887 | D11: {=INDEX(Table_Household_Alloc[UE % over Cluster],MATCH(1,(Table_Household_Alloc[Lot]=A11)*(Table_Household_Alloc[cluster]=$B$1),0))} -> 0.037 | E11: {=INDEX(Table_Household_Alloc[Stage of Dev.],MATCH(1,(Table_Household_Alloc[Lot]=A11)*(Table_Household_Alloc[cluster]=$B$1),0))} -> O | F11: {=INDEX(Amanda_energy[Daily_Supply_incl_GST],MATCH(1,(Amanda_energy[Cluster]=$B$1)*(Amanda_energy[Month]=$F$2),0))/MAX($A:$A)} -> 8.1190476 | G11: {=INDEX(Amanda_energy[Daily_Supply_incl_GST],MATCH(1,(Amanda_energy[Cluster]=$B$1)*(Amanda_energy[Month]=$G$2),0))/MAX($A:$A)} -> 7.3333333 | H11: {=INDEX(Amanda_energy[Daily_Supply_incl_GST],MATCH(1,(Amanda_energy[Cluster]=$B$1)*(Amanda_energy[Month]=$H$2),0))/MAX($A:$A)} -> #N/A | I11: =$J$40/MAX($A:$A) -> #N/A | J11: ='Tariff Rates'!$B$8*$J$3 -> 13.561644 | K11: ='Tariff Rates'!$C$8*Table1[[#This Row],[Percentage of Unit Entitlement (%)]]*'Energy billing Mastersheet'!$K$3 -> 7.8277808 | L11: =$L$3*'Tariff Rates'!$D$8*IF(Table1[[#This Row],[Stage of Dev.]]="V",0,1) -> 19.8 | M11: 1.1 | N11: =SUM(F11:M11) -> #N/A | O11: {=INDEX(Reading_import[1/1/2025],MATCH(1,(Reading_import[Lot]=A11)*(Reading_import[cluster]=$B$1),0))} -> 8272 | P11: {=INDEX(Reading_import[1/3/2025],MATCH(1,(Reading_import[Lot]=A11)*(Reading_import[cluster]=$B$1),0))} -> 8725 | Q11: =Table1[[#This Row],[Last day of reporting period: import]]-Table1[[#This Row],[1st day of reporting period: import]] -> 453 | R11: =Q11/$N$3 -> 5.0333333 | S11: =Q11/$Q$32 -> 0.083272059 | T11: =IF(Table1[[#This Row],[Stage of Dev.]]="V",0,233*Table1[[#This Row],[Percentage of Unit Entitlement (%)]]) -> 8.621 | U11: =IF(T11>R11,R11,T11) -> 5.0333333 | V11: =Table1[[#This Row],[Daily Battery allowance based on UE% (kWh)]]-Table1[[#This Row],[Applicable Battery Allowance Daily Consumption (kWh)]] -> 3.5876667 | W11: =Table1[[#This Row],[Unused Daily Allowance (kWh)]]/$V$32 -> 0.025426311 | X11: =IF(Table1[[#This Row],[Applicable Battery Allowance Daily Consumption (kWh)]]>Table1[[#This Row],[Total Daily Average Consumptio for Billing Period (kWh)]],Table1[[#This Row],[Total Consumption Import (kWh)]],U11*$N$3) -> 453 | Y11: =IF(Table1[[#This Row],[Applicable Battery Allowance Daily Consumption (kWh)]]>0,ABS(Q11-X11),0) -> 0 | Z11: =IFERROR(Table1[[#This Row],[Energy Exceeding Battery Allowance (kWh)]]/$Y$32,0) -> 0 | AA11: =IF($Y$32-$E$40>0,$Y$32-$E$40,0) -> #N/A | AB11: =IFERROR(Table1[[#This Row],[Total Cluster Energy Balance for P2P Trading (kWh)]]*Table1[[#This Row],[Energy Exceeding Battery Allowance %]],0) -> 0 | AC11: =Table1[[#This Row],[P2P Import Consumption within Battery Allowance(kWh)]]+Table1[[#This Row],[P2P Import Consumption over Battery Allowance based on Energy Exceeding Allowance % (kWh)]] -> 453 | AD11: =Table1[[#This Row],[Total Consumption Import (kWh)]]-Table1[[#This Row],[Total P2P import (kWh)]] -> 0 | AE11: =IFERROR(Table1[[#This Row],[Total P2P import (kWh)]]/$AC$32,0) -> 0.083272059 | AF11: =($Q$26-$AR$26) -> 1474 | AG11: =AF11*AE11 -> 122.74301 | AH11: =SUM($Q$28:$Q$30) -> 458 | AI11: =Table1[[#This Row],[Cluster''s Total Common Services (kWh)]]*Table1[[#This Row],[Percentage of Unit Entitlement (%)]] -> 16.946 | AJ11: =AG11*'Tariff Rates'!$B$3 -> 27.003463 | AK11: =Table1[[#This Row],[Common Services based on Split per Unit Entitlement % to battery (kWh)]]*'Tariff Rates'!$B$3 -> 3.72812 | AL11: =Table1[[#This Row],[Total P2P import (kWh)]]*IF(Table1[[#This Row],[Total Lot Export (kWh)]]=0,'Tariff Rates'!$B$3,'Tariff Rates'!$L$3) -> 99.66 | AM11: =Table1[[#This Row],[P2P Import Consumption over Battery Allowance based on Energy Exceeding Allowance % (kWh)]]*'Tariff Rates'!$J$3 -> 0 | AN11: =Table1[[#This Row],[Energy Import from Grid (kWh)]]*'Tariff Rates'!$E$3 -> 0 | AO11: =SUM(AJ11:AN11) -> 130.39158 | AP11: {=INDEX(Reading_export[1/1/2025],MATCH(1,(Reading_export[Lot]=A11)*(Reading_export[cluster]=$B$1),0))} -> 0 | AQ11: {=INDEX(Reading_export[1/3/2025],MATCH(1,(Reading_export[Lot]=A11)*(Reading_export[cluster]=$B$1),0))} -> 0 | AR11: =Table1[[#This Row],[Last day of reporting period: export]]-Table1[[#This Row],[1st day of reporting period: export]] -> 0 | AS11: =AR11/$AR$32 -> 0 | AT11: =Table1[[#This Row],[Percentage of Total export for Billing Period (%)]]*$AC$32 -> 0 | AU11: =IF($Y$32-$E$40>0,$Y$32-$E$40,0) -> #N/A | AV11: =IFERROR(Table1[[#This Row],[Total Cluster Energy Balance for P2P Trading (kWh)2]]*Table1[[#This Row],[Unused Daily Allowance %]],0) -> 0 | AW11: =AS11*AF11 -> 0 | AX11: =Table1[[#This Row],[Cluster''s Total Common Services (kWh)]]*Table1[[#This Row],[Percentage of Total export for Billing Period (%)]] -> 0 | AY11: =$Q$27*Table1[[#This Row],[Percentage of Total export for Billing Period (%)]] -> 0 | AZ11: =Table1[[#This Row],[Total Lot Export (kWh)]]-Table1[[#This Row],[Total Energy Export P2P to battery (kWh)]]-Table1[[#This Row],[Axillary Battery Losses based upon Adjusted % total export (kWh)]]-Table1[[#This Row],[Common Service based upon % total export to battery (kWh)]]-Table1[[#This Row],[EV Charger based upon % total export to battery (kWh)]] -> 0 | BA11: =IFERROR(IF($AZ$32-$F$40>0,$AZ$32-$F$40,0),0) -> 0 | BB11: =Table1[[#This Row],[Energy Losses When Export to Grid (kWh)]]*Table1[[#This Row],[Percentage of Total export for Billing Period (%)]] -> 0 | BC11: =Table1[[#This Row],[Therotical Energy Export to Grid (kWh)]]-Table1[[#This Row],[Energy Losses When Export to Grid based up % total export (kWh)]] -> 0 | BD11: =AW11*'Tariff Rates'!$C$3 -> 0 | BE11: =Table1[[#This Row],[Common Service based upon % total export to battery (kWh)]]*'Tariff Rates'!$C$3 -> 0 | BF11: =Table1[[#This Row],[EV Charger based upon % total export to battery (kWh)]]*'Tariff Rates'!$C$3 -> 0 | BG11: =AT11*'Tariff Rates'!$C$3 -> 0 | BH11: =Table1[[#This Row],[Borrowed Allowance Based on Unused Daily Allowance % (kWh)]]*'Tariff Rates'!$K$3 -> 0 | BI11: =BC11*'Tariff Rates'!$F$3 -> 0 | BJ11: =SUM(BD11:BI11) -> 0 | BK11: =$D$45*Table1[[#This Row],[Percentage of Unit Entitlement (%)]] -> 0 | BL11: =BK11*'Tariff Rates'!$H$3 -> 0 | BM11: =($Q$27)*Table1[[#This Row],[Percentage of Unit Entitlement (%)]]*'Tariff Rates'!$B$3 -> 13.16238 | BN11: =SUM(BM11,BL11) -> 13.16238 | BO11: =BK11 -> 0 | BP11: =BO11+BN11 -> 13.16238 | BQ11: =AO11+BJ11+N11+BP11 -> #N/A | BT11: 7
A12: 8 | B12: {=INDEX(Table_Household_Alloc[Owner],MATCH(1,(Table_Household_Alloc[Lot]=A12)*(Table_Household_Alloc[cluster]=$B$1),0))} -> Marcus Browne & Sook-­‐JaRebecchi | C12: {=INDEX(Reading_import[Meter'#],MATCH(1,(Table_Household_Alloc[Lot]=A12)*(Table_Household_Alloc[cluster]=$B$1),0))} -> 50002846 | D12: {=INDEX(Table_Household_Alloc[UE % over Cluster],MATCH(1,(Table_Household_Alloc[Lot]=A12)*(Table_Household_Alloc[cluster]=$B$1),0))} -> 0.036 | E12: {=INDEX(Table_Household_Alloc[Stage of Dev.],MATCH(1,(Table_Household_Alloc[Lot]=A12)*(Table_Household_Alloc[cluster]=$B$1),0))} -> O | F12: {=INDEX(Amanda_energy[Daily_Supply_incl_GST],MATCH(1,(Amanda_energy[Cluster]=$B$1)*(Amanda_energy[Month]=$F$2),0))/MAX($A:$A)} -> 8.1190476 | G12: {=INDEX(Amanda_energy[Daily_Supply_incl_GST],MATCH(1,(Amanda_energy[Cluster]=$B$1)*(Amanda_energy[Month]=$G$2),0))/MAX($A:$A)} -> 7.3333333 | H12: {=INDEX(Amanda_energy[Daily_Supply_incl_GST],MATCH(1,(Amanda_energy[Cluster]=$B$1)*(Amanda_energy[Month]=$H$2),0))/MAX($A:$A)} -> #N/A | I12: =$J$40/MAX($A:$A) -> #N/A | J12: ='Tariff Rates'!$B$8*$J$3 -> 13.561644 | K12: ='Tariff Rates'!$C$8*Table1[[#This Row],[Percentage of Unit Entitlement (%)]]*'Energy billing Mastersheet'!$K$3 -> 7.6162192 | L12: =$L$3*'Tariff Rates'!$D$8*IF(Table1[[#This Row],[Stage of Dev.]]="V",0,1) -> 19.8 | M12: 1.1 | N12: =SUM(F12:M12) -> #N/A | O12: {=INDEX(Reading_import[1/1/2025],MATCH(1,(Reading_import[Lot]=A12)*(Reading_import[cluster]=$B$1),0))} -> 3006 | P12: {=INDEX(Reading_import[1/3/2025],MATCH(1,(Reading_import[Lot]=A12)*(Reading_import[cluster]=$B$1),0))} -> 3404 | Q12: =Table1[[#This Row],[Last day of reporting period: import]]-Table1[[#This Row],[1st day of reporting period: import]] -> 398 | R12: =Q12/$N$3 -> 4.4222222 | S12: =Q12/$Q$32 -> 0.073161765 | T12: =IF(Table1[[#This Row],[Stage of Dev.]]="V",0,233*Table1[[#This Row],[Percentage of Unit Entitlement (%)]]) -> 8.388 | U12: =IF(T12>R12,R12,T12) -> 4.4222222 | V12: =Table1[[#This Row],[Daily Battery allowance based on UE% (kWh)]]-Table1[[#This Row],[Applicable Battery Allowance Daily Consumption (kWh)]] -> 3.9657778 | W12: =Table1[[#This Row],[Unused Daily Allowance (kWh)]]/$V$32 -> 0.028106039 | X12: =IF(Table1[[#This Row],[Applicable Battery Allowance Daily Consumption (kWh)]]>Table1[[#This Row],[Total Daily Average Consumptio for Billing Period (kWh)]],Table1[[#This Row],[Total Consumption Import (kWh)]],U12*$N$3) -> 398 | Y12: =IF(Table1[[#This Row],[Applicable Battery Allowance Daily Consumption (kWh)]]>0,ABS(Q12-X12),0) -> 0 | Z12: =IFERROR(Table1[[#This Row],[Energy Exceeding Battery Allowance (kWh)]]/$Y$32,0) -> 0 | AA12: =IF($Y$32-$E$40>0,$Y$32-$E$40,0) -> #N/A | AB12: =IFERROR(Table1[[#This Row],[Total Cluster Energy Balance for P2P Trading (kWh)]]*Table1[[#This Row],[Energy Exceeding Battery Allowance %]],0) -> 0 | AC12: =Table1[[#This Row],[P2P Import Consumption within Battery Allowance(kWh)]]+Table1[[#This Row],[P2P Import Consumption over Battery Allowance based on Energy Exceeding Allowance % (kWh)]] -> 398 | AD12: =Table1[[#This Row],[Total Consumption Import (kWh)]]-Table1[[#This Row],[Total P2P import (kWh)]] -> 0 | AE12: =IFERROR(Table1[[#This Row],[Total P2P import (kWh)]]/$AC$32,0) -> 0.073161765 | AF12: =($Q$26-$AR$26) -> 1474 | AG12: =AF12*AE12 -> 107.84044 | AH12: =SUM($Q$28:$Q$30) -> 458 | AI12: =Table1[[#This Row],[Cluster''s Total Common Services (kWh)]]*Table1[[#This Row],[Percentage of Unit Entitlement (%)]] -> 16.488 | AJ12: =AG12*'Tariff Rates'!$B$3 -> 23.724897 | AK12: =Table1[[#This Row],[Common Services based on Split per Unit Entitlement % to battery (kWh)]]*'Tariff Rates'!$B$3 -> 3.62736 | AL12: =Table1[[#This Row],[Total P2P import (kWh)]]*IF(Table1[[#This Row],[Total Lot Export (kWh)]]=0,'Tariff Rates'!$B$3,'Tariff Rates'!$L$3) -> 143.28 | AM12: =Table1[[#This Row],[P2P Import Consumption over Battery Allowance based on Energy Exceeding Allowance % (kWh)]]*'Tariff Rates'!$J$3 -> 0 | AN12: =Table1[[#This Row],[Energy Import from Grid (kWh)]]*'Tariff Rates'!$E$3 -> 0 | AO12: =SUM(AJ12:AN12) -> 170.63226 | AP12: {=INDEX(Reading_export[1/1/2025],MATCH(1,(Reading_export[Lot]=A12)*(Reading_export[cluster]=$B$1),0))} -> 2569 | AQ12: {=INDEX(Reading_export[1/3/2025],MATCH(1,(Reading_export[Lot]=A12)*(Reading_export[cluster]=$B$1),0))} -> 4165 | AR12: =Table1[[#This Row],[Last day of reporting period: export]]-Table1[[#This Row],[1st day of reporting period: export]] -> 1596 | AS12: =AR12/$AR$32 -> 0.059527806 | AT12: =Table1[[#This Row],[Percentage of Total export for Billing Period (%)]]*$AC$32 -> 323.83126 | AU12: =IF($Y$32-$E$40>0,$Y$32-$E$40,0) -> #N/A | AV12: =IFERROR(Table1[[#This Row],[Total Cluster Energy Balance for P2P Trading (kWh)2]]*Table1[[#This Row],[Unused Daily Allowance %]],0) -> 0 | AW12: =AS12*AF12 -> 87.743986 | AX12: =Table1[[#This Row],[Cluster''s Total Common Services (kWh)]]*Table1[[#This Row],[Percentage of Total export for Billing Period (%)]] -> 27.263735 | AY12: =$Q$27*Table1[[#This Row],[Percentage of Total export for Billing Period (%)]] -> 96.256462 | AZ12: =Table1[[#This Row],[Total Lot Export (kWh)]]-Table1[[#This Row],[Total Energy Export P2P to battery (kWh)]]-Table1[[#This Row],[Axillary Battery Losses based upon Adjusted % total export (kWh)]]-Table1[[#This Row],[Common Service based upon % total export to battery (kWh)]]-Table1[[#This Row],[EV Charger based upon % total export to battery (kWh)]] -> 1060.9046 | BA12: =IFERROR(IF($AZ$32-$F$40>0,$AZ$32-$F$40,0),0) -> 0 | BB12: =Table1[[#This Row],[Energy Losses When Export to Grid (kWh)]]*Table1[[#This Row],[Percentage of Total export for Billing Period (%)]] -> 0 | BC12: =Table1[[#This Row],[Therotical Energy Export to Grid (kWh)]]-Table1[[#This Row],[Energy Losses When Export to Grid based up % total export (kWh)]] -> 1060.9046 | BD12: =AW12*'Tariff Rates'!$C$3 -> -19.303677 | BE12: =Table1[[#This Row],[Common Service based upon % total export to battery (kWh)]]*'Tariff Rates'!$C$3 -> -5.9980217 | BF12: =Table1[[#This Row],[EV Charger based upon % total export to battery (kWh)]]*'Tariff Rates'!$C$3 -> -21.176422 | BG12: =AT12*'Tariff Rates'!$C$3 -> -71.242878 | BH12: =Table1[[#This Row],[Borrowed Allowance Based on Unused Daily Allowance % (kWh)]]*'Tariff Rates'!$K$3 -> 0 | BI12: =BC12*'Tariff Rates'!$F$3 -> -40.844825 | BJ12: =SUM(BD12:BI12) -> -158.56582 | BK12: =$D$45*Table1[[#This Row],[Percentage of Unit Entitlement (%)]] -> 0 | BL12: =BK12*'Tariff Rates'!$H$3 -> 0 | BM12: =($Q$27)*Table1[[#This Row],[Percentage of Unit Entitlement (%)]]*'Tariff Rates'!$B$3 -> 12.80664 | BN12: =SUM(BM12,BL12) -> 12.80664 | BO12: =BK12 -> 0 | BP12: =BO12+BN12 -> 12.80664 | BQ12: =AO12+BJ12+N12+BP12 -> #N/A | BT12: 8
A13: 9 | B13: {=INDEX(Table_Household_Alloc[Owner],MATCH(1,(Table_Household_Alloc[Lot]=A13)*(Table_Household_Alloc[cluster]=$B$1),0))} -> Jasmine Heah | C13: {=INDEX(Reading_import[Meter'#],MATCH(1,(Table_Household_Alloc[Lot]=A13)*(Table_Household_Alloc[cluster]=$B$1),0))} -> 50002885 | D13: {=INDEX(Table_Household_Alloc[UE % over Cluster],MATCH(1,(Table_Household_Alloc[Lot]=A13)*(Table_Household_Alloc[cluster]=$B$1),0))} -> 0.036 | E13: {=INDEX(Table_Household_Alloc[Stage of Dev.],MATCH(1,(Table_Household_Alloc[Lot]=A13)*(Table_Household_Alloc[cluster]=$B$1),0))} -> O | F13: {=INDEX(Amanda_energy[Daily_Supply_incl_GST],MATCH(1,(Amanda_energy[Cluster]=$B$1)*(Amanda_energy[Month]=$F$2),0))/MAX($A:$A)} -> 8.1190476 | G13: {=INDEX(Amanda_energy[Daily_Supply_incl_GST],MATCH(1,(Amanda_energy[Cluster]=$B$1)*(Amanda_energy[Month]=$G$2),0))/MAX($A:$A)} -> 7.3333333 | H13: {=INDEX(Amanda_energy[Daily_Supply_incl_GST],MATCH(1,(Amanda_energy[Cluster]=$B$1)*(Amanda_energy[Month]=$H$2),0))/MAX($A:$A)} -> #N/A | I13: =$J$40/MAX($A:$A) -> #N/A | J13: ='Tariff Rates'!$B$8*$J$3 -> 13.561644 | K13: ='Tariff Rates'!$C$8*Table1[[#This Row],[Percentage of Unit Entitlement (%)]]*'Energy billing Mastersheet'!$K$3 -> 7.6162192 | L13: =$L$3*'Tariff Rates'!$D$8*IF(Table1[[#This Row],[Stage of Dev.]]="V",0,1) -> 19.8 | M13: 1.1 | N13: =SUM(F13:M13) -> #N/A | O13: {=INDEX(Reading_import[1/1/2025],MATCH(1,(Reading_import[Lot]=A13)*(Reading_import[cluster]=$B$1),0))} -> 13606 | P13: {=INDEX(Reading_import[1/3/2025],MATCH(1,(Reading_import[Lot]=A13)*(Reading_import[cluster]=$B$1),0))} -> 14226 | Q13: =Table1[[#This Row],[Last day of reporting period: import]]-Table1[[#This Row],[1st day of reporting period: import]] -> 620 | R13: =Q13/$N$3 -> 6.8888889 | S13: =Q13/$Q$32 -> 0.11397059 | T13: =IF(Table1[[#This Row],[Stage of Dev.]]="V",0,233*Table1[[#This Row],[Percentage of Unit Entitlement (%)]]) -> 8.388 | U13: =IF(T13>R13,R13,T13) -> 6.8888889 | V13: =Table1[[#This Row],[Daily Battery allowance based on UE% (kWh)]]-Table1[[#This Row],[Applicable Battery Allowance Daily Consumption (kWh)]] -> 1.4991111 | W13: =Table1[[#This Row],[Unused Daily Allowance (kWh)]]/$V$32 -> 0.010624417 | X13: =IF(Table1[[#This Row],[Applicable Battery Allowance Daily Consumption (kWh)]]>Table1[[#This Row],[Total Daily Average Consumptio for Billing Period (kWh)]],Table1[[#This Row],[Total Consumption Import (kWh)]],U13*$N$3) -> 620 | Y13: =IF(Table1[[#This Row],[Applicable Battery Allowance Daily Consumption (kWh)]]>0,ABS(Q13-X13),0) -> 0 | Z13: =IFERROR(Table1[[#This Row],[Energy Exceeding Battery Allowance (kWh)]]/$Y$32,0) -> 0 | AA13: =IF($Y$32-$E$40>0,$Y$32-$E$40,0) -> #N/A | AB13: =IFERROR(Table1[[#This Row],[Total Cluster Energy Balance for P2P Trading (kWh)]]*Table1[[#This Row],[Energy Exceeding Battery Allowance %]],0) -> 0 | AC13: =Table1[[#This Row],[P2P Import Consumption within Battery Allowance(kWh)]]+Table1[[#This Row],[P2P Import Consumption over Battery Allowance based on Energy Exceeding Allowance % (kWh)]] -> 620 | AD13: =Table1[[#This Row],[Total Consumption Import (kWh)]]-Table1[[#This Row],[Total P2P import (kWh)]] -> 0 | AE13: =IFERROR(Table1[[#This Row],[Total P2P import (kWh)]]/$AC$32,0) -> 0.11397059 | AF13: =($Q$26-$AR$26) -> 1474 | AG13: =AF13*AE13 -> 167.99265 | AH13: =SUM($Q$28:$Q$30) -> 458 | AI13: =Table1[[#This Row],[Cluster''s Total Common Services (kWh)]]*Table1[[#This Row],[Percentage of Unit Entitlement (%)]] -> 16.488 | AJ13: =AG13*'Tariff Rates'!$B$3 -> 36.958382 | AK13: =Table1[[#This Row],[Common Services based on Split per Unit Entitlement % to battery (kWh)]]*'Tariff Rates'!$B$3 -> 3.62736 | AL13: =Table1[[#This Row],[Total P2P import (kWh)]]*IF(Table1[[#This Row],[Total Lot Export (kWh)]]=0,'Tariff Rates'!$B$3,'Tariff Rates'!$L$3) -> 136.4 | AM13: =Table1[[#This Row],[P2P Import Consumption over Battery Allowance based on Energy Exceeding Allowance % (kWh)]]*'Tariff Rates'!$J$3 -> 0 | AN13: =Table1[[#This Row],[Energy Import from Grid (kWh)]]*'Tariff Rates'!$E$3 -> 0 | AO13: =SUM(AJ13:AN13) -> 176.98574 | AP13: {=INDEX(Reading_export[1/1/2025],MATCH(1,(Reading_export[Lot]=A13)*(Reading_export[cluster]=$B$1),0))} -> 0 | AQ13: {=INDEX(Reading_export[1/3/2025],MATCH(1,(Reading_export[Lot]=A13)*(Reading_export[cluster]=$B$1),0))} -> 0 | AR13: =Table1[[#This Row],[Last day of reporting period: export]]-Table1[[#This Row],[1st day of reporting period: export]] -> 0 | AS13: =AR13/$AR$32 -> 0 | AT13: =Table1[[#This Row],[Percentage of Total export for Billing Period (%)]]*$AC$32 -> 0 | AU13: =IF($Y$32-$E$40>0,$Y$32-$E$40,0) -> #N/A | AV13: =IFERROR(Table1[[#This Row],[Total Cluster Energy Balance for P2P Trading (kWh)2]]*Table1[[#This Row],[Unused Daily Allowance %]],0) -> 0 | AW13: =AS13*AF13 -> 0 | AX13: =Table1[[#This Row],[Cluster''s Total Common Services (kWh)]]*Table1[[#This Row],[Percentage of Total export for Billing Period (%)]] -> 0 | AY13: =$Q$27*Table1[[#This Row],[Percentage of Total export for Billing Period (%)]] -> 0 | AZ13: =Table1[[#This Row],[Total Lot Export (kWh)]]-Table1[[#This Row],[Total Energy Export P2P to battery (kWh)]]-Table1[[#This Row],[Axillary Battery Losses based upon Adjusted % total export (kWh)]]-Table1[[#This Row],[Common Service based upon % total export to battery (kWh)]]-Table1[[#This Row],[EV Charger based upon % total export to battery (kWh)]] -> 0 | BA13: =IFERROR(IF($AZ$32-$F$40>0,$AZ$32-$F$40,0),0) -> 0 | BB13: =Table1[[#This Row],[Energy Losses When Export to Grid (kWh)]]*Table1[[#This Row],[Percentage of Total export for Billing Period (%)]] -> 0 | BC13: =Table1[[#This Row],[Therotical Energy Export to Grid (kWh)]]-Table1[[#This Row],[Energy Losses When Export to Grid based up % total export (kWh)]] -> 0 | BD13: =AW13*'Tariff Rates'!$C$3 -> 0 | BE13: =Table1[[#This Row],[Common Service based upon % total export to battery (kWh)]]*'Tariff Rates'!$C$3 -> 0 | BF13: =Table1[[#This Row],[EV Charger based upon % total export to battery (kWh)]]*'Tariff Rates'!$C$3 -> 0 | BG13: =AT13*'Tariff Rates'!$C$3 -> 0 | BH13: =Table1[[#This Row],[Borrowed Allowance Based on Unused Daily Allowance % (kWh)]]*'Tariff Rates'!$K$3 -> 0 | BI13: =BC13*'Tariff Rates'!$F$3 -> 0 | BJ13: =SUM(BD13:BI13) -> 0 | BK13: =$D$45*Table1[[#This Row],[Percentage of Unit Entitlement (%)]] -> 0 | BL13: =BK13*'Tariff Rates'!$H$3 -> 0 | BM13: =($Q$27)*Table1[[#This Row],[Percentage of Unit Entitlement (%)]]*'Tariff Rates'!$B$3 -> 12.80664 | BN13: =SUM(BM13,BL13) -> 12.80664 | BO13: =BK13 -> 0 | BP13: =BO13+BN13 -> 12.80664 | BQ13: =AO13+BJ13+N13+BP13 -> #N/A | BT13: 9
A14: 10 | B14: {=INDEX(Table_Household_Alloc[Owner],MATCH(1,(Table_Household_Alloc[Lot]=A14)*(Table_Household_Alloc[cluster]=$B$1),0))} -> Pernille Stent | C14: {=INDEX(Reading_import[Meter'#],MATCH(1,(Table_Household_Alloc[Lot]=A14)*(Table_Household_Alloc[cluster]=$B$1),0))} -> 50002850 | D14: {=INDEX(Table_Household_Alloc[UE % over Cluster],MATCH(1,(Table_Household_Alloc[Lot]=A14)*(Table_Household_Alloc[cluster]=$B$1),0))} -> 0.053 | E14: {=INDEX(Table_Household_Alloc[Stage of Dev.],MATCH(1,(Table_Household_Alloc[Lot]=A14)*(Table_Household_Alloc[cluster]=$B$1),0))} -> O | F14: {=INDEX(Amanda_energy[Daily_Supply_incl_GST],MATCH(1,(Amanda_energy[Cluster]=$B$1)*(Amanda_energy[Month]=$F$2),0))/MAX($A:$A)} -> 8.1190476 | G14: {=INDEX(Amanda_energy[Daily_Supply_incl_GST],MATCH(1,(Amanda_energy[Cluster]=$B$1)*(Amanda_energy[Month]=$G$2),0))/MAX($A:$A)} -> 7.3333333 | H14: {=INDEX(Amanda_energy[Daily_Supply_incl_GST],MATCH(1,(Amanda_energy[Cluster]=$B$1)*(Amanda_energy[Month]=$H$2),0))/MAX($A:$A)} -> #N/A | I14: =$J$40/MAX($A:$A) -> #N/A | J14: ='Tariff Rates'!$B$8*$J$3 -> 13.561644 | K14: ='Tariff Rates'!$C$8*Table1[[#This Row],[Percentage of Unit Entitlement (%)]]*'Energy billing Mastersheet'!$K$3 -> 11.212767 | L14: =$L$3*'Tariff Rates'!$D$8*IF(Table1[[#This Row],[Stage of Dev.]]="V",0,1) -> 19.8 | M14: 1.1 | N14: =SUM(F14:M14) -> #N/A | O14: {=INDEX(Reading_import[1/1/2025],MATCH(1,(Reading_import[Lot]=A14)*(Reading_import[cluster]=$B$1),0))} -> 3930 | P14: {=INDEX(Reading_import[1/3/2025],MATCH(1,(Reading_import[Lot]=A14)*(Reading_import[cluster]=$B$1),0))} -> 4324 | Q14: =Table1[[#This Row],[Last day of reporting period: import]]-Table1[[#This Row],[1st day of reporting period: import]] -> 394 | R14: =Q14/$N$3 -> 4.3777778 | S14: =Q14/$Q$32 -> 0.072426471 | T14: =IF(Table1[[#This Row],[Stage of Dev.]]="V",0,233*Table1[[#This Row],[Percentage of Unit Entitlement (%)]]) -> 12.349 | U14: =IF(T14>R14,R14,T14) -> 4.3777778 | V14: =Table1[[#This Row],[Daily Battery allowance based on UE% (kWh)]]-Table1[[#This Row],[Applicable Battery Allowance Daily Consumption (kWh)]] -> 7.9712222 | W14: =Table1[[#This Row],[Unused Daily Allowance (kWh)]]/$V$32 -> 0.056493202 | X14: =IF(Table1[[#This Row],[Applicable Battery Allowance Daily Consumption (kWh)]]>Table1[[#This Row],[Total Daily Average Consumptio for Billing Period (kWh)]],Table1[[#This Row],[Total Consumption Import (kWh)]],U14*$N$3) -> 394 | Y14: =IF(Table1[[#This Row],[Applicable Battery Allowance Daily Consumption (kWh)]]>0,ABS(Q14-X14),0) -> 5.6843419e-14 | Z14: =IFERROR(Table1[[#This Row],[Energy Exceeding Battery Allowance (kWh)]]/$Y$32,0) -> 1 | AA14: =IF($Y$32-$E$40>0,$Y$32-$E$40,0) -> #N/A | AB14: =IFERROR(Table1[[#This Row],[Total Cluster Energy Balance for P2P Trading (kWh)]]*Table1[[#This Row],[Energy Exceeding Battery Allowance %]],0) -> 0 | AC14: =Table1[[#This Row],[P2P Import Consumption within Battery Allowance(kWh)]]+Table1[[#This Row],[P2P Import Consumption over Battery Allowance based on Energy Exceeding Allowance % (kWh)]] -> 394 | AD14: =Table1[[#This Row],[Total Consumption Import (kWh)]]-Table1[[#This Row],[Total P2P import (kWh)]] -> 0 | AE14: =IFERROR(Table1[[#This Row],[Total P2P import (kWh)]]/$AC$32,0) -> 0.072426471 | AF14: =($Q$26-$AR$26) -> 1474 | AG14: =AF14*AE14 -> 106.75662 | AH14: =SUM($Q$28:$Q$30) -> 458 | AI14: =Table1[[#This Row],[Cluster''s Total Common Services (kWh)]]*Table1[[#This Row],[Percentage of Unit Entitlement (%)]] -> 24.274 | AJ14: =AG14*'Tariff Rates'!$B$3 -> 23.486456 | AK14: =Table1[[#This Row],[Common Services based on Split per Unit Entitlement % to battery (kWh)]]*'Tariff Rates'!$B$3 -> 5.34028 | AL14: =Table1[[#This Row],[Total P2P import (kWh)]]*IF(Table1[[#This Row],[Total Lot Export (kWh)]]=0,'Tariff Rates'!$B$3,'Tariff Rates'!$L$3) -> 141.84 | AM14: =Table1[[#This Row],[P2P Import Consumption over Battery Allowance based on Energy Exceeding Allowance % (kWh)]]*'Tariff Rates'!$J$3 -> 0 | AN14: =Table1[[#This Row],[Energy Import from Grid (kWh)]]*'Tariff Rates'!$E$3 -> 0 | AO14: =SUM(AJ14:AN14) -> 170.66674 | AP14: {=INDEX(Reading_export[1/1/2025],MATCH(1,(Reading_export[Lot]=A14)*(Reading_export[cluster]=$B$1),0))} -> 20316 | AQ14: {=INDEX(Reading_export[1/3/2025],MATCH(1,(Reading_export[Lot]=A14)*(Reading_export[cluster]=$B$1),0))} -> 21130 | AR14: =Table1[[#This Row],[Last day of reporting period: export]]-Table1[[#This Row],[1st day of reporting period: export]] -> 814 | AS14: =AR14/$AR$32 -> 0.030360673 | AT14: =Table1[[#This Row],[Percentage of Total export for Billing Period (%)]]*$AC$32 -> 165.16206 | AU14: =IF($Y$32-$E$40>0,$Y$32-$E$40,0) -> #N/A | AV14: =IFERROR(Table1[[#This Row],[Total Cluster Energy Balance for P2P Trading (kWh)2]]*Table1[[#This Row],[Unused Daily Allowance %]],0) -> 0 | AW14: =AS14*AF14 -> 44.751632 | AX14: =Table1[[#This Row],[Cluster''s Total Common Services (kWh)]]*Table1[[#This Row],[Percentage of Total export for Billing Period (%)]] -> 13.905188 | AY14: =$Q$27*Table1[[#This Row],[Percentage of Total export for Billing Period (%)]] -> 49.093208 | AZ14: =Table1[[#This Row],[Total Lot Export (kWh)]]-Table1[[#This Row],[Total Energy Export P2P to battery (kWh)]]-Table1[[#This Row],[Axillary Battery Losses based upon Adjusted % total export (kWh)]]-Table1[[#This Row],[Common Service based upon % total export to battery (kWh)]]-Table1[[#This Row],[EV Charger based upon % total export to battery (kWh)]] -> 541.08791 | BA14: =IFERROR(IF($AZ$32-$F$40>0,$AZ$32-$F$40,0),0) -> 0 | BB14: =Table1[[#This Row],[Energy Losses When Export to Grid (kWh)]]*Table1[[#This Row],[Percentage of Total export for Billing Period (%)]] -> 0 | BC14: =Table1[[#This Row],[Therotical Energy Export to Grid (kWh)]]-Table1[[#This Row],[Energy Losses When Export to Grid based up % total export (kWh)]] -> 541.08791 | BD14: =AW14*'Tariff Rates'!$C$3 -> -9.845359 | BE14: =Table1[[#This Row],[Common Service based upon % total export to battery (kWh)]]*'Tariff Rates'!$C$3 -> -3.0591414 | BF14: =Table1[[#This Row],[EV Charger based upon % total export to battery (kWh)]]*'Tariff Rates'!$C$3 -> -10.800506 | BG14: =AT14*'Tariff Rates'!$C$3 -> -36.335653 | BH14: =Table1[[#This Row],[Borrowed Allowance Based on Unused Daily Allowance % (kWh)]]*'Tariff Rates'!$K$3 -> 0 | BI14: =BC14*'Tariff Rates'!$F$3 -> -20.831885 | BJ14: =SUM(BD14:BI14) -> -80.872544 | BK14: =$D$45*Table1[[#This Row],[Percentage of Unit Entitlement (%)]] -> 0 | BL14: =BK14*'Tariff Rates'!$H$3 -> 0 | BM14: =($Q$27)*Table1[[#This Row],[Percentage of Unit Entitlement (%)]]*'Tariff Rates'!$B$3 -> 18.85422 | BN14: =SUM(BM14,BL14) -> 18.85422 | BO14: =BK14 -> 0 | BP14: =BO14+BN14 -> 18.85422 | BQ14: =AO14+BJ14+N14+BP14 -> #N/A | BT14: 10
A15: 11 | B15: {=INDEX(Table_Household_Alloc[Owner],MATCH(1,(Table_Household_Alloc[Lot]=A15)*(Table_Household_Alloc[cluster]=$B$1),0))} -> Levi Holden | C15: {=INDEX(Reading_import[Meter'#],MATCH(1,(Table_Household_Alloc[Lot]=A15)*(Table_Household_Alloc[cluster]=$B$1),0))} -> 50002848 | D15: {=INDEX(Table_Household_Alloc[UE % over Cluster],MATCH(1,(Table_Household_Alloc[Lot]=A15)*(Table_Household_Alloc[cluster]=$B$1),0))} -> 0.052 | E15: {=INDEX(Table_Household_Alloc[Stage of Dev.],MATCH(1,(Table_Household_Alloc[Lot]=A15)*(Table_Household_Alloc[cluster]=$B$1),0))} -> O | F15: {=INDEX(Amanda_energy[Daily_Supply_incl_GST],MATCH(1,(Amanda_energy[Cluster]=$B$1)*(Amanda_energy[Month]=$F$2),0))/MAX($A:$A)} -> 8.1190476 | G15: {=INDEX(Amanda_energy[Daily_Supply_incl_GST],MATCH(1,(Amanda_energy[Cluster]=$B$1)*(Amanda_energy[Month]=$G$2),0))/MAX($A:$A)} -> 7.3333333 | H15: {=INDEX(Amanda_energy[Daily_Supply_incl_GST],MATCH(1,(Amanda_energy[Cluster]=$B$1)*(Amanda_energy[Month]=$H$2),0))/MAX($A:$A)} -> #N/A | I15: =$J$40/MAX($A:$A) -> #N/A | J15: ='Tariff Rates'!$B$8*$J$3 -> 13.561644 | K15: ='Tariff Rates'!$C$8*Table1[[#This Row],[Percentage of Unit Entitlement (%)]]*'Energy billing Mastersheet'!$K$3 -> 11.001205 | L15: =$L$3*'Tariff Rates'!$D$8*IF(Table1[[#This Row],[Stage of Dev.]]="V",0,1) -> 19.8 | M15: 1.1 | N15: =SUM(F15:M15) -> #N/A | O15: {=INDEX(Reading_import[1/1/2025],MATCH(1,(Reading_import[Lot]=A15)*(Reading_import[cluster]=$B$1),0))} -> 1173 | P15: {=INDEX(Reading_import[1/3/2025],MATCH(1,(Reading_import[Lot]=A15)*(Reading_import[cluster]=$B$1),0))} -> 1194 | Q15: =Table1[[#This Row],[Last day of reporting period: import]]-Table1[[#This Row],[1st day of reporting period: import]] -> 21 | R15: =Q15/$N$3 -> 0.23333333 | S15: =Q15/$Q$32 -> 0.0038602941 | T15: =IF(Table1[[#This Row],[Stage of Dev.]]="V",0,233*Table1[[#This Row],[Percentage of Unit Entitlement (%)]]) -> 12.116 | U15: =IF(T15>R15,R15,T15) -> 0.23333333 | V15: =Table1[[#This Row],[Daily Battery allowance based on UE% (kWh)]]-Table1[[#This Row],[Applicable Battery Allowance Daily Consumption (kWh)]] -> 11.882667 | W15: =Table1[[#This Row],[Unused Daily Allowance (kWh)]]/$V$32 -> 0.084214174 | X15: =IF(Table1[[#This Row],[Applicable Battery Allowance Daily Consumption (kWh)]]>Table1[[#This Row],[Total Daily Average Consumptio for Billing Period (kWh)]],Table1[[#This Row],[Total Consumption Import (kWh)]],U15*$N$3) -> 21 | Y15: =IF(Table1[[#This Row],[Applicable Battery Allowance Daily Consumption (kWh)]]>0,ABS(Q15-X15),0) -> 0 | Z15: =IFERROR(Table1[[#This Row],[Energy Exceeding Battery Allowance (kWh)]]/$Y$32,0) -> 0 | AA15: =IF($Y$32-$E$40>0,$Y$32-$E$40,0) -> #N/A | AB15: =IFERROR(Table1[[#This Row],[Total Cluster Energy Balance for P2P Trading (kWh)]]*Table1[[#This Row],[Energy Exceeding Battery Allowance %]],0) -> 0 | AC15: =Table1[[#This Row],[P2P Import Consumption within Battery Allowance(kWh)]]+Table1[[#This Row],[P2P Import Consumption over Battery Allowance based on Energy Exceeding Allowance % (kWh)]] -> 21 | AD15: =Table1[[#This Row],[Total Consumption Import (kWh)]]-Table1[[#This Row],[Total P2P import (kWh)]] -> 0 | AE15: =IFERROR(Table1[[#This Row],[Total P2P import (kWh)]]/$AC$32,0) -> 0.0038602941 | AF15: =($Q$26-$AR$26) -> 1474 | AG15: =AF15*AE15 -> 5.6900735 | AH15: =SUM($Q$28:$Q$30) -> 458 | AI15: =Table1[[#This Row],[Cluster''s Total Common Services (kWh)]]*Table1[[#This Row],[Percentage of Unit Entitlement (%)]] -> 23.816 | AJ15: =AG15*'Tariff Rates'!$B$3 -> 1.2518162 | AK15: =Table1[[#This Row],[Common Services based on Split per Unit Entitlement % to battery (kWh)]]*'Tariff Rates'!$B$3 -> 5.23952 | AL15: =Table1[[#This Row],[Total P2P import (kWh)]]*IF(Table1[[#This Row],[Total Lot Export (kWh)]]=0,'Tariff Rates'!$B$3,'Tariff Rates'!$L$3) -> 7.56 | AM15: =Table1[[#This Row],[P2P Import Consumption over Battery Allowance based on Energy Exceeding Allowance % (kWh)]]*'Tariff Rates'!$J$3 -> 0 | AN15: =Table1[[#This Row],[Energy Import from Grid (kWh)]]*'Tariff Rates'!$E$3 -> 0 | AO15: =SUM(AJ15:AN15) -> 14.051336 | AP15: {=INDEX(Reading_export[1/1/2025],MATCH(1,(Reading_export[Lot]=A15)*(Reading_export[cluster]=$B$1),0))} -> 22593 | AQ15: {=INDEX(Reading_export[1/3/2025],MATCH(1,(Reading_export[Lot]=A15)*(Reading_export[cluster]=$B$1),0))} -> 24391 | AR15: =Table1[[#This Row],[Last day of reporting period: export]]-Table1[[#This Row],[1st day of reporting period: export]] -> 1798 | AS15: =AR15/$AR$32 -> 0.067062027 | AT15: =Table1[[#This Row],[Percentage of Total export for Billing Period (%)]]*$AC$32 -> 364.81743 | AU15: =IF($Y$32-$E$40>0,$Y$32-$E$40,0) -> #N/A | AV15: =IFERROR(Table1[[#This Row],[Total Cluster Energy Balance for P2P Trading (kWh)2]]*Table1[[#This Row],[Unused Daily Allowance %]],0) -> 0 | AW15: =AS15*AF15 -> 98.849427 | AX15: =Table1[[#This Row],[Cluster''s Total Common Services (kWh)]]*Table1[[#This Row],[Percentage of Total export for Billing Period (%)]] -> 30.714408 | AY15: =$Q$27*Table1[[#This Row],[Percentage of Total export for Billing Period (%)]] -> 108.4393 | AZ15: =Table1[[#This Row],[Total Lot Export (kWh)]]-Table1[[#This Row],[Total Energy Export P2P to battery (kWh)]]-Table1[[#This Row],[Axillary Battery Losses based upon Adjusted % total export (kWh)]]-Table1[[#This Row],[Common Service based upon % total export to battery (kWh)]]-Table1[[#This Row],[EV Charger based upon % total export to battery (kWh)]] -> 1195.1794 | BA15: =IFERROR(IF($AZ$32-$F$40>0,$AZ$32-$F$40,0),0) -> 0 | BB15: =Table1[[#This Row],[Energy Losses When Export to Grid (kWh)]]*Table1[[#This Row],[Percentage of Total export for Billing Period (%)]] -> 0 | BC15: =Table1[[#This Row],[Therotical Energy Export to Grid (kWh)]]-Table1[[#This Row],[Energy Losses When Export to Grid based up % total export (kWh)]] -> 1195.1794 | BD15: =AW15*'Tariff Rates'!$C$3 -> -21.746874 | BE15: =Table1[[#This Row],[Common Service based upon % total export to battery (kWh)]]*'Tariff Rates'!$C$3 -> -6.7571698 | BF15: =Table1[[#This Row],[EV Charger based upon % total export to battery (kWh)]]*'Tariff Rates'!$C$3 -> -23.856645 | BG15: =AT15*'Tariff Rates'!$C$3 -> -80.259834 | BH15: =Table1[[#This Row],[Borrowed Allowance Based on Unused Daily Allowance % (kWh)]]*'Tariff Rates'!$K$3 -> 0 | BI15: =BC15*'Tariff Rates'!$F$3 -> -46.014408 | BJ15: =SUM(BD15:BI15) -> -178.63493 | BK15: =$D$45*Table1[[#This Row],[Percentage of Unit Entitlement (%)]] -> 0 | BL15: =BK15*'Tariff Rates'!$H$3 -> 0 | BM15: =($Q$27)*Table1[[#This Row],[Percentage of Unit Entitlement (%)]]*'Tariff Rates'!$B$3 -> 18.49848 | BN15: =SUM(BM15,BL15) -> 18.49848 | BO15: =BK15 -> 0 | BP15: =BO15+BN15 -> 18.49848 | BQ15: =AO15+BJ15+N15+BP15 -> #N/A | BT15: 11
A16: 12 | B16: {=INDEX(Table_Household_Alloc[Owner],MATCH(1,(Table_Household_Alloc[Lot]=A16)*(Table_Household_Alloc[cluster]=$B$1),0))} -> Matt & Kate Shaw | C16: {=INDEX(Reading_import[Meter'#],MATCH(1,(Table_Household_Alloc[Lot]=A16)*(Table_Household_Alloc[cluster]=$B$1),0))} -> 50002847 | D16: {=INDEX(Table_Household_Alloc[UE % over Cluster],MATCH(1,(Table_Household_Alloc[Lot]=A16)*(Table_Household_Alloc[cluster]=$B$1),0))} -> 0.052 | E16: {=INDEX(Table_Household_Alloc[Stage of Dev.],MATCH(1,(Table_Household_Alloc[Lot]=A16)*(Table_Household_Alloc[cluster]=$B$1),0))} -> UC | F16: {=INDEX(Amanda_energy[Daily_Supply_incl_GST],MATCH(1,(Amanda_energy[Cluster]=$B$1)*(Amanda_energy[Month]=$F$2),0))/MAX($A:$A)} -> 8.1190476 | G16: {=INDEX(Amanda_energy[Daily_Supply_incl_GST],MATCH(1,(Amanda_energy[Cluster]=$B$1)*(Amanda_energy[Month]=$G$2),0))/MAX($A:$A)} -> 7.3333333 | H16: {=INDEX(Amanda_energy[Daily_Supply_incl_GST],MATCH(1,(Amanda_energy[Cluster]=$B$1)*(Amanda_energy[Month]=$H$2),0))/MAX($A:$A)} -> #N/A | I16: =$J$40/MAX($A:$A) -> #N/A | J16: ='Tariff Rates'!$B$8*$J$3 -> 13.561644 | K16: ='Tariff Rates'!$C$8*Table1[[#This Row],[Percentage of Unit Entitlement (%)]]*'Energy billing Mastersheet'!$K$3 -> 11.001205 | L16: =$L$3*'Tariff Rates'!$D$8*IF(Table1[[#This Row],[Stage of Dev.]]="V",0,1) -> 19.8 | M16: 1.1 | N16: =SUM(F16:M16) -> #N/A | O16: {=INDEX(Reading_import[1/1/2025],MATCH(1,(Reading_import[Lot]=A16)*(Reading_import[cluster]=$B$1),0))} -> 34 | P16: {=INDEX(Reading_import[1/3/2025],MATCH(1,(Reading_import[Lot]=A16)*(Reading_import[cluster]=$B$1),0))} -> 42 | Q16: =Table1[[#This Row],[Last day of reporting period: import]]-Table1[[#This Row],[1st day of reporting period: import]] -> 8 | R16: =Q16/$N$3 -> 0.088888889 | S16: =Q16/$Q$32 -> 0.0014705882 | T16: =IF(Table1[[#This Row],[Stage of Dev.]]="V",0,233*Table1[[#This Row],[Percentage of Unit Entitlement (%)]]) -> 12.116 | U16: =IF(T16>R16,R16,T16) -> 0.088888889 | V16: =Table1[[#This Row],[Daily Battery allowance based on UE% (kWh)]]-Table1[[#This Row],[Applicable Battery Allowance Daily Consumption (kWh)]] -> 12.027111 | W16: =Table1[[#This Row],[Unused Daily Allowance (kWh)]]/$V$32 -> 0.085237872 | X16: =IF(Table1[[#This Row],[Applicable Battery Allowance Daily Consumption (kWh)]]>Table1[[#This Row],[Total Daily Average Consumptio for Billing Period (kWh)]],Table1[[#This Row],[Total Consumption Import (kWh)]],U16*$N$3) -> 8 | Y16: =IF(Table1[[#This Row],[Applicable Battery Allowance Daily Consumption (kWh)]]>0,ABS(Q16-X16),0) -> 0 | Z16: =IFERROR(Table1[[#This Row],[Energy Exceeding Battery Allowance (kWh)]]/$Y$32,0) -> 0 | AA16: =IF($Y$32-$E$40>0,$Y$32-$E$40,0) -> #N/A | AB16: =IFERROR(Table1[[#This Row],[Total Cluster Energy Balance for P2P Trading (kWh)]]*Table1[[#This Row],[Energy Exceeding Battery Allowance %]],0) -> 0 | AC16: =Table1[[#This Row],[P2P Import Consumption within Battery Allowance(kWh)]]+Table1[[#This Row],[P2P Import Consumption over Battery Allowance based on Energy Exceeding Allowance % (kWh)]] -> 8 | AD16: =Table1[[#This Row],[Total Consumption Import (kWh)]]-Table1[[#This Row],[Total P2P import (kWh)]] -> 0 | AE16: =IFERROR(Table1[[#This Row],[Total P2P import (kWh)]]/$AC$32,0) -> 0.0014705882 | AF16: =($Q$26-$AR$26) -> 1474 | AG16: =AF16*AE16 -> 2.1676471 | AH16: =SUM($Q$28:$Q$30) -> 458 | AI16: =Table1[[#This Row],[Cluster''s Total Common Services (kWh)]]*Table1[[#This Row],[Percentage of Unit Entitlement (%)]] -> 23.816 | AJ16: =AG16*'Tariff Rates'!$B$3 -> 0.47688235 | AK16: =Table1[[#This Row],[Common Services based on Split per Unit Entitlement % to battery (kWh)]]*'Tariff Rates'!$B$3 -> 5.23952 | AL16: =Table1[[#This Row],[Total P2P import (kWh)]]*IF(Table1[[#This Row],[Total Lot Export (kWh)]]=0,'Tariff Rates'!$B$3,'Tariff Rates'!$L$3) -> 1.76 | AM16: =Table1[[#This Row],[P2P Import Consumption over Battery Allowance based on Energy Exceeding Allowance % (kWh)]]*'Tariff Rates'!$J$3 -> 0 | AN16: =Table1[[#This Row],[Energy Import from Grid (kWh)]]*'Tariff Rates'!$E$3 -> 0 | AO16: =SUM(AJ16:AN16) -> 7.4764024 | AP16: {=INDEX(Reading_export[1/1/2025],MATCH(1,(Reading_export[Lot]=A16)*(Reading_export[cluster]=$B$1),0))} -> 0 | AQ16: {=INDEX(Reading_export[1/3/2025],MATCH(1,(Reading_export[Lot]=A16)*(Reading_export[cluster]=$B$1),0))} -> 0 | AR16: =Table1[[#This Row],[Last day of reporting period: export]]-Table1[[#This Row],[1st day of reporting period: export]] -> 0 | AS16: =AR16/$AR$32 -> 0 | AT16: =Table1[[#This Row],[Percentage of Total export for Billing Period (%)]]*$AC$32 -> 0 | AU16: =IF($Y$32-$E$40>0,$Y$32-$E$40,0) -> #N/A | AV16: =IFERROR(Table1[[#This Row],[Total Cluster Energy Balance for P2P Trading (kWh)2]]*Table1[[#This Row],[Unused Daily Allowance %]],0) -> 0 | AW16: =AS16*AF16 -> 0 | AX16: =Table1[[#This Row],[Cluster''s Total Common Services (kWh)]]*Table1[[#This Row],[Percentage of Total export for Billing Period (%)]] -> 0 | AY16: =$Q$27*Table1[[#This Row],[Percentage of Total export for Billing Period (%)]] -> 0 | AZ16: =Table1[[#This Row],[Total Lot Export (kWh)]]-Table1[[#This Row],[Total Energy Export P2P to battery (kWh)]]-Table1[[#This Row],[Axillary Battery Losses based upon Adjusted % total export (kWh)]]-Table1[[#This Row],[Common Service based upon % total export to battery (kWh)]]-Table1[[#This Row],[EV Charger based upon % total export to battery (kWh)]] -> 0 | BA16: =IFERROR(IF($AZ$32-$F$40>0,$AZ$32-$F$40,0),0) -> 0 | BB16: =Table1[[#This Row],[Energy Losses When Export to Grid (kWh)]]*Table1[[#This Row],[Percentage of Total export for Billing Period (%)]] -> 0 | BC16: =Table1[[#This Row],[Therotical Energy Export to Grid (kWh)]]-Table1[[#This Row],[Energy Losses When Export to Grid based up % total export (kWh)]] -> 0 | BD16: =AW16*'Tariff Rates'!$C$3 -> 0 | BE16: =Table1[[#This Row],[Common Service based upon % total export to battery (kWh)]]*'Tariff Rates'!$C$3 -> 0 | BF16: =Table1[[#This Row],[EV Charger based upon % total export to battery (kWh)]]*'Tariff Rates'!$C$3 -> 0 | BG16: =AT16*'Tariff Rates'!$C$3 -> 0 | BH16: =Table1[[#This Row],[Borrowed Allowance Based on Unused Daily Allowance % (kWh)]]*'Tariff Rates'!$K$3 -> 0 | BI16: =BC16*'Tariff Rates'!$F$3 -> 0 | BJ16: =SUM(BD16:BI16) -> 0 | BK16: =$D$45*Table1[[#This Row],[Percentage of Unit Entitlement (%)]] -> 0 | BL16: =BK16*'Tariff Rates'!$H$3 -> 0 | BM16: =($Q$27)*Table1[[#This Row],[Percentage of Unit Entitlement (%)]]*'Tariff Rates'!$B$3 -> 18.49848 | BN16: =SUM(BM16,BL16) -> 18.49848 | BO16: =BK16 -> 0 | BP16: =BO16+BN16 -> 18.49848 | BQ16: =AO16+BJ16+N16+BP16 -> #N/A | BT16: 12
... A25: 21 | B25: {=INDEX(Table_Household_Alloc[Owner],MATCH(1,(Table_Household_Alloc[Lot]=A25)*(Table_Household_Alloc[cluster]=$B$1),0))} -> Deborah Woodman | C25: {=INDEX(Reading_import[Meter'#],MATCH(1,(Table_Household_Alloc[Lot]=A25)*(Table_Household_Alloc[cluster]=$B$1),0))} -> 50002719 | D25: {=INDEX(Table_Household_Alloc[UE % over Cluster],MATCH(1,(Table_Household_Alloc[Lot]=A25)*(Table_Household_Alloc[cluster]=$B$1),0))} -> 0.026 | E25: {=INDEX(Table_Household_Alloc[Stage of Dev.],MATCH(1,(Table_Household_Alloc[Lot]=A25)*(Table_Household_Alloc[cluster]=$B$1),0))} -> O | F25: {=INDEX(Amanda_energy[Daily_Supply_incl_GST],MATCH(1,(Amanda_energy[Cluster]=$B$1)*(Amanda_energy[Month]=$F$2),0))/MAX($A:$A)} -> 8.1190476 | G25: {=INDEX(Amanda_energy[Daily_Supply_incl_GST],MATCH(1,(Amanda_energy[Cluster]=$B$1)*(Amanda_energy[Month]=$G$2),0))/MAX($A:$A)} -> 7.3333333 | H25: {=INDEX(Amanda_energy[Daily_Supply_incl_GST],MATCH(1,(Amanda_energy[Cluster]=$B$1)*(Amanda_energy[Month]=$H$2),0))/MAX($A:$A)} -> #N/A | I25: =$J$40/MAX($A:$A) -> #N/A | J25: ='Tariff Rates'!$B$8*$J$3 -> 13.561644 | K25: ='Tariff Rates'!$C$8*Table1[[#This Row],[Percentage of Unit Entitlement (%)]]*'Energy billing Mastersheet'!$K$3 -> 5.5006027 | L25: =$L$3*'Tariff Rates'!$D$8*IF(Table1[[#This Row],[Stage of Dev.]]="V",0,1) -> 19.8 | M25: 1.1 | N25: =SUM(F25:M25) -> #N/A | O25: {=INDEX(Reading_import[1/1/2025],MATCH(1,(Reading_import[Lot]=A25)*(Reading_import[cluster]=$B$1),0))} -> 1682 | P25: {=INDEX(Reading_import[1/3/2025],MATCH(1,(Reading_import[Lot]=A25)*(Reading_import[cluster]=$B$1),0))} -> 1735 | Q25: =Table1[[#This Row],[Last day of reporting period: import]]-Table1[[#This Row],[1st day of reporting period: import]] -> 53 | R25: =Q25/$N$3 -> 0.58888889 | S25: =Q25/$Q$32 -> 0.0097426471 | T25: =IF(Table1[[#This Row],[Stage of Dev.]]="V",0,233*Table1[[#This Row],[Percentage of Unit Entitlement (%)]]) -> 6.058 | U25: =IF(T25>R25,R25,T25) -> 0.58888889 | V25: =Table1[[#This Row],[Daily Battery allowance based on UE% (kWh)]]-Table1[[#This Row],[Applicable Battery Allowance Daily Consumption (kWh)]] -> 5.4691111 | W25: =Table1[[#This Row],[Unused Daily Allowance (kWh)]]/$V$32 -> 0.03876038 | X25: =IF(Table1[[#This Row],[Applicable Battery Allowance Daily Consumption (kWh)]]>Table1[[#This Row],[Total Daily Average Consumptio for Billing Period (kWh)]],Table1[[#This Row],[Total Consumption Import (kWh)]],U25*$N$3) -> 53 | Y25: =IF(Table1[[#This Row],[Applicable Battery Allowance Daily Consumption (kWh)]]>0,ABS(Q25-X25),0) -> 0 | Z25: =IFERROR(Table1[[#This Row],[Energy Exceeding Battery Allowance (kWh)]]/$Y$32,0) -> 0 | AA25: =IF($Y$32-$E$40>0,$Y$32-$E$40,0) -> #N/A | AB25: =IFERROR(Table1[[#This Row],[Total Cluster Energy Balance for P2P Trading (kWh)]]*Table1[[#This Row],[Energy Exceeding Battery Allowance %]],0) -> 0 | AC25: =Table1[[#This Row],[P2P Import Consumption within Battery Allowance(kWh)]]+Table1[[#This Row],[P2P Import Consumption over Battery Allowance based on Energy Exceeding Allowance % (kWh)]] -> 53 | AD25: =Table1[[#This Row],[Total Consumption Import (kWh)]]-Table1[[#This Row],[Total P2P import (kWh)]] -> 0 | AE25: =IFERROR(Table1[[#This Row],[Total P2P import (kWh)]]/$AC$32,0) -> 0.0097426471 | AF25: =($Q$26-$AR$26) -> 1474 | AG25: =AF25*AE25 -> 14.360662 | AH25: =SUM($Q$28:$Q$30) -> 458 | AI25: =Table1[[#This Row],[Cluster''s Total Common Services (kWh)]]*Table1[[#This Row],[Percentage of Unit Entitlement (%)]] -> 11.908 | AJ25: =AG25*'Tariff Rates'!$B$3 -> 3.1593456 | AK25: =Table1[[#This Row],[Common Services based on Split per Unit Entitlement % to battery (kWh)]]*'Tariff Rates'!$B$3 -> 2.61976 | AL25: =Table1[[#This Row],[Total P2P import (kWh)]]*IF(Table1[[#This Row],[Total Lot Export (kWh)]]=0,'Tariff Rates'!$B$3,'Tariff Rates'!$L$3) -> 19.08 | AM25: =Table1[[#This Row],[P2P Import Consumption over Battery Allowance based on Energy Exceeding Allowance % (kWh)]]*'Tariff Rates'!$J$3 -> 0 | AN25: =Table1[[#This Row],[Energy Import from Grid (kWh)]]*'Tariff Rates'!$E$3 -> 0 | AO25: =SUM(AJ25:AN25) -> 24.859106 | AP25: {=INDEX(Reading_export[1/1/2025],MATCH(1,(Reading_export[Lot]=A25)*(Reading_export[cluster]=$B$1),0))} -> 13350 | AQ25: {=INDEX(Reading_export[1/3/2025],MATCH(1,(Reading_export[Lot]=A25)*(Reading_export[cluster]=$B$1),0))} -> 15149 | AR25: =Table1[[#This Row],[Last day of reporting period: export]]-Table1[[#This Row],[1st day of reporting period: export]] -> 1799 | AS25: =AR25/$AR$32 -> 0.067099325 | AT25: =Table1[[#This Row],[Percentage of Total export for Billing Period (%)]]*$AC$32 -> 365.02033 | AU25: =IF($Y$32-$E$40>0,$Y$32-$E$40,0) -> #N/A | AV25: =IFERROR(Table1[[#This Row],[Total Cluster Energy Balance for P2P Trading (kWh)2]]*Table1[[#This Row],[Unused Daily Allowance %]],0) -> 0 | AW25: =AS25*AF25 -> 98.904405 | AX25: =Table1[[#This Row],[Cluster''s Total Common Services (kWh)]]*Table1[[#This Row],[Percentage of Total export for Billing Period (%)]] -> 30.731491 | AY25: =$Q$27*Table1[[#This Row],[Percentage of Total export for Billing Period (%)]] -> 108.49961 | AZ25: =Table1[[#This Row],[Total Lot Export (kWh)]]-Table1[[#This Row],[Total Energy Export P2P to battery (kWh)]]-Table1[[#This Row],[Axillary Battery Losses based upon Adjusted % total export (kWh)]]-Table1[[#This Row],[Common Service based upon % total export to battery (kWh)]]-Table1[[#This Row],[EV Charger based upon % total export to battery (kWh)]] -> 1195.8442 | BA25: =IFERROR(IF($AZ$32-$F$40>0,$AZ$32-$F$40,0),0) -> 0 | BB25: =Table1[[#This Row],[Energy Losses When Export to Grid (kWh)]]*Table1[[#This Row],[Percentage of Total export for Billing Period (%)]] -> 0 | BC25: =Table1[[#This Row],[Therotical Energy Export to Grid (kWh)]]-Table1[[#This Row],[Energy Losses When Export to Grid based up % total export (kWh)]] -> 1195.8442 | BD25: =AW25*'Tariff Rates'!$C$3 -> -21.758969 | BE25: =Table1[[#This Row],[Common Service based upon % total export to battery (kWh)]]*'Tariff Rates'!$C$3 -> -6.760928 | BF25: =Table1[[#This Row],[EV Charger based upon % total export to battery (kWh)]]*'Tariff Rates'!$C$3 -> -23.869914 | BG25: =AT25*'Tariff Rates'!$C$3 -> -80.304472 | BH25: =Table1[[#This Row],[Borrowed Allowance Based on Unused Daily Allowance % (kWh)]]*'Tariff Rates'!$K$3 -> 0 | BI25: =BC25*'Tariff Rates'!$F$3 -> -46.04 | BJ25: =SUM(BD25:BI25) -> -178.73428 | BK25: =$D$45*Table1[[#This Row],[Percentage of Unit Entitlement (%)]] -> 0 | BL25: =BK25*'Tariff Rates'!$H$3 -> 0 | BM25: =($Q$27)*Table1[[#This Row],[Percentage of Unit Entitlement (%)]]*'Tariff Rates'!$B$3 -> 9.24924 | BN25: =SUM(BM25,BL25) -> 9.24924 | BO25: =BK25 -> 0 | BP25: =BO25+BN25 -> 9.24924 | BQ25: =AO25+BJ25+N25+BP25 -> #N/A | BT25: 16
A26: BESS | B26: BESS Powerpack 232kWh | C26: {=INDEX(Reading_import[Meter'#],MATCH(1,(Table_Household_Alloc[Lot]=A26)*(Table_Household_Alloc[cluster]=$B$1),0))} -> 40002686 | O26: {=INDEX(Reading_import[1/1/2025],MATCH(1,(Reading_import[Lot]=A26)*(Reading_import[cluster]=$B$1),0))} -> 59297 | P26: {=INDEX(Reading_import[1/3/2025],MATCH(1,(Reading_import[Lot]=A26)*(Reading_import[cluster]=$B$1),0))} -> 67826 | Q26: =Table1[[#This Row],[Last day of reporting period: import]]-Table1[[#This Row],[1st day of reporting period: import]] -> 8529 | AP26: {=INDEX(Reading_export[1/1/2025],MATCH(1,(Reading_export[Lot]=A26)*(Reading_export[cluster]=$B$1),0))} -> 48306 | AQ26: {=INDEX(Reading_export[1/3/2025],MATCH(1,(Reading_export[Lot]=A26)*(Reading_export[cluster]=$B$1),0))} -> 55361 | AR26: =Table1[[#This Row],[Last day of reporting period: export]]-Table1[[#This Row],[1st day of reporting period: export]] -> 7055 | BR26: data swapped | BT26: BESS
A27: EV | B27: EV Charger | C27: {=INDEX(Reading_import[Meter'#],MATCH(1,(Table_Household_Alloc[Lot]=A27)*(Table_Household_Alloc[cluster]=$B$1),0))} -> 40002693 | O27: {=INDEX(Reading_import[1/1/2025],MATCH(1,(Reading_import[Lot]=A27)*(Reading_import[cluster]=$B$1),0))} -> 4535 | P27: {=INDEX(Reading_import[1/3/2025],MATCH(1,(Reading_import[Lot]=A27)*(Reading_import[cluster]=$B$1),0))} -> 6152 | Q27: =Table1[[#This Row],[Last day of reporting period: import]]-Table1[[#This Row],[1st day of reporting period: import]] -> 1617 | AP27: {=INDEX(Reading_export[1/1/2025],MATCH(1,(Reading_export[Lot]=A27)*(Reading_export[cluster]=$B$1),0))} -> 0 | AQ27: {=INDEX(Reading_export[1/3/2025],MATCH(1,(Reading_export[Lot]=A27)*(Reading_export[cluster]=$B$1),0))} -> 0 | AR27: =Table1[[#This Row],[Last day of reporting period: export]]-Table1[[#This Row],[1st day of reporting period: export]] -> 0 | BT27: EV
A28: CS | B28: Common Services MSB | C28: {=INDEX(Reading_import[Meter'#],MATCH(1,(Table_Household_Alloc[Lot]=A28)*(Table_Household_Alloc[cluster]=$B$1),0))} -> 50002858 | O28: {=INDEX(Reading_import[1/1/2025],MATCH(1,(Reading_import[Lot]=A28)*(Reading_import[cluster]=$B$1),0))} -> 4913 | P28: {=INDEX(Reading_import[1/3/2025],MATCH(1,(Reading_import[Lot]=A28)*(Reading_import[cluster]=$B$1),0))} -> 5343 | Q28: =Table1[[#This Row],[Last day of reporting period: import]]-Table1[[#This Row],[1st day of reporting period: import]] -> 430 | AP28: {=INDEX(Reading_export[1/1/2025],MATCH(1,(Reading_export[Lot]=A28)*(Reading_export[cluster]=$B$1),0))} -> 0 | AQ28: {=INDEX(Reading_export[1/3/2025],MATCH(1,(Reading_export[Lot]=A28)*(Reading_export[cluster]=$B$1),0))} -> 0 | AR28: =Table1[[#This Row],[Last day of reporting period: export]]-Table1[[#This Row],[1st day of reporting period: export]] -> 0 | BT28: CS
A29: DB1 | B29: Common Services DB1 | O29: {=INDEX(Reading_import[1/1/2025],MATCH(1,(Reading_import[Lot]=A29)*(Reading_import[cluster]=$B$1),0))} -> 157 | P29: {=INDEX(Reading_import[1/3/2025],MATCH(1,(Reading_import[Lot]=A29)*(Reading_import[cluster]=$B$1),0))} -> 166 | Q29: =Table1[[#This Row],[Last day of reporting period: import]]-Table1[[#This Row],[1st day of reporting period: import]] -> 9 | BT29: DB1
A30: DB2 | B30: Common Services DB2 | O30: {=INDEX(Reading_import[1/1/2025],MATCH(1,(Reading_import[Lot]=A30)*(Reading_import[cluster]=$B$1),0))} -> 232 | P30: {=INDEX(Reading_import[1/3/2025],MATCH(1,(Reading_import[Lot]=A30)*(Reading_import[cluster]=$B$1),0))} -> 251 | Q30: =Table1[[#This Row],[Last day of reporting period: import]]-Table1[[#This Row],[1st day of reporting period: import]] -> 19 | BT30: DB2
A31: CP | B31: Strata consumption Site Check Meter | BT31: CP
D32: =SUM(D5:D25) -> 0.92 | E32: =SUM(E5:E25) -> 0 | F32: =SUM(F5:F25) -> 170.5 | H32: =SUM(H5:H25) -> #N/A | I32: =SUM(I5:I25) -> #N/A | J32: =SUM(J5:J25) -> 284.79452 | K32: =SUM(K5:K25) -> 194.63671 | L32: =SUM(L5:L25) -> 396 | M32: =SUM(M5:M25) -> 23.1 | N32: =SUM(N5:N25) -> #N/A | Q32: =SUM(Q5:Q25) -> 5440 | S32: =SUM(S5:S25) -> 1 | T32: =SUM(T5:T25) -> 201.545 | V32: =SUM(V5:V25) -> 141.10056 | W32: =SUM(W5:W25) -> 1 | X32: =SUM(X5:X25) -> 5440 | Y32: =SUM(Y5:Y25) -> 5.6843419e-14 | Z32: =SUM(Z5:Z25) -> 1 | AB32: =SUM(AB5:AB31) -> 0 | AC32: =SUM(AC5:AC31) -> 5440 | AD32: =SUM(AD5:AD31) -> 0 | AE32: =SUM(AE5:AE25) -> 1 | AG32: =SUM(AG5:AG25) -> 1474 | AI32: =SUM(AI5:AI25) -> 421.36 | AJ32: =SUM(AJ5:AJ31) -> 324.28 | AK32: =SUM(AK5:AK31) -> 92.6992 | AL32: =SUM(AL5:AL31) -> 1720.82 | AM32: =SUM(AM5:AM31) -> 0 | AN32: =SUM(AN5:AN31) -> 0 | AO32: =SUM(AO5:AO31) -> 2137.7992 | AR32: =SUM(AR5:AR25) -> 26811 | AS32: =SUM(AS5:AS25) -> 1 | AT32: =SUM(AT5:AT25) -> 5440 | AV32: =SUM(AV5:AV25) -> 0 | AW32: =SUM(AW5:AW25) -> 1474 | AX32: =SUM(AX5:AX25) -> 458 | AY32: =SUM(AY5:AY25) -> 1617 | AZ32: =SUM(AZ5:AZ25) -> 17822 | BB32: =SUM(BB5:BB25) -> 0 | BC32: =SUM(BC5:BC25) -> 17822 | BD32: =SUM(BD5:BD25) -> -324.28 | BE32: =SUM(BE5:BE25) -> -100.76 | BF32: =SUM(BF5:BF25) -> -355.74 | BG32: =SUM(BG5:BG25) -> -1196.8 | BH32: =SUM(BH5:BH25) -> 0 | BI32: =SUM(BI5:BI25) -> -686.147 | ... BP32: =SUM(BP5:BP25) -> 327.2808
L33: =COUNTIF(L5:L25,">0") -> 20 | M33: =COUNTIF(M5:M25,">0") -> 21
AA34: = Total Energy exceeding allowance - Actual amanda energy import | AL34: Teants with 0 export will be charge at higher rate for their consumption
B36: Amanda enegery | C36: Year | D36: Month | E36: Consumption_kWh | F36: Export_kWh | G36: Amanda_consumption_incl_GST | H36: Amanda_export_buyback_incl_GST | I36: Daily_Supply_incl_GST | J36: Other_Fees_incl_GST | K36: Total_incl_GST
B37: =B1 -> 1A | C37: 2025 | D37: =F2 -> 1 | E37: {=INDEX(Amanda_energy[Consumption_kWh],MATCH(1,(Amanda_energy[Cluster]=$B$1)*(Amanda_energy[Month]=$D37),0))} -> 33.93 | F37: {=INDEX(Amanda_energy[Export_kWh],MATCH(1,(Amanda_energy[Cluster]=$B$1)*(Amanda_energy[Month]=$D37),0))} -> 11281.06 | G37: {=INDEX(Amanda_energy[Amanda_consumption_incl_GST],MATCH(1,(Amanda_energy[Cluster]=$B$1)*(Amanda_energy[Month]=$D37),0))} -> 10.16 | H37: {=INDEX(Amanda_energy[Amanda_export_buyback_incl_GST],MATCH(1,(Amanda_energy[Cluster]=$B$1)*(Amanda_energy[Month]=$D37),0))} -> -434.32 | I37: {=INDEX(Amanda_energy[Daily_Supply_incl_GST],MATCH(1,(Amanda_energy[Cluster]=$B$1)*(Amanda_energy[Month]=$D37),0))} -> 170.5 | J37: {=INDEX(Amanda_energy[Other_Fees_incl_GST],MATCH(1,(Amanda_energy[Cluster]=$B$1)*(Amanda_energy[Month]=$D37),0))} -> 15.54 | K37: {=INDEX(Amanda_energy[Total_incl_GST],MATCH(1,(Amanda_energy[Cluster]=$B$1)*(Amanda_energy[Month]=$D37),0))} -> -238.12
B38: =B37 -> 1A | C38: 2025 | D38: =G2 -> 2 | E38: {=INDEX(Amanda_energy[Consumption_kWh],MATCH(1,(Amanda_energy[Cluster]=$B$1)*(Amanda_energy[Month]=$D38),0))} -> 9.73 | F38: {=INDEX(Amanda_energy[Export_kWh],MATCH(1,(Amanda_energy[Cluster]=$B$1)*(Amanda_energy[Month]=$D38),0))} -> 10654.83 | G38: {=INDEX(Amanda_energy[Amanda_consumption_incl_GST],MATCH(1,(Amanda_energy[Cluster]=$B$1)*(Amanda_energy[Month]=$D38),0))} -> 2.92 | H38: {=INDEX(Amanda_energy[Amanda_export_buyback_incl_GST],MATCH(1,(Amanda_energy[Cluster]=$B$1)*(Amanda_energy[Month]=$D38),0))} -> -410.21 | I38: {=INDEX(Amanda_energy[Daily_Supply_incl_GST],MATCH(1,(Amanda_energy[Cluster]=$B$1)*(Amanda_energy[Month]=$D38),0))} -> 154 | J38: {=INDEX(Amanda_energy[Other_Fees_incl_GST],MATCH(1,(Amanda_energy[Cluster]=$B$1)*(Amanda_energy[Month]=$D38),0))} -> 12.85 | K38: {=INDEX(Amanda_energy[Total_incl_GST],MATCH(1,(Amanda_energy[Cluster]=$B$1)*(Amanda_energy[Month]=$D38),0))} -> -240.45
B39: =B37 -> 1A | C39: 2025 | D39: =H2 -> 3 | E39: {=INDEX(Amanda_energy[Consumption_kWh],MATCH(1,(Amanda_energy[Cluster]=$B$1)*(Amanda_energy[Month]=$D39),0))} -> #N/A | F39: {=INDEX(Amanda_energy[Export_kWh],MATCH(1,(Amanda_energy[Cluster]=$B$1)*(Amanda_energy[Month]=$D39),0))} -> #N/A | G39: {=INDEX(Amanda_energy[Amanda_consumption_incl_GST],MATCH(1,(Amanda_energy[Cluster]=$B$1)*(Amanda_energy[Month]=$D39),0))} -> #N/A | H39: {=INDEX(Amanda_energy[Amanda_export_buyback_incl_GST],MATCH(1,(Amanda_energy[Cluster]=$B$1)*(Amanda_energy[Month]=$D39),0))} -> #N/A | I39: {=INDEX(Amanda_energy[Daily_Supply_incl_GST],MATCH(1,(Amanda_energy[Cluster]=$B$1)*(Amanda_energy[Month]=$D39),0))} -> #N/A | J39: {=INDEX(Amanda_energy[Other_Fees_incl_GST],MATCH(1,(Amanda_energy[Cluster]=$B$1)*(Amanda_energy[Month]=$D39),0))} -> #N/A | K39: {=INDEX(Amanda_energy[Total_incl_GST],MATCH(1,(Amanda_energy[Cluster]=$B$1)*(Amanda_energy[Month]=$D39),0))} -> #N/A
B40: Total | E40: =SUM(E37:E39) -> #N/A | F40: =SUM(F37:F39) -> #N/A | G40: =SUM(G37:G39) -> #N/A | H40: =SUM(H37:H39) -> #N/A | I40: =SUM(I37:I39) -> #N/A | J40: =SUM(J37:J39) -> #N/A | K40: =SUM(K37:K39) -> #N/A
G41: =G40/E40 -> #N/A | H41: =H40/F40 -> #N/A
B42: Month | C42: EV Charger KWh/month total | D42: Chargefox Revenue | E42: Chargefox Revenue -5%
B45: Total | C45: =SUM(C43:C44) -> 0 | D45: =SUM(D43:D44) -> 0 | E45: =SUM(E43:E44) -> 0
C46: =C45/Q27 -> 0
B48: Strata reconcilation table | C48: $ Incl. GST
B49: Residents supply charge | C49: =N32 -> #N/A
B50: Amanda buyback | C50: =SUM(H40)*-1 -> #N/A
B51: Residents energy consumption | C51: =AO32 -> 2137.7992
B52: EV Charger operation cost | C52: =BN32 -> 327.2808
B53: ChargeFox Income | C53: =E45*-1 -> 0
B54: Strata total income | C54: =SUM(C49:C53) -> #N/A
B55: Total payout to resident for exporting | C55: =BJ32 -> -2663.727
B56: Total payout to resident for EV charger revenue | C56: =BO32 -> 0
B57: Total payout to Amanda Energy | C57: =(G40+J40+I40)*-1 -> #N/A
B58: Total payout to supply (SwichDin, E47, ChargeFox) | C58: =SUM(J32:M32)*-1 -> -898.53123
B59: Strata total payout | C59: =SUM(C55:C58) -> #N/A
B60: Variance | C60: =C54+C59 -> #N/A
B61: Variance % | C61: =C60/C54 -> #N/A

Sheet Lot 1
A2: =VLOOKUP(E7,Rep_table[],2,FALSE) -> The Owners of Cluster 1A Witchcliffe Ecovillage Survey Strata 77784 | B2: TAX INVOICE
A3: =VLOOKUP(E7,Rep_table[],3,FALSE) -> ABN: 29 857 461 927
A5: =CONCATENATE("C/- Cluster ",E7," Strata") -> C/- Cluster 1A Strata | B5: DATE: | E5: =TODAY() -> 45769
A6: 10437 Bussell Highway | B6: Invoice # | E6: =CONCATENATE(E7,E8,"/",TEXT(E12,"mm"),TEXT(E12,"yy")) -> 1A1/0325
A7: Witchcliffe WA 6286 | B7: Cluster | E7: ='Energy billing Mastersheet'!B1 -> 1A
A8: =CONCATENATE("Email: ",VLOOKUP(E7,Rep_table[],8,FALSE)) -> Email: wevcluster1a@gmail.com | B8: Lot Number | E8: 1
B9: Lot Meter Number # | E9: =VLOOKUP(E8,'Energy billing Mastersheet'!5:32,MATCH('Energy billing Mastersheet'!C4,'Energy billing Mastersheet'!4:4,0),FALSE) -> 50002845
A10: Addressee:- | B10: Unit Entitlement | E10: {=INDEX(Table_Household_Alloc[Unit Entitlement],MATCH(1,(Table_Household_Alloc[Lot]=E8)*(Table_Household_Alloc[cluster]=E7),0))} -> 36
A11: {=INDEX(Table_Household_Alloc[Owner],MATCH(1,(Table_Household_Alloc[Lot]=E8)*(Table_Household_Alloc[cluster]=E7),0))} -> Mead Family trust | B11: Unit Entitlement % | E11: {=INDEX(Table_Household_Alloc[UE % over Cluster],MATCH(1,(Table_Household_Alloc[Lot]=E8)*(Table_Household_Alloc[cluster]=E7),0))} -> 0.036
A12: {=INDEX(Table_Household_Alloc[Street Address],MATCH(1,(Table_Household_Alloc[Lot]=E8)*(Table_Household_Alloc[cluster]=E7),0))} -> 1 Yornitj Grove | B12: Billing period | C12: ='Energy billing Mastersheet'!F1 -> 45658 | E12: ='Energy billing Mastersheet'!H1 -> 45747
A13: Witchcliffe WA 6286 | B13: Billing period days | E13: ='Energy billing Mastersheet'!N3 -> 90
A15: Items | B15: Charge Rate ($ Inc. GST) | C15: Usage | E15: Amount due ($ Inc. GST)
A16: Supply charge
A17: ="Amanda Energy Daily Supply Charge 1/"&'Energy billing Mastersheet'!F2&"/25 - "&DAY(DATE(2025,'Energy billing Mastersheet'!F2+1,0))&"/"&'Energy billing Mastersheet'!F2&"/25" -> Amanda Energy Daily Supply Charge 1/1/25 - 31/1/25 | B17: =IFERROR(Invoice3[[#This Row],[Amount due ($ Inc. GST)]]/Invoice3[[#This Row],[Usage]],0) -> 8.1190476 | C17: 1 | D17: Unit | E17: {=_xlfn.XLOOKUP($E$8,Table1[[#All],[Lot]],Table1[[#All],[Amanda Energy Daily Supply Charge ($)]],0,0,1)} -> 8.1190476
A18: ="Amanda Energy Daily Supply Charge 1/"&'Energy billing Mastersheet'!G2&"/25 - "&DAY(DATE(2025,'Energy billing Mastersheet'!G2+1,0))&"/"&'Energy billing Mastersheet'!G2&"/25" -> Amanda Energy Daily Supply Charge 1/2/25 - 28/2/25 | B18: =IFERROR(Invoice3[[#This Row],[Amount due ($ Inc. GST)]]/Invoice3[[#This Row],[Usage]],0) -> 7.3333333 | C18: 1 | D18: Unit | E18: {=_xlfn.XLOOKUP($E$8,Table1[[#All],[Lot]],Table1[[#All],[Amanda Energy Daily Supply Charge ($)2]],0,0,1)} -> 7.3333333
A19: ="Amanda Energy Daily Supply Charge 1/"&'Energy billing Mastersheet'!H2&"/25 - "&DAY(DATE(2025,'Energy billing Mastersheet'!H2+1,0))&"/"&'Energy billing Mastersheet'!H2&"/25" -> Amanda Energy Daily Supply Charge 1/3/25 - 31/3/25 | B19: =IFERROR(Invoice3[[#This Row],[Amount due ($ Inc. GST)]]/Invoice3[[#This Row],[Usage]],0) -> 0 | C19: 1 | D19: Unit | E19: {=_xlfn.XLOOKUP($E$8,Table1[[#All],[Lot]],Table1[[#All],[Amanda Energy Daily Supply Charge ($)3]],0,0,1)} -> #N/A
A20: Amanda Energy Other Fees | B20: =IFERROR(Invoice3[[#This Row],[Amount due ($ Inc. GST)]]/Invoice3[[#This Row],[Usage]],0) -> 0 | C20: 1 | D20: Unit | E20: {=_xlfn.XLOOKUP($E$8,Table1[[#All],[Lot]],Table1[[#All],[Amanda Energy Other fees ($)]],0,0,1)} -> #N/A
A21: Element47 Embedded Network Daily Supply Charges | B21: =IFERROR(Invoice3[[#This Row],[Amount due ($ Inc. GST)]]/Invoice3[[#This Row],[Usage]],0) -> 0.22 | C21: ='Energy billing Mastersheet'!N3 -> 90 | D21: Days | E21: {=_xlfn.XLOOKUP($E$8,Table1[[#All],[Lot]],Table1[[#All],[Element47 Embedded Network Daily Supply Charges]],0,0,1)} -> 19.8
A22: Element47 Embedded Network Invoicing Fees | B22: =IFERROR(Invoice3[[#This Row],[Amount due ($ Inc. GST)]]/Invoice3[[#This Row],[Usage]],0) -> 1.1 | C22: 1 | D22: Unit | E22: {=_xlfn.XLOOKUP($E$8,Table1[[#All],[Lot]],Table1[[#All],[Element47 Embedded Network Invoicing Fees]],0,0,1)} -> 1.1
A23: Chargefox EV Charger Network Fixed Fees Equitable Split % of Unit Entitlement | B23: =IFERROR(Invoice3[[#This Row],[Amount due ($ Inc. GST)]]/Invoice3[[#This Row],[Usage]],0) -> 0.084624658 | C23: =C21 -> 90 | D23: Days | E23: {=_xlfn.XLOOKUP($E$8,Table1[[#All],[Lot]],Table1[[#All],[Chargefox Daily Supply Charge ($)]],0,0,1)} -> 7.6162192
A24: SwitchdIn Supply Charge | B24: =IFERROR(Invoice3[[#This Row],[Amount due ($ Inc. GST)]]/Invoice3[[#This Row],[Usage]],0) -> 0.15068493 | C24: =C21 -> 90 | D24: Days | E24: {=_xlfn.XLOOKUP($E$8,Table1[[#All],[Lot]],Table1[[#All],[SwitchdIn Cost Daily Supply Charge ($)]],0,0,1)} -> 13.561644
A25: Total Daily Supply Charge | B25: =IFERROR(Invoice3[[#This Row],[Amount due ($ Inc. GST)]]/Invoice3[[#This Row],[Usage]],0) -> 0 | C25: =C24 -> 90 | D25: Days | E25: =SUM(E17:E24) -> #N/A
A26: Common Services Charges
A27: Common Services Fees Equitable Split % of Unit Entitlement kWh | B27: =IFERROR(Invoice3[[#This Row],[Amount due ($ Inc. GST)]]/Invoice3[[#This Row],[Usage]],0) -> 0.22 | C27: {=_xlfn.XLOOKUP($E$8,Table1[[#All],[Lot]],Table1[[#All],[Common Services based on Split per Unit Entitlement % to battery (kWh)]],0,0,1)} -> 16.488 | D27: kWh | E27: {=_xlfn.XLOOKUP($E$8,Table1[[#All],[Lot]],Table1[[#All],[Common Services Cost Split per Unit Entitlement at P2P rate ($)]],0,0,1)} -> 3.62736
A28: Common Services Reimbursement based on P2P export % kWh | B28: =IFERROR(Invoice3[[#This Row],[Amount due ($ Inc. GST)]]/Invoice3[[#This Row],[Usage]],0) -> 0 | C28: {=_xlfn.XLOOKUP($E$8,Table1[[#All],[Lot]],Table1[[#All],[Common Service based upon % total export to battery (kWh)]],0,0,1)} -> 0 | D28: kWh | E28: {=_xlfn.XLOOKUP($E$8,Table1[[#All],[Lot]],Table1[[#All],[Common Service Earning based upon % total export to Load ($)]],0,0,1)} -> 0
A29: Import Battery Loss Allocation based on P2P import % kWh | B29: =IFERROR(Invoice3[[#This Row],[Amount due ($ Inc. GST)]]/Invoice3[[#This Row],[Usage]],0) -> 0.22 | C29: {=_xlfn.XLOOKUP($E$8,Table1[[#All],[Lot]],Table1[[#All],[Axillary Battery Losses based upon P2P import % (kWh)]],0,0,1)} -> 1.8966912 | D29: kWh | E29: {=_xlfn.XLOOKUP($E$8,Table1[[#All],[Lot]],Table1[[#All],[Axillary Battery Loss Charges at P2P Rates based upon P2P import % ($)]],0,0,1)} -> 0.41727206
A30: Export of Solar PV Battery Loss Reimbursement based on P2P export % kWh | B30: =IFERROR(Invoice3[[#This Row],[Amount due ($ Inc. GST)]]/Invoice3[[#This Row],[Usage]],0) -> 0 | C30: {=_xlfn.XLOOKUP($E$8,Table1[[#All],[Lot]],Table1[[#All],[Axillary Battery Losses based upon Adjusted % total export (kWh)]],0,0,1)} -> 0 | D30: kWh | E30: {=_xlfn.XLOOKUP($E$8,Table1[[#All],[Lot]],Table1[[#All],[Axillary Battery Losses based upon % total export ($)]],0,0,1)} -> 0
A31: Community EV Charger Variable Income Equitable Split % of Unit Entitlement kWh | B31: =IFERROR(Invoice3[[#This Row],[Amount due ($ Inc. GST)]]/Invoice3[[#This Row],[Usage]],0) -> 0 | C31: {=_xlfn.XLOOKUP("EV",Table1[[#All],[Lot]],Table1[[#All],[Total Consumption Import (kWh)]],0,0,1)*E11} -> 58.212 | D31: kWh | E31: {=_xlfn.XLOOKUP($E$8,Table1[[#All],[Lot]],Table1[[#All],[EV Charger Income from Sales Equitable Distribution on UE ($)]],0,0,1)} -> 0
A32: Community EV Charger Variable Cost of Electricity Supply Equitable Split % of Unit Entitlement kWh | B32: =IFERROR(Invoice3[[#This Row],[Amount due ($ Inc. GST)]]/Invoice3[[#This Row],[Usage]],0) -> 0.22 | C32: {=_xlfn.XLOOKUP("EV",Table1[[#All],[Lot]],Table1[[#All],[Total Consumption Import (kWh)]],0,0,1)*E11} -> 58.212 | D32: kWh | E32: {=_xlfn.XLOOKUP($E$8,Table1[[#All],[Lot]],Table1[[#All],[EV Charger Cost of Electricity Supply at P2P Rates ($)]],0,0,1)} -> 12.80664
A33: Community EV Charger Reimbursement based on P2P export % kWh | B33: =IFERROR(Invoice3[[#This Row],[Amount due ($ Inc. GST)]]/Invoice3[[#This Row],[Usage]],0) -> 0 | C33: {=_xlfn.XLOOKUP($E$8,Table1[[#All],[Lot]],Table1[[#All],[EV Charger based upon % total export to battery (kWh)]],0,0,1)} -> 0 | D33: kWh | E33: {=_xlfn.XLOOKUP($E$8,Table1[[#All],[Lot]],Table1[[#All],[EV Charger based upon % total export ($)]],0,0,1)} -> 0
A34: Community EV Charger Chargefox Commission Cost Equitable Split % of Unit Entitlement kWh | B34: =IFERROR(Invoice3[[#This Row],[Amount due ($ Inc. GST)]]/Invoice3[[#This Row],[Usage]],0) -> 0 | C34: {=_xlfn.XLOOKUP("EV",Table1[[#All],[Lot]],Table1[[#All],[Total Consumption Import (kWh)]],0,0,1)*E11} -> 58.212 | D34: kWh | E34: {=_xlfn.XLOOKUP($E$8,Table1[[#All],[Lot]],Table1[[#All],[Chargefox Commission on EV Charge Consumption Sales Cost Split by Unit Entitlement ($)]],0,0,1)} -> 0
A35: Total Common Services Charges | B35: =Invoice3[[#This Row],[Amount due ($ Inc. GST)]]/Invoice3[[#This Row],[Usage]] -> 0.18723636 | C35: =C24 -> 90 | D35: Days | E35: =SUM(E27:E34) -> 16.851272
A36: Imported energy
A37: Import Peer to Peer kWh | B37: =IFERROR(Invoice3[[#This Row],[Amount due ($ Inc. GST)]]/Invoice3[[#This Row],[Usage]],0) -> 0.22 | C37: {=_xlfn.XLOOKUP($E$8,Table1[[#All],[Lot]],Table1[[#All],[Total P2P import (kWh)]],0,0,1)} -> 7 | D37: kWh | E37: {=_xlfn.XLOOKUP($E$8,Table1[[#All],[Lot]],Table1[[#All],[P2P Import Cost ($)]],0,0,1)} -> 1.54
A38: P2P Import Consumption over Battery Allowance kWh | B38: =IFERROR(Invoice3[[#This Row],[Amount due ($ Inc. GST)]]/Invoice3[[#This Row],[Usage]],0) -> 0 | C38: {=_xlfn.XLOOKUP($E$8,Table1[[#All],[Lot]],Table1[[#All],[P2P Import Consumption over Battery Allowance based on Energy Exceeding Allowance % (kWh)]],0,0,1)} -> 0 | D38: kWh | E38: {=_xlfn.XLOOKUP($E$8,Table1[[#All],[Lot]],Table1[[#All],[Exceeding Battery Allowance P2P Fee ($)]],0,0,1)} -> 0
A39: Import From Grid kWh | B39: =IFERROR(Invoice3[[#This Row],[Amount due ($ Inc. GST)]]/Invoice3[[#This Row],[Usage]],0) -> 0 | C39: {=_xlfn.XLOOKUP($E$8,Table1[[#All],[Lot]],Table1[[#All],[Energy Import from Grid (kWh)]],0,0,1)} -> 0 | D39: kWh | E39: {=_xlfn.XLOOKUP($E$8,Table1[[#All],[Lot]],Table1[[#All],[Import From Grid Cost ($)]],0,0,1)} -> 0
A40: Total Imported Energy | B40: =Invoice3[[#This Row],[Amount due ($ Inc. GST)]]/Invoice3[[#This Row],[Usage]] -> 0.017111111 | C40: =C35 -> 90 | D40: Days | E40: =SUM(E37:E39) -> 1.54
A41: Exported energy
A42: Export Peer to Peer kWh | B42: =IFERROR(Invoice3[[#This Row],[Amount due ($ Inc. GST)]]/Invoice3[[#This Row],[Usage]],0) -> 0 | C42: {=_xlfn.XLOOKUP($E$8,Table1[[#All],[Lot]],Table1[[#All],[Total Energy Export P2P to battery (kWh)]],0,0,1)} -> 0 | D42: kWh | E42: {=_xlfn.XLOOKUP($E$8,Table1[[#All],[Lot]],Table1[[#All],[P2P Export Earnings ($)]],0,0,1)} -> 0
A43: P2P Borrowed Allowance Passive Compensation kWh | B43: =IFERROR(Invoice3[[#This Row],[Amount due ($ Inc. GST)]]/Invoice3[[#This Row],[Usage]],0) -> 0 | C43: {=_xlfn.XLOOKUP($E$8,Table1[[#All],[Lot]],Table1[[#All],[Borrowed Allowance Based on Unused Daily Allowance % (kWh)]],0,0,1)} -> 0 | D43: kWh | E43: {=_xlfn.XLOOKUP($E$8,Table1[[#All],[Lot]],Table1[[#All],[Passive Compensation ($)]],0,0,1)} -> 0
A44: Exported to Grid kWh | B44: =IFERROR(Invoice3[[#This Row],[Amount due ($ Inc. GST)]]/Invoice3[[#This Row],[Usage]],0) -> 0 | C44: {=_xlfn.XLOOKUP($E$8,Table1[[#All],[Lot]],Table1[[#All],[Energy Export to Grid after Losses (kWh)]],0,0,1)} -> 0 | D44: kWh | E44: {=_xlfn.XLOOKUP($E$8,Table1[[#All],[Lot]],Table1[[#All],[Grid Export Earnings ($)]],0,0,1)} -> 0
A45: Total Exported Energy | B45: =IFERROR(Invoice3[[#This Row],[Amount due ($ Inc. GST)]]/Invoice3[[#This Row],[Usage]],0) -> 0 | C45: =C40 -> 90 | D45: Days | E45: =SUBTOTAL(109,E42:E44) -> 0
A46: Combined Energy Charge | B46: =IFERROR(Invoice3[[#This Row],[Amount due ($ Inc. GST)]]/Invoice3[[#This Row],[Usage]],0) -> 0 | C46: =C45 -> 90 | D46: Days | E46: =E25+E45+E35+E40 -> #N/A
A47: Account in credit / debit: Strata to enter where applicable
A48: =IF(E48>0,"Payment due "&TEXT(EOMONTH(TODAY(),0)+15,"dd/mm/yy"),"REFUND due "&TEXT(EOMONTH(TODAY(),0)+15,"dd/mm/yy")) -> #N/A | B48: TOTAL | E48: =E46-E47 -> #N/A
A50: =CONCATENATE("Bank Details/Account Name:",VLOOKUP(E7,Rep_table[],13,FALSE)) -> Bank Details/Account Name:Owners Cluster 1A
A51: =CONCATENATE("BSB:",VLOOKUP(E7,Rep_table[],14,FALSE)) -> BSB:633-000
A52: =CONCATENATE("Account:",VLOOKUP(E7,Rep_table[],15,FALSE)) -> Account:209 071 927
A54: =CONCATENATE("Please use payment reference: Surname Inv No i.e. ",IF(ISNUMBER(SEARCH("trust",A11)),_xlfn.TEXTBEFORE(A11," ",1),_xlfn.TEXTAFTER(A11," ",-1))," ",E6) -> Please use payment reference: Surname Inv No i.e. Mead 1A1/0325
